Workbook

Sheet Overview
B2: BEST BUY CO., INC. (BBY)
B4: Investor Analysis
B5: Prepared by: | C5: Team 1
B6: Course: | C6: SP26: VALUE FUND: 9810
B7: Date: | C7: =TODAY() -> 46172
B8: Fiscal Year End: | C8: Late January to early February
B9: Currency: | C9: USD ($ millions unless noted)
B10: Sources: | C10: Best Buy 10-Ks (FY2022–FY2024), Earnings Call Transcripts, Facset, CapitalIQ etc
B12: Content:
B13: 1. Assumptions
B14: 2. Historical Data | C14: 3-year actuals pulled from 10-K (FY2022–FY2024), geographic revenue, business segment, industry metrics, and multiples
B15: 3. Revenue Build | C15: P&L with actuals + 5-year forecasts, base case, bear case, bottom up and top down comparision
B16: 4. DCF Model | C16: base and bear case
B17: 5. FCFE Valuation
B18: 6. Comp Analysis | C18: EV/Revenue, EV/EBITDA, P/E
B19: 7. Blended Implied Price Summary
B20: 8. Unit Economics | C20: revenue changes compares to store count etc
B21: 7. WACC | C21: WACC calculation taking market estimates
B22: 8. Estimates in CAGR | C22: 5 year CAGR

Sheet Assumptions
A1: BEST BUY BUSINESS MODEL ASSUMPTIONS BASED ON HISTORICALS AND MARKET DATA
A2: All assumptions finalized and validated against SEC filings (10-K / 10-Q), Q4 FY2026 Earnings Call (Mar 3, 2026), and analyst consensus.
A3: PRIMARY SOURCES: (1) 10-K FY2025: https://www.sec.gov/Archives/edgar/data/0000764478/000076447825000007/bby-20250201x10k.htm (2) 10-Q Q1 FY2026: https://www.sec.gov/Archives/edgar/data/0000764478/000076447825000019/bby-20250503x10q.htm (3) 10-Q Q3 FY2026: https://www.sec.gov/Archives/edgar/data/0000764478/000076447825000057/bby-20251101.htm (4) Q4 FY2026 Transcript: https://www.theglobeandmail.com/investing/markets/stocks/BBY/pressreleases/536814/best-buy-bby-q4-2026-earnings-call-transcript/ (5) Q4 FY2026 Highlights: https://www.dailypolitical.com/2026/03/04/best-buy-q4-earnings-call-highlights.html | H3: Source Links
A4: Assumptions | B4: 2027E | C4: 2028E | D4: 2029E | E4: 2030E | F4: 2031E | G4: Notes
A5: Comparable sales and online mix | H5: Best Buy Q4 FY2026 8-K / Earnings Call, Mar 3, 2026: https://finance.yahoo.com/news/best-buy-q4-earnings-call-194703419.html Earnings Call Full Transcript (Globe & Mail): https://www.theglobeandmail.com/investing/markets/stocks/BBY/pressreleases/536814/best-buy-bby-q4-2026-earnings-call-transcript/
A6: Total Sales Growth % | B6: 0.01 | C6: 0.015 | D6: 0.02 | E6: 0.02 | F6: 0.02 | G6: FY2027E: Midpoint of management guidance range of -1% to +1%. FY2028 to FY2031: Analyst consensus CAGR of 1.5–2.0%, supported by AI PC refresh cycle, Windows 10 EOL tailwind, and gradual housing recovery. | H6: Best Buy Q4 FY2026 Earnings Call, Mar 3, 2026: https://www.theglobeandmail.com/investing/markets/stocks/BBY/pressreleases/536814/best-buy-bby-q4-2026-earnings-call-transcript/ Q4 FY2026 Earnings Call Highlights: https://www.dailypolitical.com/2026/03/04/best-buy-q4-earnings-call-highlights.html
A7: Domestic Sales Growth (%) | B7: 0.01 | C7: 0.015 | D7: 0.02 | E7: 0.02 | F7: 0.02 | G7: FY2027E: midpoint of BBY guidance -1% to +1% (Q4 FY26 8-K, 3-Mar-2026, SEC EDGAR). FY2028-31: analyst consensus 1.5-2.0% CAGR. Same driver set as total comp sales above. | H7: Best Buy 10-K FY2025, International Segment Disclosures: https://www.sec.gov/Archives/edgar/data/0000764478/000076447825000007/bby-20250201x10k.htm
A8: International Sales Growth (%) | B8: 0.01 | C8: 0.015 | D8: 0.02 | E8: 0.02 | F8: 0.02 | G8: No separate Canada guidance issued. Mirrors domestic SSS given similar product mix and consumer electronics cycle. CAD/USD assumed broadly neutral. | H8: Best Buy Q4 FY2026 Earnings Call, Mar 3, 2026: https://finance.yahoo.com/news/best-buy-q4-earnings-call-194703419.html
A9: Online Revenue % of Domestic | B9: 0.4 | C9: 0.41 | D9: 0.42 | E9: 0.43 | F9: 0.44 | G9: FY2027E: continuing upward trend from 39.0% (FY26 actual). FY2028-31: +1ppt/yr assumption; consistent with historical shift to online. Trajectory slowing post-COVID peak (about 37% in FY2023): conservative assumption.
A10: Store Count | H10: Best Buy Q4 FY2026 8-K/Earnings Call, Mar 3, 2026: https://finance.yahoo.com/news/best-buy-q4-earnings-call-194703419.html Earnings Call Full Transcript: https://www.theglobeandmail.com/investing/markets/stocks/BBY/pressreleases/536814/best-buy-bby-q4-2026-earnings-call-transcript/
A11: Total Stores Opened | B11: 6 | C11: 6 | D11: 5 | E11: 5 | F11: 5 | G11: FY2027E: 6 new domestic stores (BBY Q4 FY26 8-K: "first time in several years... six new locations"). FY2028 to 31: gradual normalization | H11: Best Buy Q4 FY2026 Earnings Call, Mar 3, 2026: https://finance.yahoo.com/news/best-buy-q4-earnings-call-194703419.html
A12: Total Stores Closed | B12: 18 | C12: 18 | D12: 16 | E12: 15 | F12: 15 | G12: FY2027E: 20 dom + 15 intl = 35 total, this would be extrapolating FY2026 number which is a one-time restructuring, based on portfolio rationalization trend from BBY 10-K FY2026. New FY2026E: 2 traditional domestic (mgmt guided) + approx.3 residual non-traditional (Outlet/Yardbird tail per restructuring note) + 3 international, which makes about 8 total. FY2028 to FY2031: Normalized lease-expiry attrition of 7 to 10/yr. Our prior assumption was over-relying on one quote from management about traditional domestic closures and ignoring both the non-traditional format wind-down still in progress and the company's own stated long-run closure policy. Revise upward to approx. 18 for FY2027E and 15–18 thereafter. | H12: Best Buy Q4 FY2026 Earnings Call, Mar 3, 2026: https://finance.yahoo.com/news/best-buy-q4-earnings-call-194703419.html
A13: Domestic Stores Opened | B13: 6 | C13: 6 | D13: 5 | E13: 5 | F13: 5 | G13: All new openings are domestic small-format. No international openings planned. | H13: Q4 FY2026 Earnings Call: '6 new stores, closing two as leases come up': https://www.dailypolitical.com/2026/03/04/best-buy-q4-earnings-call-highlights.html Q3 FY2026 10-Q: Restructuring, 'additional [non-traditional] closures FY2027': https://www.sec.gov/Archives/edgar/data/0000764478/000076447825000057/bby-20251101.htm
A14: Domestic Stores Closed | B14: =B12-B16 -> 15 | C14: =C12-C16 -> 15 | D14: =D12-D16 -> 14 | E14: =E12-E16 -> 13 | F14: =F12-F16 -> 13 | G14: Management guided only 2 traditional domestic closures in FY2027. FY2027E: 2 traditional (mgmt) + approx.3 non-traditional residual (Outlet Centers / Yardbird tail from FY2026 restructuring) which makes up 5 total. FY2028 to FY2031: Normalized lease-expiry run-rate of 5 to 7/yr. Yardbird went from 23 to 2 stores during FY2026. Outlet Centers dropped from 25 to 18. The Q3 FY2026 10-Q explicitly states "additional [non-traditional] closures expected in fiscal 2027" as the restructuring winds down. | H14: 10-K FY2025, Intl stores: 160 (Feb-25), 160 (Feb-24), 160 (Jan-23): https://www.sec.gov/Archives/edgar/data/0000764478/000076447825000007/bby-20250201x10k.htm
A15: International Stores Opened | B15: 0 | C15: 0 | D15: 0 | E15: 0 | F15: 0 | G15: No international openings planned. Canada store count flat for 3+ consecutive years with no announced expansion plans. | H15: 10-K FY2025, Intl stores = 160: https://www.sec.gov/Archives/edgar/data/0000764478/000076447825000007/bby-20250201x10k.htm 10-Q Q1 FY2026 (May 2025), Intl stores = 157: https://www.sec.gov/Archives/edgar/data/0000764478/000076447825000019/bby-20250503x10q.htm 10-Q Q3 FY2026 (Nov 2025), Intl stores still 157, no further movement: https://www.sec.gov/Archives/edgar/data/0000764478/000076447825000057/bby-20251101.htm
A16: International Stores Closed | B16: 3 | C16: 3 | D16: 2 | E16: 2 | F16: 2 | G16: No evidence in any filing or guidance supports aggressive Canadian closures. International went 160 to 157 across ALL of FY2026 (3 stores). FY2027E: 3, matching the FY2026 observed run-rate. FY2028 to FY2031: Conservative lease-expiry attrition of 2/yr.
A17: Segment growth | H17: Q4 FY2026 Earnings Call (memory/ASP commentary), Mar 3, 2026: https://www.theglobeandmail.com/investing/markets/stocks/BBY/pressreleases/536814/best-buy-bby-q4-2026-earnings-call-transcript/
A18: Computing & Mobile Phones | B18: 0.02 | C18: 0.04 | D18: 0.03 | E18: 0.02 | F18: 0.02 | G18: FY2027E +2.0%: AI PC upgrade cycle "sweet spot" 2026-27 (finterra/FinContent Mar 2026); memory cost inflation headwind (Q4 FY26 earnings call). FY2028E +4.0%: cycle peaks. Normalizes to +2% FY2029+ | H18: D.A. Davidson / BNN Bloomberg analysis, Nov 2025 (TV units vs. dollars). Q4 FY2026 Earnings Call (category performance), Mar 3, 2026: https://finance.yahoo.com/news/best-buy-q4-earnings-call-194703419.html
A19: Consumer Electronics | B19: -0.02 | C19: 0.015 | D19: 0.02 | E19: 0.02 | F19: 0.02 | G19: FY2027E -2.0%: TV units inflected positive but dollars still -ve (D.A. Davidson, BNN Bloomberg Nov 2025); home theater challenged. FY2028E +1.5%: dollar recovery. FY2029+ +2.0% as housing normalizes | H19: Q4 FY2026 Earnings Call: 'structural shift toward duress replacements': https://www.dailypolitical.com/2026/03/04/best-buy-q4-earnings-call-highlights.html Home Improvement Research Institute (HIRI): 2025–2028 Appliance CAGR ~4.4%: https://www.hiriinfo.org
A20: Appliances | B20: -0.05 | C20: 0 | D20: 0.025 | E20: 0.03 | F20: 0.03 | G20: FY2027E -5.0%: "structural shift toward duress replacements" (Q4 FY26 earnings call); HD/Lowes share pressure. FY2028E flat. FY2029+ +2.5-3.0%: HIRI ~4.4% appliance CAGR 2025-28; housing recovery | H20: Q4 FY2026 Earnings Call: 'AI glasses, PC gaming handhelds, collectibles delivered notable growth'; Meta store layout expansion: https://www.theglobeandmail.com/investing/markets/stocks/BBY/pressreleases/536814/best-buy-bby-q4-2026-earnings-call-transcript/
A21: Entertainment | B21: 0.03 | C21: 0.025 | D21: 0.02 | E21: 0.02 | F21: 0.02 | G21: FY2027E +3.0%: gaming console cycle; AI glasses/Meta partnership. Stable +2-2.5% FY2028+ | H21: Q4 FY2026 Earnings Call: Ads $900M+ run-rate, 10% growth guided: https://www.dailypolitical.com/2026/03/04/best-buy-q4-earnings-call-highlights.html Full transcript (Ads & Marketplace profitability FY2028 commentary): https://www.theglobeandmail.com/investing/markets/stocks/BBY/pressreleases/536814/best-buy-bby-q4-2026-earnings-call-transcript/
A22: Services (Geek Squad/Totaltech/My Best Buy) | B22: 0.04 | C22: 0.05 | D22: 0.05 | E22: 0.04 | F22: 0.04 | G22: FY2027E +4.0% / FY2028+ +5.0%: "material Ads & Marketplace contribution starting FY2028" (Q4 FY26 earnings call); My Best Buy membership; Geek Squad pivot. Eases to +4% FY2030+ | H22: Q4 FY2026 Earnings Call: Ads growth, Marketplace launch, FY2028 inflection: https://www.theglobeandmail.com/investing/markets/stocks/BBY/pressreleases/536814/best-buy-bby-q4-2026-earnings-call-transcript/ Q4 FY2026 Earnings Call Highlights: https://finance.yahoo.com/news/best-buy-q4-earnings-call-194703419.html
A23: Other (Best Buy Ads/Marketplace/New Ventures) | B23: 0.08 | C23: 0.1 | D23: 0.08 | E23: 0.06 | F23: 0.05 | G23: FY2027E +8.0% / FY2028E +10.0%: Best Buy Ads $900M run-rate (FinContent 2026); Marketplace >1,100 sellers; FY2027 final investment year per mgmt. Moderates to +5% by FY2031E
A24: Domestic SSS Growth (%) | B24: 0.004 | C24: 0.01 | D24: 0.0228 | E24: 0.03 | F24: =E24 -> 0.03 | G24: expected 1% to 3.5%, validated hrough PY revenue changes from revenue build. ranges derived from revenue growth consensus (~1.3to 1.9% CAGR), store-level math, and structural driver analysis. A bear scenario (persistent tariffs + macro weakness + memory cost inflation) could keep FY28 to FY29 near flat or slightly negative, while a bull scenario (housing recovery + AI supercycle) could push FY29–FY31 toward 4 to 5%.
A25: International stores SSS Growth (%) | B25: 0.01 | C25: 0.01 | D25: 0.01 | E25: 0.01 | F25: 0.01 | G25: flat growth expected
A26: Services comparables Sales Growth% | B26: 0.11 | C26: 0.12 | D26: 0.12 | E26: 0.1 | F26: 0.09 | G26: Marketplace ramp up due to ads scaling and healthdrag. Entering FY28, heath stabalizes and AI device services helps with the growth rate. Towards FY30 and after, predicting a mature and more stabalized % representation at around 10%
A28: DCF Parameters
A29: WACC | B29: 0.105 | C29: - | D29: - | E29: - | F29: - | G29: 10.5% — elevated vs. sector peers. Reflects tariff/macro uncertainty, consumer electronics cyclicality, and appliance softness. Source: CAPM + peer comp.
A30: Terminal Growth Rate (TGR) | B30: 0.02 | C30: - | D30: - | E30: - | F30: - | G30: 2.0% — conservative; in line with long-run nominal GDP. ~25bps below historical retail median. Implies 12.4× terminal FCFF multiple.
A31: Net Debt ($M) | B31: 1000 | C31: - | D31: - | E31: - | F31: - | G31: Gross debt ~$1.3B less cash ~$0.3B per Q4 FY26 balance sheet. BBY investment-grade rated (BBB); sustainable dividend. Source: Q4 FY26 10-K.
A32: Diluted Shares Outstanding (M) | B32: 210 | C32: - | D32: - | E32: - | F32: - | G32: Reflects ongoing repurchase program. ~200–210M diluted shares. Source: BBY FY26 10-K.
A33: Effective Tax Rate | B33: 0.24 | C33: =B33 -> 0.24 | D33: =C33 -> 0.24 | E33: =D33 -> 0.24 | F33: =E33 -> 0.24 | G33: Consistent with BBY recent historical effective tax rate (~24%). Source: BBY FY26 10-K.
A34: Depreciation & Amortization ($M) | B34: 800 | C34: 793 | D34: 782 | E34: 772 | F34: 762 | G34: Contracting as store count falls,
A35: Capital Expenditures ($M) | B35: 750 | C35: 710 | D35: 700 | E35: 690 | F35: 680 | G35: Modest decline as big-box remodel cycle winds down. Small-format openings (~$2M each × 15/yr = $30M incremental) partially offset savings.
A36: Change in Net Working Capital ($M) | B36: 75 | C36: 50 | D36: 35 | E36: 25 | F36: 20 | G36: Conservative modest outflow; BBY historically runs a lean / negative working capital cycle as a retailer.
A37: Operating Margin % | B37: 0.043 | C37: 0.046 | D37: 0.049 | E37: 0.051 | F37: 0.053
A39: Current Stock Price Used In this Model | B39: 63.39 | C39: as of 4/15/2026
A40: FFCF 2026A | B40: CFO ($1,962) + After-tax interest ($44*24% = $33) − CapEx ($704) ≈ ~$1,291M
A42: PRIMARY SOURCES: (1) 10-K FY2025: https://www.sec.gov/Archives/edgar/data/0000764478/000076447825000007/bby-20250201x10k.htm (2) 10-Q Q1 FY2026: https://www.sec.gov/Archives/edgar/data/0000764478/000076447825000019/bby-20250503x10q.htm (3) 10-Q Q3 FY2026: https://www.sec.gov/Archives/edgar/data/0000764478/000076447825000057/bby-20251101.htm (4) Q4 FY2026 Transcript: https://www.theglobeandmail.com/investing/markets/stocks/BBY/pressreleases/536814/best-buy-bby-q4-2026-earnings-call-transcript/ (5) Q4 FY2026 Highlights: https://www.dailypolitical.com/2026/03/04/best-buy-q4-earnings-call-highlights.html

Sheet Revenue Build - Draft
B2: Description | C2: Units | D2: 2021A | E2: 2022A | F2: 2023A | G2: 2024A | H2: 2025A | I2: 2026A | J2: 2027E | K2: 2028E | L2: 2029E | M2: 2030E | N2: 2031E | O2: Notes
B4: Key Revenue Drivers and Assumptions
B5: Store Sales
B6: Total Comparable Sales Growth | D6: ='Industry Metrics'!G3 -> 0.097 | E6: ='Industry Metrics'!F3 -> 0.104 | F6: ='Industry Metrics'!E3 -> -0.099 | G6: ='Industry Metrics'!D3 -> -0.068 | H6: ='Industry Metrics'!C3 -> -0.023 | I6: ='Industry Metrics'!B3 -> 0.005 | J6: =Assumptions!B6 -> 0.01 | K6: =Assumptions!C6 -> 0.015 | L6: =Assumptions!D6 -> 0.02 | M6: =Assumptions!E6 -> 0.02 | N6: =Assumptions!F6 -> 0.02 | O6: FY2027E: midpoint of BBY guidance -1% to +1% (Q4 FY26 8-K, 3-Mar-2026, SEC EDGAR). FY2028-31: analyst consensus 1.5-2.0% CAGR
B7: Domestic Comparable Sales Growth | D7: ='Industry Metrics'!G4 -> 0.092 | E7: ='Industry Metrics'!F4 -> 0.11 | F7: ='Industry Metrics'!E4 -> -0.103 | G7: ='Industry Metrics'!D4 -> -0.071 | H7: ='Industry Metrics'!C4 -> -0.025 | I7: ='Industry Metrics'!B4 -> 0.004 | J7: =Assumptions!B7 -> 0.01 | K7: =Assumptions!C7 -> 0.015 | L7: =Assumptions!D7 -> 0.02 | M7: =Assumptions!E7 -> 0.02 | N7: =Assumptions!F7 -> 0.02
B8: International Comparable Sales Growth | D8: ='Industry Metrics'!G5 -> 0.15 | E8: ='Industry Metrics'!F5 -> 0.033 | F8: ='Industry Metrics'!E5 -> -0.054 | G8: ='Industry Metrics'!D5 -> -0.032 | H8: ='Industry Metrics'!C5 -> -0.005 | I8: ='Industry Metrics'!B5 -> 0.023 | J8: =Assumptions!B8 -> 0.01 | K8: =Assumptions!C8 -> 0.015 | L8: =Assumptions!D8 -> 0.02 | M8: =Assumptions!E8 -> 0.02 | N8: =Assumptions!F8 -> 0.02
B9: Online Revenue as % of Domestic Rev | D9: ='Industry Metrics'!G9 -> 0.33 | E9: ='Industry Metrics'!F9 -> 0.36 | F9: ='Industry Metrics'!E9 -> 0.34 | G9: ='Industry Metrics'!D9 -> 0.38 | H9: ='Industry Metrics'!C9 -> 0.395 | I9: ='Industry Metrics'!B9 -> 0.39 | J9: =Assumptions!B9 -> 0.4 | K9: =Assumptions!C9 -> 0.41 | L9: =Assumptions!D9 -> 0.42 | M9: =Assumptions!E9 -> 0.43 | N9: =Assumptions!F9 -> 0.44 | O9: FY2027E: continuing upward trend from 39.0% (FY26 actual). FY2028-31: +1ppt/yr assumption; consistent with historical shift to online
B12: Total Store Count
B13: Beginning Store Count | D13: ='Industry Metrics'!G12 -> 1231 | E13: ='Industry Metrics'!F12 -> 1159 | F13: ='Industry Metrics'!E12 -> 1144 | G13: ='Industry Metrics'!D12 -> 1138 | H13: ='Industry Metrics'!C12 -> 1125 | I13: ='Industry Metrics'!B12 -> 1117 | J13: =I16 -> 1068 | K13: =J16 -> 1039 | L13: =K16 -> 1019 | M13: =L16 -> 1004 | N13: =M16 -> 994
B14: Stores Opened | D14: ='Industry Metrics'!G19 -> 3 | E14: ='Industry Metrics'!F19 -> 13 | F14: ='Industry Metrics'!E19 -> 9 | G14: ='Industry Metrics'!D20 -> 15 | H14: ='Industry Metrics'!C19 -> 0 | I14: ='Industry Metrics'!B20 -> 0 | J14: =Assumptions!B11 -> 6 | K14: =Assumptions!C11 -> 6 | L14: =Assumptions!D11 -> 5 | M14: =Assumptions!E11 -> 5 | N14: =Assumptions!F11 -> 5 | O14: FY2027E: 6 new domestic stores (BBY Q4 FY26 8-K: "first time in several years... six new locations"). FY2028-31: gradual normalization
B15: Stores Closed | D15: ='Industry Metrics'!G23 -> 75 | E15: ='Industry Metrics'!F23 -> 28 | F15: ='Industry Metrics'!E23 -> 15 | G15: ='Industry Metrics'!D23 -> 28 | H15: ='Industry Metrics'!C23 -> 8 | I15: ='Industry Metrics'!B23 -> 49 | J15: 35 | K15: 26 | L15: 20 | M15: 15 | N15: 13 | O15: FY2027E: 20 dom + 15 intl = 35 total. Declining from 49 in FY26; based on portfolio rationalization trend from BBY 10-K FY2026
B16: Ending Store Count | D16: =D13+D14-D15 -> 1159 | E16: =E13+E14-E15 -> 1144 | F16: =F13+F14-F15 -> 1138 | G16: =G13+G14-G15 -> 1125 | H16: =H13+H14-H15 -> 1117 | I16: =I13+I14-I15 -> 1068 | J16: =J13+J14-J15 -> 1039 | K16: =K13+K14-K15 -> 1019 | ... N16: =N13+N14-N15 -> 986
B17: Average Store Count | D17: =(D13+D16)/2 -> 1195 | E17: =(E13+E16)/2 -> 1151.5 | F17: =(F13+F16)/2 -> 1141 | G17: =(G13+G16)/2 -> 1131.5 | H17: =(H13+H16)/2 -> 1121 | I17: =(I13+I16)/2 -> 1092.5 | J17: =(J13+J16)/2 -> 1053.5 | K17: =(K13+K16)/2 -> 1029 | ... N17: =(N13+N16)/2 -> 990
B18: Domestic Store Count
B19: Beginning Store Count | D19: ='Industry Metrics'!G13 -> 1009 | E19: ='Industry Metrics'!F13 -> 991 | F19: ='Industry Metrics'!E13 -> 984 | G19: ='Industry Metrics'!D13 -> 978 | H19: ='Industry Metrics'!C13 -> 965 | I19: ='Industry Metrics'!B13 -> 957 | J19: =I22 -> 926 | K19: =J22 -> 912 | L19: =K22 -> 900 | M19: =L22 -> 890 | N19: =M22 -> 883
B20: Stores Opened | D20: ='Industry Metrics'!G21 -> 3 | E20: ='Industry Metrics'!F21 -> 13 | F20: ='Industry Metrics'!E21 -> 9 | G20: ='Industry Metrics'!D21 -> 14 | H20: ='Industry Metrics'!C21 -> 0 | I20: ='Industry Metrics'!B21 -> 0 | J20: 6 | K20: 6 | L20: 5 | M20: 5 | N20: 5
B21: Stores Closed | D21: ='Industry Metrics'!G24 -> 21 | E21: ='Industry Metrics'!F24 -> 20 | F21: ='Industry Metrics'!E24 -> 15 | G21: ='Industry Metrics'!D24 -> 27 | H21: ='Industry Metrics'!C24 -> 8 | I21: ='Industry Metrics'!B24 -> 31 | J21: 20 | K21: 18 | L21: 15 | M21: 12 | N21: 10
B22: Ending Store Count | D22: =D19+D20-D21 -> 991 | E22: =E19+E20-E21 -> 984 | F22: =F19+F20-F21 -> 978 | G22: =G19+G20-G21 -> 965 | H22: =H19+H20-H21 -> 957 | I22: =I19+I20-I21 -> 926 | J22: =J19+J20-J21 -> 912 | K22: =K19+K20-K21 -> 900 | ... N22: =N19+N20-N21 -> 878
B23: Average Store Count | D23: =(D19+D22)/2 -> 1000 | E23: =(E19+E22)/2 -> 987.5 | F23: =(F19+F22)/2 -> 981 | G23: =(G19+G22)/2 -> 971.5 | H23: =(H19+H22)/2 -> 961 | I23: =(I19+I22)/2 -> 941.5 | J23: =(J19+J22)/2 -> 919 | K23: =(K19+K22)/2 -> 906 | ... N23: =(N19+N22)/2 -> 880.5
B24: International Store Count
B25: Beginning Store Count | D25: ='Industry Metrics'!G14 -> 222 | E25: ='Industry Metrics'!F14 -> 168 | F25: ='Industry Metrics'!E14 -> 160 | G25: ='Industry Metrics'!D14 -> 160 | H25: ='Industry Metrics'!C14 -> 160 | I25: ='Industry Metrics'!B14 -> 160 | J25: =I28 -> 142 | K25: =J28 -> 127 | L25: =K28 -> 119 | M25: =L28 -> 114 | N25: =M28 -> 111
B26: Stores Opened | D26: ='Industry Metrics'!G22 -> 0 | E26: ='Industry Metrics'!F22 -> 0 | F26: ='Industry Metrics'!E25 -> 0 | G26: ='Industry Metrics'!D25 -> 1 | H26: ='Industry Metrics'!C25 -> 0 | I26: ='Industry Metrics'!B22 -> 0 | J26: 0 | K26: 0 | L26: 0 | M26: 0 | N26: 0
B27: Stores Closed | D27: ='Industry Metrics'!G25 -> 54 | E27: ='Industry Metrics'!F25 -> 8 | F27: ='Industry Metrics'!E25 -> 0 | G27: ='Industry Metrics'!D25 -> 1 | H27: ='Industry Metrics'!C25 -> 0 | I27: ='Industry Metrics'!B25 -> 18 | J27: 15 | K27: 8 | L27: 5 | M27: 3 | N27: 3
B28: Ending Store Count | D28: =D25+D26-D27 -> 168 | E28: =E25+E26-E27 -> 160 | F28: =F25+F26-F27 -> 160 | G28: =G25+G26-G27 -> 160 | H28: =H25+H26-H27 -> 160 | I28: =I25+I26-I27 -> 142 | J28: =J25+J26-J27 -> 127 | K28: =K25+K26-K27 -> 119 | ... N28: =N25+N26-N27 -> 108
B29: Average Store Count | D29: =(D25+D28)/2 -> 195 | E29: =(E25+E28)/2 -> 164 | F29: =(F25+F28)/2 -> 160 | G29: =(G25+G28)/2 -> 160 | H29: =(H25+H28)/2 -> 160 | I29: =(I25+I28)/2 -> 151 | J29: =(J25+J28)/2 -> 134.5 | K29: =(K25+K28)/2 -> 123 | ... N29: =(N25+N28)/2 -> 109.5
B31: Revenue Per Store
B32: Domestic Rev per Avg. Store | D32: ='Geographic Revenue'!F6/D23 -> 43.293 | E32: ='Geographic Revenue'!G6/E23 -> 48.435443 | F32: ='Geographic Revenue'!H6/F23 -> 43.622834 | G32: ='Geographic Revenue'!I6/G23 -> 41.273289 | H32: ='Geographic Revenue'!J6/H23 -> 39.789802 | I32: ='Geographic Revenue'!K6/I23 -> 40.656399 | J32: =J45/J23 -> 42.20236 | K32: =K45/K23 -> 43.59187 | L32: =L45/L23 -> 45.134389 | M32: =M45/M23 -> 46.608321 | N32: =N45/N23 -> 47.999425
B33: Y/Y Growth Domestic Rev per Store | E33: =E32/D32-1 -> 0.11878232 | F33: =F32/E32-1 -> -0.099361313 | G33: =G32/F32-1 -> -0.053860442 | H33: =H32/G32-1 -> -0.035943015 | I33: =I32/H32-1 -> 0.021779376 | J33: =J32/I32-1 -> 0.038025027 | K33: =K32/J32-1 -> 0.032924945 | L33: =L32/K32-1 -> 0.035385475 | ... N33: =N32/M32-1 -> 0.029846678
B34: International Rev per Avg. Store | D34: =SUM('Geographic Revenue'!F7:F9)/D29 -> 22.246154 | E34: =SUM('Geographic Revenue'!G7:G9)/E29 -> 24.091463 | F34: =SUM('Geographic Revenue'!H7:H9)/F29 -> 21.9 | G34: =SUM('Geographic Revenue'!I7:I9)/G29 -> 20.96875 | H34: =SUM('Geographic Revenue'!J7:J9)/H29 -> 20.5625 | I34: =SUM('Geographic Revenue'!K7:K9)/I29 -> 22.602649 | J34: =J54/J29 -> 25.629219 | K34: =K54/K29 -> 28.445829 | L34: =L54/L29 -> 30.633594 | M34: =M54/M29 -> 32.357244 | N34: =N54/N29 -> 33.908619
B35: Y/Y Growth International Rev per Store | E35: =E34/D34-1 -> 0.0829496 | F35: =F34/E34-1 -> -0.090964313 | G35: =G34/F34-1 -> -0.042522831 | H35: =H34/G34-1 -> -0.019374069 | I35: =I34/H34-1 -> 0.099216973 | J35: =J34/I34-1 -> 0.13390335 | K35: =K34/J34-1 -> 0.10989837 | L35: =L34/K34-1 -> 0.076909871 | ... N35: =N34/M34-1 -> 0.047945205
B37: Domestic Revenue Build
B38: Comparable Store Rev
B39: Prior Year Domestic Revenue | D39: ='Geographic Revenue'!E6 -> 40114 | E39: ='Geographic Revenue'!F6 -> 43293 | F39: ='Geographic Revenue'!G6 -> 47830 | G39: ='Geographic Revenue'!H6 -> 42794 | H39: ='Geographic Revenue'!I6 -> 40097 | I39: ='Geographic Revenue'!J6 -> 38238 | J39: ='Geographic Revenue'!K6 -> 38278 | K39: =J45 -> 38783.969 | L39: =K45 -> 39494.235 | M39: =L45 -> 40395.279 | N39: =M45 -> 41318.277
B40: Comp Store Base Rev | D40: =D39*(1+D7) -> 43804.488 | E40: =E39*(1+E7) -> 48055.23 | F40: =F39*(1+F7) -> 42903.51 | G40: =G39*(1+G7) -> 39755.626 | H40: =H39*(1+H7) -> 39094.575 | I40: =I39*(1+I7) -> 38390.952 | J40: =J39*(1+J7) -> 38660.78 | K40: =K39*(1+K7) -> 39365.728 | ... N40: =N39*(1+N7) -> 42144.642
B41: New Store Rev
B42: Stores Opened during year | D42: ='Industry Metrics'!G19 -> 3 | E42: ='Industry Metrics'!F19 -> 13 | F42: ='Industry Metrics'!E19 -> 9 | G42: ='Industry Metrics'!D19 -> 15 | H42: ='Industry Metrics'!C19 -> 0 | I42: ='Industry Metrics'!B20 -> 0 | J42: =J20 -> 6 | K42: =K20 -> 6 | L42: =L20 -> 5 | M42: =M20 -> 5 | N42: =N20 -> 5
B43: Rev per New Store | D43: ='Geographic Revenue'!F6/'Revenue Build - Draft'!D23*50% -> 21.6465 | E43: ='Geographic Revenue'!G6/'Revenue Build - Draft'!E23*50% -> 24.217722 | F43: ='Geographic Revenue'!H6/'Revenue Build - Draft'!F23*50% -> 21.811417 | G43: ='Geographic Revenue'!I6/'Revenue Build - Draft'!G23*50% -> 20.636644 | H43: ='Geographic Revenue'!J6/'Revenue Build - Draft'!H23*50% -> 19.894901 | I43: ='Geographic Revenue'!K6/'Revenue Build - Draft'!I23*50% -> 20.3282 | J43: ='Geographic Revenue'!K6/I23*(1+J7)*50% -> 20.531482 | K43: =J45/J23*(1+K7)*50% -> 21.417698 | L43: =K45/K23*(1+L7)*50% -> 22.231854 | M43: =L45/L23*(1+M7)*50% -> 23.018539 | N43: =M45/M23*(1+N7)*50% -> 23.770244 | O43: New store rev = (prior yr rev/avg stores) × (1 + comp growth) × 50% ramp factor (new stores earn half-year revenue in opening year)
B44: Total new Store Rev | D44: =D42*D43 -> 64.9395 | E44: =E42*E43 -> 314.83038 | F44: =F42*F43 -> 196.30275 | G44: =G42*G43 -> 309.54967 | H44: =H42*H43 -> 0 | I44: =I42*I43 -> 0 | J44: =J42*J43 -> 123.18889 | K44: =K42*K43 -> 128.50619 | ... N44: =N42*N43 -> 118.85122
B45: Total Domestic Rev | D45: =D44+D40 -> 43869.428 | E45: =E44+E40 -> 48370.06 | F45: =F44+F40 -> 43099.813 | G45: =G44+G40 -> 40065.176 | H45: =H44+H40 -> 39094.575 | I45: =I44+I40 -> 38390.952 | J45: =J44+J40 -> 38783.969 | K45: =K44+K40 -> 39494.235 | ... N45: =N44+N40 -> 42263.494
B47: International Rev Build
B48: Prior Year International Rev | D48: =SUM('Geographic Revenue'!E7:E9) -> 3923 | E48: =SUM('Geographic Revenue'!F7:F9) -> 4338 | F48: =SUM('Geographic Revenue'!G7:G9) -> 3951 | G48: =SUM('Geographic Revenue'!H7:H9) -> 3504 | H48: =SUM('Geographic Revenue'!I7:I9) -> 3355 | I48: =SUM('Geographic Revenue'!J7:J9) -> 3290 | J48: =SUM('Geographic Revenue'!K7:K9) -> 3413 | K48: =J54 -> 3447.13 | L48: =K54 -> 3498.8369 | M48: =L54 -> 3568.8137 | N48: =M54 -> 3640.19
B49: Comp Store Base Rev | D49: =D48*(1+D8) -> 4511.45 | E49: =E48*(1+E8) -> 4481.154 | F49: =F48*(1+F8) -> 3737.646 | G49: =G48*(1+G8) -> 3391.872 | H49: =H48*(1+H8) -> 3338.225 | I49: =I48*(1+I8) -> 3365.67 | J49: =J48*(1+J8) -> 3447.13 | K49: =K48*(1+K8) -> 3498.8369 | ... N49: =N48*(1+N8) -> 3712.9938
B50: New Store Rev
B51: Stores Opened during year | D51: ='Industry Metrics'!G22 -> 0 | E51: ='Industry Metrics'!F22 -> 0 | F51: ='Industry Metrics'!E25 -> 0 | G51: ='Industry Metrics'!D22 -> 1 | H51: ='Industry Metrics'!C22 -> 0 | I51: ='Industry Metrics'!B22 -> 0 | J51: =J26 -> 0 | K51: =K26 -> 0 | L51: =L26 -> 0 | M51: =M26 -> 0 | N51: =N26 -> 0
B52: Rev per New Store | D52: =SUM('Geographic Revenue'!F7:F9)/D29*50% -> 11.123077 | E52: =SUM('Geographic Revenue'!G7:G9)/E29*50% -> 12.045732 | F52: =SUM('Geographic Revenue'!H7:H9)/F29*50% -> 10.95 | G52: =SUM('Geographic Revenue'!I7:I9)/G29*50% -> 10.484375 | H52: =SUM('Geographic Revenue'!J7:J9)/H29*50% -> 10.28125 | I52: =SUM('Geographic Revenue'!K7:K9)/I29*50% -> 11.301325 | J52: =SUM('Geographic Revenue'!K7:K9)/I29*(1+J8)*50% -> 11.414338 | K52: =J54/J29*(1+K8)*50% -> 13.006829 | L52: =K54/K29*(1+L8)*50% -> 14.507373 | M52: =L54/L29*(1+M8)*50% -> 15.623133 | N52: =M54/M29*(1+N8)*50% -> 16.502194
B53: Total New Store Rev | D53: =D51*D52 -> 0 | E53: =E51*E52 -> 0 | F53: =F51*F52 -> 0 | G53: =G51*G52 -> 10.484375 | H53: =H51*H52 -> 0 | I53: =I51*I52 -> 0 | J53: =J51*J52 -> 0 | K53: =K51*K52 -> 0 | ... N53: =N51*N52 -> 0
B54: Total International Rev | D54: =D53+D49 -> 4511.45 | E54: =E53+E49 -> 4481.154 | F54: =F53+F49 -> 3737.646 | G54: =G53+G49 -> 3402.3564 | H54: =H53+H49 -> 3338.225 | I54: =I53+I49 -> 3365.67 | J54: =J53+J49 -> 3447.13 | K54: =K53+K49 -> 3498.8369 | ... N54: =N53+N49 -> 3712.9938
B55: Total Revenue | D55: =D45+D54 -> 48380.878 | E55: =E45+E54 -> 52851.214 | F55: =F45+F54 -> 46837.459 | G55: =G45+G54 -> 43467.532 | H55: =H45+H54 -> 42432.8 | I55: =I45+I54 -> 41756.622 | J55: =J45+J54 -> 42231.099 | K55: =K45+K54 -> 42993.072 | ... N55: =N45+N54 -> 45976.487
B57: Segment Revenue Build
B58: Segment Growth Rate Assumptions (%YoY)
B60: Computing & Mobile Phones | D60: ='Business Segment Revenue'!F28/100 -> 0.11619156 | E60: ='Business Segment Revenue'!G28/100 -> 0.03810096 | F60: ='Business Segment Revenue'!H28/100 -> -0.1206513 | G60: ='Business Segment Revenue'!I28/100 -> -0.06496003 | H60: ='Business Segment Revenue'!J28/100 -> 0.01076723 | I60: ='Business Segment Revenue'!K28/100 -> 0.05529683 | J60: 0.02 | K60: 0.04 | L60: 0.03 | M60: 0.02 | N60: 0.02 | O60: FY2027E +2.0%: AI PC upgrade cycle "sweet spot" 2026-27 (finterra/FinContent Mar 2026); memory cost inflation headwind (Q4 FY26 earnings call). FY2028E +4.0%: cycle peaks. Normalizes to +2% FY2029+
B61: Consumer Electronics | D61: ='Business Segment Revenue'!F29/100 -> -0.00566751 | E61: ='Business Segment Revenue'!G29/100 -> 0.1401731 | F61: ='Business Segment Revenue'!H29/100 -> -0.13016109 | G61: ='Business Segment Revenue'!I29/100 -> -0.0798212 | H61: ='Business Segment Revenue'!J29/100 -> -0.06970468 | I61: ='Business Segment Revenue'!K29/100 -> -0.05014505 | J61: -0.02 | K61: 0.015 | L61: 0.02 | M61: 0.02 | N61: 0.02 | O61: FY2027E -2.0%: TV units inflected positive but dollars still -ve (D.A. Davidson, BNN Bloomberg Nov 2025); home theater challenged. FY2028E +1.5%: dollar recovery. FY2029+ +2.0% as housing normalizes
B62: Appliances | D62: ='Business Segment Revenue'!F30/100 -> 0.22099792 | E62: ='Business Segment Revenue'!G30/100 -> 0.22033033 | F62: ='Business Segment Revenue'!H30/100 -> -0.06013674 | G62: ='Business Segment Revenue'!I30/100 -> -0.13836104 | H62: ='Business Segment Revenue'!J30/100 -> -0.15403171 | I62: ='Business Segment Revenue'!K30/100 -> -0.0898167 | J62: -0.05 | K62: 0 | L62: 0.025 | M62: 0.03 | N62: 0.03 | O62: FY2027E -5.0%: "structural shift toward duress replacements" (Q4 FY26 earnings call); HD/Lowes share pressure. FY2028E flat. FY2029+ +2.5-3.0%: HIRI ~4.4% appliance CAGR 2025-28; housing recovery
B63: Entertainment | D63: ='Business Segment Revenue'!F31/100 -> 0.18559877 | E63: ='Business Segment Revenue'!G31/100 -> 0.06365703 | F63: ='Business Segment Revenue'!H31/100 -> -0.06778626 | G63: ='Business Segment Revenue'!I31/100 -> 0.10153947 | H63: ='Business Segment Revenue'!J31/100 -> -0.13529587 | I63: ='Business Segment Revenue'!K31/100 -> 0.06327373 | J63: 0.03 | K63: 0.025 | L63: 0.02 | M63: 0.02 | N63: 0.02 | O63: FY2027E +3.0%: gaming console cycle; AI glasses/Meta partnership. Stable +2-2.5% FY2028+
B64: Services | D64: ='Business Segment Revenue'!F32/100 -> -0.03139785 | E64: ='Business Segment Revenue'!G32/100 -> 0.05683836 | F64: ='Business Segment Revenue'!H32/100 -> -0.02016807 | G64: ='Business Segment Revenue'!I32/100 -> 0.08490566 | H64: ='Business Segment Revenue'!J32/100 -> 0.03992095 | I64: ='Business Segment Revenue'!K32/100 -> 0.00950209 | J64: 0.04 | K64: 0.05 | L64: 0.05 | M64: 0.04 | N64: 0.04 | O64: FY2027E +4.0% / FY2028+ +5.0%: "material Ads & Marketplace contribution starting FY2028" (Q4 FY26 earnings call); My Best Buy membership; Geek Squad pivot. Eases to +4% FY2030+
B65: Other | D65: ='Business Segment Revenue'!F33/100 -> -0.09767442 | E65: ='Business Segment Revenue'!G33/100 -> 0.32989689 | F65: ='Business Segment Revenue'!H33/100 -> 0.22868217 | G65: ='Business Segment Revenue'!I33/100 -> -0.04100946 | H65: ='Business Segment Revenue'!J33/100 -> 0.09539474 | I65: ='Business Segment Revenue'!K33/100 -> -0.0990991 | J65: 0.08 | K65: 0.1 | L65: 0.08 | M65: 0.06 | N65: 0.05 | O65: FY2027E +8.0% / FY2028E +10.0%: Best Buy Ads $900M run-rate (FinContent 2026); Marketplace >1,100 sellers; FY2027 final investment year per mgmt. Moderates to +5% by FY2031E
B67: Segment Revenue ($M)
B68: Computing & Mobile Phones | D68: ='Business Segment Revenue'!F5 -> 21653 | E68: ='Business Segment Revenue'!G5 -> 22478 | F68: ='Business Segment Revenue'!H5 -> 19766 | G68: ='Business Segment Revenue'!I5 -> 18482 | H68: ='Business Segment Revenue'!J5 -> 18681 | I68: ='Business Segment Revenue'!K5 -> 19714 | J68: =I68*(1+J60) -> 20108.28 | K68: =J68*(1+K60) -> 20912.611 | L68: =K68*(1+L60) -> 21539.99 | M68: =L68*(1+M60) -> 21970.789 | N68: =M68*(1+N60) -> 22410.205
B69: Consumer Electronics | D69: ='Business Segment Revenue'!F6 -> 14211 | E69: ='Business Segment Revenue'!G6 -> 16203 | F69: ='Business Segment Revenue'!H6 -> 14094 | G69: ='Business Segment Revenue'!I6 -> 12969 | H69: ='Business Segment Revenue'!J6 -> 12065 | I69: ='Business Segment Revenue'!K6 -> 11460 | J69: =I69*(1+J61) -> 11230.8 | K69: =J69*(1+K61) -> 11399.262 | L69: =K69*(1+L61) -> 11627.247 | M69: =L69*(1+M61) -> 11859.792 | N69: =M69*(1+N61) -> 12096.988
B70: Appliances | D70: ='Business Segment Revenue'!F7 -> 5873 | E70: ='Business Segment Revenue'!G7 -> 7167 | F70: ='Business Segment Revenue'!H7 -> 6736 | G70: ='Business Segment Revenue'!I7 -> 5804 | H70: ='Business Segment Revenue'!J7 -> 4910 | I70: ='Business Segment Revenue'!K7 -> 4469 | J70: =I70*(1+J62) -> 4245.55 | K70: =J70*(1+K62) -> 4245.55 | L70: =K70*(1+L62) -> 4351.6888 | M70: =L70*(1+M62) -> 4482.2394 | N70: =M70*(1+N62) -> 4616.7066
B71: Entertainment | D71: ='Business Segment Revenue'!F8 -> 3079 | E71: ='Business Segment Revenue'!G8 -> 3275 | F71: ='Business Segment Revenue'!H8 -> 3053 | G71: ='Business Segment Revenue'!I8 -> 3363 | H71: ='Business Segment Revenue'!J8 -> 2908 | I71: ='Business Segment Revenue'!K8 -> 3092 | J71: =I71*(1+J63) -> 3184.76 | K71: =J71*(1+K63) -> 3264.379 | L71: =K71*(1+L63) -> 3329.6666 | M71: =L71*(1+M63) -> 3396.2599 | N71: =M71*(1+N63) -> 3464.1851
B72: Services | D72: ='Business Segment Revenue'!F9 -> 2252 | E72: ='Business Segment Revenue'!G9 -> 2380 | F72: ='Business Segment Revenue'!H9 -> 2332 | G72: ='Business Segment Revenue'!I9 -> 2530 | H72: ='Business Segment Revenue'!J9 -> 2631 | I72: ='Business Segment Revenue'!K9 -> 2656 | J72: =I72*(1+J64) -> 2762.24 | K72: =J72*(1+K64) -> 2900.352 | L72: =K72*(1+L64) -> 3045.3696 | M72: =L72*(1+M64) -> 3167.1844 | N72: =M72*(1+N64) -> 3293.8718
B73: Other | D73: ='Business Segment Revenue'!F10 -> 194 | E73: ='Business Segment Revenue'!G10 -> 258 | F73: ='Business Segment Revenue'!H10 -> 317 | G73: ='Business Segment Revenue'!I10 -> 304 | H73: ='Business Segment Revenue'!J10 -> 333 | I73: ='Business Segment Revenue'!K10 -> 300 | J73: =I73*(1+J65) -> 324 | K73: =J73*(1+K65) -> 356.4 | L73: =K73*(1+L65) -> 384.912 | M73: =L73*(1+M65) -> 408.00672 | N73: =M73*(1+N65) -> 428.40706
B74: Total Revenue from Segments | D74: =SUM(D68:D73) -> 47262 | E74: =SUM(E68:E73) -> 51761 | F74: =SUM(F68:F73) -> 46298 | G74: =SUM(G68:G73) -> 43452 | H74: =SUM(H68:H73) -> 41528 | I74: =SUM(I68:I73) -> 41691 | J74: =SUM(J68:J73) -> 41855.63 | K74: =SUM(K68:K73) -> 43078.554 | ... N74: =SUM(N68:N73) -> 46310.364
B76: % of Total Revenue
B77: Computing & Mobile Phones | D77: =D68/D74 -> 0.4581482 | E77: =E68/E74 -> 0.43426518 | F77: =F68/F74 -> 0.42692989 | G77: =G68/G74 -> 0.42534291 | H77: =H68/H74 -> 0.44984107 | I77: =I68/I74 -> 0.47285985 | J77: =J68/J74 -> 0.48041996 | K77: =K68/K74 -> 0.48545295 | ... N77: =N68/N74 -> 0.48391339
B78: Consumer Electronics | D78: =D69/D74 -> 0.30068554 | E78: =E69/E74 -> 0.31303491 | F78: =F69/F74 -> 0.3044192 | G78: =G69/G74 -> 0.29846727 | H78: =H69/H74 -> 0.29052687 | I78: =I69/I74 -> 0.27487947 | J78: =J69/J74 -> 0.26832233 | K78: =K69/K74 -> 0.26461571 | ... N78: =N69/N74 -> 0.26121557
B79: Appliances | D79: =D70/D74 -> 0.12426474 | E79: =E70/E74 -> 0.13846332 | F79: =F70/F74 -> 0.14549225 | G79: =G70/G74 -> 0.13357268 | H79: =H70/H74 -> 0.11823348 | I79: =I70/I74 -> 0.1071934 | J79: =J70/J74 -> 0.10143319 | K79: =K70/K74 -> 0.098553679 | ... N79: =N70/N74 -> 0.099690571
B80: Entertainment | D80: =D71/D74 -> 0.065147476 | E80: =E71/E74 -> 0.063271575 | F80: =F71/F74 -> 0.065942373 | G80: =G71/G74 -> 0.077395747 | H80: =H71/H74 -> 0.070025043 | I80: =I71/I74 -> 0.074164688 | J80: =J71/J74 -> 0.076089166 | K80: =K71/K74 -> 0.075777357 | ... N80: =N71/N74 -> 0.074803669
B81: Services | D81: =D72/D74 -> 0.047649274 | E81: =E72/E74 -> 0.045980565 | F81: =F72/F74 -> 0.050369346 | G81: =G72/G74 -> 0.058225168 | H81: =H72/H74 -> 0.063354845 | I81: =I72/I74 -> 0.063706795 | J81: =J72/J74 -> 0.065994467 | K81: =K72/K74 -> 0.067327051 | ... N81: =N72/N74 -> 0.071126018
B82: Other | D82: =D73/D74 -> 0.0041047776 | E82: =E73/E74 -> 0.0049844478 | F82: =F73/F74 -> 0.006846948 | G82: =G73/G74 -> 0.0069962257 | H82: =H73/H74 -> 0.0080186862 | I82: =I73/I74 -> 0.0071957977 | J82: =J73/J74 -> 0.0077408941 | K82: =K73/K74 -> 0.0082732582 | ... N82: =N73/N74 -> 0.0092507815
B84: Reconciliation: Segment vs. Geographic Build
B85: Total Rev Segment Build | D85: =D74 -> 47262 | E85: =E74 -> 51761 | F85: =F74 -> 46298 | G85: =G74 -> 43452 | H85: =H74 -> 41528 | I85: =I74 -> 41691 | J85: =J74 -> 41855.63 | K85: =K74 -> 43078.554 | ... N85: =N74 -> 46310.364
B86: Comp-Store Geographic Build | D86: =D45+D54 -> 48380.878 | E86: =E45+E54 -> 52851.214 | F86: =F45+F54 -> 46837.459 | G86: =G45+G54 -> 43467.532 | H86: =H45+H54 -> 42432.8 | I86: =I45+I54 -> 41756.622 | J86: =J45+J54 -> 42231.099 | K86: =K45+K54 -> 42993.072 | ... N86: =N45+N54 -> 45976.487
B87: Difference ($M) Comp-Store minus Segment | D87: =D86-D85 -> 1118.8775 | E87: =E86-E85 -> 1090.2144 | F87: =F86-F85 -> 539.45875 | G87: =G86-G85 -> 15.53204 | H87: =H86-H85 -> 904.8 | I87: =I86-I85 -> 65.622 | J87: =J86-J85 -> 375.46889 | K87: =K86-K85 -> -85.48264 | ... N87: =N86-N85 -> -333.87631
B88: Difference (%) | D88: =IFERROR(D87/D85,0) -> 0.023673935 | E88: =IFERROR(E87/E85,0) -> 0.021062467 | F88: =IFERROR(F87/F85,0) -> 0.01165188 | G88: =IFERROR(G87/G85,0) -> 0.00035745283 | H88: =IFERROR(H87/H85,0) -> 0.021787709 | I88: =IFERROR(I87/I85,0) -> 0.0015740088 | J88: =IFERROR(J87/J85,0) -> 0.0089705707 | K88: =IFERROR(K87/K85,0) -> -0.0019843433 | ... N88: =IFERROR(N87/N85,0) -> -0.0072095376

Sheet Historical Data ==>
A1: Historical Data

Sheet Geographic Revenue
A1: BBY-US
A2: Sales
B3: JAN '17 | C3: JAN '18 | D3: JAN '19 | E3: JAN '20 | F3: JAN '21 | G3: JAN '22 | H3: JAN '23 | I3: JAN '24 | J3: JAN '25 | K3: JAN '26
B4: 364 Days | C4: 371 Days | D4: 364 Days | E4: 364 Days | F4: 364 Days | G4: 364 Days | H4: 364 Days | I4: 371 Days | J4: 364 Days | K4: 364 Days
A5: Total | B5: =SUM(B6:B8) -> 39403 | C5: =SUM(C6:C8) -> 42151 | D5: =SUM(D6:D8) -> 42879 | E5: =SUM(E6:E8) -> 43638 | F5: =SUM(F6:F8) -> 47262 | G5: =SUM(G6:G8) -> 51761 | H5: =SUM(H6:H8) -> 46298 | I5: =SUM(I6:I8) -> 43452 | ... K5: =SUM(K6:K8) -> 41691
A6: United States | B6: 36248 | C6: 38662 | D6: 39304 | E6: 40114 | F6: 43293 | G6: 47830 | H6: 42794 | I6: 40097 | J6: 38238 | K6: 38278
A7: Canada | B7: 2899 | C7: 3187 | D7: 3214 | E7: 3125 | F7: 3600 | G7: 3911 | H7: 3504 | I7: 3355 | J7: 3290 | K7: 3413
A8: Historical Segments | B8: 256 | C8: 302 | D8: 361 | E8: 399 | F8: 369 | G8: 20 | H8: - | I8: - | J8: - | K8: -
A9: Other | B9: 256 | C9: 302 | D9: 361 | E9: 399 | F9: 369 | G9: 20 | H9: - | I9: - | J9: - | K9: -
A10: All figures in millions of U.S. Dollar
A12: Percent of Total (%)
B13: JAN '17 | C13: JAN '18 | D13: JAN '19 | E13: JAN '20 | F13: JAN '21 | G13: JAN '22 | H13: JAN '23 | I13: JAN '24 | J13: JAN '25 | K13: JAN '26
A14: Total | B14: 100 | C14: 99.999994 | D14: 99.999997 | E14: 100 | F14: 100 | G14: 100 | H14: 100 | I14: 100 | J14: 100 | K14: 100
A15: United States | B15: 91.992996 | C15: 91.72261 | D15: 91.662582 | E15: 91.924469 | F15: 91.602135 | G15: 92.405479 | H15: 92.431641 | I15: 92.278839 | J15: 92.077637 | K15: 91.813583
A16: Canada | B16: 7.357307 | C16: 7.560912 | D16: 7.495511 | E16: 7.16119 | F16: 7.617113 | G16: 7.555882 | H16: 7.568362 | I16: 7.721163 | J16: 7.922366 | K16: 8.186419
A17: Historical Segments | B17: 0.649697 | C17: 0.716472 | D17: 0.841904 | E17: 0.914341 | F17: 0.780754 | G17: 0.038639 | H17: - | I17: - | J17: - | K17: -
A18: Other | B18: 0.649697 | C18: 0.716472 | D18: 0.841904 | E18: 0.914341 | F18: 0.780754 | G18: 0.038639 | H18: - | I18: - | J18: - | K18: -
A20: Growth (%)
B21: JAN '17 | C21: JAN '18 | D21: JAN '19 | E21: JAN '20 | F21: JAN '21 | G21: JAN '22 | H21: JAN '23 | I21: JAN '24 | J21: JAN '25 | K21: JAN '26
A22: Total | B22: -0.316232 | C22: 6.97409 | D22: 1.72712 | E22: 1.7701 | F22: 8.30469 | G22: 9.51928 | H22: -10.5543 | I22: -6.14713 | J22: -4.42787 | K22: 0.392506
A23: United States | B23: -0.321738 | C23: 6.659678 | D23: 1.660545 | E23: 2.060859 | F23: 7.924914 | G23: 10.479754 | H23: -10.528956 | I23: -6.302285 | J23: -4.636257 | K23: 0.104608
A24: Canada | B24: -0.617072 | C24: 9.93446 | D24: 0.847192 | E24: -2.769135 | F24: 15.2 | G24: 8.638889 | H24: -10.406546 | I24: -4.252283 | J24: -1.937407 | K24: 3.738602
A25: Historical Segments | B25: 4.06504 | C25: 17.9688 | D25: 19.5364 | E25: 10.5263 | F25: -7.5188 | G25: -94.5799 | H25: - | I25: - | J25: - | K25: -
A26: Other | B26: 4.065041 | C26: 17.96875 | D26: 19.536425 | E26: 10.526316 | F26: -7.518797 | G26: -94.579948 | H26: - | I26: - | J26: - | K26: -

Sheet Revenue Build - Top Down
B1: Revenue forecast - using top down approach
B3: Description | C3: Units | D3: 2021A | E3: 2022A | F3: 2023A | G3: 2024A | H3: 2025A | I3: 2026A | J3: 2027E | K3: 2028E | L3: 2029E | M3: 2030E | N3: 2031E
B4: Key Revenue Drivers Based on Assumptions
B5: Store Sales
B6: Total Comparable Sales Growth | C6: % | D6: ='Industry Metrics'!G3 -> 0.097 | E6: ='Industry Metrics'!F3 -> 0.104 | F6: ='Industry Metrics'!E3 -> -0.099 | G6: ='Industry Metrics'!D3 -> -0.068 | H6: ='Industry Metrics'!C3 -> -0.023 | I6: ='Industry Metrics'!B3 -> 0.005 | J6: =Assumptions!B6 -> 0.01 | K6: =Assumptions!C6 -> 0.015 | L6: =Assumptions!D6 -> 0.02 | M6: =Assumptions!E6 -> 0.02 | N6: =Assumptions!F6 -> 0.02
B7: Domestic Comparable Sales Growth | C7: % | D7: ='Industry Metrics'!G4 -> 0.092 | E7: ='Industry Metrics'!F4 -> 0.11 | F7: ='Industry Metrics'!E4 -> -0.103 | G7: ='Industry Metrics'!D4 -> -0.071 | H7: ='Industry Metrics'!C4 -> -0.025 | I7: ='Industry Metrics'!B4 -> 0.004 | J7: =Assumptions!B7 -> 0.01 | K7: =Assumptions!C7 -> 0.015 | L7: =Assumptions!D7 -> 0.02 | M7: =Assumptions!E7 -> 0.02 | N7: =Assumptions!F7 -> 0.02
B8: International Comparable Sales Growth | C8: % | D8: ='Industry Metrics'!G5 -> 0.15 | E8: ='Industry Metrics'!F5 -> 0.033 | F8: ='Industry Metrics'!E5 -> -0.054 | G8: ='Industry Metrics'!D5 -> -0.032 | H8: ='Industry Metrics'!C5 -> -0.005 | I8: ='Industry Metrics'!B5 -> 0.023 | J8: =Assumptions!B8 -> 0.01 | K8: =Assumptions!C8 -> 0.015 | L8: =Assumptions!D8 -> 0.02 | M8: =Assumptions!E8 -> 0.02 | N8: =Assumptions!F8 -> 0.02
B9: Online Revenue as % of Domestic Rev | C9: % | D9: ='Industry Metrics'!G9 -> 0.33 | E9: ='Industry Metrics'!F9 -> 0.36 | F9: ='Industry Metrics'!E9 -> 0.34 | G9: ='Industry Metrics'!D9 -> 0.38 | H9: ='Industry Metrics'!C9 -> 0.395 | I9: ='Industry Metrics'!B9 -> 0.39 | J9: =Assumptions!B9 -> 0.4 | K9: =Assumptions!C9 -> 0.41 | L9: =Assumptions!D9 -> 0.42 | M9: =Assumptions!E9 -> 0.43 | N9: =Assumptions!F9 -> 0.44
B10: Total Store Count
B11: Beginning Store Count | C11: # | D11: ='Industry Metrics'!G12 -> 1231 | E11: ='Industry Metrics'!F12 -> 1159 | F11: ='Industry Metrics'!E12 -> 1144 | G11: ='Industry Metrics'!D12 -> 1138 | H11: ='Industry Metrics'!C12 -> 1125 | I11: ='Industry Metrics'!B12 -> 1117 | J11: =I14 -> 1068 | K11: =J14 -> 1056 | L11: =K14 -> 1044 | M11: =L14 -> 1033 | N11: =M14 -> 1023
B12: Stores Opened | C12: # | D12: ='Industry Metrics'!G19 -> 3 | E12: ='Industry Metrics'!F19 -> 13 | F12: ='Industry Metrics'!E19 -> 9 | G12: ='Industry Metrics'!D20 -> 15 | H12: ='Industry Metrics'!C19 -> 0 | I12: ='Industry Metrics'!B20 -> 0 | J12: =Assumptions!B11 -> 6 | K12: =Assumptions!C11 -> 6 | L12: =Assumptions!D11 -> 5 | M12: =Assumptions!E11 -> 5 | N12: =Assumptions!F11 -> 5
B13: Stores Closed | C13: # | D13: ='Industry Metrics'!G23 -> 75 | E13: ='Industry Metrics'!F23 -> 28 | F13: ='Industry Metrics'!E23 -> 15 | G13: ='Industry Metrics'!D23 -> 28 | H13: ='Industry Metrics'!C23 -> 8 | I13: ='Industry Metrics'!B23 -> 49 | J13: =Assumptions!B12 -> 18 | K13: =Assumptions!C12 -> 18 | L13: =Assumptions!D12 -> 16 | M13: =Assumptions!E12 -> 15 | N13: =Assumptions!F12 -> 15
B14: Ending Store Count | C14: # | D14: =D11+D12-D13 -> 1159 | E14: =E11+E12-E13 -> 1144 | F14: =F11+F12-F13 -> 1138 | G14: =G11+G12-G13 -> 1125 | H14: =H11+H12-H13 -> 1117 | I14: =I11+I12-I13 -> 1068 | J14: =J11+J12-J13 -> 1056 | K14: =K11+K12-K13 -> 1044 | ... N14: =N11+N12-N13 -> 1013
B15: Average Store Count | C15: # | D15: =(D11+D14)/2 -> 1195 | E15: =(E11+E14)/2 -> 1151.5 | F15: =(F11+F14)/2 -> 1141 | G15: =(G11+G14)/2 -> 1131.5 | H15: =(H11+H14)/2 -> 1121 | I15: =(I11+I14)/2 -> 1092.5 | J15: =(J11+J14)/2 -> 1062 | K15: =(K11+K14)/2 -> 1050 | ... N15: =(N11+N14)/2 -> 1018
B16: Domestic Store Count | C16: #
B17: Beginning Store Count | C17: # | D17: ='Industry Metrics'!G13 -> 1009 | E17: ='Industry Metrics'!F13 -> 991 | F17: ='Industry Metrics'!E13 -> 984 | G17: ='Industry Metrics'!D13 -> 978 | H17: ='Industry Metrics'!C13 -> 965 | I17: ='Industry Metrics'!B13 -> 957 | J17: =I20 -> 926 | K17: =J20 -> 917 | L17: =K20 -> 908 | M17: =L20 -> 899 | N17: =M20 -> 891
B18: Stores Opened | C18: # | D18: ='Industry Metrics'!G21 -> 3 | E18: ='Industry Metrics'!F21 -> 13 | F18: ='Industry Metrics'!E21 -> 9 | G18: ='Industry Metrics'!D21 -> 14 | H18: ='Industry Metrics'!C21 -> 0 | I18: ='Industry Metrics'!B21 -> 0 | J18: =Assumptions!B13 -> 6 | K18: =Assumptions!C13 -> 6 | L18: =Assumptions!D13 -> 5 | M18: =Assumptions!E13 -> 5 | N18: =Assumptions!F13 -> 5
B19: Stores Closed | C19: # | D19: ='Industry Metrics'!G24 -> 21 | E19: ='Industry Metrics'!F24 -> 20 | F19: ='Industry Metrics'!E24 -> 15 | G19: ='Industry Metrics'!D24 -> 27 | H19: ='Industry Metrics'!C24 -> 8 | I19: ='Industry Metrics'!B24 -> 31 | J19: =Assumptions!B14 -> 15 | K19: =Assumptions!C14 -> 15 | L19: =Assumptions!D14 -> 14 | M19: =Assumptions!E14 -> 13 | N19: =Assumptions!F14 -> 13
B20: Ending Store Count | C20: # | D20: =D17+D18-D19 -> 991 | E20: =E17+E18-E19 -> 984 | F20: =F17+F18-F19 -> 978 | G20: =G17+G18-G19 -> 965 | H20: =H17+H18-H19 -> 957 | I20: =I17+I18-I19 -> 926 | J20: =J17+J18-J19 -> 917 | K20: =K17+K18-K19 -> 908 | ... N20: =N17+N18-N19 -> 883
B21: Average Store Count | C21: # | D21: =(D17+D20)/2 -> 1000 | E21: =(E17+E20)/2 -> 987.5 | F21: =(F17+F20)/2 -> 981 | G21: =(G17+G20)/2 -> 971.5 | H21: =(H17+H20)/2 -> 961 | I21: =(I17+I20)/2 -> 941.5 | J21: =(J17+J20)/2 -> 921.5 | K21: =(K17+K20)/2 -> 912.5 | ... N21: =(N17+N20)/2 -> 887
B22: International Store Count | C22: #
B23: Beginning Store Count | C23: # | D23: ='Industry Metrics'!G14 -> 222 | E23: ='Industry Metrics'!F14 -> 168 | F23: ='Industry Metrics'!E14 -> 160 | G23: ='Industry Metrics'!D14 -> 160 | H23: ='Industry Metrics'!C14 -> 160 | I23: ='Industry Metrics'!B14 -> 160 | J23: =I26 -> 142 | K23: =J26 -> 139 | L23: =K26 -> 136 | M23: =L26 -> 134 | N23: =M26 -> 132
B24: Stores Opened | C24: # | D24: ='Industry Metrics'!G22 -> 0 | E24: ='Industry Metrics'!F22 -> 0 | F24: ='Industry Metrics'!E25 -> 0 | G24: ='Industry Metrics'!D25 -> 1 | H24: ='Industry Metrics'!C25 -> 0 | I24: ='Industry Metrics'!B22 -> 0 | J24: =Assumptions!B15 -> 0 | K24: =Assumptions!C15 -> 0 | L24: =Assumptions!D15 -> 0 | M24: =Assumptions!E15 -> 0 | N24: =Assumptions!F15 -> 0
B25: Stores Closed | C25: # | D25: ='Industry Metrics'!G25 -> 54 | E25: ='Industry Metrics'!F25 -> 8 | F25: ='Industry Metrics'!E25 -> 0 | G25: ='Industry Metrics'!D25 -> 1 | H25: ='Industry Metrics'!C25 -> 0 | I25: ='Industry Metrics'!B25 -> 18 | J25: =Assumptions!B16 -> 3 | K25: =Assumptions!C16 -> 3 | L25: =Assumptions!D16 -> 2 | M25: =Assumptions!E16 -> 2 | N25: =Assumptions!F16 -> 2
B26: Ending Store Count | C26: # | D26: =D23+D24-D25 -> 168 | E26: =E23+E24-E25 -> 160 | F26: =F23+F24-F25 -> 160 | G26: =G23+G24-G25 -> 160 | H26: =H23+H24-H25 -> 160 | I26: =I23+I24-I25 -> 142 | J26: =J23+J24-J25 -> 139 | K26: =K23+K24-K25 -> 136 | ... N26: =N23+N24-N25 -> 130
B27: Average Store Count | C27: # | D27: =(D23+D26)/2 -> 195 | E27: =(E23+E26)/2 -> 164 | F27: =(F23+F26)/2 -> 160 | G27: =(G23+G26)/2 -> 160 | H27: =(H23+H26)/2 -> 160 | I27: =(I23+I26)/2 -> 151 | J27: =(J23+J26)/2 -> 140.5 | K27: =(K23+K26)/2 -> 137.5 | ... N27: =(N23+N26)/2 -> 131
B28: Revenue Per Store
B29: Domestic Rev per Avg. Store (in millions USD) | C29: $ | D29: ='Geographic Revenue'!F6/D21 -> 43.293 | E29: ='Geographic Revenue'!G6/E21 -> 48.435443 | F29: ='Geographic Revenue'!H6/F21 -> 43.622834 | G29: ='Geographic Revenue'!I6/G21 -> 41.273289 | H29: ='Geographic Revenue'!J6/H21 -> 39.789802 | I29: ='Geographic Revenue'!K6/I21 -> 40.656399 | J29: =J43/J21 -> 42.087866 | K29: =K43/K21 -> 43.280971 | L29: =L43/L21 -> 44.7085 | M29: =M43/M21 -> 46.16315 | N29: =N43/N21 -> 47.643806
B30: Y/Y Growth Domestic Rev per Store | C30: % | E30: =E29/D29-1 -> 0.11878232 | F30: =F29/E29-1 -> -0.099361313 | G30: =G29/F29-1 -> -0.053860442 | H30: =H29/G29-1 -> -0.035943015 | I30: =I29/H29-1 -> 0.021779376 | J30: =J29/I29-1 -> 0.035208899 | K30: =K29/J29-1 -> 0.028347945 | L30: =L29/K29-1 -> 0.032982844 | ... N30: =N29/M29-1 -> 0.032074408
B31: International Rev per Avg. Store (in millions USD) | C31: $ | D31: =SUM('Geographic Revenue'!F7:F9)/D27 -> 22.246154 | E31: =SUM('Geographic Revenue'!G7:G9)/E27 -> 24.091463 | F31: =SUM('Geographic Revenue'!H7:H9)/F27 -> 21.9 | G31: =SUM('Geographic Revenue'!I7:I9)/G27 -> 20.96875 | H31: =SUM('Geographic Revenue'!J7:J9)/H27 -> 20.5625 | I31: =SUM('Geographic Revenue'!K7:K9)/I27 -> 22.602649 | J31: =J51/J27 -> 24.534733 | K31: =K51/K27 -> 25.446087 | L31: =L51/L27 -> 26.435657 | M31: =M51/M27 -> 27.369849 | N31: =N51/N27 -> 28.343464
B32: Y/Y Growth International Rev per Store | C32: % | E32: =E31/D31-1 -> 0.0829496 | F32: =F31/E31-1 -> -0.090964313 | G32: =G31/F31-1 -> -0.042522831 | H32: =H31/G31-1 -> -0.019374069 | I32: =I31/H31-1 -> 0.099216973 | J32: =J31/I31-1 -> 0.085480427 | K32: =K31/J31-1 -> 0.037145455 | L32: =L31/K31-1 -> 0.038888889 | ... N32: =N31/M31-1 -> 0.035572519
B34: Revenue Build
B35: Domestic Revenue Build (in millions USD)
B36: Comparable Store Rev
B37: Prior Year Domestic Revenue | C37: $ | D37: ='Geographic Revenue'!E6 -> 40114 | E37: ='Geographic Revenue'!F6 -> 43293 | F37: ='Geographic Revenue'!G6 -> 47830 | G37: ='Geographic Revenue'!H6 -> 42794 | H37: ='Geographic Revenue'!I6 -> 40097 | I37: ='Geographic Revenue'!J6 -> 38238 | J37: ='Geographic Revenue'!K6 -> 38278 | K37: =J43 -> 38783.969 | L37: =K43 -> 39493.886 | M37: =L43 -> 40394.13 | N37: =M43 -> 41316.019
B38: Comp Store Base Rev | C38: $ | D38: =D37*(1+D7) -> 43804.488 | E38: =E37*(1+E7) -> 48055.23 | F38: =F37*(1+F7) -> 42903.51 | G38: =G37*(1+G7) -> 39755.626 | H38: =H37*(1+H7) -> 39094.575 | I38: =I37*(1+I7) -> 38390.952 | J38: =J37*(1+J7) -> 38660.78 | K38: =K37*(1+K7) -> 39365.728 | ... N38: =N37*(1+N7) -> 42142.34
B39: New Store Rev
B40: Stores Opened during year | C40: # | D40: ='Industry Metrics'!G19 -> 3 | E40: ='Industry Metrics'!F19 -> 13 | F40: ='Industry Metrics'!E19 -> 9 | G40: ='Industry Metrics'!D19 -> 15 | H40: ='Industry Metrics'!C19 -> 0 | I40: ='Industry Metrics'!B20 -> 0 | J40: =J18 -> 6 | K40: =K18 -> 6 | L40: =L18 -> 5 | M40: =M18 -> 5 | N40: =N18 -> 5
B41: Rev per New Store | C41: # | D41: ='Geographic Revenue'!F6/'Revenue Build - Top Down'!D21*50% -> 21.6465 | E41: ='Geographic Revenue'!G6/'Revenue Build - Top Down'!E21*50% -> 24.217722 | F41: ='Geographic Revenue'!H6/'Revenue Build - Top Down'!F21*50% -> 21.811417 | G41: ='Geographic Revenue'!I6/'Revenue Build - Top Down'!G21*50% -> 20.636644 | H41: ='Geographic Revenue'!J6/'Revenue Build - Top Down'!H21*50% -> 19.894901 | I41: ='Geographic Revenue'!K6/'Revenue Build - Top Down'!I21*50% -> 20.3282 | J41: ='Geographic Revenue'!K6/I21*(1+J7)*50% -> 20.531482 | K41: =J43/J21*(1+K7)*50% -> 21.359592 | L41: =K43/K21*(1+L7)*50% -> 22.073295 | M41: =L43/L21*(1+M7)*50% -> 22.801335 | N41: =M43/M21*(1+N7)*50% -> 23.543207
B42: Total new Store Rev | C42: # | D42: =D40*D41 -> 64.9395 | E42: =E40*E41 -> 314.83038 | F42: =F40*F41 -> 196.30275 | G42: =G40*G41 -> 309.54967 | H42: =H40*H41 -> 0 | I42: =I40*I41 -> 0 | J42: =J40*J41 -> 123.18889 | K42: =K40*K41 -> 128.15755 | ... N42: =N40*N41 -> 117.71603
B43: Total Domestic Rev | C43: $ | D43: =D42+D38 -> 43869.428 | E43: =E42+E38 -> 48370.06 | F43: =F42+F38 -> 43099.813 | G43: =G42+G38 -> 40065.176 | H43: =H42+H38 -> 39094.575 | I43: =I42+I38 -> 38390.952 | J43: =J42+J38 -> 38783.969 | K43: =K42+K38 -> 39493.886 | ... N43: =N42+N38 -> 42260.056
B44: International Revenue Build (in millions USD)
B45: Prior Year International Rev | C45: $ | D45: =SUM('Geographic Revenue'!E7:E9) -> 3923 | E45: =SUM('Geographic Revenue'!F7:F9) -> 4338 | F45: =SUM('Geographic Revenue'!G7:G9) -> 3951 | G45: =SUM('Geographic Revenue'!H7:H9) -> 3504 | H45: =SUM('Geographic Revenue'!I7:I9) -> 3355 | I45: =SUM('Geographic Revenue'!J7:J9) -> 3290 | J45: =SUM('Geographic Revenue'!K7:K9) -> 3413 | K45: =J51 -> 3447.13 | L45: =K51 -> 3498.8369 | M45: =L51 -> 3568.8137 | N45: =M51 -> 3640.19
B46: Comp Store Base Rev | C46: $ | D46: =D45*(1+D8) -> 4511.45 | E46: =E45*(1+E8) -> 4481.154 | F46: =F45*(1+F8) -> 3737.646 | G46: =G45*(1+G8) -> 3391.872 | H46: =H45*(1+H8) -> 3338.225 | I46: =I45*(1+I8) -> 3365.67 | J46: =J45*(1+J8) -> 3447.13 | K46: =K45*(1+K8) -> 3498.8369 | ... N46: =N45*(1+N8) -> 3712.9938
B47: New Store Rev
B48: Stores Opened during year | C48: # | D48: ='Industry Metrics'!G22 -> 0 | E48: ='Industry Metrics'!F22 -> 0 | F48: ='Industry Metrics'!E25 -> 0 | G48: ='Industry Metrics'!D22 -> 1 | H48: ='Industry Metrics'!C22 -> 0 | I48: ='Industry Metrics'!B22 -> 0 | J48: =J24 -> 0 | K48: =K24 -> 0 | L48: =L24 -> 0 | M48: =M24 -> 0 | N48: =N24 -> 0
B49: Rev per New Store | C49: $ | D49: =SUM('Geographic Revenue'!F7:F9)/D27*50% -> 11.123077 | E49: =SUM('Geographic Revenue'!G7:G9)/E27*50% -> 12.045732 | F49: =SUM('Geographic Revenue'!H7:H9)/F27*50% -> 10.95 | G49: =SUM('Geographic Revenue'!I7:I9)/G27*50% -> 10.484375 | H49: =SUM('Geographic Revenue'!J7:J9)/H27*50% -> 10.28125 | I49: =SUM('Geographic Revenue'!K7:K9)/I27*50% -> 11.301325 | J49: =SUM('Geographic Revenue'!K7:K9)/I27*(1+J8)*50% -> 11.414338 | K49: =J51/J27*(1+K8)*50% -> 12.451377 | L49: =K51/K27*(1+L8)*50% -> 12.977504 | M49: =L51/L27*(1+M8)*50% -> 13.482185 | N49: =M51/M27*(1+N8)*50% -> 13.958623
B50: Total New Store Rev | C50: $ | D50: =D48*D49 -> 0 | E50: =E48*E49 -> 0 | F50: =F48*F49 -> 0 | G50: =G48*G49 -> 10.484375 | H50: =H48*H49 -> 0 | I50: =I48*I49 -> 0 | J50: =J48*J49 -> 0 | K50: =K48*K49 -> 0 | ... N50: =N48*N49 -> 0
B51: Total International Rev | C51: $ | D51: =D50+D46 -> 4511.45 | E51: =E50+E46 -> 4481.154 | F51: =F50+F46 -> 3737.646 | G51: =G50+G46 -> 3402.3564 | H51: =H50+H46 -> 3338.225 | I51: =I50+I46 -> 3365.67 | J51: =J50+J46 -> 3447.13 | K51: =K50+K46 -> 3498.8369 | ... N51: =N50+N46 -> 3712.9938
B52: Total Revenue (in millions USD) | C52: $ | D52: =D43+D51 -> 48380.878 | E52: =E43+E51 -> 52851.214 | F52: =F43+F51 -> 46837.459 | G52: =G43+G51 -> 43467.532 | H52: =H43+H51 -> 42432.8 | I52: =I43+I51 -> 41756.622 | J52: =J43+J51 -> 42231.099 | K52: =K43+K51 -> 42992.723 | ... N52: =N43+N51 -> 45973.05
B54: Segment Revenue Build
B55: Segment Growth Rate Assumptions (%YoY)
B56: Computing & Mobile Phones | C56: % | D56: ='Business Segment Revenue'!F28/100 -> 0.11619156 | E56: ='Business Segment Revenue'!G28/100 -> 0.03810096 | F56: ='Business Segment Revenue'!H28/100 -> -0.1206513 | G56: ='Business Segment Revenue'!I28/100 -> -0.06496003 | H56: ='Business Segment Revenue'!J28/100 -> 0.01076723 | I56: ='Business Segment Revenue'!K28/100 -> 0.05529683 | J56: =Assumptions!B18 -> 0.02 | K56: =Assumptions!C18 -> 0.04 | L56: =Assumptions!D18 -> 0.03 | M56: =Assumptions!E18 -> 0.02 | N56: =Assumptions!F18 -> 0.02
B57: Consumer Electronics | C57: % | D57: ='Business Segment Revenue'!F29/100 -> -0.00566751 | E57: ='Business Segment Revenue'!G29/100 -> 0.1401731 | F57: ='Business Segment Revenue'!H29/100 -> -0.13016109 | G57: ='Business Segment Revenue'!I29/100 -> -0.0798212 | H57: ='Business Segment Revenue'!J29/100 -> -0.06970468 | I57: ='Business Segment Revenue'!K29/100 -> -0.05014505 | J57: =Assumptions!B19 -> -0.02 | K57: =Assumptions!C19 -> 0.015 | L57: =Assumptions!D19 -> 0.02 | M57: =Assumptions!E19 -> 0.02 | N57: =Assumptions!F19 -> 0.02
B58: Appliances | C58: % | D58: ='Business Segment Revenue'!F30/100 -> 0.22099792 | E58: ='Business Segment Revenue'!G30/100 -> 0.22033033 | F58: ='Business Segment Revenue'!H30/100 -> -0.06013674 | G58: ='Business Segment Revenue'!I30/100 -> -0.13836104 | H58: ='Business Segment Revenue'!J30/100 -> -0.15403171 | I58: ='Business Segment Revenue'!K30/100 -> -0.0898167 | J58: =Assumptions!B20 -> -0.05 | K58: =Assumptions!C20 -> 0 | L58: =Assumptions!D20 -> 0.025 | M58: =Assumptions!E20 -> 0.03 | N58: =Assumptions!F20 -> 0.03
B59: Entertainment | C59: % | D59: ='Business Segment Revenue'!F31/100 -> 0.18559877 | E59: ='Business Segment Revenue'!G31/100 -> 0.06365703 | F59: ='Business Segment Revenue'!H31/100 -> -0.06778626 | G59: ='Business Segment Revenue'!I31/100 -> 0.10153947 | H59: ='Business Segment Revenue'!J31/100 -> -0.13529587 | I59: ='Business Segment Revenue'!K31/100 -> 0.06327373 | J59: =Assumptions!B21 -> 0.03 | K59: =Assumptions!C21 -> 0.025 | L59: =Assumptions!D21 -> 0.02 | M59: =Assumptions!E21 -> 0.02 | N59: =Assumptions!F21 -> 0.02
B60: Services | C60: % | D60: ='Business Segment Revenue'!F32/100 -> -0.03139785 | E60: ='Business Segment Revenue'!G32/100 -> 0.05683836 | F60: ='Business Segment Revenue'!H32/100 -> -0.02016807 | G60: ='Business Segment Revenue'!I32/100 -> 0.08490566 | H60: ='Business Segment Revenue'!J32/100 -> 0.03992095 | I60: ='Business Segment Revenue'!K32/100 -> 0.00950209 | J60: =Assumptions!B22 -> 0.04 | K60: =Assumptions!C22 -> 0.05 | L60: =Assumptions!D22 -> 0.05 | M60: =Assumptions!E22 -> 0.04 | N60: =Assumptions!F22 -> 0.04
B61: Other | C61: % | D61: ='Business Segment Revenue'!F33/100 -> -0.09767442 | E61: ='Business Segment Revenue'!G33/100 -> 0.32989689 | F61: ='Business Segment Revenue'!H33/100 -> 0.22868217 | G61: ='Business Segment Revenue'!I33/100 -> -0.04100946 | H61: ='Business Segment Revenue'!J33/100 -> 0.09539474 | I61: ='Business Segment Revenue'!K33/100 -> -0.0990991 | J61: =Assumptions!B23 -> 0.08 | K61: =Assumptions!C23 -> 0.1 | L61: =Assumptions!D23 -> 0.08 | M61: =Assumptions!E23 -> 0.06 | N61: =Assumptions!F23 -> 0.05
B62: Segment Revenue (in millions USD)
B63: Computing & Mobile Phones | C63: $ | D63: ='Business Segment Revenue'!F5 -> 21653 | E63: ='Business Segment Revenue'!G5 -> 22478 | F63: ='Business Segment Revenue'!H5 -> 19766 | G63: ='Business Segment Revenue'!I5 -> 18482 | H63: ='Business Segment Revenue'!J5 -> 18681 | I63: ='Business Segment Revenue'!K5 -> 19714 | J63: =I63*(1+J56) -> 20108.28 | K63: =J63*(1+K56) -> 20912.611 | L63: =K63*(1+L56) -> 21539.99 | M63: =L63*(1+M56) -> 21970.789 | N63: =M63*(1+N56) -> 22410.205
B64: Consumer Electronics | C64: $ | D64: ='Business Segment Revenue'!F6 -> 14211 | E64: ='Business Segment Revenue'!G6 -> 16203 | F64: ='Business Segment Revenue'!H6 -> 14094 | G64: ='Business Segment Revenue'!I6 -> 12969 | H64: ='Business Segment Revenue'!J6 -> 12065 | I64: ='Business Segment Revenue'!K6 -> 11460 | J64: =I64*(1+J57) -> 11230.8 | K64: =J64*(1+K57) -> 11399.262 | L64: =K64*(1+L57) -> 11627.247 | M64: =L64*(1+M57) -> 11859.792 | N64: =M64*(1+N57) -> 12096.988
B65: Appliances | C65: $ | D65: ='Business Segment Revenue'!F7 -> 5873 | E65: ='Business Segment Revenue'!G7 -> 7167 | F65: ='Business Segment Revenue'!H7 -> 6736 | G65: ='Business Segment Revenue'!I7 -> 5804 | H65: ='Business Segment Revenue'!J7 -> 4910 | I65: ='Business Segment Revenue'!K7 -> 4469 | J65: =I65*(1+J58) -> 4245.55 | K65: =J65*(1+K58) -> 4245.55 | L65: =K65*(1+L58) -> 4351.6888 | M65: =L65*(1+M58) -> 4482.2394 | N65: =M65*(1+N58) -> 4616.7066
B66: Entertainment | C66: $ | D66: ='Business Segment Revenue'!F8 -> 3079 | E66: ='Business Segment Revenue'!G8 -> 3275 | F66: ='Business Segment Revenue'!H8 -> 3053 | G66: ='Business Segment Revenue'!I8 -> 3363 | H66: ='Business Segment Revenue'!J8 -> 2908 | I66: ='Business Segment Revenue'!K8 -> 3092 | J66: =I66*(1+J59) -> 3184.76 | K66: =J66*(1+K59) -> 3264.379 | L66: =K66*(1+L59) -> 3329.6666 | M66: =L66*(1+M59) -> 3396.2599 | N66: =M66*(1+N59) -> 3464.1851
B67: Services | C67: $ | D67: ='Business Segment Revenue'!F9 -> 2252 | E67: ='Business Segment Revenue'!G9 -> 2380 | F67: ='Business Segment Revenue'!H9 -> 2332 | G67: ='Business Segment Revenue'!I9 -> 2530 | H67: ='Business Segment Revenue'!J9 -> 2631 | I67: ='Business Segment Revenue'!K9 -> 2656 | J67: =I67*(1+J60) -> 2762.24 | K67: =J67*(1+K60) -> 2900.352 | L67: =K67*(1+L60) -> 3045.3696 | M67: =L67*(1+M60) -> 3167.1844 | N67: =M67*(1+N60) -> 3293.8718
B68: Other | C68: $ | D68: ='Business Segment Revenue'!F10 -> 194 | E68: ='Business Segment Revenue'!G10 -> 258 | F68: ='Business Segment Revenue'!H10 -> 317 | G68: ='Business Segment Revenue'!I10 -> 304 | H68: ='Business Segment Revenue'!J10 -> 333 | I68: ='Business Segment Revenue'!K10 -> 300 | J68: =I68*(1+J61) -> 324 | K68: =J68*(1+K61) -> 356.4 | L68: =K68*(1+L61) -> 384.912 | M68: =L68*(1+M61) -> 408.00672 | N68: =M68*(1+N61) -> 428.40706
B69: Total Revenue from Segments | C69: $ | D69: =SUM(D63:D68) -> 47262 | E69: =SUM(E63:E68) -> 51761 | F69: =SUM(F63:F68) -> 46298 | G69: =SUM(G63:G68) -> 43452 | H69: =SUM(H63:H68) -> 41528 | I69: =SUM(I63:I68) -> 41691 | J69: =SUM(J63:J68) -> 41855.63 | K69: =SUM(K63:K68) -> 43078.554 | ... N69: =SUM(N63:N68) -> 46310.364
B71: % of Total Revenue
B72: Computing & Mobile Phones | C72: % | D72: =D63/D69 -> 0.4581482 | E72: =E63/E69 -> 0.43426518 | F72: =F63/F69 -> 0.42692989 | G72: =G63/G69 -> 0.42534291 | H72: =H63/H69 -> 0.44984107 | I72: =I63/I69 -> 0.47285985 | J72: =J63/J69 -> 0.48041996 | K72: =K63/K69 -> 0.48545295 | ... N72: =N63/N69 -> 0.48391339
B73: Consumer Electronics | C73: % | D73: =D64/D69 -> 0.30068554 | E73: =E64/E69 -> 0.31303491 | F73: =F64/F69 -> 0.3044192 | G73: =G64/G69 -> 0.29846727 | H73: =H64/H69 -> 0.29052687 | I73: =I64/I69 -> 0.27487947 | J73: =J64/J69 -> 0.26832233 | K73: =K64/K69 -> 0.26461571 | ... N73: =N64/N69 -> 0.26121557
B74: Appliances | C74: % | D74: =D65/D69 -> 0.12426474 | E74: =E65/E69 -> 0.13846332 | F74: =F65/F69 -> 0.14549225 | G74: =G65/G69 -> 0.13357268 | H74: =H65/H69 -> 0.11823348 | I74: =I65/I69 -> 0.1071934 | J74: =J65/J69 -> 0.10143319 | K74: =K65/K69 -> 0.098553679 | ... N74: =N65/N69 -> 0.099690571
B75: Entertainment | C75: % | D75: =D66/D69 -> 0.065147476 | E75: =E66/E69 -> 0.063271575 | F75: =F66/F69 -> 0.065942373 | G75: =G66/G69 -> 0.077395747 | H75: =H66/H69 -> 0.070025043 | I75: =I66/I69 -> 0.074164688 | J75: =J66/J69 -> 0.076089166 | K75: =K66/K69 -> 0.075777357 | ... N75: =N66/N69 -> 0.074803669
B76: Services | C76: % | D76: =D67/D69 -> 0.047649274 | E76: =E67/E69 -> 0.045980565 | F76: =F67/F69 -> 0.050369346 | G76: =G67/G69 -> 0.058225168 | H76: =H67/H69 -> 0.063354845 | I76: =I67/I69 -> 0.063706795 | J76: =J67/J69 -> 0.065994467 | K76: =K67/K69 -> 0.067327051 | ... N76: =N67/N69 -> 0.071126018
B77: Other | C77: % | D77: =D68/D69 -> 0.0041047776 | E77: =E68/E69 -> 0.0049844478 | F77: =F68/F69 -> 0.006846948 | G77: =G68/G69 -> 0.0069962257 | H77: =H68/H69 -> 0.0080186862 | I77: =I68/I69 -> 0.0071957977 | J77: =J68/J69 -> 0.0077408941 | K77: =K68/K69 -> 0.0082732582 | ... N77: =N68/N69 -> 0.0092507815
B79: Revenue Comparision And Summary
B80: Reconciliation: Segment vs. Geographic Build
B81: Total Rev Segment Build | C81: $ | D81: =D69 -> 47262 | E81: =E69 -> 51761 | F81: =F69 -> 46298 | G81: =G69 -> 43452 | H81: =H69 -> 41528 | I81: =I69 -> 41691 | J81: =J69 -> 41855.63 | K81: =K69 -> 43078.554 | ... N81: =N69 -> 46310.364
B82: Comp-Store Geographic Build | C82: $ | D82: =D43+D51 -> 48380.878 | E82: =E43+E51 -> 52851.214 | F82: =F43+F51 -> 46837.459 | G82: =G43+G51 -> 43467.532 | H82: =H43+H51 -> 42432.8 | I82: =I43+I51 -> 41756.622 | J82: =J43+J51 -> 42231.099 | K82: =K43+K51 -> 42992.723 | ... N82: =N43+N51 -> 45973.05
B83: Difference ($M) Comp-Store minus Segment | C83: $ | D83: =D82-D81 -> 1118.8775 | E83: =E82-E81 -> 1090.2144 | F83: =F82-F81 -> 539.45875 | G83: =G82-G81 -> 15.53204 | H83: =H82-H81 -> 904.8 | I83: =I82-I81 -> 65.622 | J83: =J82-J81 -> 375.46889 | K83: =K82-K81 -> -85.831273 | ... N83: =N82-N81 -> -337.31403
B84: Difference (%) | C84: % | D84: =IFERROR(D83/D81,0) -> 0.023673935 | E84: =IFERROR(E83/E81,0) -> 0.021062467 | F84: =IFERROR(F83/F81,0) -> 0.01165188 | G84: =IFERROR(G83/G81,0) -> 0.00035745283 | H84: =IFERROR(H83/H81,0) -> 0.021787709 | I84: =IFERROR(I83/I81,0) -> 0.0015740088 | J84: =IFERROR(J83/J81,0) -> 0.0089705707 | K84: =IFERROR(K83/K81,0) -> -0.0019924363 | ... N84: =IFERROR(N83/N81,0) -> -0.0072837698
B86: International Revenue as % of Total Revenue | D86: =D51/D52 -> 0.093248619 | E86: =E51/E52 -> 0.084788099 | F86: =F51/F52 -> 0.079800359 | G86: =G51/G52 -> 0.078273512 | H86: =H51/H52 -> 0.078670863 | I86: =I51/I52 -> 0.080602066 | J86: =J51/J52 -> 0.081625392 | K86: =K51/K52 -> 0.081382074 | ... N86: =N51/N52 -> 0.080764574
B87: Domestic Revenue as % of Total Revenue | D87: =D43/D52 -> 0.90675138 | E87: =E43/E52 -> 0.9152119 | F87: =F43/F52 -> 0.92019964 | G87: =G43/G52 -> 0.92172649 | H87: =H43/H52 -> 0.92132914 | I87: =I43/I52 -> 0.91939793 | J87: =J43/J52 -> 0.91837461 | K87: =K43/K52 -> 0.91861793 | ... N87: =N43/N52 -> 0.91923543

Sheet Business Segment Revenue
A1: Sales
B2: JAN '17 | C2: JAN '18 | D2: JAN '19 | E2: JAN '20 | F2: JAN '21 | G2: JAN '22 | H2: JAN '23 | I2: JAN '24 | J2: JAN '25 | K2: JAN '26
B3: 364 Days | C3: 371 Days | D3: 364 Days | E3: 364 Days | F3: 364 Days | G3: 364 Days | H3: 364 Days | I3: 371 Days | J3: 364 Days | K3: 364 Days
A4: Total | B4: 39403 | C4: 42151 | D4: 42879 | E4: 43638 | F4: 47262 | G4: 51761 | H4: 46298 | I4: 43452 | J4: 41528 | K4: 41691
A5: Computing & Mobile Phones | B5: 17826 | C5: 19002.84 | D5: 19064 | E5: 19399 | F5: 21653 | G5: 22478 | H5: 19766 | I5: 18482 | J5: 18681 | K5: 19714
A6: Consumer Electronics | B6: 13302.37 | C6: 13874.94 | D6: 14062 | E6: 14292 | F6: 14211 | G6: 16203 | H6: 14094 | I6: 12969 | J6: 12065 | K6: 11460
A7: Appliances | B7: 3451.62 | C7: 4145.32 | D7: 4344 | E7: 4810 | F7: 5873 | G7: 7167 | H7: 6736 | I7: 5804 | J7: 4910 | K7: 4469
A8: Entertainment | B8: 2758.21 | C8: 3337.19 | D8: 3210 | E8: 2597 | F8: 3079 | G8: 3275 | H8: 3053 | I8: 3363 | J8: 2908 | K8: 3092
A9: Services | B9: 2033.25 | C9: 1720.93 | D9: 1967 | E9: 2325 | F9: 2252 | G9: 2380 | H9: 2332 | I9: 2530 | J9: 2631 | K9: 2656
A10: Other | B10: 31.55 | C10: 69.78 | D10: 232 | E10: 215 | F10: 194 | G10: 258 | H10: 317 | I10: 304 | J10: 333 | K10: 300
A11: All figures in millions of U.S. Dollar
A14: Percent of Total (%)
B15: JAN '17 | C15: JAN '18 | D15: JAN '19 | E15: JAN '20 | F15: JAN '21 | G15: JAN '22 | H15: JAN '23 | I15: JAN '24 | J15: JAN '25 | K15: JAN '26
A16: Total | B16: 100 | C16: 100 | D16: 99.999995 | E16: 100 | F16: 100 | G16: 99.999999 | H16: 99.999999 | I16: 99.999999 | J16: 100 | K16: 100
A17: Computing & Mobile Phones | B17: 45.240211 | C17: 45.082775 | D17: 44.459991 | E17: 44.454376 | F17: 45.814819 | G17: 43.426517 | H17: 42.692989 | I17: 42.53429 | J17: 44.984108 | K17: 47.285988
A18: Consumer Electronics | B18: 33.759792 | C18: 32.917229 | D18: 32.794605 | E18: 32.75127 | F18: 30.068556 | G18: 31.303492 | H18: 30.441919 | I18: 29.846727 | J18: 29.052687 | K18: 27.487946
A19: Appliances | B19: 8.759789 | C19: 9.834452 | D19: 10.130833 | E19: 11.022504 | F19: 12.426474 | G19: 13.846332 | H19: 14.549224 | I19: 13.357268 | J19: 11.823348 | K19: 10.719339
A20: Entertainment | B20: 7 | C20: 7.917226 | D20: 7.486182 | E20: 5.951235 | F20: 6.514748 | G20: 6.327157 | H20: 6.594238 | I20: 7.739574 | J20: 7.002504 | K20: 7.416469
A21: Services | B21: 5.16014 | C21: 4.082774 | D21: 4.587327 | E21: 5.327925 | F21: 4.764927 | G21: 4.598056 | H21: 5.036934 | I21: 5.822517 | J21: 6.335484 | K21: 6.370679
A22: Other | B22: 0.08007 | C22: 0.165548 | D22: 0.541057 | E22: 0.49269 | F22: 0.410478 | G22: 0.498445 | H22: 0.684695 | I22: 0.699623 | J22: 0.801869 | K22: 0.71958
A25: Growth (%)
B26: JAN '17 | C26: JAN '18 | D26: JAN '19 | E26: JAN '20 | F26: JAN '21 | G26: JAN '22 | H26: JAN '23 | I26: JAN '24 | J26: JAN '25 | K26: JAN '26
A27: Total | B27: -0.316232 | C27: 6.97409 | D27: 1.72712 | E27: 1.7701 | F27: 8.30469 | G27: 9.51928 | H27: -10.5543 | I27: -6.14713 | J27: -4.42787 | K27: 0.392506
A28: Computing & Mobile Phones | B28: -2.302628 | C28: 6.601817 | D28: 0.321847 | E28: 1.757239 | F28: 11.619156 | G28: 3.810096 | H28: -12.06513 | I28: -6.496003 | J28: 1.076723 | K28: 5.529683
A29: Consumer Electronics | B29: 5.429358 | C29: 4.304273 | D29: 1.348183 | E29: 1.635614 | F29: -0.566751 | G29: 14.01731 | H29: -13.016109 | I29: -7.98212 | J29: -6.970468 | K29: -5.014505
A30: Appliances | B30: 12.527752 | C30: 20.097801 | D30: 4.792879 | E30: 10.72744 | F30: 22.099792 | G30: 22.033033 | H30: -6.013674 | I30: -13.836104 | J30: -15.403171 | K30: -8.98167
A31: Entertainment | B31: -13.640511 | C31: 20.99115 | D31: -3.811289 | E31: -19.096573 | F31: 18.559877 | G31: 6.365703 | H31: -6.778626 | I31: 10.153947 | J31: -13.529587 | K31: 6.327373
A32: Services | B32: 1.255956 | C32: -15.360626 | D32: 14.29866 | E32: 18.200306 | F32: -3.139785 | G32: 5.683836 | H32: -2.016807 | I32: 8.490566 | J32: 3.992095 | K32: 0.950209
A33: Other | B33: -92.018318 | C33: 121.17275 | D33: 232.4735 | E33: -7.327586 | F33: -9.767442 | G33: 32.989689 | H33: 22.868217 | I33: -4.100946 | J33: 9.539474 | K33: -9.90991

Sheet Industry Metrics
A1: Industry
B2: JAN '26 | C2: JAN '25 | D2: JAN '24 | E2: JAN '23 | F2: JAN '22 | G2: JAN '21
A3: Same Store Sales - Total (%) | B3: 0.005 | C3: -0.023 | D3: -0.068 | E3: -0.099 | F3: 0.104 | G3: 0.097
A4: Same Store Sales - Domestic (%) | B4: 0.004 | C4: -0.025 | D4: -0.071 | E4: -0.103 | F4: 0.11 | G4: 0.092
A5: Same Store Sales - International (%) | B5: 0.023 | C5: -0.005 | D5: -0.032 | E5: -0.054 | F5: 0.033 | G5: 0.15
A6: Floor Area Sq. Ft. (000) | B6: 39529 | C6: 40142 | D6: 40394 | E6: 41009 | F6: 41310 | G6: 42108
A7: Domestic (000) | B7: 35954 | C7: 36539 | D7: 36771 | E7: 37388 | F7: 37705 | G7: 38186
A8: International (000) | B8: 3575 | C8: 3603 | D8: 3623 | E8: 3621 | F8: 3605 | G8: 3922
A9: Online Revenue as % of Domestic Revenue | B9: 0.39 | C9: 0.395 | D9: 0.38 | E9: 0.34 | F9: 0.36 | G9: 0.33
B11: JAN '26 | C11: JAN '25 | D11: JAN '24 | E11: JAN '23 | F11: JAN '22 | G11: JAN '21
A12: # Beginning Stores | B12: 1117 | C12: 1125 | D12: 1138 | E12: 1144 | F12: 1159 | G12: 1231
A13: Domestic | B13: 957 | C13: 965 | D13: 978 | E13: 984 | F13: 991 | G13: 1009
A14: International | B14: 160 | C14: 160 | D14: 160 | E14: 160 | F14: 168 | G14: 222
A15: # Ending Stores | B15: 1068 | C15: 1117 | D15: 1125 | E15: 1138 | F15: 1144 | G15: 1159
A16: Domestic | B16: 926 | C16: 957 | D16: 965 | E16: 978 | F16: 984 | G16: 991
A17: International | B17: 142 | C17: 160 | D17: 160 | E17: 160 | F17: 160 | G17: 168
A18: # Net Additions | B18: -49 | C18: -8 | D18: -13 | E18: -6 | F18: -15 | G18: -72
A19: # New Stores | D19: 15 | E19: 9 | F19: 13 | G19: 3
A20: # Opened | D20: 15 | E20: 9 | F20: 13 | G20: 3
A21: Domestic | D21: 14 | E21: 9 | F21: 13 | G21: 3
A22: International | D22: 1
A23: # Closed Stores | B23: 49 | C23: 8 | D23: 28 | E23: 15 | F23: 28 | G23: 75
A24: Domestic | B24: 31 | C24: 8 | D24: 27 | E24: 15 | F24: 20 | G24: 21
A25: International | B25: 18 | D25: 1 | F25: 8 | G25: 54
A26: # Owned Stores | B26: 26 | C26: 27 | D26: 26 | E26: 27 | F26: 27 | G26: 27
A27: # Leased Stores | B27: 1006 | C27: 1054 | D27: 1063 | E27: 1075 | F27: 1080 | G27: 1099
A28: # Ground Leased Stores | B28: 36 | C28: 36 | D28: 36 | E28: 36 | F28: 37 | G28: 33
A29: All figures without specified units (e.g. Revenue, Net Income, Capex and Sustaining Capex) in U.S. Dollar. All figures for Sales Volume, Production, Reserves and Resources in of respective weight units. All figures for Realized Price and Unit Costs are in $ per weight unit.
B31: JAN '26 | C31: JAN '25 | D31: JAN '24 | E31: JAN '23 | F31: JAN '22 | G31: JAN '21
A32: Retail Industry Metrics
A33: Merchandise Margin (%) | B33: 22.5 | C33: 22.6 | D33: 22.1 | E33: 21.4 | F33: 22.5 | G33: 22.4
A34: EBITDAR | B34: 3584 | C34: 3594 | D34: 3644 | E34: 3849 | F34: 4861 | G34: 4420
A35: # Stores (actual) | B35: 1068 | C35: 1117 | D35: 1125 | E35: 1138 | F35: 1144 | G35: 1159
A36: # Stores Closed During Period (actual) | D36: 28 | E36: 15 | F36: 28 | G36: 75
A37: # Stores Opened During Period (actual) | D37: 15 | E37: 9 | F37: 13 | G37: 3

Sheet Historical Balance Sheet
A1: Best Buy Co., Inc. (NYSE:BBY) > Financials > Balance Sheet
A3: In Millions of the reported currency, except per share items. | B3: Template: | C3: Standard | E3: Restatement: | F3: Latest Filings
B4: Period Type: | C4: Annual | E4: Order: | F4: Latest on Right
B5: Currency: | C5: Reported Currency | E5: Conversion: | F5: Historical
B6: Units: | C6: S&P Capital IQ (Default) | E6: Decimals: | F6: Capital IQ (Default)
B7: Source: | C7: Capital IQ & Proprietary Data
A10: Balance Sheet
A11: Balance Sheet as of: | B11: 44226 | C11: 44590 | D11: 44954 | E11: 45325 | F11: 45689 | G11: 46053
A12: Currency | B12: USD | C12: USD | D12: USD | E12: USD | F12: USD | G12: USD
A13: ASSETS
A14: Cash And Equivalents | B14: 5494 | C14: 2936 | D14: 1874 | E14: 1447 | F14: 1578 | G14: 1738
A15: Short Term Investments | B15: 65 | C15: - | D15: 178 | E15: - | F15: 190 | G15: 153
A16: Total Cash & ST Investments | B16: 5559 | C16: 2936 | D16: 2052 | E16: 1447 | F16: 1768 | G16: 1891
A18: Accounts Receivable | B18: 1061 | C18: 1042 | D18: 1141 | E18: 939 | F18: 1044 | G18: 1043
A19: Total Receivables | B19: 1061 | C19: 1042 | D19: 1141 | E19: 939 | F19: 1044 | G19: 1043
A21: Inventory | B21: 5612 | C21: 5965 | D21: 5140 | E21: 4958 | F21: 5085 | G21: 5230
A22: Restricted Cash | B22: 131 | C22: 269 | D22: 379 | E22: - | F22: 290 | G22: 285
A23: Other Current Assets | B23: 177 | C23: 327 | D23: 90 | E23: 553 | F23: 37 | G23: 55
A24: Total Current Assets | B24: 12540 | C24: 10539 | D24: 8802 | E24: 7897 | F24: 8224 | G24: 8504
A26: Gross Property, Plant & Equipment | B26: 11868 | C26: 10995 | D26: 9722 | E26: 9834 | F26: 9885 | G26: 9810
A27: Accumulated Depreciation | B27: -6996 | C27: -6091 | D27: -4624 | E27: -4816 | F27: -4930 | G27: -4955
A28: Net Property, Plant & Equipment | B28: 4872 | C28: 4904 | D28: 5098 | E28: 5018 | F28: 4955 | G28: 4855
A30: Long-term Investments | B30: 91 | C30: 50 | D30: - | E30: - | F30: - | G30: -
A31: Goodwill | B31: 986 | C31: 1384 | D31: 1383 | E31: 1383 | F31: 908 | G31: 790
A32: Other Intangibles | B32: 301 | C32: 275 | D32: 189 | E32: 128 | F32: 91 | G32: 5
A33: Deferred Tax Assets, LT | B33: 17 | C33: 25 | D33: 4 | E33: 167 | F33: 223 | G33: 164
A34: Other Long-Term Assets | B34: 260 | C34: 327 | D34: 327 | E34: 374 | F34: 381 | G34: 352
A35: Total Assets | B35: 19067 | C35: 17504 | D35: 15803 | E35: 14967 | F35: 14782 | G35: 14670
A37: LIABILITIES
A38: Accounts Payable | B38: 6979 | C38: 6803 | D38: 5687 | E38: 4637 | F38: 4980 | G38: 4745
A39: Accrued Exp. | B39: 1626 | C39: 1708 | D39: 1182 | E39: 1335 | F39: 1155 | G39: 1108
A40: Short-term Borrowings | B40: 110 | C40: - | D40: - | E40: - | F40: - | G40: -
A41: Curr. Port. of Leases | B41: 707 | C41: 661 | D41: 654 | E41: 631 | F41: 627 | G41: 634
A42: Unearned Revenue, Current | B42: 1099 | C42: 1502 | D42: 1456 | E42: 1306 | F42: 1254 | G42: 1192
A43: Other Current Liabilities | B43: - | C43: - | D43: - | E43: - | F43: - | G43: -
A44: Total Current Liabilities | B44: 10521 | C44: 10674 | D44: 8979 | E44: 7909 | F44: 8016 | G44: 7679
A46: Long-Term Debt | B46: 1229 | C46: 1189 | D46: 1134 | E46: 1142 | F46: 1143 | G46: 1145
A47: Long-Term Leases | B47: 2036 | C47: 2088 | D47: 2190 | E47: 2220 | F47: 2297 | G47: 2355
A48: Unearned Revenue, Non-Current | B48: - | C48: 6 | D48: 265 | E48: 245 | F48: 229 | G48: 205
A49: Def. Tax Liability, Non-Curr. | B49: - | C49: 22 | D49: 51 | E49: - | F49: - | G49: -
A50: Other Non-Current Liabilities | B50: 694 | C50: 505 | D50: 389 | E50: 398 | F50: 289 | G50: 322
A51: Total Liabilities | B51: 14480 | C51: 14484 | D51: 13008 | E51: 11914 | F51: 11974 | G51: 11706
A53: Common Stock | B53: 26 | C53: 23 | D53: 22 | E53: 22 | F53: 22 | G53: 22
A54: Additional Paid In Capital | B54: - | C54: - | D54: 21 | E54: 31 | F54: - | G54: 14
A55: Retained Earnings | B55: 4233 | C55: 2668 | D55: 2430 | E55: 2683 | F55: 2486 | G55: 2610
A56: Treasury Stock | B56: - | C56: - | D56: - | E56: - | F56: - | G56: -
A57: Comprehensive Inc. and Other | B57: 328 | C57: 329 | D57: 322 | E57: 317 | F57: 300 | G57: 318
A58: Total Common Equity | B58: 4587 | C58: 3020 | D58: 2795 | E58: 3053 | F58: 2808 | G58: 2964
A60: Total Equity | B60: 4587 | C60: 3020 | D60: 2795 | E60: 3053 | F60: 2808 | G60: 2964
A62: Total Liabilities And Equity | B62: 19067 | C62: 17504 | D62: 15803 | E62: 14967 | F62: 14782 | G62: 14670
A64: Supplemental Items
A65: Total Shares Out. on Filing Date | B65: 250.04488 | C65: 225.22776 | D65: 218.04574 | E65: 215.38139 | F65: 211.36966 | G65: 209.11258
A66: Total Shares Out. on Balance Sheet Date | B66: 257 | C66: 227.4 | D66: 218.1 | E66: 215.4 | F66: 211.4 | G66: 209.1
A67: Book Value/Share | B67: 17.85 | C67: 13.28 | D67: 12.82 | E67: 14.17 | F67: 13.28 | G67: 14.18
A68: Tangible Book Value | B68: 3300 | C68: 1361 | D68: 1223 | E68: 1542 | F68: 1809 | G68: 2169
A69: Tangible Book Value/Share | B69: 12.84 | C69: 5.99 | D69: 5.61 | E69: 7.16 | F69: 8.56 | G69: 10.37
A70: Total Debt | B70: 4082 | C70: 3938 | D70: 3978 | E70: 3993 | F70: 4067 | G70: 4134
A71: Net Debt | B71: -1477 | C71: 1002 | D71: 1926 | E71: 2546 | F71: 2299 | G71: 2243
A72: Debt Equivalent Oper. Leases | B72: 8080 | C72: 7960 | D72: 8008 | E72: 8040 | F72: 8056 | G72: 8136
A73: Inventory Method | B73: Avg Cost | C73: Avg Cost | D73: Avg Cost | E73: Avg Cost | F73: Avg Cost | G73: Avg Cost
A74: Finished Goods Inventory | B74: 5612 | C74: 5965 | D74: 5140 | E74: 4958 | F74: 5085 | G74: 5230
A75: Land | B75: 658 | C75: 671 | D75: 688 | E75: 702 | F75: 722 | G75: 734
A76: Machinery | B76: 6333 | C76: 5419 | D76: 3928 | E76: 4002 | F76: 3872 | G76: 3732
A77: Leasehold Improvements | B77: 2192 | C77: 2160 | D77: 2260 | E77: 2275 | F77: 2370 | G77: 2395
A78: Full Time Employees | B78: 61200 | C78: 57750 | D78: 52200 | E78: 85000 | F78: 85000 | G78: 82000
A79: Part-Time Employees | B79: 35700 | C79: 36750 | D79: 28800 | E79: NA | F79: NA | G79: NA
A80: Accum. Allowance for Doubtful Accts | B80: 38 | C80: 39 | D80: 30 | E80: 32 | F80: 26 | G80: 24
A81: Filing Date | B81: 45002 | C81: 45366 | D81: 45735 | E81: 46099 | F81: 46099 | G81: 46099
A82: Restatement Type | B82: NC | C82: NC | D82: NC | E82: NC | F82: NC | G82: O
A83: Calculation Type | B83: RUP | C83: RUP | D83: RUP | E83: RUP | F83: REP | G83: REP
A86: Note: For multiple class companies, total share counts are primary class equivalent, and for foreign companies listed as primary ADRs, total share counts are ADR-equivalent.

Sheet Historical Income Statement
A1: Best Buy Co., Inc. (NYSE:BBY) > Financials > Income Statement
A3: In Millions of the reported currency, except per share items. | B3: Template: | C3: Standard | E3: Restatement: | F3: Latest Filings
B4: Period Type: | C4: Annual | E4: Order: | F4: Latest on Right
B5: Currency: | C5: Reported Currency | E5: Conversion: | F5: Historical
B6: Units: | C6: S&P Capital IQ (Default) | E6: Decimals: | F6: Capital IQ (Default)
B7: Source: | C7: Capital IQ & Proprietary Data
A10: Income Statement
A11: For the Fiscal Period Ending | B11: Reclassified 12 months Jan-30-2021 | C11: Reclassified 12 months Jan-29-2022 | D11: 12 months Jan-28-2023 | E11: Reclassified 12 months Feb-03-2024 | F11: Reclassified 12 months Feb-01-2025 | G11: 12 months Jan-31-2026
A12: Currency | B12: USD | D12: USD | E12: USD | F12: USD | G12: USD
A14: Revenue | B14: 47262 | C14: 51761 | D14: 46298 | E14: 43452 | F14: 41528 | G14: 41691
A15: Other Revenue | B15: - | C15: - | D15: - | E15: - | F15: - | G15: -
A16: Total Revenue | B16: 47262 | C16: 51761 | D16: 46298 | E16: 43452 | F16: 41528 | G16: 41691
A18: Cost Of Goods Sold | B18: 36666 | C18: 40127 | D18: 36386 | E18: 33849 | F18: 32143 | G18: 32318
A19: Gross Profit | B19: 10596 | C19: 11634 | D19: 9912 | E19: 9603 | F19: 9385 | G19: 9373
A21: Selling General & Admin Exp. | B21: 7848 | C21: 8542 | D21: 7884 | E21: 7813 | F21: 7628 | G21: 7588
A22: R & D Exp. | B22: - | C22: - | D22: - | E22: - | F22: - | G22: -
A23: Depreciation & Amort. | B23: - | C23: - | D23: - | E23: - | F23: - | G23: -
A24: Amort. of Goodwill and Intangibles | B24: 80 | C24: 82 | D24: 86 | E24: 61 | F24: 21 | G24: 14
A25: Other Operating Expense/(Income) | B25: - | C25: - | D25: - | E25: - | F25: - | G25: -
A27: Other Operating Exp., Total | B27: 7928 | C27: 8624 | D27: 7970 | E27: 7874 | F27: 7649 | G27: 7602
A29: Operating Income | B29: 2668 | C29: 3010 | D29: 1942 | E29: 1729 | F29: 1736 | G29: 1771
A31: Interest Expense | B31: -52 | C31: -25 | D31: -35 | E31: -52 | F31: -51 | G31: -47
A32: Interest and Invest. Income | B32: 38 | C32: 10 | D32: 28 | E32: 78 | F32: 84 | G32: 68
A33: Net Interest Exp. | B33: -14 | C33: -15 | D33: -7 | E33: 26 | F33: 33 | G33: 21
A35: Income/(Loss) from Affiliates | B35: - | C35: 4 | D35: 1 | E35: 1 | F35: 4 | G35: 2
A36: Other Non-Operating Inc. (Exp.) | B36: - | C36: - | D36: - | E36: - | F36: - | G36: -
A37: EBT Excl. Unusual Items | B37: 2654 | C37: 2999 | D37: 1936 | E37: 1756 | F37: 1773 | G37: 1794
A39: Restructuring Charges | B39: -277 | C39: 40 | D39: -147 | E39: -153 | F39: 3 | G39: -190
A40: Merger & Related Restruct. Charges | B40: - | C40: -11 | D40: - | E40: - | F40: - | G40: -
A41: Impairment of Goodwill | B41: - | C41: - | D41: - | E41: - | F41: -475 | G41: -118
A42: Gain (Loss) On Sale Of Assets | B42: - | C42: - | D42: - | E42: 21 | F42: - | G42: -6
A43: Asset Writedown | B43: - | C43: - | D43: - | E43: -2 | F43: -2 | G43: -74
A44: Other Unusual Items | B44: - | C44: - | D44: - | E44: - | F44: - | G44: -
A45: EBT Incl. Unusual Items | B45: 2377 | C45: 3028 | D45: 1789 | E45: 1622 | F45: 1299 | G45: 1406
A47: Income Tax Expense | B47: 579 | C47: 574 | D47: 370 | E47: 381 | F47: 372 | G47: 337
A48: Earnings from Cont. Ops. | B48: 1798 | C48: 2454 | D48: 1419 | E48: 1241 | F48: 927 | G48: 1069
A50: Earnings of Discontinued Ops. | B50: - | C50: - | D50: - | E50: - | F50: - | G50: -
A51: Extraord. Item & Account. Change | B51: - | C51: - | D51: - | E51: - | F51: - | G51: -
A52: Net Income to Company | B52: 1798 | C52: 2454 | D52: 1419 | E52: 1241 | F52: 927 | G52: 1069
A54: Minority Int. in Earnings | B54: - | C54: - | D54: - | E54: - | F54: - | G54: -
A55: Net Income | B55: 1798 | C55: 2454 | D55: 1419 | E55: 1241 | F55: 927 | G55: 1069
A57: Pref. Dividends and Other Adj. | B57: - | C57: - | D57: - | E57: - | F57: - | G57: -
A59: NI to Common Incl Extra Items | B59: 1798 | C59: 2454 | D59: 1419 | E59: 1241 | F59: 927 | G59: 1069
A60: NI to Common Excl. Extra Items | B60: 1798 | C60: 2454 | D60: 1419 | E60: 1241 | F60: 927 | G60: 1069
A62: Per Share Items
A63: Basic EPS | B63: 6.93 | C63: 9.94 | D63: 6.31 | E63: 5.7 | F63: 4.31 | G63: 5.07
A64: Basic EPS Excl. Extra Items | B64: 6.92604 | C64: 9.943273 | D64: 6.312277 | E64: 5.700505 | F64: 4.30762 | G64: 5.06635
A65: Weighted Avg. Basic Shares Out. | B65: 259.6 | C65: 246.8 | D65: 224.8 | E65: 217.7 | F65: 215.2 | G65: 211
A67: Diluted EPS | B67: 6.84 | C67: 9.84 | D67: 6.29 | E67: 5.68 | F67: 4.28 | G67: 5.04
A68: Diluted EPS Excl. Extra Items | B68: 6.84 | C68: 9.84 | D68: 6.29 | E68: 5.68 | F68: 4.28 | G68: 5.04
A69: Weighted Avg. Diluted Shares Out. | B69: 263 | C69: 249.3 | D69: 225.7 | E69: 218.5 | F69: 216.6 | G69: 212.1
A71: Normalized Basic EPS | B71: 6.39 | C71: 7.59 | D71: 5.38 | E71: 5.04 | F71: 5.15 | G71: 5.31
A72: Normalized Diluted EPS | B72: 6.307034 | C72: 7.518551 | D72: 5.361098 | E72: 5.022883 | F72: 5.115997 | G72: 5.286421
A74: Dividends per Share | B74: 2.35 | C74: 2.98 | D74: 3.52 | E74: 3.68 | F74: 3.76 | G74: 3.8
A75: Payout Ratio % | B75: 0.315906 | C75: 0.280358 | D75: 0.556025 | E75: 0.645447 | F75: 0.87055 | G75: 0.749298
A77: Shares per Depository Receipt | B77: 1 | C77: 1 | D77: 1 | E77: 1 | F77: 1 | G77: 1
A79: Supplemental Items
A80: EBITDA | B80: 3507 | C80: 3879 | D80: 2860 | E80: 2652 | F80: 2602 | G80: 2602
A81: EBITA | B81: 2748 | C81: 3092 | D81: 2028 | E81: 1790 | F81: 1757 | G81: 1785
A82: EBIT | B82: 2668 | C82: 3010 | D82: 1942 | E82: 1729 | F82: 1736 | G82: 1771
A83: EBITDAR | B83: 4517 | C83: 4874 | D83: 3861 | E83: 3657 | F83: 3609 | G83: 3619
A84: Effective Tax Rate % | B84: 0.243584 | C84: 0.189564 | D84: 0.206819 | E84: 0.234895 | F84: 0.286374 | G84: 0.239687
A85: Current Domestic Taxes | B85: 564 | C85: 499 | D85: 277 | E85: 556 | F85: 408 | G85: 249
A86: Current Foreign Taxes | B86: 51 | C86: 61 | D86: 42 | E86: 39 | F86: 23 | G86: 28
A87: Total Current Taxes | B87: 615 | C87: 560 | D87: 319 | E87: 595 | F87: 431 | G87: 277
A88: Deferred Domestic Taxes | B88: -41 | C88: 13 | D88: 52 | E88: -214 | F88: -62 | G88: 59
A89: Deferred Foreign Taxes | B89: 5 | C89: 1 | D89: -1 | E89: NA | F89: 3 | G89: 1
A90: Total Deferred Taxes | B90: -36 | C90: 14 | D90: 51 | E90: -214 | F90: -59 | G90: 60
A92: Normalized Net Income | B92: 1658.75 | C92: 1874.375 | D92: 1210 | E92: 1097.5 | F92: 1108.125 | G92: 1121.25
A93: Interest on Long Term Debt | B93: 52 | C93: 25 | D93: 35 | E93: 52 | F93: 51 | G93: 47
A94: Filing Date | B94: 45002 | C94: 45366 | D94: 45735 | E94: 46099 | F94: 46099 | G94: 46099
A95: Restatement Type | B95: RC | C95: RC | D95: NC | E95: RC | F95: RC | G95: O
A96: Calculation Type | B96: REP | C96: REP | D96: REP | E96: REP | F96: REP | G96: REP
A98: Supplemental Operating Expense Items
A99: Advertising Exp. | B99: 819 | C99: 915 | D99: 864 | E99: 794 | F99: 846 | G99: 861
A100: Selling and Marketing Exp. | B100: 819 | C100: 915 | D100: 864 | E100: 794 | F100: 846 | G100: 861
A101: Net Rental Exp. | B101: 1010 | C101: 995 | D101: 1001 | E101: 1005 | F101: 1007 | G101: 1017
A102: Imputed Oper. Lease Interest Exp. | B102: 103.09272 | C102: 49.62264 | D102: 70.806736 | E102: 104.89788 | F102: 101.94868 | G102: 93.254832
A103: Imputed Oper. Lease Depreciation | B103: 906.90728 | C103: 945.37736 | D103: 930.19326 | E103: 900.10212 | F103: 905.05132 | G103: 923.74517
A105: Stock-Based Comp., Unallocated | B105: 135 | C105: 141 | D105: 138 | E105: 145 | F105: 139 | G105: 139
A106: Stock-Based Comp., Total | B106: 135 | C106: 141 | D106: 138 | E106: 145 | F106: 139 | G106: 139
A109: Note: For multiple class companies, per share items are primary class equivalent, and for foreign companies listed as primary ADRs, per share items are ADR-equivalent.

Sheet Historical Cash Flow
A1: Best Buy Co., Inc. (NYSE:BBY) > Financials > Cash Flow
A3: In Millions of the reported currency, except per share items. | B3: Template: | C3: Standard | E3: Restatement: | F3: Latest Filings
B4: Period Type: | C4: Annual | E4: Order: | F4: Latest on Right
B5: Currency: | C5: Reported Currency | E5: Conversion: | F5: Historical
B6: Units: | C6: S&P Capital IQ (Default) | E6: Decimals: | F6: Capital IQ (Default)
B7: Source: | C7: Capital IQ & Proprietary Data
A10: Cash Flow
A11: For the Fiscal Period Ending | B11: 12 months Jan-30-2021 | C11: 12 months Jan-29-2022 | D11: 12 months Jan-28-2023 | E11: 12 months Feb-03-2024 | F11: 12 months Feb-01-2025 | G11: 12 months Jan-31-2026
A12: Currency | B12: USD | C12: USD | D12: USD | E12: USD | F12: USD | G12: USD
A14: Net Income | B14: 1798 | C14: 2454 | D14: 1419 | E14: 1241 | F14: 927 | G14: 1069
A15: Depreciation & Amort. | B15: 759 | C15: 787 | D15: 832 | E15: 862 | F15: 845 | G15: 817
A16: Amort. of Goodwill and Intangibles | B16: 80 | C16: 82 | D16: 86 | E16: 61 | F16: 21 | G16: 14
A17: Depreciation & Amort., Total | B17: 839 | C17: 869 | D17: 918 | E17: 923 | F17: 866 | G17: 831
A19: (Gain) Loss From Sale Of Assets | B19: - | C19: - | D19: - | E19: -21 | F19: - | G19: 6
A20: Asset Writedown & Restructuring Costs | B20: 254 | C20: -34 | D20: 147 | E20: 155 | F20: 474 | G20: 382
A21: Stock-Based Compensation | B21: 135 | C21: 141 | D21: 138 | E21: 145 | F21: 139 | G21: 139
A22: Other Operating Activities | B22: -33 | C22: 25 | D22: 63 | E22: -190 | F22: -49 | G22: 74
A23: Change in Acc. Receivable | B23: 73 | C23: 17 | D23: -103 | E23: 204 | F23: -111 | G23: -3
A24: Change In Inventories | B24: -435 | C24: -328 | D24: 809 | E24: 178 | F24: -155 | G24: -126
A25: Change in Acc. Payable | B25: 1676 | C25: -201 | D25: -1099 | E25: -1025 | F25: 358 | G25: -238
A26: Change in Inc. Taxes | B26: 173 | C26: -156 | D26: 36 | E26: 52 | F26: -212 | G26: -7
A27: Change in Other Net Operating Assets | B27: 447 | C27: 465 | D27: -504 | E27: -192 | F27: -139 | G27: -165
A28: Cash from Ops. | B28: 4927 | C28: 3252 | D28: 1824 | E28: 1470 | F28: 2098 | G28: 1962
A30: Capital Expenditure | B30: -713 | C30: -737 | D30: -930 | E30: -795 | F30: -706 | G30: -704
A31: Cash Acquisitions | B31: - | C31: -468 | D31: - | E31: - | F31: - | G31: -
A32: Divestitures | B32: - | C32: - | D32: - | E32: 14 | F32: - | G32: -27
A33: Invest. in Marketable & Equity Securt. | B33: -74 | C33: -167 | D33: -39 | E33: -2 | F33: -6 | G33: -1
A34: Net (Inc.) Dec. in Loans Originated/Sold | B34: - | C34: - | D34: - | E34: - | F34: - | G34: -
A35: Other Investing Activities | B35: -1 | C35: - | D35: 7 | E35: 2 | F35: 8 | G35: 2
A36: Cash from Investing | B36: -788 | C36: -1372 | D36: -962 | E36: -781 | F36: -704 | G36: -730
A38: Short Term Debt Issued | B38: - | C38: - | D38: - | E38: - | F38: - | G38: -
A39: Long-Term Debt Issued | B39: 1892 | C39: - | D39: - | E39: - | F39: - | G39: -
A40: Total Debt Issued | B40: 1892 | C40: - | D40: - | E40: - | F40: - | G40: -
A41: Short Term Debt Repaid | B41: - | C41: - | D41: - | E41: - | F41: - | G41: -
A42: Long-Term Debt Repaid | B42: -1916 | C42: -133 | D42: -19 | E42: -19 | F42: -17 | G42: -13
A43: Total Debt Repaid | B43: -1916 | C43: -133 | D43: -19 | E43: -19 | F43: -17 | G43: -13
A45: Issuance of Common Stock | B45: 28 | C45: 29 | D45: 16 | E45: 19 | F45: 17 | G45: 5
A46: Repurchase of Common Stock | B46: -312 | C46: -3502 | D46: -1014 | E46: -340 | F46: -500 | G46: -273
A48: Common Dividends Paid | B48: -568 | C48: -688 | D48: -789 | E48: -801 | F48: -807 | G48: -801
A49: Total Dividends Paid | B49: -568 | C49: -688 | D49: -789 | E49: -801 | F49: -807 | G49: -801
A51: Special Dividend Paid | B51: - | C51: - | D51: - | E51: - | F51: - | G51: -
A52: Other Financing Activities | B52: - | C52: -3 | D52: - | E52: -3 | F52: -2 | G52: -1
A53: Cash from Financing | B53: -876 | C53: -4297 | D53: -1806 | E53: -1144 | F53: -1309 | G53: -1083
A55: Foreign Exchange Rate Adj. | B55: 7 | C55: -3 | D55: -8 | E55: -5 | F55: -10 | G55: 6
A56: Net Change in Cash | B56: 3270 | C56: -2420 | D56: -952 | E56: -460 | F56: 75 | G56: 155
A58: Supplemental Items
A59: Cash Interest Paid | B59: 50 | C59: 22 | D59: 31 | E59: 51 | F59: 46 | G59: 44
A60: Cash Taxes Paid | B60: 442 | C60: 716 | D60: 283 | E60: 543 | F60: 643 | G60: 284
A61: Levered Free Cash Flow | B61: 3760 | C61: 1825.625 | D61: 482.875 | E61: 574.125 | F61: 1457.125 | G61: 842.5
A62: Unlevered Free Cash Flow | B62: 3792.5 | C62: 1841.25 | D62: 504.75 | E62: 606.625 | F62: 1489 | G62: 871.875
A63: Change in Net Working Capital | B63: -1864 | C63: 313 | D63: 835 | E63: 747 | F63: -105 | G63: 501
A64: Net Debt Issued | B64: -24 | C64: -133 | D64: -19 | E64: -19 | F64: -17 | G64: -13
A65: Filing Date | B65: 45002 | C65: 45366 | D65: 45735 | E65: 46099 | F65: 46099 | G65: 46099
A66: Restatement Type | B66: NC | C66: NC | D66: NC | E66: NC | F66: NC | G66: O
A67: Calculation Type | B67: REP | C67: REP | D67: REP | E67: REP | F67: REP | G67: REP

Sheet Historical Capitalization
A1: Best Buy Co., Inc. (NYSE:BBY) > Financials > Historical Capitalization
A3: In Millions of the trading currency, except per share items. | B3: Frequency: | C3: Quarterly | E3: Order: | F3: Latest on Right
B4: Currency: | C4: Trading Currency | E4: Conversion: | F4: Historical
B5: Units: | C5: S&P Capital IQ (Default) | E5: Decimals: | F5: Capital IQ (Default)
B6: Dilution: | C6: Basic
A9: Historical Capitalization
A10: Balance Sheet as of: | B10: 45598 | C10: 45689 | D10: 45780 | E10: 45871 | F10: 45962 | G10: 46053
A11: Pricing as of* | B11: 45632 | C11: 45735 | D11: 45814 | E11: 45905 | F11: 45996 | G11: 46099
A12: Currency | B12: USD | C12: USD | D12: USD | E12: USD | F12: USD | G12: USD
A13: Capitalization Detail
A14: Share Price | B14: 88.17 | C14: 73.79 | D14: 73.02 | E14: 76.17 | F14: 74.17 | G14: 62.87
A15: Shares Out. | B15: 213.7956 | C15: 211.36966 | D15: 211.34669 | E15: 210.10127 | F15: 209.5351 | G15: 209.11258
A17: Market Capitalization | B17: 18850.358 | C17: 15596.967 | D17: 15432.536 | E17: 16003.413 | F17: 15541.219 | G17: 13146.908
A18: - Cash & Short Term Investments | B18: 832 | C18: 1768 | D18: 1339 | E18: 1619 | F18: 1085 | G18: 1891
A19: + Total Debt | B19: 4081 | C19: 4067 | D19: 4059 | E19: 4076 | F19: 4100 | G19: 4134
A20: + Pref. Equity | B20: - | C20: - | D20: - | E20: - | F20: - | G20: -
A21: + Total Minority Interest | B21: - | C21: - | D21: - | E21: - | F21: - | G21: -
A22: - Long Term Marketable Securities | B22: - | C22: - | D22: - | E22: - | F22: - | G22: -
A23: = Total Enterprise Value (TEV) | B23: 22099.358 | C23: 17895.967 | D23: 18152.536 | E23: 18460.413 | F23: 18556.219 | G23: 15389.908
A25: Book Value of Common Equity | B25: 3082 | C25: 2808 | D25: 2763 | E25: 2716 | F25: 2653 | G25: 2964
A26: + Pref. Equity | B26: - | C26: - | D26: - | E26: - | F26: - | G26: -
A27: + Total Minority Interest | B27: - | C27: - | D27: - | E27: - | F27: - | G27: -
A28: + Total Debt | B28: 4081 | C28: 4067 | D28: 4059 | E28: 4076 | F28: 4100 | G28: 4134
A29: = Total Capital | B29: 7163 | C29: 6875 | D29: 6822 | E29: 6792 | F29: 6753 | G29: 7098
A32: * Pricing as of the filing date of the balance sheet period end date. For TEV calculation purposes on this page Capital IQ only uses balance sheet components from the original filing that is publicly available as of a given pricing date and does not use restated balance sheet data from a later filing. In the cases where a company did not disclose balance sheet values for a particular period, TEV is calculated using balance sheet components from the last reported balance sheet as of this date. The table above is organized along period end dates.
A33: ** For companies that have multiple share classes that publicly trade, we are incorporating the different prices to calculate our company level market capitalization. Please click on the value to see the detailed calculation. Prices shown on this page are the close price of the company’s primary stock class. Shares shown on this page are total company as-reported share values.
A35: Historical Equity Pricing Data supplied by Interactive Data Pricing and Reference Data LLC

Sheet Multiples
A1: Best Buy Co., Inc. (NYSE:BBY) > Financials > Multiples
B3: View: | C3: Data | E3: Frequency: | F3: Quarterly
B4: Order: | C4: Latest on Right | E4: Decimals: | F4: Capital IQ (Default)
B5: Dilution: | C5: Basic
A8: Multiples Detail In Millions of the reported currency, except per share items.
A10: For Quarter Ending | C10: 45565 | D10: 45657 | E10: 45747 | F10: 45838 | G10: 45930 | H10: 46022 | I10: 46112 | J10: 46119
A11: TEV/LTM Total Revenue | B11: Average | C11: 0.51745584 | D11: 0.52767127 | E11: 0.48941468 | F11: 0.40564106 | G11: 0.42812634 | H11: 0.44885027 | I11: 0.39558675 | J11: 0.376101
B12: High | C12: 0.580532 | D12: 0.570689 | E12: 0.538193 | F12: 0.447596 | G12: 0.455347 | H12: 0.483328 | I12: 0.433643 | J12: 0.377317
B13: Low | C13: 0.468731 | D13: 0.495777 | E13: 0.421518 | F13: 0.341254 | G13: 0.392577 | H13: 0.407392 | I13: 0.356753 | J13: 0.37491
B14: Close | C14: 0.580532 | D14: 0.511359 | E14: 0.430021 | F14: 0.407925 | G14: 0.441003 | H14: 0.407392 | I14: 0.375813 | J14: 0.37491
A16: TEV/NTM Total Revenues | B16: Average | C16: 0.525941 | D16: 0.534847 | E16: 0.494288 | F16: 0.405356 | G16: 0.425871 | H16: 0.444067 | I16: 0.392896 | J16: 0.375293
B17: High | C17: 0.587851 | D17: 0.577883 | E17: 0.546734 | F17: 0.44675 | G17: 0.450277 | H17: 0.478192 | I17: 0.429257 | J17: 0.376507
B18: Low | C18: 0.47737 | D18: 0.502436 | E18: 0.419845 | F18: 0.340551 | G18: 0.391835 | H18: 0.403271 | I18: 0.355986 | J18: 0.374104
B19: Close | C19: 0.587851 | D19: 0.519502 | E19: 0.428391 | F19: 0.407154 | G19: 0.436092 | H19: 0.403271 | I19: 0.375005 | J19: 0.374104
A21: TEV/LTM EBITDA | B21: Average | C21: 6.0192871 | D21: 6.0896658 | E21: 5.6394373 | F21: 4.6657831 | G21: 4.9412117 | H21: 5.2026955 | I21: 4.5722297 | J21: 4.3303095
B22: High | C22: 6.703072 | D22: 6.589414 | E22: 6.205838 | F22: 5.149751 | G22: 5.283555 | H22: 5.60823 | I22: 5.017885 | J22: 4.344314
B23: Low | C23: 5.476463 | D23: 5.724451 | E23: 4.850327 | F23: 3.924573 | G23: 4.516738 | H23: 4.714119 | I23: 4.107539 | J23: 4.316594
B24: Close | C24: 6.703072 | D24: 5.896412 | E24: 4.945422 | F24: 4.693325 | G24: 5.117115 | H24: 4.714119 | I24: 4.326989 | J24: 4.316594
A26: TEV/NTM EBITDA | B26: Average | C26: 8.302593 | D26: 8.366515 | E26: 7.794261 | F26: 6.457449 | G26: 6.827824 | H26: 7.083676 | I26: 6.228795 | J26: 5.910956
B27: High | C27: 9.169237 | D27: 9.013763 | E27: 8.617115 | F27: 7.161339 | G27: 7.218066 | H27: 7.660189 | I27: 6.808821 | J27: 5.930073
B28: Low | C28: 7.585558 | D28: 7.848909 | E28: 6.627467 | F28: 5.390975 | G28: 6.281058 | H28: 6.396637 | I28: 5.60687 | J28: 5.892234
B29: Close | C29: 9.169237 | D29: 8.189985 | E29: 6.767225 | F29: 6.526623 | G29: 6.989383 | H29: 6.396637 | I29: 5.906424 | J29: 5.892234
A31: TEV/LTM EBIT | B31: Average | C31: 12.505057 | D31: 12.523514 | E31: 11.621595 | F31: 9.6876225 | G31: 10.253603 | H31: 10.755262 | I31: 9.3612819 | J31: 8.843796
B32: High | C32: 13.795596 | D32: 13.561678 | E32: 12.74581 | F32: 10.680472 | G32: 10.974244 | H32: 11.648613 | I32: 10.2935 | J32: 8.872397
B33: Low | C33: 11.439723 | D33: 11.781497 | E33: 10.071824 | F33: 8.153989 | G33: 9.367616 | H33: 9.670365 | I33: 8.388832 | J33: 8.815785
B34: Close | C34: 13.795596 | D34: 12.110298 | E34: 10.274982 | F34: 9.733853 | G34: 10.628538 | H34: 9.670365 | I34: 8.837014 | J34: 8.815785
A36: TEV/NTM EBIT | B36: Average | C36: 12.507386 | D36: 12.523776 | E36: 11.678864 | F36: 9.68291 | G36: 10.091067 | H36: 10.375193 | I36: 9.101872 | J36: 8.654663
B37: High | C37: 13.717762 | D37: 13.485163 | E37: 12.913261 | F37: 10.622188 | G37: 10.704603 | H37: 11.246026 | I37: 9.933896 | J37: 8.682653
B38: Low | C38: 11.469426 | D38: 11.740587 | E38: 9.921484 | F38: 8.10467 | G38: 9.316497 | H38: 9.33253 | I38: 8.209429 | J38: 8.627251
B39: Close | C39: 13.717762 | D39: 12.270232 | E39: 10.131239 | F39: 9.680735 | G39: 10.264651 | H39: 9.33253 | I39: 8.648027 | J39: 8.627251
A41: P/LTM EPS | B41: Average | C41: 15.702455 | D41: 15.700247 | E41: 15.657332 | F41: 16.123612 | G41: 18.343877 | H41: 22.606236 | I41: 18.811628 | J41: 12.749503
B42: High | C42: 17.825702 | D42: 17.489205 | E42: 18.553738 | F42: 18.266454 | G42: 21.625823 | H42: 26.79591 | I42: 23.880721 | J42: 12.797619
B43: Low | C43: 14.066098 | D43: 14.573741 | E43: 14.009265 | F43: 13.123831 | G43: 15.635363 | H43: 19.412525 | I43: 11.984126 | J43: 12.70238
B44: Close | C44: 17.825702 | D44: 14.676373 | E44: 17.198598 | F44: 16.369337 | G44: 20.843037 | H44: 22.146829 | I44: 12.738095 | J44: 12.70238
A46: P/NTM EPS | B46: Average | C46: 14.12308 | D46: 13.965772 | E46: 12.817336 | F46: 10.81383 | G46: 11.244334 | H46: 11.640285 | I46: 9.986151 | J46: 9.878276
B47: High | C47: 15.762329 | D47: 15.464782 | E47: 14.100857 | F47: 11.929027 | G47: 12.092535 | H47: 12.9394 | I47: 10.849857 | J47: 9.915556
B48: Low | C48: 12.77019 | D48: 13.133757 | E48: 11.042382 | F48: 8.912378 | G48: 10.151994 | H48: 10.062089 | I48: 9.285265 | J48: 9.841766
B49: Close | C49: 15.762329 | D49: 13.242784 | E49: 11.595084 | F49: 10.627721 | G49: 11.654824 | H49: 10.062089 | I49: 9.869437 | J49: 9.841766
A51: P/LTM Normalized EPS | B51: Average | C51: 17.42125 | D51: 17.338443 | E51: 15.775772 | F51: 13.300018 | G51: 14.060121 | H51: 14.828431 | I51: 12.508829 | J51: 12.155199
B52: High | C52: 19.651867 | D52: 19.280897 | E52: 17.261787 | F52: 14.819305 | G52: 15.395585 | H52: 16.482656 | I52: 13.801301 | J52: 12.201071
B53: Low | C53: 15.664852 | D53: 16.143845 | E53: 13.75673 | F53: 10.991686 | G53: 12.564606 | H53: 12.799239 | I53: 11.425499 | J53: 12.110272
B54: Close | C54: 19.651867 | D54: 16.257534 | E54: 14.40445 | F54: 13.154429 | G54: 14.838314 | H54: 12.799239 | I54: 12.144322 | J54: 12.110272
A56: P/BV | B56: Average | C56: 6.288741 | D56: 6.3246453 | E56: 5.8768763 | F56: 5.1453012 | G56: 5.5134959 | H56: 5.9607666 | I56: 5.010457 | J56: 4.5331452
B57: High | C57: 7.148214 | D57: 7.013276 | E57: 6.319656 | F57: 5.728731 | G57: 6.07805 | H57: 6.507216 | I57: 5.712665 | J57: 4.550253
B58: Low | C58: 5.625471 | D58: 5.91037 | E58: 5.347607 | F58: 4.228752 | G58: 4.903567 | H58: 5.297889 | I58: 4.261012 | J58: 4.51639
B59: Close | C59: 7.148214 | D59: 5.951992 | E59: 5.541721 | F59: 5.133756 | G59: 5.858044 | H59: 5.297889 | I59: 4.529089 | J59: 4.51639
A61: P/Tangible BV | B61: Average | C61: 12.134943 | D61: 12.083496 | E61: 10.60218 | F61: 7.9464557 | G61: 8.523135 | H61: 8.9901005 | I61: 7.0617511 | J61: 6.1946715
B62: High | C62: 13.684227 | D62: 13.425909 | E62: 12.272955 | F62: 8.857573 | G62: 9.465587 | H62: 10.133945 | I62: 8.165786 | J62: 6.218049
B63: Low | C63: 10.994105 | D63: 11.147096 | E63: 7.9032 | F63: 6.564034 | G63: 7.581733 | H63: 7.572898 | I63: 5.822794 | J63: 6.171776
B64: Close | C64: 13.684227 | D64: 11.558941 | E64: 8.602075 | F64: 7.937644 | G64: 9.122963 | H64: 7.572898 | I64: 6.189128 | J64: 6.171776
A66: P/NTM CFPS | B66: Average | C66: 8.674189 | D66: 8.496645 | E66: 7.709934 | F66: 6.642751 | G66: 7.327423 | H66: 8.07281 | I66: 7.127479 | J66: 6.848741
B67: High | C67: 9.650688 | D67: 9.468511 | E67: 8.428317 | F67: 7.556057 | G67: 8.362489 | H67: 9.478661 | I67: 8.803683 | J67: 6.874588
B68: Low | C68: 7.861447 | D68: 7.882466 | E68: 6.736749 | F68: 5.382691 | G68: 6.467686 | H68: 7.243898 | I68: 6.437598 | J68: 6.823428
B69: Close | C69: 9.650688 | D69: 7.937976 | E69: 7.053941 | F69: 6.7713 | G69: 7.856949 | H69: 7.243898 | I69: 6.842613 | J69: 6.823428
A71: TEV/LTM Unlevered FCF | B71: Average | C71: 17.997201 | D71: 16.991191 | E71: 16.400949 | F71: 11.677619 | G71: 13.610586 | H71: 16.167296 | I71: 16.366193 | J71: 17.984288
B72: High | C72: 19.635606 | D72: 22.499783 | E72: 18.799114 | F72: 14.435939 | G72: 18.579128 | H72: 19.927434 | I72: 22.974189 | J72: 18.04245
B73: Low | C73: 16.060954 | D73: 14.595643 | E73: 11.838502 | F73: 9.525547 | G73: 11.407624 | H73: 14.502976 | I73: 13.550604 | J73: 17.927325
B74: Close | C74: 17.090833 | D74: 17.861782 | E74: 12.003307 | F74: 11.853617 | G74: 15.539904 | H74: 14.502976 | I74: 17.970497 | J74: 17.927325
A76: Market Cap/LTM Levered FCF | B76: Average | C76: 16.217203 | D76: 15.207592 | E76: 14.400724 | F76: 10.186779 | G76: 11.894595 | H76: 14.216574 | I76: 14.100354 | J76: 15.949022
B77: High | C77: 17.939564 | D77: 19.774621 | E77: 16.556607 | F77: 12.403628 | G77: 16.511293 | H77: 17.321456 | I77: 20.479435 | J77: 16.009212
B78: Low | C78: 14.657745 | D78: 13.158052 | E78: 10.518575 | F78: 8.154981 | G78: 9.717855 | H78: 12.256224 | I78: 11.278363 | J78: 15.890073
B79: Close | C79: 15.711788 | D79: 15.59338 | E79: 10.686989 | F79: 10.174043 | G79: 13.824544 | H79: 12.256224 | I79: 15.93475 | J79: 15.890073
A81: Average multiples are calculated using positive close values on each trading day within the frequency periods selected. Negative values are excluded from the calculation. When the Multiples are not meaningful, due to negative values, then they will not be displayed in the chart.
A83: When a mismatch exists between the currency of the equity listing and the reported financial results such results are translated into the currency of the listing at the exchange rate applicable on the financial period end date.
A87: Historical Equity Pricing Data supplied by Interactive Data Pricing and Reference Data LLC

Sheet Model ==>
A1: Financial Model and Calculations

Sheet Revenue Build - Bottom Up
B1: Revenue forecast - using bottom up approach
B2: Bottom-up revenue: (Domestic * SSS growth * Store Count) + Online + Canada
B3: Description | C3: 2021A | D3: 2022A | E3: 2023A | F3: 2024A | G3: 2025A | H3: 2026A | I3: 2027E | J3: 2028E | K3: 2029E | L3: 2030E | M3: 2031E
B4: DOMESTIC REVENUE
B5: Prior Year Domestic Revenue | C5: ='Revenue Build - Top Down'!D37 -> 40114 | D5: ='Revenue Build - Top Down'!E37 -> 43293 | E5: ='Revenue Build - Top Down'!F37 -> 47830 | F5: ='Revenue Build - Top Down'!G37 -> 42794 | G5: ='Revenue Build - Top Down'!H37 -> 40097 | H5: ='Revenue Build - Top Down'!I37 -> 38238 | I5: =H5*(1+Assumptions!B7) -> 38620.38 | J5: =I5*(1+Assumptions!C7) -> 39199.686 | K5: =J5*(1+Assumptions!D7) -> 39983.679 | L5: =K5*(1+Assumptions!E7) -> 40783.353 | M5: =L5*(1+Assumptions!F7) -> 41599.02
B6: SSS Growth % | C6: =(D5-C5)/C5 -> 0.07924914 | D6: =(E5-D5)/D5 -> 0.10479754 | E6: =(F5-E5)/E5 -> -0.10528957 | F6: =(G5-F5)/F5 -> -0.063022854 | G6: =(H5-G5)/G5 -> -0.046362571 | H6: =(I5-H5)/H5 -> 0.01 | I6: =Assumptions!B24 -> 0.004 | J6: =Assumptions!C24 -> 0.01 | K6: =Assumptions!D24 -> 0.0228 | L6: =Assumptions!E24 -> 0.03 | M6: =L6 -> 0.03
B7: Projected Domestic Revenue | C7: =C5*(1+C6) -> 43293 | D7: =D5*(1+D6) -> 47830 | E7: =E5*(1+E6) -> 42794 | F7: =F5*(1+F6) -> 40097 | G7: =G5*(1+G6) -> 38238 | H7: =H5*(1+H6) -> 38620.38 | I7: =I5*(1+I6) -> 38774.862 | J7: =J5*(1+J6) -> 39591.683 | ... M7: =M5*(1+M6) -> 42846.991
B8: INTERNATIONAL REVENUE
B9: Canada Revenue | C9: ='Revenue Build - Top Down'!D51 -> 4511.45 | D9: ='Revenue Build - Top Down'!E51 -> 4481.154 | E9: ='Revenue Build - Top Down'!F51 -> 3737.646 | F9: ='Revenue Build - Top Down'!G51 -> 3402.3564 | G9: ='Revenue Build - Top Down'!H51 -> 3338.225 | H9: ='Revenue Build - Top Down'!I51 -> 3365.67 | I9: =H9*(1+Assumptions!B8) -> 3399.3267 | J9: =I9*(1+Assumptions!C8) -> 3450.3166 | K9: =J9*(1+Assumptions!D8) -> 3519.3229 | L9: =K9*(1+Assumptions!E8) -> 3589.7094 | M9: =L9*(1+Assumptions!F8) -> 3661.5036
B10: Total Revenue (domestic and international) | C10: =C7+C9 -> 47804.45 | D10: =D7+D9 -> 52311.154 | E10: =E7+E9 -> 46531.646 | F10: =F7+F9 -> 43499.356 | G10: =G7+G9 -> 41576.225 | H10: =H7+H9 -> 41986.05 | I10: =I7+I9 -> 42174.188 | J10: =J7+J9 -> 43041.999 | ... M10: =M7+M9 -> 46508.494
B12: Difference in total bottom up to top down | C12: =C10-'Revenue Build - Top Down'!D69 -> 542.45 | D12: =D10-'Revenue Build - Top Down'!E69 -> 550.154 | E12: =E10-'Revenue Build - Top Down'!F69 -> 233.646 | F12: =F10-'Revenue Build - Top Down'!G69 -> 47.356375 | G12: =G10-'Revenue Build - Top Down'!H69 -> 48.225 | H12: =H10-'Revenue Build - Top Down'!I69 -> 295.05 | I12: =I10-'Revenue Build - Top Down'!J69 -> 318.55822 | J12: =J10-'Revenue Build - Top Down'!K69 -> -36.555043 | ... M12: =M10-'Revenue Build - Top Down'!N69 -> 198.13058
B13: Segment breakdown:
B14: ONLINE REVENUE
B15: Online Penetration Rate | C15: ='Revenue Build - Top Down'!D9 -> 0.33 | D15: ='Revenue Build - Top Down'!E9 -> 0.36 | E15: ='Revenue Build - Top Down'!F9 -> 0.34 | F15: ='Revenue Build - Top Down'!G9 -> 0.38 | G15: ='Revenue Build - Top Down'!H9 -> 0.395 | H15: ='Revenue Build - Top Down'!I9 -> 0.39 | I15: =Assumptions!B9 -> 0.4 | J15: =Assumptions!C9 -> 0.41 | K15: =Assumptions!D9 -> 0.42 | L15: =Assumptions!E9 -> 0.43 | M15: =Assumptions!F9 -> 0.44
B16: Online Revenue | C16: =C15*C7 -> 14286.69 | D16: =D15*D7 -> 17218.8 | E16: =E15*E7 -> 14549.96 | F16: =F15*F7 -> 15236.86 | G16: =G15*G7 -> 15104.01 | H16: =H15*H7 -> 15061.948 | I16: =I15*I7 -> 15509.945 | J16: =J15*J7 -> 16232.59 | ... M16: =M15*M7 -> 18852.676
B17: SERVICES REVENUE
B18: Services Revenue | C18: ='Revenue Build - Top Down'!D67 -> 2252 | D18: ='Revenue Build - Top Down'!E67 -> 2380 | E18: ='Revenue Build - Top Down'!F67 -> 2332 | F18: ='Revenue Build - Top Down'!G67 -> 2530 | G18: ='Revenue Build - Top Down'!H67 -> 2631 | H18: ='Revenue Build - Top Down'!I67 -> 2656 | I18: =H18*(1+Assumptions!B26) -> 2948.16 | J18: =I18*(1+Assumptions!C26) -> 3301.9392 | K18: =J18*(1+Assumptions!D26) -> 3698.1719 | L18: =K18*(1+Assumptions!E26) -> 4067.9891 | M18: =L18*(1+Assumptions!F26) -> 4434.1081

Sheet DCF - Base Model
B1: Base Case: Discounted Cash Flow Model
B2: Fiscal Year Ending January | $ in Millions | Blue = Hardcoded Input | Black = Formula
B3: WACC | C3: =WACC!C22 -> 0.10490729
B4: Terminal growth | C4: =Assumptions!B30 -> 0.02
B5: Description | C5: 2026A | D5: 2027E | E5: 2028E | F5: 2029E | G5: 2030E | H5: 2031E
B6: Total Revenue | C6: ='Revenue Build - Top Down'!I69 -> 41691 | D6: ='Revenue Build - Top Down'!J69 -> 41855.63 | E6: ='Revenue Build - Top Down'!K69 -> 43078.554 | F6: ='Revenue Build - Top Down'!L69 -> 44278.874 | G6: ='Revenue Build - Top Down'!M69 -> 45284.272 | H6: ='Revenue Build - Top Down'!N69 -> 46310.364
B7: Free Cashflow Projection
B8: EBIT (Operating Income) | C8: ='Pro Forma Income Statement'!F15 -> 1763.8963 | D8: =D6*Assumptions!B37 -> 1799.7921 | E8: =E6*Assumptions!C37 -> 1981.6135 | F8: =F6*Assumptions!D37 -> 2169.6648 | G8: =G6*Assumptions!E37 -> 2309.4979 | H8: =H6*Assumptions!F37 -> 2454.4493 | I8: =(D8-C8)/C8 -> 0.020350263 | J8: =(E8-$C$8)/$C$8 -> 0.12342968 | K8: =(F8-$C$8)/$C$8 -> 0.230041 | L8: =(G8-$C$8)/$C$8 -> 0.3093161 | M8: =(H8-$C$8)/$C$8 -> 0.39149293
B9: Less: Taxes | C9: =Assumptions!B33*C8 -> 423.33512 | D9: =Assumptions!B33*D8 -> 431.9501 | E9: =Assumptions!C33*E8 -> 475.58724 | F9: =Assumptions!D33*F8 -> 520.71955 | G9: =Assumptions!E33*G8 -> 554.27949 | H9: =Assumptions!F33*H8 -> 589.06783
B10: NOPAT | C10: =C8-C9 -> 1340.5612 | D10: =D8-D9 -> 1367.842 | E10: =E8-E9 -> 1506.0263 | F10: =F8-F9 -> 1648.9453 | G10: =G8-G9 -> 1755.2184 | H10: =H8-H9 -> 1865.3814
B11: (+) Depreciation & Amortization | D11: =Assumptions!B34 -> 800 | E11: =Assumptions!C34 -> 793 | F11: =Assumptions!D34 -> 782 | G11: =Assumptions!E34 -> 772 | H11: =Assumptions!F34 -> 762
B12: (-) Capital Expenditures | C12: =-'Historical Cash Flow'!G30 -> 704 | D12: =Assumptions!B35 -> 750 | E12: =Assumptions!C35 -> 710 | F12: =Assumptions!D35 -> 700 | G12: =Assumptions!E35 -> 690 | H12: =Assumptions!F35 -> 680
B13: (-) Change in Working Capital | D13: =Assumptions!B36 -> 75 | E13: =Assumptions!C36 -> 50 | F13: =Assumptions!D36 -> 35 | G13: =Assumptions!E36 -> 25 | H13: =Assumptions!F36 -> 20
B14: Free Cash Flow to Firm (FCFF) | C14: ='Historical Cash Flow'!G28+('Historical Cash Flow'!G59*Assumptions!B33)-C12 -> 1268.56 | D14: =D10+D11-D12-D13 -> 1342.842 | E14: =E10+E11-E12-E13 -> 1539.0263 | F14: =F10+F11-F12-F13 -> 1695.9453 | G14: =G10+G11-G12-G13 -> 1812.2184 | H14: =H10+H11-H12-H13 -> 1927.3814
B15: PV of FCFF | D15: =D14/(1+$C$3)^1 -> 1215.3436 | E15: =E14/(1+$C$3)^1 -> 1392.9008 | F15: =F14/(1+$C$3)^1 -> 1534.9209 | G15: =G14/(1+$C$3)^1 -> 1640.1542 | H15: =H14/(1+$C$3)^1 -> 1744.383
B16: Terminal Value (Gordon Growth Model)
B17: Terminal Value | H17: =(H14*(1+$C$4))/($C$3-$C$4) -> 23153.83
B18: PV of Terminal Value | H18: =H17/(1+C3)^5 -> 14060.269
B19: Enterprise Value
B20: Sum of PV(FCFs) | C20: =SUM(D15:H15) -> 7527.7024
B21: PV of Terminal Value | C21: =H18 -> 14060.269
B22: Terminal Value as % of EV | C22: =C21/C23 -> 0.65130108
B23: EV | C23: =C21+C20 -> 21587.972
B24: Less: Net Debt | C24: -1155
B25: Equity Value | C25: =C23+C24 -> 20432.972
B27: Diluted Shares Outstanding (M) | C27: 210
B29: Implied Share Price (Per Share) | C29: =C25/C27 -> 97.299866
B31: Exit Multiple Method
B32: EBITDA | C32: =H8+H11 -> 3216.4493
B33: Exit Multiple | C33: 5.2
B34: EV | C34: =C32*C33 -> 16725.536
B35: Less: Net Debt | C35: =C24 -> -1155
B36: Equity Value | C36: =C34-C35 -> 17880.536
B38: Implied Share Price (Per Share) | C38: =C36/C27 -> 85.145411
B40: FCFF GGM Sensitivity Analysis | I40: EM Sensitivity Analysis
B42: =C29 -> 97.299866 | C42: 0.095 | D42: 0.1 | E42: 0.105 | F42: 0.11 | G42: 0.115 | I42: =C38 -> 85.145411 | J42: 0.095 | K42: 0.1 | L42: 0.105 | M42: 0.11 | N42: 0.115
B43: 0.01 | C43: 99.94612 | D43: 94.459545 | E43: 89.572243 | F43: 85.193413 | G43: 81.24958 | I43: 3.5 | J43: 59.107488 | K43: 59.107488 | L43: 59.107488 | M43: 59.107488 | N43: 59.107488
B44: 0.015 | C44: 104.64023 | D44: 98.556736 | E44: 93.172249 | F44: 88.375432 | G44: 84.077255 | I44: 4 | J44: 66.7657 | K44: 66.7657 | L44: 66.7657 | M44: 66.7657 | N44: 66.7657
B45: 0.02 | C45: 109.96021 | D45: 103.16608 | E45: 97.195784 | F45: 91.91101 | G45: 87.202581 | I45: 4.62 | J45: 76.261884 | K45: 76.261884 | L45: 76.261884 | M45: 76.261884 | N45: 76.261884
B46: 0.025 | C46: 116.0402 | D46: 108.38999 | E46: 101.72226 | F46: 95.862538 | G46: 90.675166 | I46: 5 | J46: 82.082126 | K46: 82.082126 | L46: 82.082126 | M46: 82.082126 | N46: 82.082126
B47: 0.03 | C47: 123.05557 | D47: 114.36019 | E47: 106.85227 | F47: 100.30801 | G47: 94.556289 | I47: 5.5 | J47: 89.740338 | K47: 89.740338 | L47: 89.740338 | M47: 89.740338 | N47: 89.740338
B49: With current stock price 4/15/2026
B50: 63.39
B51: =(G43-B50)/B50 -> 0.28174128
B52: =(F44-B50)/B50 -> 0.39415416
B53: Even at a higher WACC and lower growth, we are looking at a $81-88 per share. Which is about 30% or higher growth in price.

Sheet Revenue Build - Final Bear Case
B1: Revenue forecast - Bear Case
B3: Description | C3: Units | D3: 2021A | E3: 2022A | F3: 2023A | G3: 2024A | H3: 2025A | I3: 2026A | J3: 2027E | K3: 2028E | L3: 2029E | M3: 2030E | N3: 2031E
B4: Key Revenue Drivers Based on Assumptions
B5: Store Sales
B6: Total Comparable Sales Growth | C6: % | D6: ='Industry Metrics'!G3 -> 0.097 | E6: ='Industry Metrics'!F3 -> 0.104 | F6: ='Industry Metrics'!E3 -> -0.099 | G6: ='Industry Metrics'!D3 -> -0.068 | H6: ='Industry Metrics'!C3 -> -0.023 | I6: ='Industry Metrics'!B3 -> 0.005 | J6: -0.03 | K6: 0.01 | L6: 0.015 | M6: =Assumptions!E6 -> 0.02 | N6: =Assumptions!F6 -> 0.02 | O6: Bear case if the AI PC doesnt go through
B7: Domestic Comparable Sales Growth | C7: % | D7: ='Industry Metrics'!G4 -> 0.092 | E7: ='Industry Metrics'!F4 -> 0.11 | F7: ='Industry Metrics'!E4 -> -0.103 | G7: ='Industry Metrics'!D4 -> -0.071 | H7: ='Industry Metrics'!C4 -> -0.025 | I7: ='Industry Metrics'!B4 -> 0.004 | J7: -0.03 | K7: 0.01 | L7: 0.015 | M7: =Assumptions!E7 -> 0.02 | N7: =Assumptions!F7 -> 0.02
B8: International Comparable Sales Growth | C8: % | D8: ='Industry Metrics'!G5 -> 0.15 | E8: ='Industry Metrics'!F5 -> 0.033 | F8: ='Industry Metrics'!E5 -> -0.054 | G8: ='Industry Metrics'!D5 -> -0.032 | H8: ='Industry Metrics'!C5 -> -0.005 | I8: ='Industry Metrics'!B5 -> 0.023 | J8: -0.03 | K8: 0.01 | L8: 0.015 | M8: =Assumptions!E8 -> 0.02 | N8: =Assumptions!F8 -> 0.02
B9: Online Revenue as % of Domestic Rev | C9: % | D9: ='Industry Metrics'!G9 -> 0.33 | E9: ='Industry Metrics'!F9 -> 0.36 | F9: ='Industry Metrics'!E9 -> 0.34 | G9: ='Industry Metrics'!D9 -> 0.38 | H9: ='Industry Metrics'!C9 -> 0.395 | I9: ='Industry Metrics'!B9 -> 0.39 | J9: =Assumptions!B9 -> 0.4 | K9: =Assumptions!C9 -> 0.41 | L9: =Assumptions!D9 -> 0.42 | M9: =Assumptions!E9 -> 0.43 | N9: =Assumptions!F9 -> 0.44
B10: Total Store Count
B11: Beginning Store Count | C11: # | D11: ='Industry Metrics'!G12 -> 1231 | E11: ='Industry Metrics'!F12 -> 1159 | F11: ='Industry Metrics'!E12 -> 1144 | G11: ='Industry Metrics'!D12 -> 1138 | H11: ='Industry Metrics'!C12 -> 1125 | I11: ='Industry Metrics'!B12 -> 1117 | J11: =I14 -> 1068 | K11: =J14 -> 1056 | L11: =K14 -> 1044 | M11: =L14 -> 1033 | N11: =M14 -> 1023
B12: Stores Opened | C12: # | D12: ='Industry Metrics'!G19 -> 3 | E12: ='Industry Metrics'!F19 -> 13 | F12: ='Industry Metrics'!E19 -> 9 | G12: ='Industry Metrics'!D20 -> 15 | H12: ='Industry Metrics'!C19 -> 0 | I12: ='Industry Metrics'!B20 -> 0 | J12: =Assumptions!B11 -> 6 | K12: =Assumptions!C11 -> 6 | L12: =Assumptions!D11 -> 5 | M12: =Assumptions!E11 -> 5 | N12: =Assumptions!F11 -> 5
B13: Stores Closed | C13: # | D13: ='Industry Metrics'!G23 -> 75 | E13: ='Industry Metrics'!F23 -> 28 | F13: ='Industry Metrics'!E23 -> 15 | G13: ='Industry Metrics'!D23 -> 28 | H13: ='Industry Metrics'!C23 -> 8 | I13: ='Industry Metrics'!B23 -> 49 | J13: =Assumptions!B12 -> 18 | K13: =Assumptions!C12 -> 18 | L13: =Assumptions!D12 -> 16 | M13: =Assumptions!E12 -> 15 | N13: =Assumptions!F12 -> 15
B14: Ending Store Count | C14: # | D14: =D11+D12-D13 -> 1159 | E14: =E11+E12-E13 -> 1144 | F14: =F11+F12-F13 -> 1138 | G14: =G11+G12-G13 -> 1125 | H14: =H11+H12-H13 -> 1117 | I14: =I11+I12-I13 -> 1068 | J14: =J11+J12-J13 -> 1056 | K14: =K11+K12-K13 -> 1044 | ... N14: =N11+N12-N13 -> 1013
B15: Average Store Count | C15: # | D15: =(D11+D14)/2 -> 1195 | E15: =(E11+E14)/2 -> 1151.5 | F15: =(F11+F14)/2 -> 1141 | G15: =(G11+G14)/2 -> 1131.5 | H15: =(H11+H14)/2 -> 1121 | I15: =(I11+I14)/2 -> 1092.5 | J15: =(J11+J14)/2 -> 1062 | K15: =(K11+K14)/2 -> 1050 | ... N15: =(N11+N14)/2 -> 1018
B16: Domestic Store Count | C16: #
B17: Beginning Store Count | C17: # | D17: ='Industry Metrics'!G13 -> 1009 | E17: ='Industry Metrics'!F13 -> 991 | F17: ='Industry Metrics'!E13 -> 984 | G17: ='Industry Metrics'!D13 -> 978 | H17: ='Industry Metrics'!C13 -> 965 | I17: ='Industry Metrics'!B13 -> 957 | J17: =I20 -> 926 | K17: =J20 -> 917 | L17: =K20 -> 908 | M17: =L20 -> 899 | N17: =M20 -> 891
B18: Stores Opened | C18: # | D18: ='Industry Metrics'!G21 -> 3 | E18: ='Industry Metrics'!F21 -> 13 | F18: ='Industry Metrics'!E21 -> 9 | G18: ='Industry Metrics'!D21 -> 14 | H18: ='Industry Metrics'!C21 -> 0 | I18: ='Industry Metrics'!B21 -> 0 | J18: =Assumptions!B13 -> 6 | K18: =Assumptions!C13 -> 6 | L18: =Assumptions!D13 -> 5 | M18: =Assumptions!E13 -> 5 | N18: =Assumptions!F13 -> 5
B19: Stores Closed | C19: # | D19: ='Industry Metrics'!G24 -> 21 | E19: ='Industry Metrics'!F24 -> 20 | F19: ='Industry Metrics'!E24 -> 15 | G19: ='Industry Metrics'!D24 -> 27 | H19: ='Industry Metrics'!C24 -> 8 | I19: ='Industry Metrics'!B24 -> 31 | J19: =Assumptions!B14 -> 15 | K19: =Assumptions!C14 -> 15 | L19: =Assumptions!D14 -> 14 | M19: =Assumptions!E14 -> 13 | N19: =Assumptions!F14 -> 13
B20: Ending Store Count | C20: # | D20: =D17+D18-D19 -> 991 | E20: =E17+E18-E19 -> 984 | F20: =F17+F18-F19 -> 978 | G20: =G17+G18-G19 -> 965 | H20: =H17+H18-H19 -> 957 | I20: =I17+I18-I19 -> 926 | J20: =J17+J18-J19 -> 917 | K20: =K17+K18-K19 -> 908 | ... N20: =N17+N18-N19 -> 883
B21: Average Store Count | C21: # | D21: =(D17+D20)/2 -> 1000 | E21: =(E17+E20)/2 -> 987.5 | F21: =(F17+F20)/2 -> 981 | G21: =(G17+G20)/2 -> 971.5 | H21: =(H17+H20)/2 -> 961 | I21: =(I17+I20)/2 -> 941.5 | J21: =(J17+J20)/2 -> 921.5 | K21: =(K17+K20)/2 -> 912.5 | ... N21: =(N17+N20)/2 -> 887
B22: International Store Count | C22: #
B23: Beginning Store Count | C23: # | D23: ='Industry Metrics'!G14 -> 222 | E23: ='Industry Metrics'!F14 -> 168 | F23: ='Industry Metrics'!E14 -> 160 | G23: ='Industry Metrics'!D14 -> 160 | H23: ='Industry Metrics'!C14 -> 160 | I23: ='Industry Metrics'!B14 -> 160 | J23: =I26 -> 142 | K23: =J26 -> 139 | L23: =K26 -> 136 | M23: =L26 -> 134 | N23: =M26 -> 132
B24: Stores Opened | C24: # | D24: ='Industry Metrics'!G22 -> 0 | E24: ='Industry Metrics'!F22 -> 0 | F24: ='Industry Metrics'!E25 -> 0 | G24: ='Industry Metrics'!D25 -> 1 | H24: ='Industry Metrics'!C25 -> 0 | I24: ='Industry Metrics'!B22 -> 0 | J24: =Assumptions!B15 -> 0 | K24: =Assumptions!C15 -> 0 | L24: =Assumptions!D15 -> 0 | M24: =Assumptions!E15 -> 0 | N24: =Assumptions!F15 -> 0
B25: Stores Closed | C25: # | D25: ='Industry Metrics'!G25 -> 54 | E25: ='Industry Metrics'!F25 -> 8 | F25: ='Industry Metrics'!E25 -> 0 | G25: ='Industry Metrics'!D25 -> 1 | H25: ='Industry Metrics'!C25 -> 0 | I25: ='Industry Metrics'!B25 -> 18 | J25: =Assumptions!B16 -> 3 | K25: =Assumptions!C16 -> 3 | L25: =Assumptions!D16 -> 2 | M25: =Assumptions!E16 -> 2 | N25: =Assumptions!F16 -> 2
B26: Ending Store Count | C26: # | D26: =D23+D24-D25 -> 168 | E26: =E23+E24-E25 -> 160 | F26: =F23+F24-F25 -> 160 | G26: =G23+G24-G25 -> 160 | H26: =H23+H24-H25 -> 160 | I26: =I23+I24-I25 -> 142 | J26: =J23+J24-J25 -> 139 | K26: =K23+K24-K25 -> 136 | ... N26: =N23+N24-N25 -> 130
B27: Average Store Count | C27: # | D27: =(D23+D26)/2 -> 195 | E27: =(E23+E26)/2 -> 164 | F27: =(F23+F26)/2 -> 160 | G27: =(G23+G26)/2 -> 160 | H27: =(H23+H26)/2 -> 160 | I27: =(I23+I26)/2 -> 151 | J27: =(J23+J26)/2 -> 140.5 | K27: =(K23+K26)/2 -> 137.5 | ... N27: =(N23+N26)/2 -> 131
B28: Revenue Per Store
B29: Domestic Rev per Avg. Store (in millions USD) | C29: $ | D29: ='Geographic Revenue'!F6/D21 -> 43.293 | E29: ='Geographic Revenue'!G6/E21 -> 48.435443 | F29: ='Geographic Revenue'!H6/F21 -> 43.622834 | G29: ='Geographic Revenue'!I6/G21 -> 41.273289 | H29: ='Geographic Revenue'!J6/H21 -> 39.789802 | I29: ='Geographic Revenue'!K6/I21 -> 40.656399 | J29: =J43/J21 -> 40.42102 | K29: =K43/K21 -> 41.36211 | L29: =L43/L21 -> 42.516907 | M29: =M43/M21 -> 43.900251 | N29: =N43/N21 -> 45.308325
B30: Y/Y Growth Domestic Rev per Store | C30: % | E30: =E29/D29-1 -> 0.11878232 | F30: =F29/E29-1 -> -0.099361313 | G30: =G29/F29-1 -> -0.053860442 | H30: =H29/G29-1 -> -0.035943015 | I30: =I29/H29-1 -> 0.021779376 | J30: =J29/I29-1 -> -0.0057894737 | K30: =K29/J29-1 -> 0.023282192 | L30: =L29/K29-1 -> 0.027919203 | ... N30: =N29/M29-1 -> 0.032074408
B31: International Rev per Avg. Store (in millions USD) | C31: $ | D31: =SUM('Geographic Revenue'!F7:F9)/D27 -> 22.246154 | E31: =SUM('Geographic Revenue'!G7:G9)/E27 -> 24.091463 | F31: =SUM('Geographic Revenue'!H7:H9)/F27 -> 21.9 | G31: =SUM('Geographic Revenue'!I7:I9)/G27 -> 20.96875 | H31: =SUM('Geographic Revenue'!J7:J9)/H27 -> 20.5625 | I31: =SUM('Geographic Revenue'!K7:K9)/I27 -> 22.602649 | J31: =J51/J27 -> 23.56306 | K31: =K51/K27 -> 24.317935 | L31: =L51/L27 -> 25.139791 | M31: =M51/M27 -> 26.02819 | N31: =N51/N27 -> 26.954078
B32: Y/Y Growth International Rev per Store | C32: % | E32: =E31/D31-1 -> 0.0829496 | F32: =F31/E31-1 -> -0.090964313 | G32: =G31/F31-1 -> -0.042522831 | H32: =H31/G31-1 -> -0.019374069 | I32: =I31/H31-1 -> 0.099216973 | J32: =J31/I31-1 -> 0.042491103 | K32: =K31/J31-1 -> 0.032036364 | L32: =L31/K31-1 -> 0.033796296 | ... N32: =N31/M31-1 -> 0.035572519
B34: Revenue Build
B35: Domestic Revenue Build (in millions USD)
B36: Comparable Store Rev
B37: Prior Year Domestic Revenue | C37: $ | D37: ='Geographic Revenue'!E6 -> 40114 | E37: ='Geographic Revenue'!F6 -> 43293 | F37: ='Geographic Revenue'!G6 -> 47830 | G37: ='Geographic Revenue'!H6 -> 42794 | H37: ='Geographic Revenue'!I6 -> 40097 | I37: ='Geographic Revenue'!J6 -> 38238 | J37: ='Geographic Revenue'!K6 -> 38278 | K37: =J43 -> 37247.97 | L37: =K43 -> 37742.926 | M37: =L43 -> 38414.026 | N37: =M43 -> 39290.724
B38: Comp Store Base Rev | C38: $ | D38: =D37*(1+D7) -> 43804.488 | E38: =E37*(1+E7) -> 48055.23 | F38: =F37*(1+F7) -> 42903.51 | G38: =G37*(1+G7) -> 39755.626 | H38: =H37*(1+H7) -> 39094.575 | I38: =I37*(1+I7) -> 38390.952 | J38: =J37*(1+J7) -> 37129.66 | K38: =K37*(1+K7) -> 37620.45 | ... N38: =N37*(1+N7) -> 40076.539
B39: New Store Rev
B40: Stores Opened during year | C40: # | D40: ='Industry Metrics'!G19 -> 3 | E40: ='Industry Metrics'!F19 -> 13 | F40: ='Industry Metrics'!E19 -> 9 | G40: ='Industry Metrics'!D19 -> 15 | H40: ='Industry Metrics'!C19 -> 0 | I40: ='Industry Metrics'!B20 -> 0 | J40: =J18 -> 6 | K40: =K18 -> 6 | L40: =L18 -> 5 | M40: =M18 -> 5 | N40: =N18 -> 5
B41: Rev per New Store | C41: # | D41: ='Geographic Revenue'!F6/'Revenue Build - Final Bear Case'!D21*50% -> 21.6465 | E41: ='Geographic Revenue'!G6/'Revenue Build - Final Bear Case'!E21*50% -> 24.217722 | F41: ='Geographic Revenue'!H6/'Revenue Build - Final Bear Case'!F21*50% -> 21.811417 | G41: ='Geographic Revenue'!I6/'Revenue Build - Final Bear Case'!G21*50% -> 20.636644 | H41: ='Geographic Revenue'!J6/'Revenue Build - Final Bear Case'!H21*50% -> 19.894901 | I41: ='Geographic Revenue'!K6/'Revenue Build - Final Bear Case'!I21*50% -> 20.3282 | J41: ='Geographic Revenue'!K6/I21*(1+J7)*50% -> 19.718354 | K41: =J43/J21*(1+K7)*50% -> 20.412615 | L41: =K43/K21*(1+L7)*50% -> 20.991271 | M41: =L43/L21*(1+M7)*50% -> 21.683623 | N41: =M43/M21*(1+N7)*50% -> 22.389128
B42: Total new Store Rev | C42: # | D42: =D40*D41 -> 64.9395 | E42: =E40*E41 -> 314.83038 | F42: =F40*F41 -> 196.30275 | G42: =G40*G41 -> 309.54967 | H42: =H40*H41 -> 0 | I42: =I40*I41 -> 0 | J42: =J40*J41 -> 118.31012 | K42: =K40*K41 -> 122.47569 | ... N42: =N40*N41 -> 111.94564
B43: Total Domestic Rev | C43: $ | D43: =D42+D38 -> 43869.428 | E43: =E42+E38 -> 48370.06 | F43: =F42+F38 -> 43099.813 | G43: =G42+G38 -> 40065.176 | H43: =H42+H38 -> 39094.575 | I43: =I42+I38 -> 38390.952 | J43: =J42+J38 -> 37247.97 | K43: =K42+K38 -> 37742.926 | ... N43: =N42+N38 -> 40188.485
B44: International Revenue Build (in millions USD)
B45: Prior Year International Rev | C45: $ | D45: =SUM('Geographic Revenue'!E7:E9) -> 3923 | E45: =SUM('Geographic Revenue'!F7:F9) -> 4338 | F45: =SUM('Geographic Revenue'!G7:G9) -> 3951 | G45: =SUM('Geographic Revenue'!H7:H9) -> 3504 | H45: =SUM('Geographic Revenue'!I7:I9) -> 3355 | I45: =SUM('Geographic Revenue'!J7:J9) -> 3290 | J45: =SUM('Geographic Revenue'!K7:K9) -> 3413 | K45: =J51 -> 3310.61 | L45: =K51 -> 3343.7161 | M45: =L51 -> 3393.8718 | N45: =M51 -> 3461.7493
B46: Comp Store Base Rev | C46: $ | D46: =D45*(1+D8) -> 4511.45 | E46: =E45*(1+E8) -> 4481.154 | F46: =F45*(1+F8) -> 3737.646 | G46: =G45*(1+G8) -> 3391.872 | H46: =H45*(1+H8) -> 3338.225 | I46: =I45*(1+I8) -> 3365.67 | J46: =J45*(1+J8) -> 3310.61 | K46: =K45*(1+K8) -> 3343.7161 | ... N46: =N45*(1+N8) -> 3530.9843
B47: New Store Rev
B48: Stores Opened during year | C48: # | D48: ='Industry Metrics'!G22 -> 0 | E48: ='Industry Metrics'!F22 -> 0 | F48: ='Industry Metrics'!E25 -> 0 | G48: ='Industry Metrics'!D22 -> 1 | H48: ='Industry Metrics'!C22 -> 0 | I48: ='Industry Metrics'!B22 -> 0 | J48: =J24 -> 0 | K48: =K24 -> 0 | L48: =L24 -> 0 | M48: =M24 -> 0 | N48: =N24 -> 0
B49: Rev per New Store | C49: $ | D49: =SUM('Geographic Revenue'!F7:F9)/D27*50% -> 11.123077 | E49: =SUM('Geographic Revenue'!G7:G9)/E27*50% -> 12.045732 | F49: =SUM('Geographic Revenue'!H7:H9)/F27*50% -> 10.95 | G49: =SUM('Geographic Revenue'!I7:I9)/G27*50% -> 10.484375 | H49: =SUM('Geographic Revenue'!J7:J9)/H27*50% -> 10.28125 | I49: =SUM('Geographic Revenue'!K7:K9)/I27*50% -> 11.301325 | J49: =SUM('Geographic Revenue'!K7:K9)/I27*(1+J8)*50% -> 10.962285 | K49: =J51/J27*(1+K8)*50% -> 11.899346 | L49: =K51/K27*(1+L8)*50% -> 12.341352 | M49: =L51/L27*(1+M8)*50% -> 12.821294 | N49: =M51/M27*(1+N8)*50% -> 13.274377
B50: Total New Store Rev | C50: $ | D50: =D48*D49 -> 0 | E50: =E48*E49 -> 0 | F50: =F48*F49 -> 0 | G50: =G48*G49 -> 10.484375 | H50: =H48*H49 -> 0 | I50: =I48*I49 -> 0 | J50: =J48*J49 -> 0 | K50: =K48*K49 -> 0 | ... N50: =N48*N49 -> 0
B51: Total International Rev | C51: $ | D51: =D50+D46 -> 4511.45 | E51: =E50+E46 -> 4481.154 | F51: =F50+F46 -> 3737.646 | G51: =G50+G46 -> 3402.3564 | H51: =H50+H46 -> 3338.225 | I51: =I50+I46 -> 3365.67 | J51: =J50+J46 -> 3310.61 | K51: =K50+K46 -> 3343.7161 | ... N51: =N50+N46 -> 3530.9843
B52: Total Revenue (in millions USD) | C52: $ | D52: =D43+D51 -> 48380.878 | E52: =E43+E51 -> 52851.214 | F52: =F43+F51 -> 46837.459 | G52: =G43+G51 -> 43467.532 | H52: =H43+H51 -> 42432.8 | I52: =I43+I51 -> 41756.622 | J52: =J43+J51 -> 40558.58 | K52: =K43+K51 -> 41086.642 | ... N52: =N43+N51 -> 43719.469
B54: Segment Revenue Build
B55: Segment Growth Rate Assumptions (%YoY)
B56: Computing & Mobile Phones | C56: % | D56: ='Business Segment Revenue'!F28/100 -> 0.11619156 | E56: ='Business Segment Revenue'!G28/100 -> 0.03810096 | F56: ='Business Segment Revenue'!H28/100 -> -0.1206513 | G56: ='Business Segment Revenue'!I28/100 -> -0.06496003 | H56: ='Business Segment Revenue'!J28/100 -> 0.01076723 | I56: ='Business Segment Revenue'!K28/100 -> 0.05529683 | J56: =Assumptions!B18 -> 0.02 | K56: =Assumptions!C18 -> 0.04 | L56: =Assumptions!D18 -> 0.03 | M56: =Assumptions!E18 -> 0.02 | N56: =Assumptions!F18 -> 0.02
B57: Consumer Electronics | C57: % | D57: ='Business Segment Revenue'!F29/100 -> -0.00566751 | E57: ='Business Segment Revenue'!G29/100 -> 0.1401731 | F57: ='Business Segment Revenue'!H29/100 -> -0.13016109 | G57: ='Business Segment Revenue'!I29/100 -> -0.0798212 | H57: ='Business Segment Revenue'!J29/100 -> -0.06970468 | I57: ='Business Segment Revenue'!K29/100 -> -0.05014505 | J57: =Assumptions!B19 -> -0.02 | K57: =Assumptions!C19 -> 0.015 | L57: =Assumptions!D19 -> 0.02 | M57: =Assumptions!E19 -> 0.02 | N57: =Assumptions!F19 -> 0.02
B58: Appliances | C58: % | D58: ='Business Segment Revenue'!F30/100 -> 0.22099792 | E58: ='Business Segment Revenue'!G30/100 -> 0.22033033 | F58: ='Business Segment Revenue'!H30/100 -> -0.06013674 | G58: ='Business Segment Revenue'!I30/100 -> -0.13836104 | H58: ='Business Segment Revenue'!J30/100 -> -0.15403171 | I58: ='Business Segment Revenue'!K30/100 -> -0.0898167 | J58: =Assumptions!B20 -> -0.05 | K58: =Assumptions!C20 -> 0 | L58: =Assumptions!D20 -> 0.025 | M58: =Assumptions!E20 -> 0.03 | N58: =Assumptions!F20 -> 0.03
B59: Entertainment | C59: % | D59: ='Business Segment Revenue'!F31/100 -> 0.18559877 | E59: ='Business Segment Revenue'!G31/100 -> 0.06365703 | F59: ='Business Segment Revenue'!H31/100 -> -0.06778626 | G59: ='Business Segment Revenue'!I31/100 -> 0.10153947 | H59: ='Business Segment Revenue'!J31/100 -> -0.13529587 | I59: ='Business Segment Revenue'!K31/100 -> 0.06327373 | J59: =Assumptions!B21 -> 0.03 | K59: =Assumptions!C21 -> 0.025 | L59: =Assumptions!D21 -> 0.02 | M59: =Assumptions!E21 -> 0.02 | N59: =Assumptions!F21 -> 0.02
B60: Services | C60: % | D60: ='Business Segment Revenue'!F32/100 -> -0.03139785 | E60: ='Business Segment Revenue'!G32/100 -> 0.05683836 | F60: ='Business Segment Revenue'!H32/100 -> -0.02016807 | G60: ='Business Segment Revenue'!I32/100 -> 0.08490566 | H60: ='Business Segment Revenue'!J32/100 -> 0.03992095 | I60: ='Business Segment Revenue'!K32/100 -> 0.00950209 | J60: =Assumptions!B22 -> 0.04 | K60: =Assumptions!C22 -> 0.05 | L60: =Assumptions!D22 -> 0.05 | M60: =Assumptions!E22 -> 0.04 | N60: =Assumptions!F22 -> 0.04
B61: Other | C61: % | D61: ='Business Segment Revenue'!F33/100 -> -0.09767442 | E61: ='Business Segment Revenue'!G33/100 -> 0.32989689 | F61: ='Business Segment Revenue'!H33/100 -> 0.22868217 | G61: ='Business Segment Revenue'!I33/100 -> -0.04100946 | H61: ='Business Segment Revenue'!J33/100 -> 0.09539474 | I61: ='Business Segment Revenue'!K33/100 -> -0.0990991 | J61: =Assumptions!B23 -> 0.08 | K61: =Assumptions!C23 -> 0.1 | L61: =Assumptions!D23 -> 0.08 | M61: =Assumptions!E23 -> 0.06 | N61: =Assumptions!F23 -> 0.05
B62: Segment Revenue (in millions USD)
B63: Computing & Mobile Phones | C63: $ | D63: ='Business Segment Revenue'!F5 -> 21653 | E63: ='Business Segment Revenue'!G5 -> 22478 | F63: ='Business Segment Revenue'!H5 -> 19766 | G63: ='Business Segment Revenue'!I5 -> 18482 | H63: ='Business Segment Revenue'!J5 -> 18681 | I63: ='Business Segment Revenue'!K5 -> 19714 | J63: =I63*(1+J56) -> 20108.28 | K63: =J63*(1+K56) -> 20912.611 | L63: =K63*(1+L56) -> 21539.99 | M63: =L63*(1+M56) -> 21970.789 | N63: =M63*(1+N56) -> 22410.205
B64: Consumer Electronics | C64: $ | D64: ='Business Segment Revenue'!F6 -> 14211 | E64: ='Business Segment Revenue'!G6 -> 16203 | F64: ='Business Segment Revenue'!H6 -> 14094 | G64: ='Business Segment Revenue'!I6 -> 12969 | H64: ='Business Segment Revenue'!J6 -> 12065 | I64: ='Business Segment Revenue'!K6 -> 11460 | J64: =I64*(1+J57) -> 11230.8 | K64: =J64*(1+K57) -> 11399.262 | L64: =K64*(1+L57) -> 11627.247 | M64: =L64*(1+M57) -> 11859.792 | N64: =M64*(1+N57) -> 12096.988
B65: Appliances | C65: $ | D65: ='Business Segment Revenue'!F7 -> 5873 | E65: ='Business Segment Revenue'!G7 -> 7167 | F65: ='Business Segment Revenue'!H7 -> 6736 | G65: ='Business Segment Revenue'!I7 -> 5804 | H65: ='Business Segment Revenue'!J7 -> 4910 | I65: ='Business Segment Revenue'!K7 -> 4469 | J65: =I65*(1+J58) -> 4245.55 | K65: =J65*(1+K58) -> 4245.55 | L65: =K65*(1+L58) -> 4351.6888 | M65: =L65*(1+M58) -> 4482.2394 | N65: =M65*(1+N58) -> 4616.7066
B66: Entertainment | C66: $ | D66: ='Business Segment Revenue'!F8 -> 3079 | E66: ='Business Segment Revenue'!G8 -> 3275 | F66: ='Business Segment Revenue'!H8 -> 3053 | G66: ='Business Segment Revenue'!I8 -> 3363 | H66: ='Business Segment Revenue'!J8 -> 2908 | I66: ='Business Segment Revenue'!K8 -> 3092 | J66: =I66*(1+J59) -> 3184.76 | K66: =J66*(1+K59) -> 3264.379 | L66: =K66*(1+L59) -> 3329.6666 | M66: =L66*(1+M59) -> 3396.2599 | N66: =M66*(1+N59) -> 3464.1851
B67: Services | C67: $ | D67: ='Business Segment Revenue'!F9 -> 2252 | E67: ='Business Segment Revenue'!G9 -> 2380 | F67: ='Business Segment Revenue'!H9 -> 2332 | G67: ='Business Segment Revenue'!I9 -> 2530 | H67: ='Business Segment Revenue'!J9 -> 2631 | I67: ='Business Segment Revenue'!K9 -> 2656 | J67: =I67*(1+J60) -> 2762.24 | K67: =J67*(1+K60) -> 2900.352 | L67: =K67*(1+L60) -> 3045.3696 | M67: =L67*(1+M60) -> 3167.1844 | N67: =M67*(1+N60) -> 3293.8718
B68: Other | C68: $ | D68: ='Business Segment Revenue'!F10 -> 194 | E68: ='Business Segment Revenue'!G10 -> 258 | F68: ='Business Segment Revenue'!H10 -> 317 | G68: ='Business Segment Revenue'!I10 -> 304 | H68: ='Business Segment Revenue'!J10 -> 333 | I68: ='Business Segment Revenue'!K10 -> 300 | J68: =I68*(1+J61) -> 324 | K68: =J68*(1+K61) -> 356.4 | L68: =K68*(1+L61) -> 384.912 | M68: =L68*(1+M61) -> 408.00672 | N68: =M68*(1+N61) -> 428.40706
B69: Total Revenue from Segments | C69: $ | D69: =SUM(D63:D68) -> 47262 | E69: =SUM(E63:E68) -> 51761 | F69: =SUM(F63:F68) -> 46298 | G69: =SUM(G63:G68) -> 43452 | H69: =SUM(H63:H68) -> 41528 | I69: =SUM(I63:I68) -> 41691 | J69: =SUM(J63:J68) -> 41855.63 | K69: =SUM(K63:K68) -> 43078.554 | ... N69: =SUM(N63:N68) -> 46310.364
B71: % of Total Revenue
B72: Computing & Mobile Phones | C72: % | D72: =D63/D69 -> 0.4581482 | E72: =E63/E69 -> 0.43426518 | F72: =F63/F69 -> 0.42692989 | G72: =G63/G69 -> 0.42534291 | H72: =H63/H69 -> 0.44984107 | I72: =I63/I69 -> 0.47285985 | J72: =J63/J69 -> 0.48041996 | K72: =K63/K69 -> 0.48545295 | ... N72: =N63/N69 -> 0.48391339
B73: Consumer Electronics | C73: % | D73: =D64/D69 -> 0.30068554 | E73: =E64/E69 -> 0.31303491 | F73: =F64/F69 -> 0.3044192 | G73: =G64/G69 -> 0.29846727 | H73: =H64/H69 -> 0.29052687 | I73: =I64/I69 -> 0.27487947 | J73: =J64/J69 -> 0.26832233 | K73: =K64/K69 -> 0.26461571 | ... N73: =N64/N69 -> 0.26121557
B74: Appliances | C74: % | D74: =D65/D69 -> 0.12426474 | E74: =E65/E69 -> 0.13846332 | F74: =F65/F69 -> 0.14549225 | G74: =G65/G69 -> 0.13357268 | H74: =H65/H69 -> 0.11823348 | I74: =I65/I69 -> 0.1071934 | J74: =J65/J69 -> 0.10143319 | K74: =K65/K69 -> 0.098553679 | ... N74: =N65/N69 -> 0.099690571
B75: Entertainment | C75: % | D75: =D66/D69 -> 0.065147476 | E75: =E66/E69 -> 0.063271575 | F75: =F66/F69 -> 0.065942373 | G75: =G66/G69 -> 0.077395747 | H75: =H66/H69 -> 0.070025043 | I75: =I66/I69 -> 0.074164688 | J75: =J66/J69 -> 0.076089166 | K75: =K66/K69 -> 0.075777357 | ... N75: =N66/N69 -> 0.074803669
B76: Services | C76: % | D76: =D67/D69 -> 0.047649274 | E76: =E67/E69 -> 0.045980565 | F76: =F67/F69 -> 0.050369346 | G76: =G67/G69 -> 0.058225168 | H76: =H67/H69 -> 0.063354845 | I76: =I67/I69 -> 0.063706795 | J76: =J67/J69 -> 0.065994467 | K76: =K67/K69 -> 0.067327051 | ... N76: =N67/N69 -> 0.071126018
B77: Other | C77: % | D77: =D68/D69 -> 0.0041047776 | E77: =E68/E69 -> 0.0049844478 | F77: =F68/F69 -> 0.006846948 | G77: =G68/G69 -> 0.0069962257 | H77: =H68/H69 -> 0.0080186862 | I77: =I68/I69 -> 0.0071957977 | J77: =J68/J69 -> 0.0077408941 | K77: =K68/K69 -> 0.0082732582 | ... N77: =N68/N69 -> 0.0092507815
B79: Revenue Comparision And Summary
B80: Reconciliation: Segment vs. Geographic Build
B81: Total Rev Segment Build | C81: $ | D81: =D69 -> 47262 | E81: =E69 -> 51761 | F81: =F69 -> 46298 | G81: =G69 -> 43452 | H81: =H69 -> 41528 | I81: =I69 -> 41691 | J81: =J69 -> 41855.63 | K81: =K69 -> 43078.554 | ... N81: =N69 -> 46310.364
B82: Comp-Store Geographic Build | C82: $ | D82: =D43+D51 -> 48380.878 | E82: =E43+E51 -> 52851.214 | F82: =F43+F51 -> 46837.459 | G82: =G43+G51 -> 43467.532 | H82: =H43+H51 -> 42432.8 | I82: =I43+I51 -> 41756.622 | J82: =J43+J51 -> 40558.58 | K82: =K43+K51 -> 41086.642 | ... N82: =N43+N51 -> 43719.469
B83: Difference ($M) Comp-Store minus Segment | C83: $ | D83: =D82-D81 -> 1118.8775 | E83: =E82-E81 -> 1090.2144 | F83: =F82-F81 -> 539.45875 | G83: =G82-G81 -> 15.53204 | H83: =H82-H81 -> 904.8 | I83: =I82-I81 -> 65.622 | J83: =J82-J81 -> -1297.0499 | K83: =K82-K81 -> -1991.9126 | ... N83: =N82-N81 -> -2590.8949
B84: Difference (%) | C84: % | D84: =IFERROR(D83/D81,0) -> 0.023673935 | E84: =IFERROR(E83/E81,0) -> 0.021062467 | F84: =IFERROR(F83/F81,0) -> 0.01165188 | G84: =IFERROR(G83/G81,0) -> 0.00035745283 | H84: =IFERROR(H83/H81,0) -> 0.021787709 | I84: =IFERROR(I83/I81,0) -> 0.0015740088 | J84: =IFERROR(J83/J81,0) -> -0.03098866 | K84: =IFERROR(K83/K81,0) -> -0.046239077 | ... N84: =IFERROR(N83/N81,0) -> -0.05594633
B86: International Revenue as % of Total Revenue | D86: =D51/D52 -> 0.093248619 | E86: =E51/E52 -> 0.084788099 | F86: =F51/F52 -> 0.079800359 | G86: =G51/G52 -> 0.078273512 | H86: =H51/H52 -> 0.078670863 | I86: =I51/I52 -> 0.080602066 | J86: =J51/J52 -> 0.081625392 | K86: =K51/K52 -> 0.081382074 | ... N86: =N51/N52 -> 0.080764574
B87: Domestic Revenue as % of Total Revenue | D87: =D43/D52 -> 0.90675138 | E87: =E43/E52 -> 0.9152119 | F87: =F43/F52 -> 0.92019964 | G87: =G43/G52 -> 0.92172649 | H87: =H43/H52 -> 0.92132914 | I87: =I43/I52 -> 0.91939793 | J87: =J43/J52 -> 0.91837461 | K87: =K43/K52 -> 0.91861793 | ... N87: =N43/N52 -> 0.91923543

Sheet DCF - Bear Model
B1: Bear Case: Discounted Cash Flow Model
B2: Fiscal Year Ending January | $ in Millions | Blue = Hardcoded Input | Black = Formula
B3: WACC | C3: =WACC!C22 -> 0.10490729
B4: Terminal growth | C4: =Assumptions!B30 -> 0.02
B5: Description | C5: 2026A | D5: 2027E | E5: 2028E | F5: 2029E | G5: 2030E | H5: 2031E | I5: Notes
B6: Total Revenue | D6: ='Revenue Build - Final Bear Case'!J52 -> 40558.58 | E6: ='Revenue Build - Final Bear Case'!K52 -> 41086.642 | F6: ='Revenue Build - Final Bear Case'!L52 -> 41807.898 | G6: ='Revenue Build - Final Bear Case'!M52 -> 42752.474 | H6: ='Revenue Build - Final Bear Case'!N52 -> 43719.469 | I6: if the AI PC updgrade doesnt go through , it directly impact revenue for 2027 and then slowly adjusts in later years. Here we showed this through a sharp decline in same store sales for 2027E and then a steady % growth for later years
B7: Free Cashflow Projection
B8: Operating Margin % | D8: 0.043 | E8: 0.046 | F8: 0.049 | G8: 0.051 | H8: 0.053
B9: Operating Margin % Bear Case | D9: =D8-2% -> 0.023 | E9: =E8-2% -> 0.026 | F9: =F8-2% -> 0.029 | G9: =G8-2% -> 0.031 | H9: =H8-2% -> 0.033 | I9: direct impact of store traffic decline due to e-commerce, high cogs due to products being shipped in from other countries (tarrifs) ~ -2% from the base case
B10: EBIT (Operating Income) | D10: =D9*D6 -> 932.84734 | E10: =E9*E6 -> 1068.2527 | F10: =F9*F6 -> 1212.429 | G10: =G9*G6 -> 1325.3267 | H10: =H9*H6 -> 1442.7425
B11: Less: Taxes | D11: =Assumptions!B33*D10 -> 223.88336 | E11: =Assumptions!C33*E10 -> 256.38064 | F11: =Assumptions!D33*F10 -> 290.98297 | G11: =Assumptions!E33*G10 -> 318.0784 | H11: =Assumptions!F33*H10 -> 346.25819
B12: NOPAT | D12: =D10-D11 -> 708.96398 | E12: =E10-E11 -> 811.87204 | F12: =F10-F11 -> 921.44606 | G12: =G10-G11 -> 1007.2483 | H12: =H10-H11 -> 1096.4843
B13: (+) Depreciation & Amortization | D13: =Assumptions!B34 -> 800 | E13: =Assumptions!C34 -> 793 | F13: =Assumptions!D34 -> 782 | G13: =Assumptions!E34 -> 772 | H13: =Assumptions!F34 -> 762
B14: (-) Capital Expenditures | D14: =Assumptions!B35 -> 750 | E14: =Assumptions!C35 -> 710 | F14: =Assumptions!D35 -> 700 | G14: =Assumptions!E35 -> 690 | H14: =Assumptions!F35 -> 680
B15: (-) Change in Working Capital | D15: =Assumptions!B36 -> 75 | E15: =Assumptions!C36 -> 50 | F15: =Assumptions!D36 -> 35 | G15: =Assumptions!E36 -> 25 | H15: =Assumptions!F36 -> 20
B16: Free Cash Flow to Firm (FCFF) | D16: =D12+D13-D14-D15 -> 683.96398 | E16: =E12+E13-E14-E15 -> 844.87204 | F16: =F12+F13-F14-F15 -> 968.44606 | G16: =G12+G13-G14-G15 -> 1064.2483 | H16: =H12+H13-H14-H15 -> 1158.4843
B17: PV of FCFF | D17: =D16/(1+$C$3)^1 -> 619.02386 | E17: =E16/(1+$C$3)^1 -> 764.65423 | F17: =F16/(1+$C$3)^1 -> 876.49531 | G17: =G16/(1+$C$3)^1 -> 963.20142 | H17: =H16/(1+$C$3)^1 -> 1048.49
B18: Terminal Value (Gordon Growth Model)
B19: Terminal Value | H19: =(H16*(1+$C$4))/($C$3-$C$4) -> 13916.99
B20: PV of Terminal Value | H20: =H19/(1+C3)^5 -> 8451.1558
B21: Enterprise Value
B22: Sum of PV(FCFs) | C22: =SUM(D17:H17) -> 4271.8649
B23: PV of Terminal Value | C23: =H20 -> 8451.1558
B24: Terminal Value as % of EV | C24: =C23/C25 -> 0.6642413
B25: Enterprise Value | C25: =C23+C22 -> 12723.021
B26: Less: Net Debt | C26: -1155
B27: Equity Value | C27: =C25+C26 -> 11568.021
B29: Diluted Shares Outstanding (M) | C29: 210
B31: Implied Share Price (Per Share) | C31: =C27/C29 -> 55.085813
B33: Sensitivity Analysis: Projecting different wacc and growth rate to see the impact on share price
I34: Decline in share price as % of original, given different WACC and Growth
B35: =C31 -> 55.085813 | C35: 0.095 | D35: 0.1 | E35: 0.105 | F35: 0.11 | G35: 0.115 | J35: 0.095 | K35: 0.1 | L35: 0.105 | M35: 0.11 | N35: 0.115
B36: 0.01 | C36: 56.665496 | D36: 53.373221 | E36: 50.4411 | F36: 47.814553 | G36: 45.449421 | I36: 0.01 | J36: =(C36-$K$43)/$K$43 -> -0.10608146 | K36: =(D36-$K$43)/$K$43 -> -0.15801828 | L36: =(E36-$K$43)/$K$43 -> -0.20427355 | M36: =(F36-$K$43)/$K$43 -> -0.24570826 | N36: =(G36-$K$43)/$K$43 -> -0.28301908
B37: 0.015 | C37: 59.486966 | D37: 55.835905 | E37: 52.604942 | F37: 49.727158 | G37: 47.149042 | I37: 0.015 | J37: =(C37-$K$43)/$K$43 -> -0.061571758 | K37: =(D37-$K$43)/$K$43 -> -0.11916856 | L37: =(E37-$K$43)/$K$43 -> -0.17013816 | M37: =(F37-$K$43)/$K$43 -> -0.21553623 | N37: =(G37-$K$43)/$K$43 -> -0.25620695
B38: 0.02 | C38: 62.684632 | D38: 58.606425 | E38: 55.023354 | F38: 51.852275 | G38: 49.02757 | I38: 0.02 | J38: =(C38-$K$43)/$K$43 -> -0.011127426 | K38: =(D38-$K$43)/$K$43 -> -0.075462618 | L38: =(E38-$K$43)/$K$43 -> -0.13198684 | M38: =(F38-$K$43)/$K$43 -> -0.18201175 | N38: =(G38-$K$43)/$K$43 -> -0.22657249
B39: 0.025 | C39: 66.339108 | D39: 61.746347 | E39: 57.744068 | F39: 54.227406 | G39: 51.114824 | I39: 0.025 | J39: =(C39-$K$43)/$K$43 -> 0.046523239 | K39: =(D39-$K$43)/$K$43 -> -0.025929222 | L39: =(E39-$K$43)/$K$43 -> -0.089066609 | M39: =(F39-$K$43)/$K$43 -> -0.14454321 | N39: =(G39-$K$43)/$K$43 -> -0.19364531
B40: 0.03 | C40: 70.555811 | D40: 65.334829 | E40: 60.827543 | F40: 56.899428 | G40: 53.447637 | I40: 0.03 | J40: =(C40-$K$43)/$K$43 -> 0.11304324 | K40: =(D40-$K$43)/$K$43 -> 0.030680375 | L40: =(E40-$K$43)/$K$43 -> -0.040423677 | M40: =(F40-$K$43)/$K$43 -> -0.1023911 | N40: =(G40-$K$43)/$K$43 -> -0.15684434
I42: 52 week low range: | K42: ='Valuation Football Field '!C9 -> 59.77 | L42: the bear case presents a stock price lower than a 52 week low
I43: Base Stock Price as of 4/15/2026 | K43: =Assumptions!B39 -> 63.39 | L43: the bear case presents a stock price with 13% downside risk

Sheet FCFE Valuation
B1: FCFE Valuation Model
B2: Best Buy Debt | C2: Amount | D2: Weight | E2: Rate
B3: 2028 Notes | C3: 500 | D3: =C3/(SUM($C$3:$C$4)) -> 0.44247788 | E3: 0.0445
B4: 2030 Notes | C4: 630 | D4: =C4/(SUM($C$3:$C$4)) -> 0.55752212 | E4: 0.0195
B5: Weighted Average Rate | E5: =(E3*D3)+(E4*D4) -> 0.030561947
B7: Cost of Equity | C7: =WACC!C19 -> 0.1115
B8: Terminal growth | C8: 0.02
C10: 1 | D10: 2 | E10: 3 | F10: 4 | G10: 5
B11: FCFE valuation | C11: 2027E | D11: 2028E | E11: 2029E | F11: 2030E | G11: 2031E
B12: FCFF | C12: ='DCF - Base Model'!D14 -> 1342.842 | D12: ='DCF - Base Model'!E14 -> 1539.0263 | E12: ='DCF - Base Model'!F14 -> 1695.9453 | F12: ='DCF - Base Model'!G14 -> 1812.2184 | G12: ='DCF - Base Model'!H14 -> 1927.3814
B13: Interest tax sheild | C13: =($E$5*SUM(C3:C4))*Assumptions!$B$33 -> 8.2884 | D13: =C13 -> 8.2884 | E13: =D13 -> 8.2884 | F13: =E13 -> 8.2884 | G13: =F13 -> 8.2884
B14: FCFE | C14: =C12-C13 -> 1334.5536 | D14: =D12-D13 -> 1530.7379 | E14: =E12-E13 -> 1687.6569 | F14: =F12-F13 -> 1803.93 | G14: =G12-G13 -> 1919.093
B15: PV factor | C15: =(1/(1+$C$7))^C10 -> 0.89968511 | D15: =(1/(1+$C$7))^D10 -> 0.8094333 | E15: =(1/(1+$C$7))^E10 -> 0.72823509 | F15: =(1/(1+$C$7))^F10 -> 0.65518226 | G15: =(1/(1+$C$7))^G10 -> 0.58945773
B16: PV of FCFE | C16: =C14*C15 -> 1200.678 | D16: =D14*D15 -> 1239.0302 | E16: =E14*E15 -> 1229.0109 | F16: =F14*F15 -> 1181.9029 | G16: =G14*G15 -> 1131.2242
B17: Terminal Value | G17: =G14/(C7-C8) -> 20973.695
B18: PV of Terminal Value | G18: =G17*G15 -> 12363.106
B19: Enterpirse Value | G19: =SUM(C16:G16)+G18 -> 18344.953
B20: Less debt | G20: =SUM(C3:C4) -> 1130
B21: Equity Value | G21: =G19-G20 -> 17214.953
B22: Diluted Shares Outstanding (M) | G22: 210
B23: Implied Share Price | G23: =G21/G22 -> 81.975965
B26: FCFE GGM Sensitivity Analysis to WACC and Growth Rate
B28: =G23 -> 81.975965 | C28: 0.105 | D28: 0.11 | E28: 0.1115 | F28: 0.12 | G28: 0.1215
B29: 0.01 | C29: 81.995515 | D29: 77.451228 | E29: 76.175774 | F29: 69.609409 | G29: 68.555276
B30: 0.015 | C30: 85.239428 | D30: 80.305585 | E30: 78.925605 | F30: 71.854193 | G30: 70.724108
B31: 0.02 | C31: 88.864978 | D31: 83.477092 | E31: 81.975965 | F31: 74.323456 | G31: 73.106617
B32: 0.025 | C32: 92.943722 | D32: 87.021718 | E32: 85.378967 | F32: 77.052641 | G32: 75.73602
B33: 0.03 | C33: 97.566299 | D33: 91.009422 | E33: 89.199515 | F33: 80.085069 | G33: 78.652788

Sheet Comp Analysis
B1: Comp Analysis - Best Buy
J3: Financials (LTM) | N3: Valuation | R3: Financials (NTM) | V3: Valuation
B4: Company | C4: Ticker | D4: Share Price | E4: Shares Outstanding | F4: Equity Value | G4: Net Debt | H4: Enterprise Value | J4: Revenue | K4: EBITDA | L4: Net Income | N4: EV/Revenue | O4: EV/EBITDA | P4: P/E | R4: Revenue | S4: EBITDA | T4: Net Income | V4: EV/Revenue | W4: EV/EBITDA | X4: P/E
B6: Best Buy | C6: BBY | D6: 62.060001 | E6: =209.112577*1000000 -> 209112577 | F6: =E6*D6 -> 1.2977527e+10 | G6: =-2250*1000000 -> -2250000000 | H6: =G6+F6 -> 1.0727527e+10 | J6: =41691*1000000 -> 41691000000 | K6: =2567*1000000 -> 2567000000 | L6: =1069*1000000 -> 1069000000 | N6: =H6/J6 -> 0.25731037 | O6: =H6/K6 -> 4.1790131 | P6: =D6/(L6/E6) -> 12.139875 | R6: ='Revenue Build - Top Down'!J52*1000000 -> 4.2231099e+10 | S6: =1000000*('DCF - Base Model'!D8+'DCF - Base Model'!D11) -> 2599792090 | T6: =1361.45*1000000 -> 1361450000 | V6: =H6/R6 -> 0.2540196 | W6: =H6/S6 -> 4.1263018 | X6: =D6/(T6/E6) -> 9.5321361
B7: Target | C7: TGT | D7: 119.53 | E7: =452.855589*1000000 -> 452855589 | F7: =E7*D7 -> 5.4129828e+10 | G7: =6968*1000000 -> 6968000000 | H7: =G7+F7 -> 6.1097828e+10 | J7: =104780*1000000 -> 104780000000 | K7: =7977*1000000 -> 7977000000 | L7: =3705*1000000 -> 3705000000 | N7: =H7/J7 -> 0.58310582 | O7: =H7/K7 -> 7.6592489 | P7: =D7/(L7/E7) -> 14.60994 | R7: =107367.453125*1000000 -> 107367453125 | S7: =8210.787109*1000000 -> 8.2107871e+09 | T7: =3659.2*1000000 -> 3659200000 | V7: =H7/R7 -> 0.56905353 | W7: =F7/S7 -> 6.5925261 | X7: =D7/(T7/E7) -> 14.792804
B8: Currys | C8: CURY | D8: 1.86 | E8: =1038.1*1000000 -> 1.0381e+09 | F8: =E8*D8 -> 1.930866e+09 | G8: 0 | H8: =G8+F8 -> 1.930866e+09 | J8: =11797.2*1000000 -> 11797200000 | K8: =662.1*1000000 -> 662100000 | L8: =172.7*10000000 -> 1727000000 | N8: =H8/J8 -> 0.16367155 | O8: =H8/K8 -> 2.9162755 | P8: =D8/(L8/E8) -> 1.1180463 | R8: =12987.2*1000000 -> 12987200000 | S8: =728*1000000 -> 728000000 | T8: =203.6*1000000 -> 203600000 | V8: =H8/R8 -> 0.14867454 | W8: =F8/S8 -> 2.6522885 | X8: =D8/(T8/E8) -> 9.4836248
B13: High | N13: =MAX(N7:N8) -> 0.58310582 | O13: =MAX(O7:O8) -> 7.6592489 | P13: =MAX(P7:P8) -> 14.60994 | V13: =MAX(V7:V8) -> 0.56905353 | W13: =MAX(W7:W8) -> 6.5925261 | X13: =MAX(X7:X8) -> 14.792804
B14: 75th Percentile | N14: =QUARTILE(N7:N8,) -> 0.16367155 | O14: =QUARTILE(O7:O8,) -> 2.9162755 | P14: =QUARTILE(P7:P8,) -> 1.1180463 | V14: =QUARTILE(V7:V8,) -> 0.14867454 | W14: =QUARTILE(W7:W8,) -> 2.6522885 | X14: =QUARTILE(X7:X8,) -> 9.4836248
B15: Average | N15: =AVERAGE(N7:N8) -> 0.37338869 | O15: =AVERAGE(O7:O8) -> 5.2877622 | P15: =AVERAGE(P7:P8) -> 7.8639932 | V15: =AVERAGE(V7:V8) -> 0.35886404 | W15: =AVERAGE(W7:W8) -> 4.6224073 | X15: =AVERAGE(X7:X8) -> 12.138214
B16: Median | N16: =MEDIAN(N7:N8) -> 0.37338869 | O16: =MEDIAN(O7:O8) -> 5.2877622 | P16: =MEDIAN(P7:P8) -> 7.8639932 | V16: =MEDIAN(V7:V8) -> 0.35886404 | W16: =MEDIAN(W7:W8) -> 4.6224073 | X16: =MEDIAN(X7:X8) -> 12.138214
B17: 25th Percentile | N17: =QUARTILE(N7:N8,1) -> 0.26853012 | O17: =QUARTILE(O7:O8,1) -> 4.1020188 | P17: =QUARTILE(P7:P8,1) -> 4.4910198 | V17: =QUARTILE(V7:V8,1) -> 0.25376929 | W17: =QUARTILE(W7:W8,1) -> 3.6373479 | X17: =QUARTILE(X7:X8,1) -> 10.81092
B18: Low | N18: =MIN(N7:N8) -> 0.16367155 | O18: =MIN(O7:O8) -> 2.9162755 | P18: =MIN(P7:P8) -> 1.1180463 | V18: =MIN(V7:V8) -> 0.14867454 | W18: =MIN(W7:W8) -> 2.6522885 | X18: =MIN(X7:X8) -> 9.4836248
B20: Best Buy Valuation | N20: EV/Revenue | O20: EV/EBITDA | P20: P/E | V20: EV/Revenue | W20: EV/EBITDA | X20: P/E
B21: Implied Enterprise Value | N21: =N15*J6 -> 1.5566948e+10 | O21: =O15*K6 -> 1.3573685e+10 | P21: =P22+P23 -> 6.1566087e+09 | V21: =V15*R6 -> 1.5155223e+10 | W21: =W15*S6 -> 1.2017298e+10 | X21: =X22+X23 -> 1.2468526e+10
B22: Net Debt | N22: =$G$6 -> -2250000000 | O22: =$G$6 -> -2250000000 | P22: =$G$6 -> -2250000000 | V22: =$G$6 -> -2250000000 | W22: =$G$6 -> -2250000000 | X22: =$G$6 -> -2250000000
B23: Implied Market Value | N23: =N21+N22 -> 1.3316948e+10 | O23: =O21+O22 -> 1.1323685e+10 | P23: =P15*L6 -> 8.4066087e+09 | V23: =V21+V22 -> 1.2905223e+10 | W23: =W21+W22 -> 9.7672979e+09 | X23: =X17*T6 -> 1.4718526e+10
B24: Shares Outstanding | N24: =$E$6 -> 209112577 | O24: =$E$6 -> 209112577 | P24: =$E$6 -> 209112577 | V24: =$E$6 -> 209112577 | W24: =$E$6 -> 209112577 | X24: =$E$6 -> 209112577
B25: Implied Value Per Share | N25: =N23/N24 -> 63.68315 | O25: =O23/O24 -> 54.151145 | P25: =P23/P24 -> 40.201354 | V25: =V23/V24 -> 61.714234 | W25: =W23/W24 -> 46.708323 | X25: =X23/X24 -> 70.385658
V26: Average Implied Price | X26: =AVERAGE(V25:X25) -> 59.602739
B27: Justification for comps used:
B28: Our comp universe contains two companies because the selection criteria are strict and the universe is genuinely small. We required four conditions simultaneously: omnichannel retail as the primary revenue driver, a services or media layer creating margin structure above pure hardware, publicly traded with audited financials sufficient to extract clean EV/EBITDA, and a market cap between $1B and $300B. Two companies survive that screen globally: Target and Currys. The most frequently cited electronics retail competitors: Micro Center and B&H Photo Video, are both privately held and file no public financials. There is no audited GAAP income statement, no disclosed EBITDA, and no traded market multiple to extract. Including them in a public comps table would require fabricating inputs, which is not analysis. They are operationally relevant competitors but analytically unusable as valuation benchmarks. Walmart and Costco are excluded on analytical grounds, not convenience. Both trade at 22-30x EV/EBITDA precisely because their advertising and membership businesses are fully disclosed, separately quantified in earnings calls, and explicitly cited by sell-side analysts as the justification for premium multiples. Using them as consolidated EV/EBITDA comps for BBY would be circular, we would be benchmarking a company whose media business is invisible in its income statement against companies whose re-rating has already fully occurred. Walmart Connect and Target Roundel appear in our SOTP section, where they belong: as margin benchmarks and multiple anchors for valuing BBY Ads as a standalone business. That is a more rigorous use of those data points than folding them into a consolidated comp average that would obscure exactly the gap we are trying to quantify.

Sheet Football Field
B2: Metrics | C2: Low | D2: Difference | E2: High
B3: Public Comparables- P/E (NTM) | C3: 62 | D3: =E3-C3 -> 34 | E3: 96 | F3: NTM EPS $6.49 (FY2027E - Comp Analysis sheet) × peer P/E range
B4: Public Comparables- EV/EBITDA (NTM) | C4: 50 | D4: =E4-C4 -> 26 | E4: 76 | F4: NTM EBITDA ~$2,600M (FY2027E from DCF model) × peer range. TGT NTM EV/EBITDA 6.59× → high $76. Bear uses 4.5× = $50
B5: FCFF DCF (Base Case) | C5: 81 | D5: =E5-C5 -> 42 | E5: 123 | F5: Directly from DCF - Base Model sheet sensitivity table. Low = WACC 11.5% + TGR 1.0% ≈ $81. High = WACC 9.5% + TGR 3.0% ≈ $123. Base case = $97.30 (WACC 10.49%, TGR 2.0%)
B6: Analyst Targets | C6: 62.37 | D6: =E6-C6 -> 27.63 | E6: 90 | F6: FactSet: Estimates from Guggenheim Securities
B7: 52-week High-Low | C7: 62.87 | D7: =E7-C7 -> 25.3 | E7: 88.17 | F7: Historicals Sheet

Sheet Valuation Football Field 
B1: Valuation Football Field
C3: L | E3: H
B4: FCFF GGM | C4: 81.25 | D4: =E4-C4 -> 41.81 | E4: 123.06
B5: FCFE GGM | C5: 68.56 | D5: 14 | E5: 85.24
B6: EV/NTM EBITDA | C6: 45.16 | D6: =E6-C6 -> 26.04 | E6: 71.2
B7: NTM PE | C7: 61.73 | D7: =E7-C7 -> 35.78 | E7: 97.51
B8: Analyst Targets | C8: 65 | D8: =E8-C8 -> 25 | E8: 90
B9: 52 WK Hi/Lo | C9: 59.77 | D9: =E9-C9 -> 25.11 | E9: 84.88

Sheet Blended Implied Pricing Summary
B1: Stock Price Prediction based on valuation methods
B3: Analysis Method Used | C3: Share Price Target | D3: Weight | E3: Contribution
B4: FCFF GGM | C4: ='DCF - Base Model'!C29 -> 97.299866 | D4: 0.6 | E4: =D4*C4 -> 58.379919
B5: Comparables: (P/E) | C5: ='Comp Analysis'!X25 -> 70.385658 | D5: 0.4 | E5: =D5*C5 -> 28.154263
B6: Blended Implied Share Price | C6: =SUMPRODUCT(C4:C5,D4:D5) -> 86.534183
B7: Upside % | C7: =(C6-Assumptions!B39)/Assumptions!B39 -> 0.36510779
B8: Sensitivity Analysis with DCF percent allocation in columns and Comparables in rows

Sheet Unit Economics
A1: Best Buy Co., Inc. Per-Store Unit Economics
A2: Domestic Operations | $ in Millions unless noted | FY2021A - FY2031E
A3: Blue = Input | Black = Formula | Green = Cross-sheet link
A5: I. Domestic Store Count Build
C6: FY2021A | D6: FY2022A | E6: FY2023A | F6: FY2024A | G6: FY2025A | H6: FY2026A | I6: FY2027E | J6: FY2028E | K6: FY2029E | L6: FY2030E | M6: FY2031E
A7: Beginning Store Count | B7: # | C7: ='Revenue Build - Top Down'!D17 -> 1009 | D7: ='Revenue Build - Top Down'!E17 -> 991 | E7: ='Revenue Build - Top Down'!F17 -> 984 | F7: ='Revenue Build - Top Down'!G17 -> 978 | G7: ='Revenue Build - Top Down'!H17 -> 965 | H7: ='Revenue Build - Top Down'!I17 -> 957 | I7: ='Revenue Build - Top Down'!J17 -> 926 | J7: ='Revenue Build - Top Down'!K17 -> 917 | ... M7: ='Revenue Build - Top Down'!N17 -> 891
A8: Stores Opened | B8: # | C8: ='Revenue Build - Top Down'!D18 -> 3 | D8: ='Revenue Build - Top Down'!E18 -> 13 | E8: ='Revenue Build - Top Down'!F18 -> 9 | F8: ='Revenue Build - Top Down'!G18 -> 14 | G8: ='Revenue Build - Top Down'!H18 -> 0 | H8: ='Revenue Build - Top Down'!I18 -> 0 | I8: ='Revenue Build - Top Down'!J18 -> 6 | J8: ='Revenue Build - Top Down'!K18 -> 6 | ... M8: ='Revenue Build - Top Down'!N18 -> 5
A9: Stores Closed | B9: # | C9: ='Revenue Build - Top Down'!D19 -> 21 | D9: ='Revenue Build - Top Down'!E19 -> 20 | E9: ='Revenue Build - Top Down'!F19 -> 15 | F9: ='Revenue Build - Top Down'!G19 -> 27 | G9: ='Revenue Build - Top Down'!H19 -> 8 | H9: ='Revenue Build - Top Down'!I19 -> 31 | I9: ='Revenue Build - Top Down'!J19 -> 15 | J9: ='Revenue Build - Top Down'!K19 -> 15 | ... M9: ='Revenue Build - Top Down'!N19 -> 13
A10: Ending Store Count | B10: # | C10: ='Revenue Build - Top Down'!D20 -> 991 | D10: ='Revenue Build - Top Down'!E20 -> 984 | E10: ='Revenue Build - Top Down'!F20 -> 978 | F10: ='Revenue Build - Top Down'!G20 -> 965 | G10: ='Revenue Build - Top Down'!H20 -> 957 | H10: ='Revenue Build - Top Down'!I20 -> 926 | I10: ='Revenue Build - Top Down'!J20 -> 917 | J10: ='Revenue Build - Top Down'!K20 -> 908 | ... M10: ='Revenue Build - Top Down'!N20 -> 883
A11: Average Store Count | B11: # | C11: ='Revenue Build - Top Down'!D21 -> 1000 | D11: ='Revenue Build - Top Down'!E21 -> 987.5 | E11: ='Revenue Build - Top Down'!F21 -> 981 | F11: ='Revenue Build - Top Down'!G21 -> 971.5 | G11: ='Revenue Build - Top Down'!H21 -> 961 | H11: ='Revenue Build - Top Down'!I21 -> 941.5 | I11: ='Revenue Build - Top Down'!J21 -> 921.5 | J11: ='Revenue Build - Top Down'!K21 -> 912.5 | ... M11: ='Revenue Build - Top Down'!N21 -> 887
A13: II. Revenue per Store ($M)
C14: FY2021A | D14: FY2022A | E14: FY2023A | F14: FY2024A | G14: FY2025A | H14: FY2026A | I14: FY2027E | J14: FY2028E | K14: FY2029E | L14: FY2030E | M14: FY2031E
A15: Domestic Total Revenue ($M) | C15: =SUM('Revenue Build - Top Down'!D63:D68) -> 47262 | D15: =SUM('Revenue Build - Top Down'!E63:E68) -> 51761 | E15: =SUM('Revenue Build - Top Down'!F63:F68) -> 46298 | F15: =SUM('Revenue Build - Top Down'!G63:G68) -> 43452 | G15: =SUM('Revenue Build - Top Down'!H63:H68) -> 41528 | H15: =SUM('Revenue Build - Top Down'!I63:I68) -> 41691 | I15: =SUM('Revenue Build - Top Down'!J63:J68) -> 41855.63 | J15: =SUM('Revenue Build - Top Down'!K63:K68) -> 43078.554 | ... M15: =SUM('Revenue Build - Top Down'!N63:N68) -> 46310.364
A16: Domestic Revenue per Avg. Store ($M) | B16: $M | C16: ='Revenue Build - Top Down'!D29 -> 43.293 | D16: ='Revenue Build - Top Down'!E29 -> 48.435443 | E16: ='Revenue Build - Top Down'!F29 -> 43.622834 | F16: ='Revenue Build - Top Down'!G29 -> 41.273289 | G16: ='Revenue Build - Top Down'!H29 -> 39.789802 | H16: ='Revenue Build - Top Down'!I29 -> 40.656399 | I16: ='Revenue Build - Top Down'!J29 -> 42.087866 | J16: ='Revenue Build - Top Down'!K29 -> 43.280971 | ... M16: ='Revenue Build - Top Down'!N29 -> 47.643806
A17: YoY Growth | D17: =(D16-C16)/C16 -> 0.11878232 | E17: =(E16-D16)/D16 -> -0.099361313 | F17: =(F16-E16)/E16 -> -0.053860442 | G17: =(G16-F16)/F16 -> -0.035943015 | H17: =(H16-G16)/G16 -> 0.021779376 | I17: =(I16-H16)/H16 -> 0.035208899 | J17: =(J16-I16)/I16 -> 0.028347945 | K17: =(K16-J16)/J16 -> 0.032982844 | ... M17: =(M16-L16)/L16 -> 0.032074408
A18: Domestic SSS Growth (%) | C18: ='Revenue Build - Top Down'!D7 -> 0.092 | D18: ='Revenue Build - Top Down'!E7 -> 0.11 | E18: ='Revenue Build - Top Down'!F7 -> -0.103 | F18: ='Revenue Build - Top Down'!G7 -> -0.071 | G18: ='Revenue Build - Top Down'!H7 -> -0.025 | H18: ='Revenue Build - Top Down'!I7 -> 0.004 | I18: ='Revenue Build - Top Down'!J7 -> 0.01 | J18: ='Revenue Build - Top Down'!K7 -> 0.015 | ... M18: ='Revenue Build - Top Down'!N7 -> 0.02
A20: III. Profitability per Store ($M unless noted)
C21: FY2021A | D21: FY2022A | E21: FY2023A | F21: FY2024A | G21: FY2025A | H21: FY2026A | I21: FY2027E | J21: FY2028E | K21: FY2029E | L21: FY2030E | M21: FY2031E
A22: Operating Margin (%) | C22: 0.056 | D22: 0.086 | E22: 0.034 | F22: 0.039 | G22: 0.042 | H22: 0.042 | I22: =[1]Assumptions!B36 -> 0.043 | J22: =[1]Assumptions!C36 -> 0.046 | K22: =[1]Assumptions!D36 -> 0.049 | L22: =[1]Assumptions!E36 -> 0.051 | M22: =[1]Assumptions!F36 -> 0.053
A23: Operating Income ($M) — Total | C23: =C15*C22 -> 2646.672 | D23: =D15*D22 -> 4451.446 | E23: =E15*E22 -> 1574.132 | F23: =F15*F22 -> 1694.628 | G23: =G15*G22 -> 1744.176 | H23: =H15*H22 -> 1751.022 | I23: =I15*I22 -> 1799.7921 | J23: =J15*J22 -> 1981.6135 | ... M23: =M15*M22 -> 2454.4493
A24: EBIT per Store ($M) | B24: $M | C24: =C23/C11 -> 2.646672 | D24: =D23/D11 -> 4.5077934 | E24: =E23/E11 -> 1.6046198 | F24: =F23/F11 -> 1.7443417 | G24: =G23/G11 -> 1.8149594 | H24: =H23/H11 -> 1.8598216 | I24: =I23/I11 -> 1.9531113 | J24: =J23/J11 -> 2.1716312 | ... M24: =M23/M11 -> 2.7671356
A25: D&A per Store ($M, est.) | C25: =830/C11 -> 0.83 | D25: =820/D11 -> 0.83037975 | E25: =810/E11 -> 0.82568807 | F25: =805/F11 -> 0.82861554 | G25: =802/G11 -> 0.83454735 | H25: =800/H11 -> 0.84970791 | I25: ='[1]DCF - Base Model'!D12/I11 -> 0.86814976 | J25: ='[1]DCF - Base Model'!E12/J11 -> 0.8690411 | K25: ='[1]DCF - Base Model'!F12/K11 -> 0.86552297 | L25: ='[1]DCF - Base Model'!G12/L11 -> 0.86256983 | M25: ='[1]DCF - Base Model'!H12/M11 -> 0.85907554
A26: EBITDA per Store ($M) | B26: $M | C26: =C24+C25 -> 3.476672 | D26: =D24+D25 -> 5.3381732 | E26: =E24+E25 -> 2.4303078 | F26: =F24+F25 -> 2.5729573 | G26: =G24+G25 -> 2.6495068 | H26: =H24+H25 -> 2.7095295 | I26: =I24+I25 -> 2.8212611 | J26: =J24+J25 -> 3.0406723 | ... M26: =M24+M25 -> 3.6262111
A28: IV. CapEx & New Store Payback
C29: FY2021A | D29: FY2022A | E29: FY2023A | F29: FY2024A | G29: FY2025A | H29: FY2026A | I29: FY2027E | J29: FY2028E | K29: FY2029E | L29: FY2030E | M29: FY2031E
A30: Total CapEx ($M) | C30: 688 | D30: 758 | E30: 745 | F30: 735 | G30: 716 | H30: 704 | I30: ='[1]DCF - Base Model'!D13 -> 750 | J30: ='[1]DCF - Base Model'!E13 -> 710 | K30: ='[1]DCF - Base Model'!F13 -> 700 | L30: ='[1]DCF - Base Model'!G13 -> 690 | M30: ='[1]DCF - Base Model'!H13 -> 680
A31: Maintenance CapEx (~65% of total, est.) | C31: =C30*0.65 -> 447.2 | D31: =D30*0.65 -> 492.7 | E31: =E30*0.65 -> 484.25 | F31: =F30*0.65 -> 477.75 | G31: =G30*0.65 -> 465.4 | H31: =H30*0.65 -> 457.6 | I31: =I30*0.65 -> 487.5 | J31: =J30*0.65 -> 461.5 | ... M31: =M30*0.65 -> 442
A32: Growth / New-Store CapEx (~35% of total) | C32: =C30*0.35 -> 240.8 | D32: =D30*0.35 -> 265.3 | E32: =E30*0.35 -> 260.75 | F32: =F30*0.35 -> 257.25 | G32: =G30*0.35 -> 250.6 | H32: =H30*0.35 -> 246.4 | I32: =I30*0.35 -> 262.5 | J32: =J30*0.35 -> 248.5 | ... M32: =M30*0.35 -> 238
A33: Total CapEx per Avg. Store ($M) | B33: $M | C33: =C30/C11 -> 0.688 | D33: =D30/D11 -> 0.76759494 | E33: =E30/E11 -> 0.75942915 | F33: =F30/F11 -> 0.75656202 | G33: =G30/G11 -> 0.74505723 | H33: =H30/H11 -> 0.74774296 | I33: =I30/I11 -> 0.8138904 | J33: =J30/J11 -> 0.77808219 | ... M33: =M30/M11 -> 0.76662909
A34: New Store Initial Investment ($M, est.) | C34: 1.5 | D34: 1.5 | E34: 1.5 | F34: 1.5 | G34: 1.5 | H34: 1.5 | I34: 1.5 | J34: 1.5 | K34: 1.5 | L34: 1.5 | M34: 1.5
A35: New Store Year-1 Revenue ($M, est.) | C35: =C16*0.55 -> 23.81115 | D35: =D16*0.55 -> 26.639494 | E35: =E16*0.55 -> 23.992559 | F35: =F16*0.55 -> 22.700309 | G35: =G16*0.55 -> 21.884391 | H35: =H16*0.55 -> 22.36102 | I35: =I16*0.55 -> 23.148327 | J35: =J16*0.55 -> 23.804534 | ... M35: =M16*0.55 -> 26.204093
A36: New Store 4-Wall EBITDA Margin (est. 8%) | C36: 0.08 | D36: 0.08 | E36: 0.08 | F36: 0.08 | G36: 0.08 | H36: 0.08 | I36: 0.08 | J36: 0.08 | K36: 0.08 | L36: 0.08 | M36: 0.08
A37: New Store Year-1 EBITDA ($M) | C37: =C35*C36 -> 1.904892 | D37: =D35*D36 -> 2.1311595 | E37: =E35*E36 -> 1.9194047 | F37: =F35*F36 -> 1.8160247 | G37: =G35*G36 -> 1.7507513 | H37: =H35*H36 -> 1.7888816 | I37: =I35*I36 -> 1.8518661 | J37: =J35*J36 -> 1.9043627 | ... M37: =M35*M36 -> 2.0963275
A38: New Store Cash-on-Cash Payback (years) | C38: =C34/C37 -> 0.78744622 | D38: =D34/D37 -> 0.70384221 | E38: =E34/E37 -> 0.78149231 | F38: =F34/F37 -> 0.82597995 | G38: =G34/G37 -> 0.85677503 | H38: =H34/H37 -> 0.83851275 | I38: =I34/I37 -> 0.80999376 | J38: =J34/J37 -> 0.78766507 | ... M38: =M34/M37 -> 0.71553707
A40: V. Free Cash Flow per Store ($M)
C41: FY2021A | D41: FY2022A | E41: FY2023A | F41: FY2024A | G41: FY2025A | H41: FY2026A | I41: FY2027E | J41: FY2028E | K41: FY2029E | L41: FY2030E | M41: FY2031E
A42: EBITDA per Store ($M) | C42: =C26 -> 3.476672 | D42: =D26 -> 5.3381732 | E42: =E26 -> 2.4303078 | F42: =F26 -> 2.5729573 | G42: =G26 -> 2.6495068 | H42: =H26 -> 2.7095295 | I42: =I26 -> 2.8212611 | J42: =J26 -> 3.0406723 | ... M42: =M26 -> 3.6262111
A43: (-) Maintenance CapEx per Store ($M) | C43: =C30*0.65/C11 -> 0.4472 | D43: =D30*0.65/D11 -> 0.49893671 | E43: =E30*0.65/E11 -> 0.49362895 | F43: =F30*0.65/F11 -> 0.49176531 | G43: =G30*0.65/G11 -> 0.4842872 | H43: =H30*0.65/H11 -> 0.48603293 | I43: =I30*0.65/I11 -> 0.52902876 | J43: =J30*0.65/J11 -> 0.50575342 | ... M43: =M30*0.65/M11 -> 0.49830891
A44: (-) Taxes @ 24% | C44: =C24*0.24 -> 0.63520128 | D44: =D24*0.24 -> 1.0818704 | E44: =E24*0.24 -> 0.38510875 | F44: =F24*0.24 -> 0.41864202 | G44: =G24*0.24 -> 0.43559026 | H44: =H24*0.24 -> 0.44635717 | I44: =I24*0.24 -> 0.46874672 | J44: =J24*0.24 -> 0.52119149 | ... M44: =M24*0.24 -> 0.66411254
A45: Store-Level FCF per Store ($M) | B45: $M | C45: =C26-C43-C44 -> 2.3942707 | D45: =D26-D43-D44 -> 3.757366 | E45: =E26-E43-E44 -> 1.5515702 | F45: =F26-F43-F44 -> 1.66255 | G45: =G26-G43-G44 -> 1.7296293 | H45: =H26-H43-H44 -> 1.7771394 | I45: =I26-I43-I44 -> 1.8234856 | J45: =J26-J43-J44 -> 2.0137274 | ... M45: =M26-M43-M44 -> 2.4637897
A46: Store-Level ROIC (FCF / Inv. per Store) | C46: =C45/C34 -> 1.5961805 | D46: =D45/D34 -> 2.5049107 | E46: =E45/E34 -> 1.0343801 | F46: =F45/F34 -> 1.1083666 | G46: =G45/G34 -> 1.1530862 | H46: =H45/H34 -> 1.1847596 | I46: =I45/I34 -> 1.2156571 | J46: =J45/J34 -> 1.3424849 | ... M46: =M45/M34 -> 1.6425265
A48: Sources: Best Buy Q4 FY2026 10-K (Mar 3, 2026); Assumptions sheet. Maintenance CapEx estimated at 65% of total. New store investment ~$1.5M based on mgmt commentary. 4-wall EBITDA margin 8% per FY2026 earnings call context.

Sheet Pro Forma Income Statement
A1: Income Statement Proforma
A2: Description | B2: FY2022A | C2: FY2023A | D2: FY2024A | E2: FY2025A | F2: FY2026A | G2: FY2027E | H2: FY2028E | I2: FY2029E | J2: FY2030E | K2: FY2031E | L2: Notes:
A3: REVENUE
A4: Total Revenue ($mm) | B4: ='Historical Income Statement'!C16 -> 51761 | C4: ='Historical Income Statement'!D16 -> 46298 | D4: ='Historical Income Statement'!E16 -> 43452 | E4: ='Historical Income Statement'!F16 -> 41528 | F4: ='Historical Income Statement'!G16 -> 41691 | G4: ='Revenue Build - Top Down'!J52 -> 42231.099 | H4: ='Revenue Build - Top Down'!K52 -> 42992.723 | I4: ='Revenue Build - Top Down'!L52 -> 43962.944 | J4: ='Revenue Build - Top Down'!M52 -> 44956.209 | K4: ='Revenue Build - Top Down'!N52 -> 45973.05 | L4: from revenue build
A5: COST OF GOODS SOLD & GROSS PROFIT | L5: Gross Margin expansion: From 22.48% (FY26A) to 23.50% (FY31E). Driven by Services/Ads revenue mix shift.
A6: Gross Margin % (assumption) | B6: ='Historical Income Statement'!B19/'Historical Income Statement'!B16 -> 0.22419703 | C6: ='Historical Income Statement'!C19/'Historical Income Statement'!C16 -> 0.22476382 | D6: ='Historical Income Statement'!D19/'Historical Income Statement'!D16 -> 0.21409132 | E6: ='Historical Income Statement'!E19/'Historical Income Statement'!E16 -> 0.22100249 | F6: ='Historical Income Statement'!F19/'Historical Income Statement'!F16 -> 0.2259921 | G6: 0.23 | H6: 0.233 | I6: 0.234 | J6: 0.235 | K6: 0.236 | L6: Calculated from Historical IS sheet: Gross Profit ÷ Revenue. E.g. FY2026A: $9,373M ÷ $41,691M = 22.48%, From 27 and on EBIT margin ramp (4.3% → 5.3% from DCF) by holding SG&A roughly flat and letting GP margin absorb the expansion. | M6: Ads ($900M, 70-75% op margin) recorded as COGS offset in reported P&L — expansion understates true margin improvement.
A7: Cost of Goods Sold | B7: =(B4)*(1-B6) -> 40156.338 | C7: =(C4)*(1-C6) -> 35891.885 | D7: =(D4)*(1-D6) -> 34149.304 | E7: =(E4)*(1-E6) -> 32350.209 | F7: =(F4)*(1-F6) -> 32269.163 | G7: =(G4)*(1-G6) -> 32517.946 | H7: =(H4)*(1-H6) -> 32975.418 | I7: =(I4)*(1-I6) -> 33675.615 | ... K7: =(K4)*(1-K6) -> 35123.41 | L7: Until 2026
A8: Gross Profit | B8: =B4-B7 -> 11604.662 | C8: =C4-C7 -> 10406.115 | D8: =D4-D7 -> 9302.6961 | E8: =E4-E7 -> 9177.7912 | F8: =F4-F7 -> 9421.8367 | G8: =G4-G7 -> 9713.1527 | H8: =H4-H7 -> 10017.304 | I8: =I4-I7 -> 10287.329 | ... K8: =K4-K7 -> 10849.64
A9: Gross Margin % | B9: =B8/B4 -> 0.22419703 | C9: =C8/C4 -> 0.22476382 | D9: =D8/D4 -> 0.21409132 | E9: =E8/E4 -> 0.22100249 | F9: =F8/F4 -> 0.2259921 | G9: =G8/G4 -> 0.23 | H9: =H8/H4 -> 0.233 | I9: =I8/I4 -> 0.234 | ... K9: =K8/K4 -> 0.236
A10: OPERATING EXPENSES (SG&A)
A11: SG&A % Revenue (assumption) | B11: ='Historical Income Statement'!B21/'Historical Income Statement'!B16 -> 0.16605307 | C11: ='Historical Income Statement'!C21/'Historical Income Statement'!C16 -> 0.16502772 | D11: ='Historical Income Statement'!D21/'Historical Income Statement'!D16 -> 0.17028813 | E11: ='Historical Income Statement'!E21/'Historical Income Statement'!E16 -> 0.1798076 | F11: ='Historical Income Statement'!F21/'Historical Income Statement'!F16 -> 0.1836833 | G11: =G9-('DCF - Base Model'!C8/'DCF - Base Model'!C6) -> 0.1876912 | H11: =G11 -> 0.1876912 | I11: =H11 -> 0.1876912 | J11: =I11 -> 0.1876912 | K11: =J11 -> 0.1876912 | L11: Based on common size averages, the SG&A% comes from GM%-EBIT%FY22-26, Flat after 2027 | M11: inline with sales
A12: SG&A CAGR | C12: =(C11-B11)/B11 -> -0.006174787 | D12: =(D11-C11)/C11 -> 0.031875916 | E12: =(E11-D11)/D11 -> 0.055902136 | F12: =(F11-E11)/E11 -> 0.021554674 | G12: =(G11-F11)/F11 -> 0.021819612 | H12: =(H11-G11)/G11 -> 0 | I12: =(I11-H11)/H11 -> 0 | J12: =(J11-I11)/I11 -> 0 | K12: =(K11-J11)/J11 -> 0
A13: Selling, General & Administrative | B13: =B4*B11 -> 8595.0727 | C13: =C4*C11 -> 7640.4535 | D13: =D4*D11 -> 7399.36 | E13: =E4*E11 -> 7467.0502 | F13: =F4*F11 -> 7657.9404 | G13: =G4*G11 -> 7926.4055 | H13: =H4*H11 -> 8069.3556 | I13: =I4*I11 -> 8251.4575 | ... K13: =K4*K11 -> 8628.7367
A14: EBIT (OPERATING INCOME)
A15: EBIT (Operating Income) | B15: =B8-B13 -> 3009.5897 | C15: =C8-C13 -> 2765.6617 | D15: =D8-D13 -> 1903.3361 | E15: =E8-E13 -> 1710.741 | F15: =F8-F13 -> 1763.8963 | G15: =G8-G13 -> 1786.7473 | H15: =H8-H13 -> 1947.9488 | I15: =I8-I13 -> 2035.8713 | ... K15: =K8-K13 -> 2220.903
A16: EBIT Margin % | B16: =B15/B4 -> 0.058143963 | C16: =C15/C4 -> 0.059736095 | D16: =D15/D4 -> 0.043803188 | E16: =E15/E4 -> 0.041194882 | F16: =F15/F4 -> 0.042308804 | G16: =G15/G4 -> 0.042308804 | H16: =H15/H4 -> 0.045308804 | I16: =I15/I4 -> 0.046308804 | ... K16: =K15/K4 -> 0.048308804 | L16: EBIT (FY27E–FY31E): Pulled directly from DCF Base Case model [Green = cross-sheet link]. WACC 10.49%, TGR 2.0%.
A17: D&A AND EBITDA
A18: Depreciation & Amortization | B18: 867 | C18: 831 | D18: 856 | E18: 821 | F18: 831 | G18: ='DCF - Base Model'!D11 -> 800 | H18: ='DCF - Base Model'!E11 -> 793 | I18: ='DCF - Base Model'!F11 -> 782 | J18: ='DCF - Base Model'!G11 -> 772 | K18: ='DCF - Base Model'!H11 -> 762
A19: EBITDA | B19: =B15+B18 -> 3876.5897 | C19: =C15+C18 -> 3596.6617 | D19: =D15+D18 -> 2759.3361 | E19: =E15+E18 -> 2531.741 | F19: =F15+F18 -> 2594.8963 | G19: =G15+G18 -> 2586.7473 | H19: =H15+H18 -> 2740.9488 | I19: =I15+I18 -> 2817.8713 | ... K19: =K15+K18 -> 2982.903
A20: EBITDA Margin % | B20: =B19/B4 -> 0.074894026 | C20: =C19/C4 -> 0.077685034 | D20: =D19/D4 -> 0.063503087 | E20: =E19/E4 -> 0.060964676 | F20: =F19/F4 -> 0.062241163 | G20: =G19/G4 -> 0.06125219 | H20: =H19/H4 -> 0.063753786 | I20: =I19/I4 -> 0.064096512 | ... K20: =K19/K4 -> 0.064883732
A21: BELOW-THE-LINE ITEMS
A22: Interest Expense | B22: -52 | C22: -35 | D22: -52 | E22: -51 | F22: -47 | G22: =-WACC!C13*WACC!C8 -> -35.72646 | H22: =G22 -> -35.72646 | I22: =H22 -> -35.72646 | J22: =I22 -> -35.72646 | K22: =J22 -> -35.72646 | L22: Source: WACC sheet – weighted avg rate 3.06% × $1,130M debt = ~$35M forward | M22: Interest Expense forward: $35M/yr from WACC sheet (3.06% wtd avg rate × $1,130M debt [2028 Notes $500M + 2030 Notes $630M]).
A23: Interest & Investment Income | B23: 10 | C23: 28 | D23: 78 | E23: 84 | F23: 68 | G23: 50 | H23: 45 | I23: 42 | J23: 40 | K23: 38 | L23: Source: Historical actuals; forward assumes declining as cash deployed
A24: Net Interest Income / (Expense) | B24: =B22+B23 -> -42 | C24: =C22+C23 -> -7 | D24: =D22+D23 -> 26 | E24: =E22+E23 -> 33 | F24: =F22+F23 -> 21 | G24: =G22+G23 -> 14.27354 | H24: =H22+H23 -> 9.27354 | I24: =I22+I23 -> 6.27354 | ... K24: =K22+K23 -> 2.27354
A25: Restructuring & Other (one-time) | B25: 0 | C25: 0 | D25: 0 | E25: ='Historical Income Statement'!F39+'Historical Income Statement'!F41+'Historical Income Statement'!F43 -> -474 | F25: ='Historical Income Statement'!G39+'Historical Income Statement'!G41+'Historical Income Statement'!G43+'Historical Income Statement'!G42 -> -388 | G25: 0 | H25: 0 | I25: 0 | J25: 0 | K25: 0 | L25: Note: FY25A=-$386M; FY26A=-$386M approx bridge. Forward=0 (non-recurring) | M25: Restructuring charges: $0 forward. FY2025A/FY2026A included ~$382M restructuring. Non-recurring; excluded from forward EPS.
A26: PRE-TAX INCOME
A27: Earnings Before Tax (EBT) | B27: =B15+B24+B25 -> 2967.5897 | C27: =C15+C24+C25 -> 2758.6617 | D27: =D15+D24+D25 -> 1929.3361 | E27: =E15+E24+E25 -> 1269.741 | F27: =F15+F24+F25 -> 1396.8963 | G27: =G15+G24+G25 -> 1801.0208 | H27: =H15+H24+H25 -> 1957.2224 | I27: =I15+I24+I25 -> 2042.1449 | ... K27: =K15+K24+K25 -> 2223.1766
A28: Effective Tax Rate (assumption) | B28: =Assumptions!$B$33 -> 0.24 | C28: =Assumptions!$B$33 -> 0.24 | D28: =Assumptions!$B$33 -> 0.24 | E28: =Assumptions!$B$33 -> 0.24 | F28: =Assumptions!$B$33 -> 0.24 | G28: =Assumptions!$B$33 -> 0.24 | H28: =Assumptions!$B$33 -> 0.24 | I28: =Assumptions!$B$33 -> 0.24 | ... K28: =Assumptions!$B$33 -> 0.24 | L28: Tax Rate: 24% flat (consistent with BBY adj. effective rate per FY26 10-K and model assumptions sheet).
A29: Income Tax Expense | B29: =B27*B28 -> 712.22153 | C29: =C27*C28 -> 662.07881 | D29: =D27*D28 -> 463.04067 | E29: =E27*E28 -> 304.73785 | F29: =F27*F28 -> 335.25512 | G29: =G27*G28 -> 432.245 | H29: =H27*H28 -> 469.73337 | I29: =I27*I28 -> 490.11477 | ... K29: =K27*K28 -> 533.56238
A30: NET INCOME & EPS
A31: NET INCOME | B31: =B27-B29 -> 2255.3682 | C31: =C27-C29 -> 2096.5829 | D31: =D27-D29 -> 1466.2955 | E31: =E27-E29 -> 965.0032 | F31: =F27-F29 -> 1061.6412 | G31: =G27-G29 -> 1368.7758 | H31: =H27-H29 -> 1487.489 | I31: =I27-I29 -> 1552.0301 | ... K31: =K27-K29 -> 1689.6142
A32: Net Margin % | B32: =B31/B4 -> 0.043572732 | C32: =C31/C4 -> 0.045284524 | D32: =D31/D4 -> 0.033745178 | E32: =E31/E4 -> 0.023237411 | F32: =F31/F4 -> 0.025464518 | G32: =G31/G4 -> 0.032411561 | H32: =H31/H4 -> 0.034598623 | I32: =I31/I4 -> 0.035303143 | ... K32: =K31/K4 -> 0.036752276
A33: Diluted Shares Outstanding (mm) | B33: 211 | C33: 213 | D33: 210 | E33: 210 | F33: 209 | G33: ='DCF - Base Model'!C27 -> 210 | H33: =G33 -> 210 | I33: =H33 -> 210 | J33: =I33 -> 210 | K33: =J33 -> 210 | L33: Source: BBY 10-K FY26 – 209.1M diluted; forward assumes ~210M with minor buybacks | M33: This is the PRIMARY reason our FY2027E EPS ($6.57) is ~1.2% above Street consensus ($6.49).
A34: EPS (Diluted, GAAP) | B34: =(B31*1000000)/(B33*1000000) -> 10.688949 | C34: =(C31*1000000)/(C33*1000000) -> 9.8431122 | D34: =(D31*1000000)/(D33*1000000) -> 6.9823593 | E34: =(E31*1000000)/(E33*1000000) -> 4.5952533 | F34: =(F31*1000000)/(F33*1000000) -> 5.079623 | G34: =(G31*1000000)/(G33*1000000) -> 6.5179801 | H34: =(H31*1000000)/(H33*1000000) -> 7.083281 | I34: =(I31*1000000)/(I33*1000000) -> 7.3906196 | ... K34: =(K31*1000000)/(K33*1000000) -> 8.0457819
A35: Street Consensus EPS (GAAP) | F35: 5.11 | G35: 6.49 | L35: Source: Comp Analysis sheet – NTM EPS $6.49 (FY27E)
A36: Premium/(Discount) to Consensus | F36: =IF(F35=0,"",(F34-F35)/F35) -> -0.0059446113 | G36: =IF(G35=0,"",(G34-G35)/G35) -> 0.0043112611
A37: P/E | F37: =('DCF - Base Model'!B50/F34) -> 12.479272 | G37: =('Blended Implied Pricing Summary'!$C$6/G34) -> 13.276227 | H37: =('Blended Implied Pricing Summary'!$C$6/H34) -> 12.216681 | I37: =('DCF - Base Model'!$C$29/I34) -> 13.165319 | J37: =('DCF - Base Model'!$C$29/J34) -> 12.615792 | K37: =('DCF - Base Model'!$C$29/K34) -> 12.093277 | L37: Using blemded for first 2 yrs then the DCF
A38: Hardware retail trades at 5-7x EBITDA. Retail media trades at 15-20x EBITDA. Blending those two on $700M of Ads EBITDA at 15x adds roughly $10.5B to the implied enterprise value versus applying 5-7x to the whole thing.

Sheet Estimates in CAGR
B1: Forward looking estimates as CAGR
C3: 2026A | D3: 2027E | E3: 2028E | F3: 3-y CAGR | G3: 5-y CAGR
B4: Sales ($mm) | C4: ='DCF - Base Model'!C6 -> 41691 | D4: ='DCF - Base Model'!D6 -> 41855.63 | E4: ='DCF - Base Model'!H6 -> 46310.364 | F4: =((E4/C4)^(1/3)-1) -> 0.035647497 | G4: =(('Pro Forma Income Statement'!K4/C4)^(1/5)-1) -> 0.019746446
B5: EPS | C5: ='Pro Forma Income Statement'!F34 -> 5.079623 | D5: ='Pro Forma Income Statement'!G34 -> 6.5179801 | E5: ='Pro Forma Income Statement'!H34 -> 7.083281 | F5: =((E5/C5)^(1/3)-1) -> 0.11720875 | G5: =(('Pro Forma Income Statement'!K34/C5)^(1/5)-1) -> 0.096345287 | H5: this is diluted eps
B6: P/E | C6: ='Pro Forma Income Statement'!F37 -> 12.479272 | D6: ='Pro Forma Income Statement'!G37 -> 13.276227 | E6: ='Pro Forma Income Statement'!H37 -> 12.216681 | F6: - | G6: -
B8: EPS and P/E forcaste: numbers below are copied from DCF Base Model
B9: WACC | C9: ='DCF - Base Model'!C3 -> 0.10490729
B10: Terminal growth | C10: ='DCF - Base Model'!C4 -> 0.02 | I10: same store
B11: Description | C11: 2026A | D11: 2027E | E11: 2028E | F11: 2029E | G11: 2030E | H11: 2031E
B12: Total Revenue | C12: ='DCF - Base Model'!C6 -> 41691 | D12: ='DCF - Base Model'!D6 -> 41855.63 | E12: ='DCF - Base Model'!E6 -> 43078.554 | F12: ='DCF - Base Model'!F6 -> 44278.874 | G12: ='DCF - Base Model'!G6 -> 45284.272 | H12: ='DCF - Base Model'!H6 -> 46310.364
B13: Free Cashflow Projection
B14: EBIT (Operating Income) | C14: 1771 | D14: 1799.7921 | E14: 1981.6135 | F14: 2169.6648 | G14: 2309.4979 | H14: 2454.4493
B15: Less: Taxes | C15: 425.04 | D15: 431.9501 | E15: 475.58724 | F15: 520.71955 | G15: 554.27949 | H15: 589.06783
B16: NOPAT | C16: 1345.96 | D16: 1367.842 | E16: 1506.0263 | F16: 1648.9453 | G16: 1755.2184 | H16: 1865.3814
B17: Interest | C17: =-'Historical Income Statement'!G31 -> 47 | D17: =C17 -> 47 | E17: =D17 -> 47 | F17: =E17 -> 47 | G17: =F17 -> 47 | H17: =G17 -> 47
B18: less: after tax interest expense | C18: =C17*(1-24%) -> 35.72 | D18: =C18 -> 35.72 | E18: =D18 -> 35.72 | F18: =E18 -> 35.72 | G18: =F18 -> 35.72 | H18: =G18 -> 35.72
B19: Net Income | C19: =C16-C18 -> 1310.24 | D19: =D16-D18 -> 1332.122 | E19: =E16-E18 -> 1470.3063 | F19: =F16-F18 -> 1613.2253 | G19: =G16-G18 -> 1719.4984 | H19: =H16-H18 -> 1829.6614
B21: EPS | C21: =C19/'Historical Balance Sheet'!$G$65 -> 6.2657159 | D21: =D19/'Historical Balance Sheet'!$G$65 -> 6.3703581 | E21: =E19/'Historical Balance Sheet'!$G$65 -> 7.0311708 | F21: =F19/'Historical Balance Sheet'!$G$65 -> 7.7146257 | G21: =G19/'Historical Balance Sheet'!$G$65 -> 8.2228358 | H21: =H19/'Historical Balance Sheet'!$G$65 -> 8.749648 | I21: below consensus in 2027 and above in 2028
B22: Price per share | C22: ='DCF - Base Model'!B50 -> 63.39 | H22: ='DCF - Base Model'!C29 -> 97.299866
B23: P/E | C23: ='DCF - Base Model'!B50/'Estimates in CAGR'!C21 -> 10.11696 | H23: =H22/H21 -> 11.120432
B25: Price | C25: =C5*C6 -> 63.39 | D25: =D5*D6 -> 86.534183 | E25: =E5*E6 -> 86.534183

Sheet WACC
B1: WACC Calculation
B2: I. Market Inputs
B3: Risk-free rate (Rf) | C3: 0.043 | D3: 10Y US Treasury yield, April 14 2026
B4: Equity risk premium (ERP) | C4: 0.05 | D4: Damodaran US ERP, base case
B5: 5-year monthly beta (raw) | C5: 1.37 | D5: Yahoo Finance / CNBC, April 2026
B6: Pre-tax cost of debt (Kd) | C6: 0.0407 | D6: BBY FY2026 10-K
B7: Effective tax rate (t) | C7: 0.24 | D7: BBY FY2026 10-K, adj. effective rate
B8: After-tax cost of debt | C8: =C6*(1-C7) -> 0.030932 | D8: Kd × (1 − t)
B10: II. Capital Structure (Market Value Weights)
C11: Amount ($M) | D11: Source / Note
B12: Equity (market cap) | C12: 12960 | D12: ~$62/share × 210M diluted shares outstanding
B13: Financial debt (gross) | C13: 1155 | D13: FY2026 10-K, Note 7 — long-term debt
B14: Total capital (E + D) | C14: =C13+C12 -> 14115
B15: Weight of equity (E/V) | C15: =C12/C14 -> 0.91817216
B16: Weight of debt (D/V) | C16: =C13/C14 -> 0.081827843
B18: IV. WACC
B19: Cost Equity | C19: =C3+C5*C4 -> 0.1115
B20: Equity contribution | C20: =C19*C15 -> 0.1023762
B21: Debt contribution | C21: =C16*C8 -> 0.0025310988
B22: WACC | C22: =C20+C21 -> 0.10490729

Sheet Appendix ==>
A1: Appendix

Sheet Chart Data
A2: T1 | Segment Revenue ($M) | FY2022A–FY2031E
B3: FY2022A | C3: FY2023A | D3: FY2024A | E3: FY2025A | F3: FY2026A | G3: FY2027E | H3: FY2028E | I3: FY2029E | J3: FY2030E | K3: FY2031E
A4: Computing & Mobile | B4: ='Revenue Build - Top Down'!E63 -> 22478 | C4: ='Revenue Build - Top Down'!F63 -> 19766 | D4: ='Revenue Build - Top Down'!G63 -> 18482 | E4: ='Revenue Build - Top Down'!H63 -> 18681 | F4: ='Revenue Build - Top Down'!I63 -> 19714 | G4: ='Revenue Build - Top Down'!J63 -> 20108.28 | H4: ='Revenue Build - Top Down'!K63 -> 20912.611 | I4: ='Revenue Build - Top Down'!L63 -> 21539.99 | ... K4: ='Revenue Build - Top Down'!N63 -> 22410.205
A5: Consumer Electronics | B5: ='Revenue Build - Top Down'!E64 -> 16203 | C5: ='Revenue Build - Top Down'!F64 -> 14094 | D5: ='Revenue Build - Top Down'!G64 -> 12969 | E5: ='Revenue Build - Top Down'!H64 -> 12065 | F5: ='Revenue Build - Top Down'!I64 -> 11460 | G5: ='Revenue Build - Top Down'!J64 -> 11230.8 | H5: ='Revenue Build - Top Down'!K64 -> 11399.262 | I5: ='Revenue Build - Top Down'!L64 -> 11627.247 | ... K5: ='Revenue Build - Top Down'!N64 -> 12096.988
A6: Appliances | B6: ='Revenue Build - Top Down'!E65 -> 7167 | C6: ='Revenue Build - Top Down'!F65 -> 6736 | D6: ='Revenue Build - Top Down'!G65 -> 5804 | E6: ='Revenue Build - Top Down'!H65 -> 4910 | F6: ='Revenue Build - Top Down'!I65 -> 4469 | G6: ='Revenue Build - Top Down'!J65 -> 4245.55 | H6: ='Revenue Build - Top Down'!K65 -> 4245.55 | I6: ='Revenue Build - Top Down'!L65 -> 4351.6888 | ... K6: ='Revenue Build - Top Down'!N65 -> 4616.7066
A7: Entertainment | B7: ='Revenue Build - Top Down'!E66 -> 3275 | C7: ='Revenue Build - Top Down'!F66 -> 3053 | D7: ='Revenue Build - Top Down'!G66 -> 3363 | E7: ='Revenue Build - Top Down'!H66 -> 2908 | F7: ='Revenue Build - Top Down'!I66 -> 3092 | G7: ='Revenue Build - Top Down'!J66 -> 3184.76 | H7: ='Revenue Build - Top Down'!K66 -> 3264.379 | I7: ='Revenue Build - Top Down'!L66 -> 3329.6666 | ... K7: ='Revenue Build - Top Down'!N66 -> 3464.1851
A8: Services | B8: ='Revenue Build - Top Down'!E67 -> 2380 | C8: ='Revenue Build - Top Down'!F67 -> 2332 | D8: ='Revenue Build - Top Down'!G67 -> 2530 | E8: ='Revenue Build - Top Down'!H67 -> 2631 | F8: ='Revenue Build - Top Down'!I67 -> 2656 | G8: ='Revenue Build - Top Down'!J67 -> 2762.24 | H8: ='Revenue Build - Top Down'!K67 -> 2900.352 | I8: ='Revenue Build - Top Down'!L67 -> 3045.3696 | ... K8: ='Revenue Build - Top Down'!N67 -> 3293.8718
A9: Other | B9: ='Revenue Build - Top Down'!E68 -> 258 | C9: ='Revenue Build - Top Down'!F68 -> 317 | D9: ='Revenue Build - Top Down'!G68 -> 304 | E9: ='Revenue Build - Top Down'!H68 -> 333 | F9: ='Revenue Build - Top Down'!I68 -> 300 | G9: ='Revenue Build - Top Down'!J68 -> 324 | H9: ='Revenue Build - Top Down'!K68 -> 356.4 | I9: ='Revenue Build - Top Down'!L68 -> 384.912 | ... K9: ='Revenue Build - Top Down'!N68 -> 428.40706
A12: T2 | Operating Margin % | FY2021A–FY2031E
B13: FY2021A | C13: FY2022A | D13: FY2023A | E13: FY2024A | F13: FY2025A | G13: FY2026A | H13: FY2027E | I13: FY2028E | J13: FY2029E | K13: FY2030E | L13: FY2031E
A14: BBY Base | B14: ='Historical Income Statement'!B29/'Historical Income Statement'!B16 -> 0.056451272 | C14: ='Historical Income Statement'!C29/'Historical Income Statement'!C16 -> 0.05815189 | D14: ='Historical Income Statement'!D29/'Historical Income Statement'!D16 -> 0.041945656 | E14: ='Historical Income Statement'!E29/'Historical Income Statement'!E16 -> 0.039791034 | F14: ='Historical Income Statement'!F29/'Historical Income Statement'!F16 -> 0.041803121 | G14: ='Historical Income Statement'!G29/'Historical Income Statement'!G16 -> 0.042479192 | H14: =Assumptions!B37 -> 0.043 | I14: =Assumptions!C37 -> 0.046 | J14: =Assumptions!D37 -> 0.049 | K14: =Assumptions!E37 -> 0.051 | L14: =Assumptions!F37 -> 0.053
A15: Bear Case | B15: ='Historical Income Statement'!B29/'Historical Income Statement'!B16 -> 0.056451272 | C15: ='Historical Income Statement'!C29/'Historical Income Statement'!C16 -> 0.05815189 | D15: ='Historical Income Statement'!D29/'Historical Income Statement'!D16 -> 0.041945656 | E15: ='Historical Income Statement'!E29/'Historical Income Statement'!E16 -> 0.039791034 | F15: ='Historical Income Statement'!F29/'Historical Income Statement'!F16 -> 0.041803121 | G15: ='Historical Income Statement'!G29/'Historical Income Statement'!G16 -> 0.042479192 | H15: ='DCF - Bear Model'!D9 -> 0.023 | I15: ='DCF - Bear Model'!E9 -> 0.026 | J15: ='DCF - Bear Model'!F9 -> 0.029 | K15: ='DCF - Bear Model'!G9 -> 0.031 | L15: ='DCF - Bear Model'!H9 -> 0.033
A18: T3 | Segment Mix % | FY2022A / FY2026A / FY2031E
B19: FY2022A | C19: FY2026A | D19: FY2031E
A20: Computing & Mobile | B20: ='Revenue Build - Top Down'!E72 -> 0.43426518 | C20: ='Revenue Build - Top Down'!I72 -> 0.47285985 | D20: ='Revenue Build - Top Down'!N72 -> 0.48391339
A21: Consumer Electronics | B21: ='Revenue Build - Top Down'!E73 -> 0.31303491 | C21: ='Revenue Build - Top Down'!I73 -> 0.27487947 | D21: ='Revenue Build - Top Down'!N73 -> 0.26121557
A22: Appliances | B22: ='Revenue Build - Top Down'!E74 -> 0.13846332 | C22: ='Revenue Build - Top Down'!I74 -> 0.1071934 | D22: ='Revenue Build - Top Down'!N74 -> 0.099690571
A23: Entertainment | B23: ='Revenue Build - Top Down'!E75 -> 0.063271575 | C23: ='Revenue Build - Top Down'!I75 -> 0.074164688 | D23: ='Revenue Build - Top Down'!N75 -> 0.074803669
A24: Services | B24: ='Revenue Build - Top Down'!E76 -> 0.045980565 | C24: ='Revenue Build - Top Down'!I76 -> 0.063706795 | D24: ='Revenue Build - Top Down'!N76 -> 0.071126018
A25: Other | B25: ='Revenue Build - Top Down'!E77 -> 0.0049844478 | C25: ='Revenue Build - Top Down'!I77 -> 0.0071957977 | D25: ='Revenue Build - Top Down'!N77 -> 0.0092507815
A28: T4 | SOTP Value Bridge ($)
A29: Bridge Step | B29: Invis. Base | C29: Anchor (Navy) | D29: Uplift (Green)
A30: Current Market Price | B30: 0 | C30: =Assumptions!B39 -> 63.39 | D30: 0
A31: BBY Ads Platform (+$11.9) | B31: =Assumptions!B39 -> 63.39 | C31: 0 | D31: 11.9
A32: Services / Totaltech (+$6.5) | B32: =B31+C31+D31 -> 75.29 | C32: 0 | D32: 6.5
A33: Op. Leverage & Margin Exp. | B33: =B32+C32+D32 -> 81.79 | C33: 0 | D33: ='DCF - Base Model'!C29-B33 -> 15.509866
A34: DCF Base Target | B34: 0 | C34: ='DCF - Base Model'!C29 -> 97.299866 | D34: 0
A37: T5 | DCF GGM Sensitivity | Implied Share Price
A38: ='DCF - Base Model'!C29 -> 97.299866 | B38: 0.095 | C38: 0.1 | D38: 0.105 | E38: 0.11 | F38: 0.115
A39: 0.01 | B39: 99.94612 | C39: 94.459545 | D39: 89.572243 | E39: 85.193413 | F39: 81.24958
A40: 0.015 | B40: 104.64023 | C40: 98.556736 | D40: 93.172249 | E40: 88.375432 | F40: 84.077255
A41: 0.02 | B41: 109.96021 | C41: 103.16608 | D41: 97.195784 | E41: 91.91101 | F41: 87.202581
A42: 0.025 | B42: 116.0402 | C42: 108.38999 | D42: 101.72226 | E42: 95.862538 | F42: 90.675166
A43: 0.03 | B43: 123.05557 | C43: 114.36019 | D43: 106.85227 | E43: 100.30801 | F43: 94.556289
A46: T6 | Normalized EPS | Base vs. Bear | FY2021A–FY2031E
B47: FY2021A | C47: FY2022A | D47: FY2023A | E47: FY2024A | F47: FY2025A | G47: FY2026A | H47: FY2027E | I47: FY2028E | J47: FY2029E | K47: FY2030E | L47: FY2031E
A48: Base Case EPS | B48: ='Historical Income Statement'!B72 -> 6.307034 | C48: ='Historical Income Statement'!C72 -> 7.518551 | D48: ='Historical Income Statement'!D72 -> 5.361098 | E48: ='Historical Income Statement'!E72 -> 5.022883 | F48: ='Historical Income Statement'!F72 -> 5.115997 | G48: ='Historical Income Statement'!G72 -> 5.286421 | H48: ='DCF - Base Model'!D10/'DCF - Base Model'!C27 -> 6.5135333 | I48: ='DCF - Base Model'!E10/'DCF - Base Model'!C27 -> 7.1715536 | J48: ='DCF - Base Model'!F10/'DCF - Base Model'!C27 -> 7.8521203 | K48: ='DCF - Base Model'!G10/'DCF - Base Model'!C27 -> 8.3581828 | L48: ='DCF - Base Model'!H10/'DCF - Base Model'!C27 -> 8.8827688
A49: Bear Case EPS | B49: ='Historical Income Statement'!B72 -> 6.307034 | C49: ='Historical Income Statement'!C72 -> 7.518551 | D49: ='Historical Income Statement'!D72 -> 5.361098 | E49: ='Historical Income Statement'!E72 -> 5.022883 | F49: ='Historical Income Statement'!F72 -> 5.115997 | G49: ='Historical Income Statement'!G72 -> 5.286421 | H49: ='DCF - Bear Model'!D12/'DCF - Bear Model'!C29 -> 3.376019 | I49: ='DCF - Bear Model'!E12/'DCF - Bear Model'!C29 -> 3.8660573 | J49: ='DCF - Bear Model'!F12/'DCF - Bear Model'!C29 -> 4.3878384 | K49: ='DCF - Bear Model'!G12/'DCF - Bear Model'!C29 -> 4.7964204 | L49: ='DCF - Bear Model'!H12/'DCF - Bear Model'!C29 -> 5.2213537
A51: T7 | Domestic SSS % & Rev per Store ($M) | FY2021A–FY2031E
B52: FY2021A | C52: FY2022A | D52: FY2023A | E52: FY2024A | F52: FY2025A | G52: FY2026A | H52: FY2027E | I52: FY2028E | J52: FY2029E | K52: FY2030E | L52: FY2031E
A53: Domestic SSS % | B53: ='Revenue Build - Top Down'!D7 -> 0.092 | C53: ='Revenue Build - Top Down'!E7 -> 0.11 | D53: ='Revenue Build - Top Down'!F7 -> -0.103 | E53: ='Revenue Build - Top Down'!G7 -> -0.071 | F53: ='Revenue Build - Top Down'!H7 -> -0.025 | G53: ='Revenue Build - Top Down'!I7 -> 0.004 | H53: ='Revenue Build - Top Down'!J7 -> 0.01 | I53: ='Revenue Build - Top Down'!K7 -> 0.015 | ... L53: ='Revenue Build - Top Down'!N7 -> 0.02
A54: Dom. Rev/Store ($M) | B54: ='Revenue Build - Top Down'!D29 -> 43.293 | C54: ='Revenue Build - Top Down'!E29 -> 48.435443 | D54: ='Revenue Build - Top Down'!F29 -> 43.622834 | E54: ='Revenue Build - Top Down'!G29 -> 41.273289 | F54: ='Revenue Build - Top Down'!H29 -> 39.789802 | G54: ='Revenue Build - Top Down'!I29 -> 40.656399 | H54: ='Revenue Build - Top Down'!J29 -> 42.087866 | I54: ='Revenue Build - Top Down'!K29 -> 43.280971 | ... L54: ='Revenue Build - Top Down'!N29 -> 47.643806
A57: T8 | Football Field Valuation
A58: Methodology | B58: Low ($) | C58: Range ($)
A59: P/E Comps (NTM) | B59: ='Football Field'!C3 -> 62 | C59: ='Football Field'!D3 -> 34
A60: EV/EBITDA Comps (NTM) | B60: ='Football Field'!C4 -> 50 | C60: ='Football Field'!D4 -> 26
A61: FCFF DCF (Base Case) | B61: ='Football Field'!C5 -> 81 | C61: ='Football Field'!D5 -> 42
A62: Analyst Price Targets | B62: ='Football Field'!C6 -> 62.37 | C62: ='Football Field'!D6 -> 27.63
A63: 52-Week Hi-Lo Range | B63: ='Football Field'!C7 -> 62.87 | C63: ='Football Field'!D7 -> 25.3

Sheet Charts
B88: Chart 5 | DCF GGM Sensitivity — Implied Share Price ($)
B89: Base case: WACC 10.5% | TGR 2.0% | Current Price: $63.39
B91: TGR \ WACC | C91: 9.5% | D91: 10.0% | E91: 10.5% | F91: 11.0% | G91: 11.5%
B92: 1.0% | C92: 99.95 | D92: 94.46 | E92: 89.57 | F92: 85.19 | G92: 81.25
B93: 1.5% | C93: 104.64 | D93: 98.56 | E93: 93.17 | F93: 88.38 | G93: 84.08
B94: 2.0% | C94: 109.96 | D94: 103.17 | E94: 97.2 | F94: 91.91 | G94: 87.2
B95: 2.5% | C95: 116.04 | D95: 108.39 | E95: 101.72 | F95: 95.86 | G95: 90.68
B96: 3.0% | C96: 123.06 | D96: 114.36 | E96: 106.85 | F96: 100.31 | G96: 94.56
