Workbook

Sheet Overview
A4: Valuation on : Deckers Outdoor (DECK): Initiating Coverage - BUY recommendation
A5: Presented by: Felipe Schmidt, Faisal Hidayah, Shaira Katuwal, Vaishnavi Ramesh
A7: This model is a comprehensive valuation of Deckers Outdoor Corporation, focusing on its financial health, growth prospects, and intrinsic value. We'll present our investment recommendation based on a detailed DCF analysis, highlighting key assumptions and sensitivity insights.

Sheet Balance Sheet
D1: DECKERS OUTDOOR CORPORATION AND SUBSIDIARIES
D2: CONSOLIDATED BALANCE SHEETS
D3: (amounts in thousands, except par value, As of March 31)
B4: Historical | D4: Historical | J4: Projected
B5: 2018 | C5: 2019 | D5: 2020 | E5: 2021 | F5: 2022 | G5: 2023 | H5: 2024 | I5: 2025 | J5: 2026 | K5: 2027 | L5: 2028 | M5: 2029 | N5: 2030 | O5: 2031 | P5: 2032 | Q5: 2033 | R5: 2034 | S5: 2035
A6: ASSETS
A7: Cash and cash equivalents | B7: 429970 | C7: 589692 | D7: 649436 | E7: 1089361 | F7: 843527 | G7: 981795 | H7: 1502051 | I7: 1889188 | J7: ='Balanced Proforma'!C21 -> 2131469.5 | K7: =Proforma!D18 -> 2335668.7 | L7: =Proforma!E18 -> 2768891.9 | M7: =Proforma!F18 -> 3282469.9 | N7: =Proforma!G18 -> 3891307 | O7: =Proforma!H18 -> 4613072.1 | P7: =Proforma!I18 -> 5468711.3 | Q7: =Proforma!J18 -> 6483055.6 | R7: =Proforma!K18 -> 7685541.9 | S7: =Proforma!L18 -> 9111067.1
A8: Trade accounts receivable, net of allowances | B8: 143704 | C8: 178602 | D8: 185596 | E8: 215718 | F8: 302688 | G8: 301511 | H8: 296565 | I8: 332872 | J8: =Proforma!C19 -> 971564.44 | K8: =Proforma!D19 -> 1151771.6 | L8: =Proforma!E19 -> 1365403.8 | M8: =Proforma!F19 -> 1618660.8 | N8: =Proforma!G19 -> 1918892.3 | O8: =Proforma!H19 -> 2274811.2 | P8: =Proforma!I19 -> 2696746.4 | Q8: =Proforma!J19 -> 3196942.7 | ... S8: =Proforma!L19 -> 4492875.2
A9: Inventories | B9: 299602 | C9: 278842 | D9: 311620 | E9: 278242 | F9: 506796 | G9: 532852 | H9: 474311 | I9: 495226 | J9: =Proforma!C20 -> 603246.02 | K9: =Proforma!D20 -> 715136.94 | L9: =Proforma!E20 -> 847781.55 | M9: =Proforma!F20 -> 1005029.3 | N9: =Proforma!G20 -> 1191443.5 | O9: =Proforma!H20 -> 1412434.1 | P9: =Proforma!I20 -> 1674414.4 | Q9: =Proforma!J20 -> 1984987.2 | ... S9: =Proforma!L20 -> 2789633.9
A10: Prepaid expenses | B10: 17639 | C10: 19901 | D10: 17760 | E10: 16924 | F10: 25610 | G10: 33788 | H10: 34284 | I10: 39294 | J10: =Proforma!C21 -> 142160.56 | K10: =Proforma!D21 -> 168528.7 | L10: =Proforma!E21 -> 199787.64 | M10: =Proforma!F21 -> 236844.53 | N10: =Proforma!G21 -> 280774.79 | O10: =Proforma!H21 -> 332853.3 | P10: =Proforma!I21 -> 394591.4 | Q10: =Proforma!J21 -> 467780.77 | ... S10: =Proforma!L21 -> 657403.28
A11: Other current assets | B11: 17599 | C11: 26028 | D11: 21548 | E11: 44244 | F11: 55264 | G11: 55523 | H11: 92713 | I11: 67282
A12: Income tax receivable | B12: 2176 | C12: 2340 | D12: 8151 | E12: 6310 | F12: 18243 | G12: 4784 | H12: 43559 | I12: 36613 | J12: 0 | K12: 0 | L12: 0 | M12: 0 | N12: 0 | O12: 0 | P12: 0 | Q12: 0 | R12: 0 | S12: 0
A13: Total current assets | B13: =SUM(B7:B12) -> 910690 | C13: =SUM(C7:C12) -> 1095405 | D13: =SUM(D7:D12) -> 1194111 | E13: =SUM(E7:E12) -> 1650799 | F13: =SUM(F7:F12) -> 1752128 | G13: =SUM(G7:G12) -> 1910253 | H13: =SUM(H7:H12) -> 2443483 | I13: =SUM(I7:I12) -> 2860475 | J13: =Proforma!C23 -> 3687199.1 | K13: =Proforma!D23 -> 4371106 | L13: =Proforma!E23 -> 5181864.9 | M13: =Proforma!F23 -> 6143004.5 | N13: =Proforma!G23 -> 7282417.7 | O13: =Proforma!H23 -> 8633170.8 | P13: =Proforma!I23 -> 10234464 | Q13: =Proforma!J23 -> 12132766 | ... S13: =Proforma!L23 -> 17050979
A14: PPE gross | D14: =D15+D16 -> 444976 | E14: =E15+E16 -> 473115 | F14: =F15+F16 -> 505020 | G14: =G15+G16 -> 584187 | H14: =H15+H16 -> 651260 | I14: =I15+I16 -> 728563 | J14: =Proforma!C24 -> 998730.72 | K14: =Proforma!D24 -> 1183976.7 | L14: =Proforma!E24 -> 1403582.4 | M14: =Proforma!F24 -> 1663920.8 | N14: =Proforma!G24 -> 1972547.2 | O14: =Proforma!H24 -> 2338418.1 | P14: =Proforma!I24 -> 2772151.1 | Q14: =Proforma!J24 -> 3286333.7 | ... S14: =Proforma!L24 -> 4618502.2
A15: Depreciation | D15: 235939 | E15: 266905 | F15: 282571 | G15: 317508 | H15: 349138 | I15: 402964 | J15: =Proforma!C25 -> 547069.98 | K15: =Proforma!D25 -> 648541.29 | L15: =Proforma!E25 -> 768833.65 | M15: =Proforma!F25 -> 911438 | N15: =Proforma!G25 -> 1080492.8 | O15: =Proforma!H25 -> 1280904.1 | P15: =Proforma!I25 -> 1518488.1 | Q15: =Proforma!J25 -> 1800139.4 | ... S15: =Proforma!L25 -> 2529855
A16: PPE net | D16: 209037 | E16: 206210 | F16: 222449 | G16: 266679 | H16: 302122 | I16: 325599 | J16: Assumption: Already calculated in PPE Gross. Derived from PPE gross minus accumulated depreciation.
A17: Operating lease assets | B17: 0 | C17: 0 | D17: 243522 | E17: 186991 | F17: 182459 | G17: 213302 | H17: 225669 | I17: 237352 | J17: =Proforma!C27 -> 214882.5 | K17: =Proforma!D27 -> 214882.5 | L17: =Proforma!E27 -> 214882.5 | M17: =Proforma!F27 -> 214882.5 | N17: =Proforma!G27 -> 214882.5 | O17: =Proforma!H27 -> 214882.5 | P17: =Proforma!I27 -> 214882.5 | Q17: =Proforma!J27 -> 214882.5 | ... S17: =Proforma!L27 -> 214882.5
A18: Goodwill | B18: 13990 | C18: 13990 | D18: 13990 | E18: 13990 | F18: 13990 | G18: 13990 | H18: 13990 | I18: 13990 | J18: =Proforma!C28 -> 13990 | K18: =Proforma!D28 -> 13990 | L18: =Proforma!E28 -> 13990 | M18: =Proforma!F28 -> 13990 | N18: =Proforma!G28 -> 13990 | O18: =Proforma!H28 -> 13990 | P18: =Proforma!I28 -> 13990 | Q18: =Proforma!J28 -> 13990 | ... S18: =Proforma!L28 -> 13990
A19: Other intangible assets, net of accumulated amortization | B19: 57850 | C19: 51494 | D19: 48016 | E19: 41945 | F19: 39688 | G19: 37457 | H19: 27083 | I19: 15699 | J19: =Proforma!C29 -> 34981.333 | K19: =Proforma!D29 -> 34981.333 | L19: =Proforma!E29 -> 34981.333 | M19: =Proforma!F29 -> 34981.333 | N19: =Proforma!G29 -> 34981.333 | O19: =Proforma!H29 -> 34981.333 | P19: =Proforma!I29 -> 34981.333 | Q19: =Proforma!J29 -> 34981.333 | ... S19: =Proforma!L29 -> 34981.333
A20: Deferred tax assets, net | B20: 38381 | C20: 30870 | D20: 28233 | E20: 37194 | F20: 64217 | G20: 72592 | H20: 72584 | I20: 77591 | J20: Assumption: Non-operating; timing difference in taxes. Often excluded in operating asset base for ROIC/valuation.
A21: Other non-current assets | B21: 23306 | C21: 21651 | D21: 28209 | E21: 30576 | F21: 57319 | G21: 41930 | H21: 50648 | I21: 39546 | J21: =Proforma!C31 -> 73619.803 | K21: 87274.908 | L21: 103462.78 | M21: 122653.2 | N21: 145403.09 | O21: 172372.67 | P21: 204344.59 | Q21: 242246.71 | R21: 287178.98 | S21: 340445.34
A22: Total Non-current Assets | D22: =SUM(D14:D21) -> 1251922 | E22: =SUM(E14:E21) -> 1256926 | F22: =SUM(F14:F21) -> 1367713 | G22: =SUM(G14:G21) -> 1547645 | H22: =SUM(H14:H21) -> 1692494 | I22: =SUM(I14:I21) -> 1841304 | J22: =Proforma!C32 -> 789134.38 | K22: =Proforma!D32 -> 886564.16 | L22: =Proforma!E32 -> 1002065.3 | M22: =Proforma!F32 -> 1138989.9 | N22: =Proforma!G32 -> 1301311.3 | O22: =Proforma!H32 -> 1493740.4 | P22: =Proforma!I32 -> 1721861.5 | Q22: =Proforma!J32 -> 1992294.8 | ... S22: =Proforma!L32 -> 2692946.4
A23: Total assets | B23: =SUM(B14:B21)+B13 -> 1044217 | C23: =SUM(C14:C21)+C13 -> 1213410 | D23: =SUM(D16:D21)+D13 -> 1765118 | E23: =SUM(E16:E21)+E13 -> 2167705 | F23: =SUM(F16:F21)+F13 -> 2332250 | G23: =SUM(G16:G21)+G13 -> 2556203 | H23: =SUM(H16:H21)+H13 -> 3135579 | I23: =SUM(I16:I21)+I13 -> 3570252 | J23: =Proforma!C33 -> 4476333.5 | K23: =Proforma!D33 -> 5257670.1 | L23: =Proforma!E33 -> 6183930.2 | M23: =Proforma!F33 -> 7281994.4 | N23: =Proforma!G33 -> 8583729 | O23: =Proforma!H33 -> 10126911 | P23: =Proforma!I33 -> 11956325 | Q23: =Proforma!J33 -> 14125061 | ... S23: =Proforma!L33 -> 19743926
A24: LIABILITIES AND STOCKHOLDERS' EQUITY
A25: Short-term borrowings | B25: 578 | C25: 603 | D25: 638 | E25: 0 | F25: 0 | G25: 0 | H25: 0 | I25: 0 | J25: 0 | K25: 0 | L25: 0 | M25: 0 | N25: 0 | O25: 0 | P25: 0 | Q25: 0 | R25: 0 | S25: 0
A26: Trade accounts payable | B26: 93939 | C26: 124974 | D26: 147892 | E26: 231632 | F26: 327487 | G26: 265605 | H26: 378503 | I26: 417955 | J26: =Proforma!C35 -> 504182.66 | K26: =Proforma!D35 -> 597699.17 | L26: =Proforma!E35 -> 708561.26 | M26: =Proforma!F35 -> 839986.2 | N26: =Proforma!G35 -> 995788.03 | O26: =Proforma!H35 -> 1180488.2 | P26: =Proforma!I35 -> 1399446.8 | Q26: =Proforma!J35 -> 1659018.2 | ... S26: =Proforma!L35 -> 2331528.1
A27: Accrued payroll | B27: 55695 | C27: 54462 | D27: 42309 | E27: 79152 | F27: 67553 | G27: 63781 | H27: 123653 | I27: 125417 | J27: =Proforma!C36 -> 143389.27 | K27: =Proforma!D36 -> 169985.31 | L27: =Proforma!E36 -> 201514.43 | M27: =Proforma!F36 -> 238891.61 | N27: =Proforma!G36 -> 283201.57 | O27: =Proforma!H36 -> 335730.19 | P27: =Proforma!I36 -> 398001.9 | Q27: =Proforma!J36 -> 471823.86 | ... S27: =Proforma!L36 -> 663085.3
A28: Operating lease liabilities | B28: 0 | C28: 0 | D28: 49091 | E28: 46768 | F28: 50098 | G28: 50765 | H28: 53581 | I28: 54453 | J28: =Proforma!C37 -> 93291.11 | K28: =Proforma!D37 -> 110594.88 | L28: =Proforma!E37 -> 131108.17 | M28: =Proforma!F37 -> 155426.3 | N28: =Proforma!G37 -> 184254.99 | O28: =Proforma!H37 -> 218430.87 | P28: =Proforma!I37 -> 258945.73 | Q28: =Proforma!J37 -> 306975.35 | ... S28: =Proforma!L37 -> 431412.78
A29: Other accrued expenses | B29: 24446 | C29: 47963 | D29: 46281 | E29: 68995 | F29: 81400 | G29: 86753 | H29: 106785 | I29: 142120 | J29: =Proforma!C38 -> 150729.21 | K29: =Proforma!D38 -> 178686.68 | L29: =Proforma!E38 -> 211829.74 | M29: =Proforma!F38 -> 251120.22 | N29: =Proforma!G38 -> 297698.35 | O29: =Proforma!H38 -> 352915.86 | P29: =Proforma!I38 -> 418375.2 | Q29: =Proforma!J38 -> 495976.02 | ... S29: =Proforma!L38 -> 697027.93
A30: Income tax payable | B30: 11006 | C30: 19283 | D30: 11104 | E30: 36920 | F30: 12426 | G30: 17322 | H30: 52338 | I30: 23299 | J30: 0 | K30: 0 | L30: 0 | M30: 0 | N30: 0 | O30: 0 | P30: 0 | Q30: 0 | R30: 0 | S30: 0
A31: Value added tax payable | B31: 3502 | C31: 3239 | D31: 3631 | E31: 4901 | F31: 2720 | G31: 13154 | H31: 5133 | I31: 6697 | J31: 0 | K31: 0 | L31: 0 | M31: 0 | N31: 0 | O31: 0 | P31: 0 | Q31: 0 | R31: 0 | S31: 0
A32: Total current liabilities | B32: =SUM(B25:B31) -> 189166 | C32: =SUM(C25:C31) -> 250524 | D32: =SUM(D25:D31) -> 300946 | E32: =SUM(E25:E31) -> 468368 | F32: =SUM(F25:F31) -> 541684 | G32: =SUM(G25:G31) -> 497380 | H32: =SUM(H25:H31) -> 719993 | I32: =SUM(I25:I31) -> 769941 | J32: =Proforma!C41 -> 891592.25 | K32: =Proforma!D41 -> 1056966 | L32: =Proforma!E41 -> 1253013.6 | M32: =Proforma!F41 -> 1485424.3 | N32: =Proforma!G41 -> 1760942.9 | O32: =Proforma!H41 -> 2087565.1 | P32: =Proforma!I41 -> 2474769.7 | Q32: =Proforma!J41 -> 2933793.4 | ... S32: =Proforma!L41 -> 4123054.1
A33: Long-term operating lease liabilities | B33: 0 | C33: 0 | D33: 215724 | E33: 176274 | F33: 171972 | G33: 195723 | H33: 213298 | I33: 222522 | J33: =Proforma!C42 -> 204296 | K33: =Proforma!D42 -> 204296 | L33: =Proforma!E42 -> 204296 | M33: =Proforma!F42 -> 204296 | N33: =Proforma!G42 -> 204296 | O33: =Proforma!H42 -> 204296 | P33: =Proforma!I42 -> 204296 | Q33: =Proforma!J42 -> 204296 | ... S33: =Proforma!L42 -> 204296
A34: Mortgage Payable | B34: 31504 | C34: 30901 | D34: 30263 | E34: 0 | F34: 0 | G34: 0 | H34: 0 | I34: 0 | J34: 0 | K34: 0 | L34: 0 | M34: 0 | N34: 0 | O34: 0 | P34: 0 | Q34: 0 | R34: 0 | S34: 0
A35: Income tax liability | B35: 64735 | C35: 60616 | D35: 63547 | E35: 60094 | F35: 54259 | G35: 62032 | H35: 52470 | I35: 13587 | J35: Assumption: Non-operating; timing difference.
A36: Deferred rent obligations | B36: 22499 | C36: 21107 | D36: 0 | E36: 0 | F36: 0 | G36: 0 | H36: 0 | I36: 0 | J36: Assumption: Obsolete under ASC 842 unless separate.
A37: Other long-term liabilities | B37: 15696 | C37: 18928 | D37: 14518 | E37: 18744 | F37: 25510 | G37: 35335 | H37: 42350 | I37: 51189 | J37: =Proforma!C45 -> 51785.507 | K37: =Proforma!D45 -> 61390.756 | L37: =Proforma!E45 -> 72777.6 | M37: =Proforma!F45 -> 86276.492 | N37: =Proforma!G45 -> 102279.18 | O37: =Proforma!H45 -> 121250.06 | P37: =Proforma!I45 -> 143739.7 | Q37: =Proforma!J45 -> 170400.74 | ... S37: =Proforma!L45 -> 239475.44
A38: Total liabilities | B38: =SUM(B33:B37) +B32 -> 323600 | C38: =SUM(C33:C37) +C32 -> 382076 | D38: =SUM(D33:D37) +D32 -> 624998 | E38: =SUM(E33:E37) +E32 -> 723480 | F38: =SUM(F33:F37) +F32 -> 793425 | G38: =SUM(G33:G37) +G32 -> 790470 | H38: =SUM(H33:H37) +H32 -> 1028111 | I38: =SUM(I33:I37)+I32 -> 1057239 | J38: =Proforma!C46 -> 256081.51 | K38: =Proforma!D46 -> 265686.76 | L38: =Proforma!E46 -> 277073.6 | M38: =Proforma!F46 -> 290572.49 | N38: =Proforma!G46 -> 306575.18 | O38: =Proforma!H46 -> 325546.06 | P38: =Proforma!I46 -> 348035.7 | Q38: =Proforma!J46 -> 374696.74 | ... S38: =Proforma!L46 -> 443771.44
A39: Common stock ($0.01 par value; 125,000 shares authorized) | B39: 304 | C39: 291 | D39: 280 | E39: 279 | F39: 270 | G39: 262 | H39: 1536 | I39: 1502 | J39: =Proforma!C47 -> 32455.309 | K39: =Proforma!D47 -> -391877.23 | L39: =Proforma!E47 -> -894915.57 | M39: =Proforma!F47 -> -894915.57 | N39: =Proforma!G47 -> -894915.57 | O39: =Proforma!H47 -> -894915.57 | P39: =Proforma!I47 -> -894915.57 | Q39: =Proforma!J47 -> -894915.57 | ... S39: =Proforma!L47 -> -894915.57
A40: Additional paid-in capital | B40: 167587 | C40: 178227 | D40: 191451 | E40: 203310 | F40: 210825 | G40: 232932 | H40: 243050 | I40: 253466 | J40: =Proforma!C48 -> 253466 | K40: =Proforma!D48 -> 253466 | L40: =Proforma!E48 -> 253466 | M40: =Proforma!F48 -> 253466 | N40: =Proforma!G48 -> 253466 | O40: =Proforma!H48 -> 253466 | P40: =Proforma!I48 -> 253466 | Q40: =Proforma!J48 -> 253466 | ... S40: =Proforma!L48 -> 253466
A41: Retained earnings | B41: 785871 | C41: 889266 | D41: 973948 | E41: 1257379 | F41: 1352685 | G41: 1571574 | H41: 1913615 | I41: 2307699 | J41: 3203979.8 | K41: 4266504 | L41: 5526106.7 | M41: 7019342.3 | N41: 8789545.3 | O41: 10888088 | P41: 13375872 | Q41: 16325093 | R41: 19821339 | S41: 23966075
A42: Accumulated other comprehensive loss (Note 10) | B42: -12983 | C42: -22654 | D42: -25559 | E42: -16743 | F42: -24955 | G42: -39035 | H42: -50733 | I42: -49654 | J42: Assumption: Relates to unrealized gains/losses; non-cash, non-operating.
A43: Total stockholders' equity | B43: =SUM(B39:B42) -> 940779 | C43: =SUM(C39:C42) -> 1045130 | D43: =SUM(D39:D42) -> 1140120 | E43: =SUM(E39:E42) -> 1444225 | F43: =SUM(F39:F42) -> 1538825 | G43: =SUM(G39:G42) -> 1765733 | H43: =SUM(H39:H42) -> 2107468 | I43: =SUM(I39:I42) -> 2513013 | J43: =Proforma!C51 -> 3489901.1 | K43: =Proforma!D51 -> 4128092.8 | L43: =Proforma!E51 -> 4884657.1 | M43: =Proforma!F51 -> 6377892.7 | N43: =Proforma!G51 -> 8148095.7 | O43: =Proforma!H51 -> 10246639 | P43: =Proforma!I51 -> 12734422 | Q43: =Proforma!J51 -> 15683643 | ... S43: =Proforma!L51 -> 23324625
A44: Total liabilities and stockholders' equity | B44: =B43+B38 -> 1264379 | C44: =C43+C38 -> 1427206 | D44: =D43+D38 -> 1765118 | E44: =E43+E38 -> 2167705 | F44: =F43+F38 -> 2332250 | G44: =G43+G38 -> 2556203 | H44: =H43+H38 -> 3135579 | I44: =I43+I38 -> 3570252 | J44: =Proforma!C52 -> 4637574.8 | K44: =Proforma!D52 -> 5450745.6 | L44: =Proforma!E52 -> 6414744.3 | M44: =Proforma!F52 -> 8153889.5 | N44: =Proforma!G52 -> 10215614 | O44: =Proforma!H52 -> 12659750 | P44: =Proforma!I52 -> 15557227 | Q44: =Proforma!J52 -> 18992133 | ... S44: =Proforma!L52 -> 27891451
A46: NWC | D46: =D13-D32 -> 893165 | E46: =E13-E32 -> 1182431 | F46: =F13-F32 -> 1210444 | G46: =G13-G32 -> 1412873 | H46: =H13-H32 -> 1723490 | I46: =I13-I32 -> 2090534 | J46: =J13-J32 -> 2795606.8 | K46: =K13-K32 -> 3314139.9 | ... S46: =S13-S32 -> 12927925
A48: Balance Sheet Drivers | B48: Historical | D48: Historical | J48: Projection | K48: Commentary:
A49: Year | B49: 2017 | C49: 2018 | D49: 2020 | E49: 2021 | F49: 2022 | G49: 2023 | H49: 2024 | I49: 2025
A50: Assets
A51: Days Sales Outstanding | B51: =(B9/'[1]Income Statement'!B9)*365.25 -> #DIV/0! | C51: =(C9/'[1]Income Statement'!C9)*365.25 -> #VALUE! | D51: =(D8/'Balance Sheet'!D7)*365 -> 104.3098 | E51: =(E8/'Balance Sheet'!E7)*365 -> 72.278216 | F51: =(F8/'Balance Sheet'!F7)*365 -> 130.9752 | G51: =(G8/'Balance Sheet'!G7)*365 -> 112.09215 | H51: =(H8/'Balance Sheet'!H7)*365 -> 72.065612 | I51: =(I8/'Balance Sheet'!I7)*365 -> 64.312435 | J51: 60 | K51: For ease of projection we are estimating that days of sales outstanding will be 60 going forward as it has been declining over the past several years
A52: Days Inventory Held | B52: =(B10/'[1]Income Statement'!B13)*365.25 -> #DIV/0! | C52: =(C10/'[1]Income Statement'!C13)*365.25 -> #VALUE! | D52: =(D9/'Income Statement'!D7)*365 -> 110.53404 | E52: =(E9/'Income Statement'!E7)*365 -> 86.687076 | F52: =(F9/'Income Statement'!F7)*365 -> 119.90017 | G52: =(G9/'Income Statement'!G7)*365 -> 107.93565 | H52: =(H9/'Income Statement'!H7)*365 -> 91.008669 | I52: =(I9/'Income Statement'!I7)*365 -> 86.077086 | J52: 80 | K52: For ease of projection we are estimating that days of inventory will be 80 as it has been declining over the past several years
A53: Prepaid & Other (% of COGS) | B53: =B11/'[1]Income Statement'!B13 -> #DIV/0! | C53: =C11/'[1]Income Statement'!C13 -> #VALUE! | D53: =(D10+D11)/'Income Statement'!D7 -> 0.0381996 | E53: =(E10+E11)/'Income Statement'!E7 -> 0.052211129 | F53: =(F10+F11)/'Income Statement'!F7 -> 0.052420683 | G53: =(G10+G11)/'Income Statement'!G7 -> 0.049564464 | H53: =(H10+H11)/'Income Statement'!H7 -> 0.066760589 | I53: =(I10+I11)/'Income Statement'!I7 -> 0.050751709 | J53: =AVERAGE(D53:I53) -> 0.051651362 | K53: Averaging 5.17%, this remains consistent with long-term historical norms, indicating no major operational shifts.
A54: Operating Lease Right-of-Use Assets | D54: =D17 -> 243522 | E54: =E17 -> 186991 | F54: =F17 -> 182459 | G54: =G17 -> 213302 | H54: =H17 -> 225669 | I54: =I17 -> 237352 | J54: =AVERAGE(D54:I54) -> 214882.5 | K54: Averaged 214,882.5 reflects gradual amortization of lease assets over time without significant new lease additions.
A55: Goodwill | B55: =B18 -> 13990 | C55: =C18 -> 13990 | D55: =D18 -> 13990 | E55: =E18 -> 13990 | F55: =F18 -> 13990 | G55: =G18 -> 13990 | H55: =H18 -> 13990 | I55: =I18 -> 13990 | J55: =AVERAGE(D55:I55) -> 13990 | K55: Constant at $13,990, reflecting an assumption of no new acquisitions or goodwill impairment.
A56: Other Non-Current Assets (% of Sales) | B56: =B20/'[1]Income Statement'!B9 -> #DIV/0! | C56: =C20/'[1]Income Statement'!C9 -> #VALUE! | D56: =D21/'Income Statement'!D6 -> 0.013226964 | E56: =E21/'Income Statement'!E6 -> 0.01201112 | F56: =F21/'Income Statement'!F6 -> 0.01819455 | G56: =G21/'Income Statement'!G6 -> 0.011559607 | H56: =H21/'Income Statement'!H6 -> 0.01181222 | I56: =I21/'Income Statement'!I6 -> 0.0079320252 | J56: =AVERAGE(D56:I56) -> 0.012456081 | K56: Average of 1.25% is aligned with the historical range, suggesting no expected structural change in other long-term asset composition.
A57: Depreciation(% of PPE Gross) | D57: =D15/D14 -> 0.5302286 | E57: =E15/E14 -> 0.56414402 | F57: =F15/F14 -> 0.55952438 | G57: =G15/G14 -> 0.54350405 | H57: =H15/H14 -> 0.53609618 | I57: =I15/I14 -> 0.55309424 | J57: =AVERAGE(D57:I57) -> 0.54776524 | K57: Steady at 54.78%, indicating a stable depreciation schedule and asset replacement cycle.
A58: PPE Gross (% of Sales) | D58: =D14/'Income Statement'!D6 -> 0.20864552 | E58: =E14/'Income Statement'!E6 -> 0.18585299 | F58: =F14/'Income Statement'!F6 -> 0.16030656 | G58: =G14/'Income Statement'!G6 -> 0.16105347 | H58: =H14/'Income Statement'!H6 -> 0.15188806 | I58: =I14/'Income Statement'!I6 -> 0.14613311 | J58: =AVERAGE(D58:I58) -> 0.16897995 | K58: Averaging 16.90%, suggesting consistent capital investment relative to revenue.
A59: Other intangible assets, net of accumulated amortization | D59: =D19 -> 48016 | E59: =E19 -> 41945 | F59: =F19 -> 39688 | G59: =G19 -> 37457 | H59: =H19 -> 27083 | I59: =I19 -> 15699 | J59: =AVERAGE(D59:I59) -> 34981.333
A60: Liabilities
A61: Current Portion of LT Debt | B61: =B26 -> 93939 | C61: =C26 -> 124974 | D61: =D33+D34 -> 245987 | E61: =E33+E34 -> 176274 | F61: =F33+F34 -> 171972 | G61: =G33+G34 -> 195723 | H61: =H33+H34 -> 213298 | I61: =I33+I34 -> 222522 | J61: =AVERAGE(D61:I61) -> 204296 | K61: Average of 204,296.0 reflects consistent annual amortization without significant refinancing or new debt issuance.
A62: Current Portion of Lease Liabilities (% of LT Lease Liabilities) | D62: =(D28/D33) -> 0.22756392 | E62: =(E28/E33) -> 0.26531423 | F62: =(F28/F33) -> 0.29131487 | G62: =(G28/G33) -> 0.25937166 | H62: =(H28/H33) -> 0.25120254 | I62: =(I28/I33) -> 0.24470839 | J62: =AVERAGE(D62:I62) -> 0.25657927 | K62: Stable at 25.66%, providing predictability for short-term lease obligations.
A63: Days Payable | B63: =(B28/'[1]Income Statement'!B13)*365.25 -> #DIV/0! | C63: =(C28/'[1]Income Statement'!C13)*365.25 -> #VALUE! | D63: =(D26/'Income Statement'!D7)*365 -> 52.458446 | E63: =(E26/'Income Statement'!E7)*365 -> 72.165599 | F63: =(F26/'Income Statement'!F7)*365 -> 77.478406 | G63: =(G26/'Income Statement'!G7)*365 -> 53.801523 | H63: =(H26/'Income Statement'!H7)*365 -> 72.625459 | I63: =(I26/'Income Statement'!I7)*365 -> 72.646324 | J63: =AVERAGE(D63:I63) -> 66.862626 | K63: Averaging 66.9 days, slightly below 2025 levels, indicating moderately faster payments to suppliers.
A64: Accrued Payroll (% of COGS) | D64: =D27/'Income Statement'!D7 -> 0.041115979 | E64: =E27/'Income Statement'!E7 -> 0.067561719 | F64: =F27/'Income Statement'!F7 -> 0.043786314 | G64: =G27/'Income Statement'!G7 -> 0.035396212 | H64: =H27/'Income Statement'!H7 -> 0.065002694 | I64: =I27/'Income Statement'!I7 -> 0.059723831 | J64: =AVERAGE(D64:I64) -> 0.052097792 | K64: Average of 5.21% falls in the middle of historical values, reflecting steady payroll accrual practices.
A65: Other Accrued Expenses (% of COGS) | B65: =B29/'[1]Income Statement'!B13 -> #DIV/0! | C65: =C29/'[1]Income Statement'!C13 -> #VALUE! | D65: =D29/'Income Statement'!D7 -> 0.044975977 | E65: =E29/'Income Statement'!E7 -> 0.058892016 | F65: =F29/'Income Statement'!F7 -> 0.052761624 | G65: =G29/'Income Statement'!G7 -> 0.048144864 | H65: =H29/'Income Statement'!H7 -> 0.056135417 | I65: =I29/'Income Statement'!I7 -> 0.067677834 | J65: =AVERAGE(D65:I65) -> 0.054764622 | K65: Averaging 5.48%, slightly above recent lows but within normal operating variance.
A66: Operating Lease Liabilities (% of Operating Lease Right of Use Assets) | D66: =D28/D17 -> 0.20158754 | E66: =E28/E17 -> 0.25010829 | F66: =F28/F17 -> 0.27457127 | G66: =G28/G17 -> 0.23799589 | H66: =H28/H17 -> 0.23743181 | I66: =I28/I17 -> 0.22941875 | J66: =AVERAGE(D66:I66) -> 0.23851893 | K66: At 23.85%, consistent with historical patterns, indicating a stable lease liability profile.
A67: Operating Lease Liabilities (% of Sales) | D67: =D28/'Income Statement'!D6 -> 0.023018359 | E67: =E28/'Income Statement'!E6 -> 0.018371797 | F67: =F28/'Income Statement'!F6 -> 0.015902416 | G67: =G28/'Income Statement'!G6 -> 0.013995312 | H67: =H28/'Income Statement'!H6 -> 0.01249626 | I67: =I28/'Income Statement'!I6 -> 0.010922029 | J67: =AVERAGE(D67:I67) -> 0.015784362 | K67: Averaging 1.58%, reflecting minimal leverage from operating leases relative to revenue.
A68: Deferred Income Tax Liabilities (% of Goodwill) | B68: =B34/B18 -> 2.2518942 | C68: =C34/C18 -> 2.208792 | D68: =D35/D18 -> 4.5423159 | E68: =E35/E18 -> 4.2954968 | F68: =F35/F18 -> 3.8784132 | G68: =G35/G18 -> 4.4340243 | H68: =H35/H18 -> 3.7505361 | I68: =I35/I18 -> 0.97119371 | J68: =AVERAGE(D68:I68) -> 3.64533 | K68: Average of 364.53% is significantly lower than historical highs, consistent with the assumption of no new acquisitions.
A69: Other Long Term Liabilities (% of COGS) | B69: =B35/'[1]Income Statement'!B13 -> #DIV/0! | C69: =C35/'[1]Income Statement'!C13 -> #VALUE! | D69: =D37/'Income Statement'!D7 -> 0.014108624 | E69: =E37/'Income Statement'!E7 -> 0.015999303 | F69: =F37/'Income Statement'!F7 -> 0.016535 | G69: =G37/'Income Statement'!G7 -> 0.019609682 | H69: =H37/'Income Statement'!H7 -> 0.022262817 | I69: =I37/'Income Statement'!I7 -> 0.024376306 | J69: =AVERAGE(D69:I69) -> 0.018815289 | K69: Average of 1.88% suggests stable long-term obligations with no significant changes expected.
A70: Accumulated, Comprehensive & Other Income | B70: =B42 -> -12983 | C70: =C42 -> -22654 | D70: =D42 -> -25559 | E70: =E42 -> -16743 | F70: =F42 -> -24955 | G70: =G42 -> -39035 | H70: =H42 -> -50733 | I70: =I42 -> -49654 | J70: =AVERAGE(D70:I70) -> -34446.5

Sheet Income Statement
D1: DECKERS OUTDOOR CORPORATION AND SUBSIDIARIES
D2: CONSOLIDATED STATEMENTS OF COMPREHENSIVE INCOME
D3: (dollar and share data amounts in thousands, except per share data)
B4: Historical | D4: Historical | J4: Projected
A5: Year | B5: 2018 | C5: 2019 | D5: 2020 | E5: 2021 | F5: 2022 | G5: 2023 | H5: 2024 | I5: 2025 | J5: 2026 | K5: 2027 | L5: 2028 | M5: 2029 | N5: 2030 | O5: 2031 | P5: 2032 | Q5: 2033 | R5: 2034 | S5: 2035
A6: Net sales | B6: 1903339 | C6: 2020437 | D6: 2132689 | E6: 2545641 | F6: 3150339 | G6: 3627286 | H6: 4287763 | I6: 4985612 | J6: =Proforma!C3 -> 5910350.4 | K6: =Proforma!D3 -> 7006610.5 | L6: =Proforma!E3 -> 8306206.5 | M6: =Proforma!F3 -> 9846853.5 | N6: =Proforma!G3 -> 11673262 | O6: =Proforma!H3 -> 13838435 | P6: =Proforma!I3 -> 16405207 | Q6: =Proforma!J3 -> 19448068 | ... S6: =Proforma!L3 -> 27331658
A7: Cost of Sales | B7: 971697 | C7: 980187 | D7: 1029016 | E7: 1171551 | F7: 1542788 | G7: 1801916 | H7: 1902275 | I7: 2099949 | J7: =Proforma!C4 -> 2752309.9 | K7: =Proforma!D4 -> 3262812.3 | L7: =Proforma!E4 -> 3868003.3 | M7: =Proforma!F4 -> 4585446 | N7: =Proforma!G4 -> 5435961.1 | O7: =Proforma!H4 -> 6444230.8 | P7: =Proforma!I4 -> 7639515.8 | Q7: =Proforma!J4 -> 9056504.1 | ... S7: =Proforma!L4 -> 12727705
A8: Gross Profit | B8: =B6-B7 -> 931642 | C8: =C6-C7 -> 1040250 | D8: =D6-D7 -> 1103673 | E8: =E6-E7 -> 1374090 | F8: =F6-F7 -> 1607551 | G8: =G6-G7 -> 1825370 | H8: =H6-H7 -> 2385488 | I8: =I6-I7 -> 2885663 | J8: =Proforma!C5 -> 3158040.4 | K8: =Proforma!D5 -> 3743798.2 | L8: =Proforma!E5 -> 4438203.2 | M8: =Proforma!F5 -> 5261407.4 | N8: =Proforma!G5 -> 6237300.7 | O8: =Proforma!H5 -> 7394204.1 | P8: =Proforma!I5 -> 8765691.5 | Q8: =Proforma!J5 -> 10391564 | ... S8: =Proforma!L5 -> 14603953
A9: Selling, general, and administrative expenses | B9: 709058 | C9: 712930 | D9: 765538 | E9: 869885 | F9: 1042844 | G9: 1172619 | H9: 1457974 | I9: 1706571 | J9: =Proforma!C6 -> 2006863.1 | K9: =Proforma!D6 -> 2379098.9 | L9: =Proforma!E6 -> 2820377.5 | M9: =Proforma!F6 -> 3343505.1 | N9: =Proforma!G6 -> 3963663.1 | O9: =Proforma!H6 -> 4698849 | P9: =Proforma!I6 -> 5570398.1 | Q9: =Proforma!J6 -> 6603603.4 | ... S9: =Proforma!L6 -> 9280481
A10: EBIT, Income from operations | B10: =B8-B9 -> 222584 | C10: =C8-C9 -> 327320 | D10: =D8-D9 -> 338135 | E10: =E8-E9 -> 504205 | F10: =F8-F9 -> 564707 | G10: =G8-G9 -> 652751 | H10: =H8-H9 -> 927514 | I10: =I8-I9 -> 1179092 | J10: =Proforma!B7 -> 1179092 | K10: =Proforma!C7 -> 1151177.4 | L10: =Proforma!D7 -> 1364699.4 | M10: =Proforma!E7 -> 1617825.7 | N10: =Proforma!F7 -> 1917902.3 | O10: =Proforma!G7 -> 2273637.6 | P10: =Proforma!H7 -> 2695355.1 | Q10: =Proforma!I7 -> 3195293.4 | ... S10: =Proforma!K7 -> 4490557.2
A11: Interest income | B11: -3057 | C11: -6028 | D11: -7261 | E11: -2637 | F11: -1901 | G11: -15563 | H11: -52208 | I11: -68389 | J11: Assumption: Other income, net is excluded from the pro forma projections because it consists primarily of non-operating and non-recurring items (e.g., foreign currency gains/losses, asset sale gains/losses). These items are not reflective of the company’s ongoing operations and are immaterial relative to total EBIT.
A12: Interest expense | B12: 4585 | C12: 4661 | D12: 5046 | E12: 6028 | F12: 2083 | G12: 3442 | H12: 2564 | I12: 3517 | J12: =Proforma!B9 -> 3517 | K12: =Proforma!C9 -> 7533.2585 | L12: =Proforma!D9 -> 8930.5379 | M12: =Proforma!E9 -> 10586.987 | N12: =Proforma!F9 -> 12550.676 | O12: =Proforma!G9 -> 14878.593 | P12: =Proforma!H9 -> 17638.296 | Q12: =Proforma!I9 -> 20909.872 | ... S12: =Proforma!K9 -> 29386.026
A13: Other income, net | B13: 360 | C13: -247 | D13: -516 | E13: -700 | F13: -113 | G13: -1210 | H13: -1783 | I13: 665 | J13: Assumption: Other income excluded due to immateriality and non-recurring nature.
A14: Total other (income) expense, net | B14: 1888 | C14: =SUM(C11:C13) -> -1614 | D14: =SUM(D11:D13) -> -2731 | E14: =SUM(E11:E13) -> 2691 | F14: =SUM(F11:F13) -> 69 | G14: =SUM(G11:G13) -> -13331 | H14: =SUM(H11:H13) -> -51427 | I14: =SUM(I11:I13) -> -64207
A15: EBT, Income before income taxes | B15: =B10-B14 -> 220696 | C15: =C10-C14 -> 328934 | D15: =D10-D14 -> 340866 | E15: =E10-E14 -> 501514 | F15: =F10-F14 -> 564638 | G15: =G10-G14 -> 666082 | H15: =H10-H14 -> 978941 | I15: =I10-I14 -> 1243299 | J15: =Proforma!C11 -> 1143644.1 | K15: =Proforma!D11 -> 1355768.8 | L15: =Proforma!E11 -> 1607238.7 | M15: =Proforma!F11 -> 1905351.7 | N15: =Proforma!G11 -> 2258759 | O15: =Proforma!H11 -> 2677716.8 | P15: =Proforma!I11 -> 3174383.5 | Q15: =Proforma!J11 -> 3763172.6 | ... S15: =Proforma!L11 -> 5288635.6
A16: Income tax expense | B16: 106302 | C16: 64626 | D16: 64724 | E16: 118939 | F16: 112689 | G16: 149260 | H16: 219378 | I16: 277208 | J16: =Proforma!C12 -> 247363.32 | K16: =Proforma!D12 -> 293244.62 | L16: =Proforma!E12 -> 347636.05 | M16: =Proforma!F12 -> 412116.07 | N16: =Proforma!G12 -> 488555.95 | O16: =Proforma!H12 -> 579174 | P16: =Proforma!I12 -> 686600.01 | Q16: =Proforma!J12 -> 813951.55 | ... S16: =Proforma!L12 -> 1143900
A17: Net Income | B17: =B15-B16 -> 114394 | C17: =C15-C16 -> 264308 | D17: =D15-D16 -> 276142 | E17: =E15-E16 -> 382575 | F17: =F15-F16 -> 451949 | G17: =G15-G16 -> 516822 | H17: 759563 | I17: 966091 | J17: =Proforma!C13 -> 896280.78 | K17: =Proforma!D13 -> 1062524.2 | L17: =Proforma!E13 -> 1259602.7 | M17: =Proforma!F13 -> 1493235.6 | N17: =Proforma!G13 -> 1770203 | O17: =Proforma!H13 -> 2098542.8 | P17: =Proforma!I13 -> 2487783.5 | Q17: =Proforma!J13 -> 2949221.1 | ... S17: =Proforma!L13 -> 4144735.6
A18: Other comprehensive (loss) income, net of tax
A19: Unrealized loss on cash flow hedges | B19: -613 | C19: -243 | D19: 0 | E19: 0 | F19: 0 | G19: 0 | H19: 0 | I19: 1584
A20: Foreign currency translation (loss) gain | B20: 14081 | C20: -9428 | D20: -2905 | E20: 8816 | F20: -8212 | G20: -14080 | H20: -11698 | I20: -505
A21: Total other comprehensive (loss) income, net of tax | B21: =B20+B19 -> 13468 | C21: =C20+C19 -> -9671 | D21: =D20+D19 -> -2905 | E21: =E20+E19 -> 8816 | F21: =F20+F19 -> -8212 | G21: =G20+G19 -> -14080 | H21: =H20+H19 -> -11698 | I21: =I20+I19 -> 1079
A22: Comprehensive income | B22: =B17+B21 -> 127862 | C22: =C17+C21 -> 254637 | D22: =D17+D21 -> 273237 | E22: =E17+E21 -> 391391 | F22: =F17+F21 -> 443737 | G22: =G17+G21 -> 502742 | H22: =H17+H21 -> 747865 | I22: =I17+I21 -> 967170
A23: Net income per share
A24: Basic | B24: 3.6 | C24: 8.92 | D24: 9.73 | E24: 13.64 | F24: 16.43 | G24: 19.5 | H24: 4.89 | I24: 6.36
A25: Diluted | B25: 3.58 | C25: 8.84 | D25: 9.62 | E25: 13.47 | F25: 16.26 | G25: 19.37 | H25: 4.86 | I25: 6.33
A26: Weighted-average common shares outstanding
A27: Basic | B27: 31758 | C27: 29641 | D27: 28385 | E27: 28055 | F27: 27508 | G27: 26504 | H27: 155225 | I27: 151992
A28: Diluted | B28: 31996 | C28: 29903 | D28: 28694 | E28: 28406 | F28: 27789 | G28: 26686 | H28: 156285 | I28: 152670
A31: Income Statement Drivers | D31: Historical | J31: Historical Average | K31: Projected | P31: Commentary
A32: Year | D32: 2020 | E32: 2021 | F32: 2022 | G32: 2023 | H32: 2024 | I32: 2025 | K32: =N5+1 -> 2031 | L32: =O5+1 -> 2032 | M32: =P5+1 -> 2033 | N32: =Q5+1 -> 2034 | O32: =R5+1 -> 2035
A33: Sales Growth | E33: =E6/D6-1 -> 0.19362973 | F33: =F6/E6-1 -> 0.23754253 | G33: =G6/F6-1 -> 0.15139545 | H33: =H6/G6-1 -> 0.18208572 | I33: =I6/H6-1 -> 0.16275363 | J33: =AVERAGE(D33:I33) -> 0.18548141 | K33: =10% -> 0.1 | L33: 0.08 | M33: 0.07 | N33: 0.05 | O33: 0.05 | P33: We are making the assumption that growth rate will stablize to 5% at the end of of our projection for ease of TV calculations
A34: COGS Growth | E34: =E7/D7-1 -> 0.13851582 | F34: =F7/E7-1 -> 0.31687652 | G34: =G7/F7-1 -> 0.16796086 | H34: =H7/G7-1 -> 0.055695715 | I34: =I7/H7-1 -> 0.10391452 | J34: =AVERAGE(D34:I34) -> 0.15659269
A35: SGA Growth | E35: =E9/D9-1 -> 0.13630545 | F35: =F9/E9-1 -> 0.19882973 | G35: =G9/F9-1 -> 0.12444335 | H35: =H9/G9-1 -> 0.24334844 | I35: =I9/H9-1 -> 0.17050853 | J35: =AVERAGE(D35:I35) -> 0.1746871
A36: COGS (% of Sales) | D36: =D7/D6 -> 0.48249698 | E36: =E7/E6 -> 0.46021847 | F36: =F7/F6 -> 0.48972126 | G36: =G7/G6 -> 0.496767 | H36: =H7/H6 -> 0.44365209 | I36: =I7/I6 -> 0.42120185 | J36: =AVERAGE(D36:I36) -> 0.46567628
A37: SG&A (% of Sales) | D37: =D9/D6 -> 0.35895435 | E37: =E9/E6 -> 0.34171551 | F37: =F9/F6 -> 0.33102596 | G37: =G9/G6 -> 0.32327724 | H37: =H9/H6 -> 0.34003139 | I37: =I9/I6 -> 0.3422992 | J37: =AVERAGE(D37:I37) -> 0.33955061
A38: Tax Rate | D38: =D16/D15 -> 0.18988107 | E38: =E16/E15 -> 0.23715988 | F38: =F16/F15 -> 0.19957743 | G38: =G16/G15 -> 0.22408652 | H38: =H16/H15 -> 0.22409726 | I38: =I16/I15 -> 0.22296165 | J38: =AVERAGE(D38:I38) -> 0.21629397
A39: Net Income (% of Sales) | D39: =D17/D6 -> 0.12948067 | E39: =E17/E6 -> 0.15028631 | F39: =F17/F6 -> 0.14346043 | G39: =G17/G6 -> 0.14248173 | H39: =H17/H6 -> 0.17714668 | I39: =I17/I6 -> 0.19377581 | J39: =AVERAGE(D39:I39) -> 0.15610527
A40: Interest Expense (% of Sales) | D40: =D12/D6 -> 0.0023660271 | E40: =E12/E6 -> 0.0023679694 | F40: =F12/F6 -> 0.00066119868 | G40: =G12/G6 -> 0.00094891883 | H40: =H12/H6 -> 0.00059798081 | I40: =I12/I6 -> 0.00070542995 | J40: =AVERAGE(D40:I40) -> 0.0012745875
A41: Operating Income (% of Sales) | D41: =D10/D6 -> 0.15854867 | E41: =E10/E6 -> 0.19806603 | F41: =F10/F6 -> 0.17925277 | G41: =G10/G6 -> 0.17995576 | H41: =H10/H6 -> 0.21631653 | I41: =I10/I6 -> 0.23649895 | J41: =AVERAGE(D41:I41) -> 0.19477312
A42: Gross Profit (% of Sales) | D42: =D8/D6 -> 0.51750302 | E42: =E8/E6 -> 0.53978153 | F42: =F8/F6 -> 0.51027874 | G42: =G8/G6 -> 0.503233 | H42: =H8/H6 -> 0.55634791 | I42: =I8/I6 -> 0.57879815 | J42: =AVERAGE(D42:I42) -> 0.53432372
A43: Cash (% of sales) | D43: ='Balance Sheet'!D7/'Income Statement'!D6 -> 0.3045151 | E43: ='Balance Sheet'!E7/'Income Statement'!E6 -> 0.4279319 | F43: ='Balance Sheet'!F7/'Income Statement'!F6 -> 0.26775753 | G43: ='Balance Sheet'!G7/'Income Statement'!G6 -> 0.27066931 | H43: ='Balance Sheet'!H7/'Income Statement'!H6 -> 0.35031111 | I43: ='Balance Sheet'!I7/'Income Statement'!I6 -> 0.378928 | J43: =AVERAGE(D43:I43) -> 0.33335216

Sheet Cash Flows
A1: DECKERS OUTDOOR CORPORATION AND SUBSIDIARIES
A2: CONSOLIDATED STATEMENTS OF CASH FLOWS
A3: (dollar and share data amounts in thousands)
B4: Historical
A5: Year | B5: 2018 | C5: 2019 | D5: 2020 | E5: 2021 | F5: 2022 | G5: 2023 | H5: 2024 | I5: 2025
A6: OPERATING ACTIVITIES
A7: Net income | C7: 264308 | D7: 276142 | E7: 382575 | F7: 451949 | G7: 516822 | H7: 759563 | I7: 966091
A8: Reconciliation of net income to net cash provided by (used in) operating activities:
A9: Depreciation, amortization, and accretion | C9: 44941 | D9: 38912 | E9: 40530 | F9: 42878 | G9: 47858 | H9: 57587 | I9: 69353
A10: Amortization on cloud computing arrangements | D10: - | E10: 737 | F10: 1552 | G10: 2149 | H10: 2075 | I10: 2380
A11: Loss on extinguishment of debt | G11: 226
A12: Bad debt expense (benefit) | D12: 3498 | E12: 3053 | F12: -342 | G12: 1983 | H12: 789 | I12: 5032
A13: Deferred tax benefit | D13: 2934 | E13: -8171 | F13: -27796 | G13: -9719 | H13: -1510 | I13: -5545
A14: Stock-based compensation | D14: 14477 | E14: 22701 | F14: 26816 | G14: 26897 | H14: 37288 | I14: 37943
A15: Excess tax benefit from stock based compensation | C15: -546 | D15: -1953 | E15: -586
A16: Loss on disposal of long-lived assets | C16: 277 | D16: 698 | E16: 1019 | F16: 107 | G16: 2691 | H16: 407 | I16: 3183
A17: Impairment of intangible assets | E17: 3522 | H17: 8164
A18: Impairment of operating lease and other long-lived assets | C18: 180 | D18: 1365 | E18: 14084 | F18: 3186 | G18: 2817 | H18: 1015 | I18: 4290
A19: Gain on settlement of asset retirement obligations | D19: -705 | E19: -207
A20: Changes in operating assets and liabilities:
A21: Trade accounts receivable, net | C21: -16157 | D21: -10493 | E21: -33173 | F21: -86627 | G21: -806 | H21: 4157 | I21: 41339
A22: Inventories | C22: 8827 | D22: -32777 | E22: 33378 | F22: -228554 | G22: -26056 | H22: 58541 | I22: -24344
A23: Prepaid expenses and other current assets | C23: -515 | D23: 2477 | E23: -22128 | F23: -19095 | G23: -5609 | H23: -38490 | I23: 20946
A24: Income tax receivable | C24: -165 | D24: -5811 | E24: 1842 | F24: -11933 | G24: 13459 | H24: -38775 | I24: 6945
A25: Net operating lease assets and lease liabilities | D25: -3264 | E25: 250 | F25: 3189 | G25: -8308 | H25: -567 | I25: -2583
A26: Other assets | D26: -6558 | E26: -3103 | F26: -28296 | G26: 13240 | H26: -9989 | I26: 6566
A27: Trade accounts payable | D27: 23312 | E27: 79176 | F27: 89184 | G27: -74247 | H27: 119601 | I27: 35636
A28: Other accrued expenses | D28: -11112 | E28: 53785 | F28: -20370 | G28: 11528 | H28: 43534 | I28: 22222
A29: Income tax payable | D29: -6226 | E29: 25817 | F29: -24494 | G29: 4897 | H29: 35016 | I29: -29039
A30: Other long-term liabilities | D30: 1418 | E30: 530 | F30: 999 | G30: 17600 | H30: -5222 | I30: -33214
A31: Net cash provided by operating activities | D31: 286334 | E31: 596217 | F31: 172353 | G31: 537422 | H31: 1033184 | I31: 1044523
A33: INVESTING ACTIVITIES
A34: Purchases of property and equipment | D34: -32455 | E34: -32218 | F34: -51017 | G34: -81025 | H34: -89365 | I34: -86171
A35: Proceeds from sales of property and equipment | D35: 491 | E35: 49 | F35: 8 | G35: 12 | H35: 34 | I35: 11168
A36: Net cash used in investing activities | D36: -31964 | E36: -32169 | F36: -51009 | G36: -81013 | H36: -89331 | I36: -75003
A38: FINANCING ACTIVITIES
A39: Proceeds from short-term borrowings | D39: 69336 | E39: 9100
A40: Repayments of short-term borrowings | D40: 69197 | E40: -9478
A41: Loan origination costs on revolving credit facilities | G41: -1537
A42: Proceeds from issuance of stock | D42: 1288 | E42: 1502 | F42: 1991 | G42: 2170 | H42: 2444 | I42: 3804
A43: Proceeds from exercise of stock options | D43: 3615 | E43: 6775 | F43: 1204 | G43: 4396 | H43: 4786 | I43: 968
A44: Repurchases of common stock | D44: 190405 | E44: -99147 | F44: -356653 | G44: -297372 | H44: -414931 | I44: -567002
A45: Cash paid for excise taxes related to repurchases of common stock | I45: -3985
A46: Cash paid for shares withheld for taxes | D46: 6148 | E46: -7432 | F46: -14024 | G46: -16688 | H46: -9974 | I46: -15119
A47: Repayments of mortgage principal | D47: 603 | E47: -30901
A48: Net cash used in financing activities | D48: 192114 | E48: -129581 | F48: -367482 | G48: -309031 | H48: 417675 | I48: 581334
A49: Effect of foreign currency exchange rates on cash and cash equivalents | D49: -2512 | E49: 5458 | F49: 304 | G49: -9110 | H49: -5922 | I49: -1049
A50: Net change in cash and cash equivalents | D50: 59744 | E50: 439925 | F50: -245834 | G50: 138268 | H50: 520256 | I50: 387137
A51: Cash and cash equivalents at beginning of period | D51: 589692 | E51: 649436 | F51: 1089361 | G51: 843527 | H51: 981795 | I51: 1502051
A52: Cash and cash equivalents at end of period | D52: 649436 | E52: 1089361 | F52: 843527 | G52: 981795 | H52: 1502051 | I52: 1889188
A54: SUPPLEMENTAL CASH FLOW DISCLOSURE
A55: Cash paid during the period
A56: Income taxes, net of refunds of $1,421, $77, and $1,564, as of March 31, 2023, 2022, and 2021, respectively | D56: 74573 | E56: 104068 | F56: 192013 | G56: 135986 | H56: 234062 | I56: 345397
A57: Interest | D57: 2466 | E57: 2931 | F57: 1842 | G57: 1880 | H57: 1783 | I57: 1789
A58: Operating leases | D58: 61120 | E58: 57376 | F58: 55588 | G58: 60353 | H58: 65672 | I58: 70326
A59: Non-cash investing activities
A60: Change in accounts payable and other accrued expenses for purchases of property and equipment | D60: 1171 | E60: 2721 | F60: 2797 | G60: 5325 | H60: -6705 | I60: 3819
A61: Accrued for asset retirement obligation assets related to leasehold improvements | D61: 224 | E61: 1842 | F61: 3900 | G61: 8203 | H61: 2278 | I61: 2233
A62: Leasehold improvements acquired through tenant allowances | F62: 4061 | H62: 8127
A63: Non-cash financing activities
A64: Accrued for shares withheld for taxes | D64: - | E64: 11679 | F64: 8435 | G64: 5371 | H64: 22287 | I64: 17148
A65: Accrued excise taxes related to repurchases of common stock | D65: - | E65: - | F65: - | G65: 569 | H65: 3416 | I65: 5043

Sheet Proforma
A1: Income Statement (in thousands of dollars)
A2: Year | B2: 2025 | C2: 2026 | D2: 2027 | E2: 2028 | F2: 2029 | G2: 2030 | H2: 2031 | I2: 2032 | J2: 2033 | K2: 2034 | L2: 2035
A3: Net sales | B3: 4985612 | C3: =B3*(1+'Income Statement'!$J$33) -> 5910350.4 | D3: =C3*(1+'Income Statement'!$J$33) -> 7006610.5 | E3: =D3*(1+'Income Statement'!$J$33) -> 8306206.5 | F3: =E3*(1+'Income Statement'!$J$33) -> 9846853.5 | G3: =F3*(1+'Income Statement'!$J$33) -> 11673262 | H3: =G3*(1+'Income Statement'!$J$33) -> 13838435 | I3: =H3*(1+'Income Statement'!$J$33) -> 16405207 | J3: =I3*(1+'Income Statement'!$J$33) -> 19448068 | ... L3: =K3*(1+'Income Statement'!$J$33) -> 27331658
A4: Cost of Sales | B4: 2099949 | C4: ='Income Statement'!$J$36*Proforma!C3 -> 2752309.9 | D4: ='Income Statement'!$J$36*Proforma!D3 -> 3262812.3 | E4: ='Income Statement'!$J$36*Proforma!E3 -> 3868003.3 | F4: ='Income Statement'!$J$36*Proforma!F3 -> 4585446 | G4: ='Income Statement'!$J$36*Proforma!G3 -> 5435961.1 | H4: ='Income Statement'!$J$36*Proforma!H3 -> 6444230.8 | I4: ='Income Statement'!$J$36*Proforma!I3 -> 7639515.8 | J4: ='Income Statement'!$J$36*Proforma!J3 -> 9056504.1 | ... L4: ='Income Statement'!$J$36*Proforma!L3 -> 12727705
A5: Gross Profit | B5: =B3-B4 -> 2885663 | C5: =C3-C4 -> 3158040.4 | D5: =D3-D4 -> 3743798.2 | E5: =E3-E4 -> 4438203.2 | F5: =F3-F4 -> 5261407.4 | G5: =G3-G4 -> 6237300.7 | H5: =H3-H4 -> 7394204.1 | I5: =I3-I4 -> 8765691.5 | ... L5: =L3-L4 -> 14603953
A6: Selling, general, and administrative expenses | B6: 1706571 | C6: =C3*'Income Statement'!$J$37 -> 2006863.1 | D6: =D3*'Income Statement'!$J$37 -> 2379098.9 | E6: =E3*'Income Statement'!$J$37 -> 2820377.5 | F6: =F3*'Income Statement'!$J$37 -> 3343505.1 | G6: =G3*'Income Statement'!$J$37 -> 3963663.1 | H6: =H3*'Income Statement'!$J$37 -> 4698849 | I6: =I3*'Income Statement'!$J$37 -> 5570398.1 | J6: =J3*'Income Statement'!$J$37 -> 6603603.4 | ... L6: =L3*'Income Statement'!$J$37 -> 9280481
A7: EBIT, Earnings before interest & taxes | B7: =B5-B6 -> 1179092 | C7: =C5-C6 -> 1151177.4 | D7: =D5-D6 -> 1364699.4 | E7: =E5-E6 -> 1617825.7 | F7: =F5-F6 -> 1917902.3 | G7: =G5-G6 -> 2273637.6 | H7: =H5-H6 -> 2695355.1 | I7: =I5-I6 -> 3195293.4 | ... L7: =L5-L6 -> 5323472.1
A8: Interest income | B8: Assumption: Other income, net is excluded from the pro forma projections because it consists primarily of non-operating and non-recurring items (e.g., foreign currency gains/losses, asset sale gains/losses). These items are not reflective of the company’s ongoing operations and are immaterial relative to total EBIT.
A9: Interest expense | B9: 3517 | C9: =C3*'Income Statement'!$J$40 -> 7533.2585 | D9: =D3*'Income Statement'!$J$40 -> 8930.5379 | E9: =E3*'Income Statement'!$J$40 -> 10586.987 | F9: =F3*'Income Statement'!$J$40 -> 12550.676 | G9: =G3*'Income Statement'!$J$40 -> 14878.593 | H9: =H3*'Income Statement'!$J$40 -> 17638.296 | I9: =I3*'Income Statement'!$J$40 -> 20909.872 | J9: =J3*'Income Statement'!$J$40 -> 24788.264 | ... L9: =L3*'Income Statement'!$J$40 -> 34836.588
A10: Other income, net | B10: Assumption: Other income excluded due to immateriality and non-recurring nature.
A11: EBT, Income before income taxes | B11: =B7-B9 -> 1175575 | C11: =C7-C9 -> 1143644.1 | D11: =D7-D9 -> 1355768.8 | E11: =E7-E9 -> 1607238.7 | F11: =F7-F9 -> 1905351.7 | G11: =G7-G9 -> 2258759 | H11: =H7-H9 -> 2677716.8 | I11: =I7-I9 -> 3174383.5 | ... L11: =L7-L9 -> 5288635.6
A12: Income tax expense | B12: 277208 | C12: =C11*'Income Statement'!$J$38 -> 247363.32 | D12: =D11*'Income Statement'!$J$38 -> 293244.62 | E12: =E11*'Income Statement'!$J$38 -> 347636.05 | F12: =F11*'Income Statement'!$J$38 -> 412116.07 | G12: =G11*'Income Statement'!$J$38 -> 488555.95 | H12: =H11*'Income Statement'!$J$38 -> 579174 | I12: =I11*'Income Statement'!$J$38 -> 686600.01 | J12: =J11*'Income Statement'!$J$38 -> 813951.55 | ... L12: =L11*'Income Statement'!$J$38 -> 1143900
A13: Net Income | B13: =B11-B12 -> 898367 | C13: =C11-C12 -> 896280.78 | D13: =D11-D12 -> 1062524.2 | E13: =E11-E12 -> 1259602.7 | F13: =F11-F12 -> 1493235.6 | G13: =G11-G12 -> 1770203 | H13: =H11-H12 -> 2098542.8 | I13: =I11-I12 -> 2487783.5 | ... L13: =L11-L12 -> 4144735.6
A15: Balance Sheet (in thousands of dollars)
A16: Year | B16: 2025 | C16: 2026 | D16: 2027 | E16: 2028 | F16: 2029 | G16: 2030 | H16: 2031 | I16: 2032 | J16: 2033 | K16: 2034 | L16: 2035
A17: ASSETS
A18: Cash and cash equivalents | B18: 1889188 | C18: ='Income Statement'!$J$43*Proforma!C3 -> 1970228.1 | D18: ='Income Statement'!$J$43*Proforma!D3 -> 2335668.7 | E18: ='Income Statement'!$J$43*Proforma!E3 -> 2768891.9 | F18: ='Income Statement'!$J$43*Proforma!F3 -> 3282469.9 | G18: ='Income Statement'!$J$43*Proforma!G3 -> 3891307 | H18: ='Income Statement'!$J$43*Proforma!H3 -> 4613072.1 | I18: ='Income Statement'!$J$43*Proforma!I3 -> 5468711.3 | J18: ='Income Statement'!$J$43*Proforma!J3 -> 6483055.6 | ... L18: ='Income Statement'!$J$43*Proforma!L3 -> 9111067.1
A19: Trade accounts receivable, net of allowances | B19: 332872 | C19: =C3*('Balance Sheet'!$J$51/365) -> 971564.44 | D19: =D3*('Balance Sheet'!$J$51/365) -> 1151771.6 | E19: =E3*('Balance Sheet'!$J$51/365) -> 1365403.8 | F19: =F3*('Balance Sheet'!$J$51/365) -> 1618660.8 | G19: =G3*('Balance Sheet'!$J$51/365) -> 1918892.3 | H19: =H3*('Balance Sheet'!$J$51/365) -> 2274811.2 | I19: =I3*('Balance Sheet'!$J$51/365) -> 2696746.4 | J19: =J3*('Balance Sheet'!$J$51/365) -> 3196942.7 | ... L19: =L3*('Balance Sheet'!$J$51/365) -> 4492875.2
A20: Inventories | B20: 495226 | C20: =C4 * ('Balance Sheet'!$J$52/365) -> 603246.02 | D20: =D4 * ('Balance Sheet'!$J$52/365) -> 715136.94 | E20: =E4 * ('Balance Sheet'!$J$52/365) -> 847781.55 | F20: =F4 * ('Balance Sheet'!$J$52/365) -> 1005029.3 | G20: =G4 * ('Balance Sheet'!$J$52/365) -> 1191443.5 | H20: =H4 * ('Balance Sheet'!$J$52/365) -> 1412434.1 | I20: =I4 * ('Balance Sheet'!$J$52/365) -> 1674414.4 | J20: =J4 * ('Balance Sheet'!$J$52/365) -> 1984987.2 | ... L20: =L4 * ('Balance Sheet'!$J$52/365) -> 2789633.9
A21: Prepaid expenses & Other Current Assets | B21: 106576 | C21: ='Balance Sheet'!$J$53*Proforma!C4 -> 142160.56 | D21: ='Balance Sheet'!$J$53*Proforma!D4 -> 168528.7 | E21: ='Balance Sheet'!$J$53*Proforma!E4 -> 199787.64 | F21: ='Balance Sheet'!$J$53*Proforma!F4 -> 236844.53 | G21: ='Balance Sheet'!$J$53*Proforma!G4 -> 280774.79 | H21: ='Balance Sheet'!$J$53*Proforma!H4 -> 332853.3 | I21: ='Balance Sheet'!$J$53*Proforma!I4 -> 394591.4 | J21: ='Balance Sheet'!$J$53*Proforma!J4 -> 467780.77 | ... L21: ='Balance Sheet'!$J$53*Proforma!L4 -> 657403.28
A22: Income tax receivable | B22: Non-operating; reflects timing of tax refunds, not a recurring operating driver. Including it complicates projections without improving accuracy.
A23: Total current assets | B23: =SUM(B18:B21) -> 2823862 | C23: =SUM(C18:C21) -> 3687199.1 | D23: =SUM(D18:D21) -> 4371106 | E23: =SUM(E18:E21) -> 5181864.9 | F23: =SUM(F18:F21) -> 6143004.5 | G23: =SUM(G18:G21) -> 7282417.7 | H23: =SUM(H18:H21) -> 8633170.8 | I23: =SUM(I18:I21) -> 10234464 | ... L23: =SUM(L18:L21) -> 17050979
A24: PPE gross | B24: 728563 | C24: =C3*'Balance Sheet'!$J$58 -> 998730.72 | D24: =D3*'Balance Sheet'!$J$58 -> 1183976.7 | E24: =E3*'Balance Sheet'!$J$58 -> 1403582.4 | F24: =F3*'Balance Sheet'!$J$58 -> 1663920.8 | G24: =G3*'Balance Sheet'!$J$58 -> 1972547.2 | H24: =H3*'Balance Sheet'!$J$58 -> 2338418.1 | I24: =I3*'Balance Sheet'!$J$58 -> 2772151.1 | J24: =J3*'Balance Sheet'!$J$58 -> 3286333.7 | ... L24: =L3*'Balance Sheet'!$J$58 -> 4618502.2
A25: Depreciation | B25: 402964 | C25: ='Balance Sheet'!$J$57*Proforma!C24 -> 547069.98 | D25: ='Balance Sheet'!$J$57*Proforma!D24 -> 648541.29 | E25: ='Balance Sheet'!$J$57*Proforma!E24 -> 768833.65 | F25: ='Balance Sheet'!$J$57*Proforma!F24 -> 911438 | G25: ='Balance Sheet'!$J$57*Proforma!G24 -> 1080492.8 | H25: ='Balance Sheet'!$J$57*Proforma!H24 -> 1280904.1 | I25: ='Balance Sheet'!$J$57*Proforma!I24 -> 1518488.1 | J25: ='Balance Sheet'!$J$57*Proforma!J24 -> 1800139.4 | ... L25: ='Balance Sheet'!$J$57*Proforma!L24 -> 2529855
A26: PPE net
A27: Operating lease assets | B27: 237352 | C27: ='Balance Sheet'!$J$54 -> 214882.5 | D27: ='Balance Sheet'!$J$54 -> 214882.5 | E27: ='Balance Sheet'!$J$54 -> 214882.5 | F27: ='Balance Sheet'!$J$54 -> 214882.5 | G27: ='Balance Sheet'!$J$54 -> 214882.5 | H27: ='Balance Sheet'!$J$54 -> 214882.5 | I27: ='Balance Sheet'!$J$54 -> 214882.5 | J27: ='Balance Sheet'!$J$54 -> 214882.5 | ... L27: ='Balance Sheet'!$J$54 -> 214882.5
A28: Goodwill | B28: 13990 | C28: ='Balance Sheet'!$J$55 -> 13990 | D28: ='Balance Sheet'!$J$55 -> 13990 | E28: ='Balance Sheet'!$J$55 -> 13990 | F28: ='Balance Sheet'!$J$55 -> 13990 | G28: ='Balance Sheet'!$J$55 -> 13990 | H28: ='Balance Sheet'!$J$55 -> 13990 | I28: ='Balance Sheet'!$J$55 -> 13990 | J28: ='Balance Sheet'!$J$55 -> 13990 | ... L28: ='Balance Sheet'!$J$55 -> 13990
A29: Other intangible assets, net of accumulated amortization | B29: 15699 | C29: ='Balance Sheet'!$J$59 -> 34981.333 | D29: ='Balance Sheet'!$J$59 -> 34981.333 | E29: ='Balance Sheet'!$J$59 -> 34981.333 | F29: ='Balance Sheet'!$J$59 -> 34981.333 | G29: ='Balance Sheet'!$J$59 -> 34981.333 | H29: ='Balance Sheet'!$J$59 -> 34981.333 | I29: ='Balance Sheet'!$J$59 -> 34981.333 | J29: ='Balance Sheet'!$J$59 -> 34981.333 | ... L29: ='Balance Sheet'!$J$59 -> 34981.333
A30: Deferred tax assets, net | B30: Non-operating; timing difference in taxes. Often excluded in operating asset base for ROIC/valuation.
A31: Other non-current assets | B31: 39546 | C31: =C3*'Balance Sheet'!$J$56 -> 73619.803 | D31: =D3*'Balance Sheet'!$J$56 -> 87274.908 | E31: =E3*'Balance Sheet'!$J$56 -> 103462.78 | F31: =F3*'Balance Sheet'!$J$56 -> 122653.2 | G31: =G3*'Balance Sheet'!$J$56 -> 145403.09 | H31: =H3*'Balance Sheet'!$J$56 -> 172372.67 | I31: =I3*'Balance Sheet'!$J$56 -> 204344.59 | J31: =J3*'Balance Sheet'!$J$56 -> 242246.71 | ... L31: =L3*'Balance Sheet'!$J$56 -> 340445.34
A32: Total Non-current Assets | B32: =B24-B25+B27+B28+B29+B31 -> 632186 | C32: =C24-C25+C27+C28+C29+C31 -> 789134.38 | D32: =D24-D25+D27+D28+D29+D31 -> 886564.16 | E32: =E24-E25+E27+E28+E29+E31 -> 1002065.3 | F32: =F24-F25+F27+F28+F29+F31 -> 1138989.9 | G32: =G24-G25+G27+G28+G29+G31 -> 1301311.3 | H32: =H24-H25+H27+H28+H29+H31 -> 1493740.4 | I32: =I24-I25+I27+I28+I29+I31 -> 1721861.5 | ... L32: =L24-L25+L27+L28+L29+L31 -> 2692946.4
A33: Total assets | B33: =B23+B32 -> 3456048 | C33: =C23+C32 -> 4476333.5 | D33: =D23+D32 -> 5257670.1 | E33: =E23+E32 -> 6183930.2 | F33: =F23+F32 -> 7281994.4 | G33: =G23+G32 -> 8583729 | H33: =H23+H32 -> 10126911 | I33: =I23+I32 -> 11956325 | ... L33: =L23+L32 -> 19743926
A34: LIABILITIES AND STOCKHOLDERS' EQUITY
A35: Trade accounts payable | B35: 417955 | C35: =C4*('Balance Sheet'!$J$63/365) -> 504182.66 | D35: =D4*('Balance Sheet'!$J$63/365) -> 597699.17 | E35: =E4*('Balance Sheet'!$J$63/365) -> 708561.26 | F35: =F4*('Balance Sheet'!$J$63/365) -> 839986.2 | G35: =G4*('Balance Sheet'!$J$63/365) -> 995788.03 | H35: =H4*('Balance Sheet'!$J$63/365) -> 1180488.2 | I35: =I4*('Balance Sheet'!$J$63/365) -> 1399446.8 | J35: =J4*('Balance Sheet'!$J$63/365) -> 1659018.2 | ... L35: =L4*('Balance Sheet'!$J$63/365) -> 2331528.1
A36: Accrued payroll | B36: 125417 | C36: =C4*'Balance Sheet'!$J$64 -> 143389.27 | D36: =D4*'Balance Sheet'!$J$64 -> 169985.31 | E36: =E4*'Balance Sheet'!$J$64 -> 201514.43 | F36: =F4*'Balance Sheet'!$J$64 -> 238891.61 | G36: =G4*'Balance Sheet'!$J$64 -> 283201.57 | H36: =H4*'Balance Sheet'!$J$64 -> 335730.19 | I36: =I4*'Balance Sheet'!$J$64 -> 398001.9 | J36: =J4*'Balance Sheet'!$J$64 -> 471823.86 | ... L36: =L4*'Balance Sheet'!$J$64 -> 663085.3
A37: Operating lease liabilities | B37: 54453 | C37: ='Balance Sheet'!$J$67*C3 -> 93291.11 | D37: ='Balance Sheet'!$J$67*D3 -> 110594.88 | E37: ='Balance Sheet'!$J$67*E3 -> 131108.17 | F37: ='Balance Sheet'!$J$67*F3 -> 155426.3 | G37: ='Balance Sheet'!$J$67*G3 -> 184254.99 | H37: ='Balance Sheet'!$J$67*H3 -> 218430.87 | I37: ='Balance Sheet'!$J$67*I3 -> 258945.73 | J37: ='Balance Sheet'!$J$67*J3 -> 306975.35 | ... L37: ='Balance Sheet'!$J$67*L3 -> 431412.78
A38: Other accrued expenses | B38: 142120 | C38: =C4*'Balance Sheet'!$J$65 -> 150729.21 | D38: =D4*'Balance Sheet'!$J$65 -> 178686.68 | E38: =E4*'Balance Sheet'!$J$65 -> 211829.74 | F38: =F4*'Balance Sheet'!$J$65 -> 251120.22 | G38: =G4*'Balance Sheet'!$J$65 -> 297698.35 | H38: =H4*'Balance Sheet'!$J$65 -> 352915.86 | I38: =I4*'Balance Sheet'!$J$65 -> 418375.2 | J38: =J4*'Balance Sheet'!$J$65 -> 495976.02 | ... L38: =L4*'Balance Sheet'!$J$65 -> 697027.93
A39: Income tax payable | B39: Non-operating liability; reflects timing of tax payments.
A40: Value added tax payable | B40: Government tax pass-through, not part of operations profitably.
A41: Total current liabilities | B41: =SUM(B35:B38) -> 739945 | C41: =SUM(C35:C38) -> 891592.25 | D41: =SUM(D35:D38) -> 1056966 | E41: =SUM(E35:E38) -> 1253013.6 | F41: =SUM(F35:F38) -> 1485424.3 | G41: =SUM(G35:G38) -> 1760942.9 | H41: =SUM(H35:H38) -> 2087565.1 | I41: =SUM(I35:I38) -> 2474769.7 | ... L41: =SUM(L35:L38) -> 4123054.1
A42: Long-term operating lease liabilities | B42: 222522 | C42: ='Balance Sheet'!$J$61 -> 204296 | D42: ='Balance Sheet'!$J$61 -> 204296 | E42: ='Balance Sheet'!$J$61 -> 204296 | F42: ='Balance Sheet'!$J$61 -> 204296 | G42: ='Balance Sheet'!$J$61 -> 204296 | H42: ='Balance Sheet'!$J$61 -> 204296 | I42: ='Balance Sheet'!$J$61 -> 204296 | J42: ='Balance Sheet'!$J$61 -> 204296 | ... L42: ='Balance Sheet'!$J$61 -> 204296
A43: Income tax liability | B43: Non-operating; timing difference.
A44: Deferred rent obligations | B44: Obsolete under ASC 842 unless separate.
A45: Other long-term liabilities | B45: 51189 | C45: =C4*'Balance Sheet'!$J$69 -> 51785.507 | D45: =D4*'Balance Sheet'!$J$69 -> 61390.756 | E45: =E4*'Balance Sheet'!$J$69 -> 72777.6 | F45: =F4*'Balance Sheet'!$J$69 -> 86276.492 | G45: =G4*'Balance Sheet'!$J$69 -> 102279.18 | H45: =H4*'Balance Sheet'!$J$69 -> 121250.06 | I45: =I4*'Balance Sheet'!$J$69 -> 143739.7 | J45: =J4*'Balance Sheet'!$J$69 -> 170400.74 | ... L45: =L4*'Balance Sheet'!$J$69 -> 239475.44
A46: Total Long Term liabilities | B46: =B42+B45 -> 273711 | C46: =C42+C45 -> 256081.51 | D46: =D42+D45 -> 265686.76 | E46: =E42+E45 -> 277073.6 | F46: =F42+F45 -> 290572.49 | G46: =G42+G45 -> 306575.18 | H46: =H42+H45 -> 325546.06 | I46: =I42+I45 -> 348035.7 | ... L46: =L42+L45 -> 443771.44
A47: Common stock ($0.01 par value; 125,000 shares authorized) | B47: 1502 | C47: =B47+C58 -> 32455.309 | D47: =B47+D58 -> -391877.23 | E47: =B47+E58 -> -894915.57 | F47: =E47 -> -894915.57 | G47: =F47 -> -894915.57 | H47: =G47 -> -894915.57 | I47: =H47 -> -894915.57 | J47: =I47 -> -894915.57 | K47: =J47 -> -894915.57 | L47: =K47 -> -894915.57
A48: Additional paid-in capital | B48: 253466 | C48: =B48 -> 253466 | D48: =C48 -> 253466 | E48: =D48 -> 253466 | F48: =E48 -> 253466 | G48: =F48 -> 253466 | H48: =G48 -> 253466 | I48: =H48 -> 253466 | J48: =I48 -> 253466 | ... L48: =K48 -> 253466
A49: Retained earnings | B49: 2307699 | C49: =B49+C13 -> 3203979.8 | D49: =C49+D13 -> 4266504 | E49: =D49+E13 -> 5526106.7 | F49: =E49+F13 -> 7019342.3 | G49: =F49+G13 -> 8789545.3 | H49: =G49+H13 -> 10888088 | I49: =H49+I13 -> 13375872 | J49: =I49+J13 -> 16325093 | ... L49: =K49+L13 -> 23966075
A50: Accumulated other comprehensive loss (Note 10) | B50: Relates to unrealized gains/losses; non-cash, non-operating.
A51: Total stockholders' equity | B51: =SUM(B47:B49) -> 2562667 | C51: =SUM(C47:C49) -> 3489901.1 | D51: =SUM(D47:D49) -> 4128092.8 | E51: =SUM(E47:E49) -> 4884657.1 | F51: =SUM(F47:F49) -> 6377892.7 | G51: =SUM(G47:G49) -> 8148095.7 | H51: =SUM(H47:H49) -> 10246639 | I51: =SUM(I47:I49) -> 12734422 | ... L51: =SUM(L47:L49) -> 23324625
A52: Total liabilities and stockholders' equity | B52: =B51+B46+B41 -> 3576323 | C52: =C51+C46+C41 -> 4637574.8 | D52: =D51+D46+D41 -> 5450745.6 | E52: =E51+E46+E41 -> 6414744.3 | F52: =F51+F46+F41 -> 8153889.5 | G52: =G51+G46+G41 -> 10215614 | H52: =H51+H46+H41 -> 12659750 | I52: =I51+I46+I41 -> 15557227 | ... L52: =L51+L46+L41 -> 27891451
A54: Difference needed to balance | B54: =B52-B33 -> 120275 | C54: =C52-C33 -> 161241.4 | D54: =D52-D33 -> 193075.43 | E54: =E52-E33 -> 230814.09 | F54: =F52-F33 -> 871895.16 | G54: =G52-G33 -> 1631884.9 | H54: =H52-H33 -> 2532838.5 | I54: =I52-I33 -> 3600902.3 | ... L54: =L52-L33 -> 8147525.2
A56: Min cash balance | C56: =C3*'Income Statement'!$J$43 -> 1970228.1 | D56: =D3*'Income Statement'!$J$43 -> 2335668.7 | E56: =E3*'Income Statement'!$J$43 -> 2768891.9 | F56: =F3*'Income Statement'!$J$43 -> 3282469.9 | G56: =G3*'Income Statement'!$J$43 -> 3891307 | H56: =H3*'Income Statement'!$J$43 -> 4613072.1 | I56: =I3*'Income Statement'!$J$43 -> 5468711.3 | J56: =J3*'Income Statement'!$J$43 -> 6483055.6 | ... L56: =L3*'Income Statement'!$J$43 -> 9111067.1
A57: Planned debt repayment | C57: =C58 -> 30953.309 | D57: =D58 -> -393379.23 | E57: =E58 -> -896417.57 | F57: =F58 -> -1492760.2 | G57: =G58 -> -2199713.2 | H57: =H58 -> -3037793 | I57: =I58 -> -4031320.9 | J57: =J58 -> -5209129.8 | ... L57: =L58 -> -8260653.2
A58: External Financing Needed (EFN) | C58: =C56+C19+C20+(C24-C25)-C35-((C42+C45))-$B$47-C49 -> 30953.309 | D58: =D56+D19+D20+(D24-D25)-D35-((D42+D45))-$B$47-D49 -> -393379.23 | E58: =E56+E19+E20+(E24-E25)-E35-((E42+E45))-$B$47-E49 -> -896417.57 | F58: =F56+F19+F20+(F24-F25)-F35-((F42+F45))-$B$47-F49 -> -1492760.2 | G58: =G56+G19+G20+(G24-G25)-G35-((G42+G45))-$B$47-G49 -> -2199713.2 | H58: =H56+H19+H20+(H24-H25)-H35-((H42+H45))-$B$47-H49 -> -3037793 | I58: =I56+I19+I20+(I24-I25)-I35-((I42+I45))-$B$47-I49 -> -4031320.9 | J58: =J56+J19+J20+(J24-J25)-J35-((J42+J45))-$B$47-J49 -> -5209129.8 | ... L58: =L56+L19+L20+(L24-L25)-L35-((L42+L45))-$B$47-L49 -> -8260653.2
C59: What a Shortfall Means | F59: What a Surplus Means
C61: EFN > 0 (positive number) | F61: EFN < 0 (negative number)
C63: Your company needs additional external financing (debt, equity, or other) to support the projected growth. | F63: Your company has excess financing — more internal funds than needed.
C65: It means the internally generated funds plus spontaneous liabilities are not enough to finance the new assets required for the growth. | F65: The firm can potentially pay down debt, repurchase stock, or increase dividends since it doesn’t need external funds to support growth.
A66: first change: current liabilities were not added to total liabilites and stockholders equity
A67: We have to make an assumption with goodwill as it has practically doubled from 2022 to 2025
A68: Operating leases cant stay consistent also

Sheet Balanced Proforma
A1: DECKERS OUTDOOR CORPORATION AND SUBSIDIARIES
A2: CONSOLIDATED PRO FORMA
A3: (dollar and share data amounts in thousands)
A4: Income Statement Projection
A5: Year | B5: 2025 | C5: 2026 | D5: 2027 | E5: 2028 | F5: 2029 | G5: 2030 | H5: 2031 | I5: 2032 | J5: 2033 | K5: 2034 | L5: 2035
A6: Net sales | B6: 4985612 | C6: =B6*(1+'Income Statement'!$J$33) -> 5910350.4 | D6: =C6*(1+'Income Statement'!$J$33) -> 7006610.5 | E6: =D6*(1+'Income Statement'!$J$33) -> 8306206.5 | F6: =E6*(1+'Income Statement'!$J$33) -> 9846853.5 | G6: =F6*(1+'Income Statement'!$J$33) -> 11673262 | H6: =G6*(1+'Income Statement'!$K$33) -> 12840588 | I6: =H6*(1+'Income Statement'!$L$33) -> 13867835 | J6: =I6*(1+'Income Statement'!$M$33) -> 14838583 | K6: =J6*(1+'Income Statement'!$N$33) -> 15580513 | L6: =K6*(1+'Income Statement'!$O$33) -> 16359538
A7: Cost of Sales | B7: 2099949 | C7: ='Income Statement'!$J$36*Proforma!C3 -> 2752309.9 | D7: ='Income Statement'!$J$36*Proforma!D3 -> 3262812.3 | E7: ='Income Statement'!$J$36*Proforma!E3 -> 3868003.3 | F7: ='Income Statement'!$J$36*Proforma!F3 -> 4585446 | G7: ='Income Statement'!$J$36*Proforma!G3 -> 5435961.1 | H7: ='Income Statement'!$J$36*Proforma!H3 -> 6444230.8 | I7: ='Income Statement'!$J$36*Proforma!I3 -> 7639515.8 | J7: ='Income Statement'!$J$36*Proforma!J3 -> 9056504.1 | K7: ='Income Statement'!$J$36*Proforma!K3 -> 10736317 | L7: ='Income Statement'!$J$36*L6 -> 7618248.8
A8: Gross Profit | B8: =B6-B7 -> 2885663 | C8: =C6-C7 -> 3158040.4 | D8: =D6-D7 -> 3743798.2 | E8: =E6-E7 -> 4438203.2 | F8: =F6-F7 -> 5261407.4 | G8: =G6-G7 -> 6237300.7 | H8: =H6-H7 -> 6396357.1 | I8: =I6-I7 -> 6228319.1 | ... L8: =L6-L7 -> 8741289.4
A9: Selling, general, and administrative expenses | B9: 1706571 | C9: =C6*'Income Statement'!$J$37 -> 2006863.1 | D9: =D6*'Income Statement'!$J$37 -> 2379098.9 | E9: =E6*'Income Statement'!$J$37 -> 2820377.5 | F9: =F6*'Income Statement'!$J$37 -> 3343505.1 | G9: =G6*'Income Statement'!$J$37 -> 3963663.1 | H9: =H6*'Income Statement'!$J$37 -> 4360029.4 | I9: =I6*'Income Statement'!$J$37 -> 4708831.8 | J9: =J6*'Income Statement'!$J$37 -> 5038450 | ... L9: =L6*'Income Statement'!$J$37 -> 5554891.1
A10: EBIT, Earnings before interest & taxes | B10: =B8-B9 -> 1179092 | C10: =C8-C9 -> 1151177.4 | D10: =D8-D9 -> 1364699.4 | E10: =E8-E9 -> 1617825.7 | F10: =F8-F9 -> 1917902.3 | G10: =G8-G9 -> 2273637.6 | H10: =H8-H9 -> 2036327.7 | I10: =I8-I9 -> 1519487.3 | ... L10: =L8-L9 -> 3186398.3
A11: Interest income | B11: Assumption: Other income, net is excluded from the pro forma projections because it consists primarily of non-operating and non-recurring items (e.g., foreign currency gains/losses, asset sale gains/losses). These items are not reflective of the company’s ongoing operations and are immaterial relative to total EBIT.
A12: Interest expense | B12: 3517 | C12: =C6*'Income Statement'!$J$40 -> 7533.2585 | D12: =D6*'Income Statement'!$J$40 -> 8930.5379 | E12: =E6*'Income Statement'!$J$40 -> 10586.987 | F12: =F6*'Income Statement'!$J$40 -> 12550.676 | G12: =G6*'Income Statement'!$J$40 -> 14878.593 | H12: =H6*'Income Statement'!$J$40 -> 16366.452 | I12: =I6*'Income Statement'!$J$40 -> 17675.769 | J12: =J6*'Income Statement'!$J$40 -> 18913.072 | ... L12: =L6*'Income Statement'!$J$40 -> 20851.662
A13: Other income, net | B13: Assumption: Other income excluded due to immateriality and non-recurring nature.
A14: EBT, Income before income taxes | B14: =B10-B12 -> 1175575 | C14: =C10-C12 -> 1143644.1 | D14: =D10-D12 -> 1355768.8 | E14: =E10-E12 -> 1607238.7 | F14: =F10-F12 -> 1905351.7 | G14: =G10-G12 -> 2258759 | H14: =H10-H12 -> 2019961.2 | I14: =I10-I12 -> 1501811.6 | ... L14: =L10-L12 -> 3165546.6
A15: Income tax expense | B15: 277208 | C15: =C14*'Income Statement'!$J$38 -> 247363.32 | D15: =D14*'Income Statement'!$J$38 -> 293244.62 | E15: =E14*'Income Statement'!$J$38 -> 347636.05 | F15: =F14*'Income Statement'!$J$38 -> 412116.07 | G15: =G14*'Income Statement'!$J$38 -> 488555.95 | H15: =H14*'Income Statement'!$J$38 -> 436905.44 | I15: =I14*'Income Statement'!$J$38 -> 324832.79 | J15: =J14*'Income Statement'!$J$38 -> 156751.76 | ... L15: =L14*'Income Statement'!$J$38 -> 684688.64
A16: Net Income | B16: =B14-B15 -> 898367 | C16: =C14-C15 -> 896280.78 | D16: =D14-D15 -> 1062524.2 | E16: =E14-E15 -> 1259602.7 | F16: =F14-F15 -> 1493235.6 | G16: =G14-G15 -> 1770203 | H16: =H14-H15 -> 1583055.8 | I16: =I14-I15 -> 1176978.8 | ... L16: =L14-L15 -> 2480858
A18: Balance Sheet Projection
A19: Year | B19: 2025 | C19: 2026 | D19: 2027 | E19: 2028 | F19: 2029 | G19: 2030 | H19: 2031 | I19: 2032 | J19: 2033 | K19: 2034 | L19: 2035
A20: ASSETS
A21: Cash and cash equivalents | B21: =B55-B22-B23-B24-B35 -> 2009463 | C21: =C55-C22-C23-C24-C35 -> 2131469.5 | D21: =D55-D22-D23-D24-D35 -> 2528744.2 | E21: =E55-E22-E23-E24-E35 -> 2999706 | F21: =F55-F22-F23-F24-F35 -> 4154365 | G21: =G55-G22-G23-G24-G35 -> 5523191.9 | H21: =H55-H22-H23-H24-H35 -> 6959748.3 | I21: =I55-I22-I23-I24-I35 -> 8080744.2 | ... L21: =L55-L22-L23-L24-L35 -> 10688629
A22: Trade accounts receivable, net of allowances | B22: 332872 | C22: =C6*('Balance Sheet'!$J$51/365) -> 971564.44 | D22: =D6*('Balance Sheet'!$J$51/365) -> 1151771.6 | E22: =E6*('Balance Sheet'!$J$51/365) -> 1365403.8 | F22: =F6*('Balance Sheet'!$J$51/365) -> 1618660.8 | G22: =G6*('Balance Sheet'!$J$51/365) -> 1918892.3 | H22: =H6*('Balance Sheet'!$J$51/365) -> 2110781.6 | I22: =I6*('Balance Sheet'!$J$51/365) -> 2279644.1 | J22: =J6*('Balance Sheet'!$J$51/365) -> 2439219.2 | ... L22: =L6*('Balance Sheet'!$J$51/365) -> 2689239.2
A23: Inventories | B23: 495226 | C23: =C7 * ('Balance Sheet'!$J$52/365) -> 603246.02 | D23: =D7 * ('Balance Sheet'!$J$52/365) -> 715136.94 | E23: =E7 * ('Balance Sheet'!$J$52/365) -> 847781.55 | F23: =F7 * ('Balance Sheet'!$J$52/365) -> 1005029.3 | G23: =G7 * ('Balance Sheet'!$J$52/365) -> 1191443.5 | H23: =H7 * ('Balance Sheet'!$J$52/365) -> 1412434.1 | I23: =I7 * ('Balance Sheet'!$J$52/365) -> 1674414.4 | J23: =J7 * ('Balance Sheet'!$J$52/365) -> 1984987.2 | ... L23: =L7 * ('Balance Sheet'!$J$52/365) -> 1669753.2
A24: Prepaid expenses & Other Current Assets | B24: 106576 | C24: ='Balance Sheet'!$J$53*Proforma!C4 -> 142160.56 | D24: ='Balance Sheet'!$J$53*Proforma!D4 -> 168528.7 | E24: ='Balance Sheet'!$J$53*Proforma!E4 -> 199787.64 | F24: ='Balance Sheet'!$J$53*Proforma!F4 -> 236844.53 | G24: ='Balance Sheet'!$J$53*Proforma!G4 -> 280774.79 | H24: ='Balance Sheet'!$J$53*Proforma!H4 -> 332853.3 | I24: ='Balance Sheet'!$J$53*Proforma!I4 -> 394591.4 | J24: ='Balance Sheet'!$J$53*Proforma!J4 -> 467780.77 | ... L24: ='Balance Sheet'!$J$53*Proforma!L4 -> 657403.28
A25: Income tax receivable | B25: Assumption: Non-operating; reflects timing of tax refunds, not a recurring operating driver. Including it complicates projections without improving accuracy.
A26: Total current assets | B26: =SUM(B21:B24) -> 2944137 | C26: =SUM(C21:C24) -> 3848440.5 | D26: =SUM(D21:D24) -> 4564181.4 | E26: =SUM(E21:E24) -> 5412679 | F26: =SUM(F21:F24) -> 7014899.7 | G26: =SUM(G21:G24) -> 8914302.5 | H26: =SUM(H21:H24) -> 10815817 | I26: =SUM(I21:I24) -> 12429394 | ... L26: =SUM(L21:L24) -> 15705025
A27: PPE gross | B27: 728563 | C27: =C6*'Balance Sheet'!$J$58 -> 998730.72 | D27: =D6*'Balance Sheet'!$J$58 -> 1183976.7 | E27: =E6*'Balance Sheet'!$J$58 -> 1403582.4 | F27: =F6*'Balance Sheet'!$J$58 -> 1663920.8 | G27: =G6*'Balance Sheet'!$J$58 -> 1972547.2 | H27: =H6*'Balance Sheet'!$J$58 -> 2169801.9 | I27: =I6*'Balance Sheet'!$J$58 -> 2343386.1 | J27: =J6*'Balance Sheet'!$J$58 -> 2507423.1 | ... L27: =L6*'Balance Sheet'!$J$58 -> 2764434
A28: Depreciation | B28: 402964 | C28: ='Balance Sheet'!$J$57*Proforma!C24 -> 547069.98 | D28: ='Balance Sheet'!$J$57*Proforma!D24 -> 648541.29 | E28: ='Balance Sheet'!$J$57*Proforma!E24 -> 768833.65 | F28: ='Balance Sheet'!$J$57*Proforma!F24 -> 911438 | G28: ='Balance Sheet'!$J$57*Proforma!G24 -> 1080492.8 | H28: ='Balance Sheet'!$J$57*Proforma!H24 -> 1280904.1 | I28: ='Balance Sheet'!$J$57*Proforma!I24 -> 1518488.1 | J28: ='Balance Sheet'!$J$57*Proforma!J24 -> 1800139.4 | ... L28: ='Balance Sheet'!$J$57*Proforma!L24 -> 2529855
A29: PPE net | B29: Assumption: Already calculated in PPE Gross. Derived from PPE gross minus accumulated depreciation.
A30: Operating lease assets | B30: 237352 | C30: ='Balance Sheet'!$J$54 -> 214882.5 | D30: ='Balance Sheet'!$J$54 -> 214882.5 | E30: ='Balance Sheet'!$J$54 -> 214882.5 | F30: ='Balance Sheet'!$J$54 -> 214882.5 | G30: ='Balance Sheet'!$J$54 -> 214882.5 | H30: ='Balance Sheet'!$J$54 -> 214882.5 | I30: ='Balance Sheet'!$J$54 -> 214882.5 | J30: ='Balance Sheet'!$J$54 -> 214882.5 | ... L30: ='Balance Sheet'!$J$54 -> 214882.5
A31: Goodwill | B31: 13990 | C31: ='Balance Sheet'!$J$55 -> 13990 | D31: ='Balance Sheet'!$J$55 -> 13990 | E31: ='Balance Sheet'!$J$55 -> 13990 | F31: ='Balance Sheet'!$J$55 -> 13990 | G31: ='Balance Sheet'!$J$55 -> 13990 | H31: ='Balance Sheet'!$J$55 -> 13990 | I31: ='Balance Sheet'!$J$55 -> 13990 | J31: ='Balance Sheet'!$J$55 -> 13990 | ... L31: ='Balance Sheet'!$J$55 -> 13990
A32: Other intangible assets, net of accumulated amortization | B32: 15699 | C32: ='Balance Sheet'!$J$59 -> 34981.333 | D32: ='Balance Sheet'!$J$59 -> 34981.333 | E32: ='Balance Sheet'!$J$59 -> 34981.333 | F32: ='Balance Sheet'!$J$59 -> 34981.333 | G32: ='Balance Sheet'!$J$59 -> 34981.333 | H32: ='Balance Sheet'!$J$59 -> 34981.333 | I32: ='Balance Sheet'!$J$59 -> 34981.333 | J32: ='Balance Sheet'!$J$59 -> 34981.333 | ... L32: ='Balance Sheet'!$J$59 -> 34981.333
A33: Deferred tax assets, net | B33: Assumption: Non-operating; timing difference in taxes. Often excluded in operating asset base for ROIC/valuation.
A34: Other non-current assets | B34: 39546 | C34: =C6*'Balance Sheet'!$J$56 -> 73619.803 | D34: =D6*'Balance Sheet'!$J$56 -> 87274.908 | E34: =E6*'Balance Sheet'!$J$56 -> 103462.78 | F34: =F6*'Balance Sheet'!$J$56 -> 122653.2 | G34: =G6*'Balance Sheet'!$J$56 -> 145403.09 | H34: =H6*'Balance Sheet'!$J$56 -> 159943.4 | I34: =I6*'Balance Sheet'!$J$56 -> 172738.88 | J34: =J6*'Balance Sheet'!$J$56 -> 184830.6 | ... L34: =L6*'Balance Sheet'!$J$56 -> 203775.73
A35: Total Non-current Assets | B35: =B27-B28+B30+B31+B32+B34 -> 632186 | C35: =C27-C28+C30+C31+C32+C34 -> 789134.38 | D35: =D27-D28+D30+D31+D32+D34 -> 886564.16 | E35: =E27-E28+E30+E31+E32+E34 -> 1002065.3 | F35: =F27-F28+F30+F31+F32+F34 -> 1138989.9 | G35: =G27-G28+G30+G31+G32+G34 -> 1301311.3 | H35: =H27-H28+H30+H31+H32+H34 -> 1312695 | I35: =I27-I28+I30+I31+I32+I34 -> 1261490.7 | ... L35: =L27-L28+L30+L31+L32+L34 -> 702208.56
A36: Total assets | B36: =B26+B35 -> 3576323 | C36: =C26+C35 -> 4637574.8 | D36: =D26+D35 -> 5450745.6 | E36: =E26+E35 -> 6414744.3 | F36: =F26+F35 -> 8153889.5 | G36: =G26+G35 -> 10215614 | H36: =H26+H35 -> 12128512 | I36: =I26+I35 -> 13690885 | ... L36: =L26+L35 -> 16407234
A37: LIABILITIES AND STOCKHOLDERS' EQUITY
A38: Trade accounts payable | B38: 417955 | C38: =C7*('Balance Sheet'!$J$63/365) -> 504182.66 | D38: =D7*('Balance Sheet'!$J$63/365) -> 597699.17 | E38: =E7*('Balance Sheet'!$J$63/365) -> 708561.26 | F38: =F7*('Balance Sheet'!$J$63/365) -> 839986.2 | G38: =G7*('Balance Sheet'!$J$63/365) -> 995788.03 | H38: =H7*('Balance Sheet'!$J$63/365) -> 1180488.2 | I38: =I7*('Balance Sheet'!$J$63/365) -> 1399446.8 | J38: =J7*('Balance Sheet'!$J$63/365) -> 1659018.2 | ... L38: =L7*('Balance Sheet'!$J$63/365) -> 1395551
A39: Accrued payroll | B39: 125417 | C39: =C7*'Balance Sheet'!$J$64 -> 143389.27 | D39: =D7*'Balance Sheet'!$J$64 -> 169985.31 | E39: =E7*'Balance Sheet'!$J$64 -> 201514.43 | F39: =F7*'Balance Sheet'!$J$64 -> 238891.61 | G39: =G7*'Balance Sheet'!$J$64 -> 283201.57 | H39: =H7*'Balance Sheet'!$J$64 -> 335730.19 | I39: =I7*'Balance Sheet'!$J$64 -> 398001.9 | J39: =J7*'Balance Sheet'!$J$64 -> 471823.86 | ... L39: =L7*'Balance Sheet'!$J$64 -> 396893.94
A40: Operating lease liabilities | B40: 54453 | C40: ='Balance Sheet'!$J$67*C6 -> 93291.11 | D40: ='Balance Sheet'!$J$67*D6 -> 110594.88 | E40: ='Balance Sheet'!$J$67*E6 -> 131108.17 | F40: ='Balance Sheet'!$J$67*F6 -> 155426.3 | G40: ='Balance Sheet'!$J$67*G6 -> 184254.99 | H40: ='Balance Sheet'!$J$67*H6 -> 202680.49 | I40: ='Balance Sheet'!$J$67*I6 -> 218894.93 | J40: ='Balance Sheet'!$J$67*J6 -> 234217.57 | ... L40: ='Balance Sheet'!$J$67*L6 -> 258224.87
A41: Other accrued expenses | B41: 142120 | C41: =C7*'Balance Sheet'!$J$65 -> 150729.21 | D41: =D7*'Balance Sheet'!$J$65 -> 178686.68 | E41: =E7*'Balance Sheet'!$J$65 -> 211829.74 | F41: =F7*'Balance Sheet'!$J$65 -> 251120.22 | G41: =G7*'Balance Sheet'!$J$65 -> 297698.35 | H41: =H7*'Balance Sheet'!$J$65 -> 352915.86 | I41: =I7*'Balance Sheet'!$J$65 -> 418375.2 | J41: =J7*'Balance Sheet'!$J$65 -> 495976.02 | ... L41: =L7*'Balance Sheet'!$J$65 -> 417210.52
A42: Income tax payable | B42: Assumption: Non-operating liability; reflects timing of tax payments.
A43: Value added tax payable | B43: Assumption: Government tax pass-through, not part of operations profitably.
A44: Total current liabilities | B44: =SUM(B38:B41) -> 739945 | C44: =SUM(C38:C41) -> 891592.25 | D44: =SUM(D38:D41) -> 1056966 | E44: =SUM(E38:E41) -> 1253013.6 | F44: =SUM(F38:F41) -> 1485424.3 | G44: =SUM(G38:G41) -> 1760942.9 | H44: =SUM(H38:H41) -> 2071814.8 | I44: =SUM(I38:I41) -> 2434718.9 | ... L44: =SUM(L38:L41) -> 2467880.4
A45: Long-term operating lease liabilities | B45: 222522 | C45: ='Balance Sheet'!$J$61 -> 204296 | D45: ='Balance Sheet'!$J$61 -> 204296 | E45: ='Balance Sheet'!$J$61 -> 204296 | F45: ='Balance Sheet'!$J$61 -> 204296 | G45: ='Balance Sheet'!$J$61 -> 204296 | H45: ='Balance Sheet'!$J$61 -> 204296 | I45: ='Balance Sheet'!$J$61 -> 204296 | J45: ='Balance Sheet'!$J$61 -> 204296 | ... L45: ='Balance Sheet'!$J$61 -> 204296
A46: Income tax liability | B46: Assumption: Non-operating; timing difference.
A47: Deferred rent obligations | B47: Assumption: Obsolete under ASC 842 unless separate.
A48: Other long-term liabilities | B48: 51189 | C48: =C7*'Balance Sheet'!$J$69 -> 51785.507 | D48: =D7*'Balance Sheet'!$J$69 -> 61390.756 | E48: =E7*'Balance Sheet'!$J$69 -> 72777.6 | F48: =F7*'Balance Sheet'!$J$69 -> 86276.492 | G48: =G7*'Balance Sheet'!$J$69 -> 102279.18 | H48: =H7*'Balance Sheet'!$J$69 -> 121250.06 | I48: =I7*'Balance Sheet'!$J$69 -> 143739.7 | J48: =J7*'Balance Sheet'!$J$69 -> 170400.74 | ... L48: =L7*'Balance Sheet'!$J$69 -> 143339.55
A49: Total Long Term liabilities | B49: =B45+B48 -> 273711 | C49: =C45+C48 -> 256081.51 | D49: =D45+D48 -> 265686.76 | E49: =E45+E48 -> 277073.6 | F49: =F45+F48 -> 290572.49 | G49: =G45+G48 -> 306575.18 | H49: =H45+H48 -> 325546.06 | I49: =I45+I48 -> 348035.7 | ... L49: =L45+L48 -> 347635.55
A50: Common stock ($0.01 par value; 125,000 shares authorized) | B50: 1502 | C50: =B50+C61 -> 32455.309 | D50: =B50+D61 -> -391877.23 | E50: =B50+E61 -> -894915.57 | F50: =E50 -> -894915.57 | G50: =F50 -> -894915.57 | H50: =G50 -> -894915.57 | I50: =H50 -> -894915.57 | J50: =I50 -> -894915.57 | K50: =J50 -> -894915.57 | L50: =K50 -> -894915.57
A51: Additional paid-in capital | B51: 253466 | C51: =B51 -> 253466 | D51: =C51 -> 253466 | E51: =D51 -> 253466 | F51: =E51 -> 253466 | G51: =F51 -> 253466 | H51: =G51 -> 253466 | I51: =H51 -> 253466 | J51: =I51 -> 253466 | ... L51: =K51 -> 253466
A52: Retained earnings | B52: 2307699 | C52: =B52+C16 -> 3203979.8 | D52: =C52+D16 -> 4266504 | E52: =D52+E16 -> 5526106.7 | F52: =E52+F16 -> 7019342.3 | G52: =F52+G16 -> 8789545.3 | H52: =G52+H16 -> 10372601 | I52: =H52+I16 -> 11549580 | J52: =I52+J16 -> 12117544 | ... L52: =K52+L16 -> 14233167
A53: Accumulated other comprehensive loss (Note 10) | B53: Assumption: Relates to unrealized gains/losses; non-cash, non-operating.
A54: Total stockholders' equity | B54: =SUM(B50:B52) -> 2562667 | C54: =SUM(C50:C52) -> 3489901.1 | D54: =SUM(D50:D52) -> 4128092.8 | E54: =SUM(E50:E52) -> 4884657.1 | F54: =SUM(F50:F52) -> 6377892.7 | G54: =SUM(G50:G52) -> 8148095.7 | H54: =SUM(H50:H52) -> 9731151.6 | I54: =SUM(I50:I52) -> 10908130 | ... L54: =SUM(L50:L52) -> 13591718
A55: Total liabilities and stockholders' equity | B55: =B54+B49+B44 -> 3576323 | C55: =C54+C49+C44 -> 4637574.8 | D55: =D54+D49+D44 -> 5450745.6 | E55: =E54+E49+E44 -> 6414744.3 | F55: =F54+F49+F44 -> 8153889.5 | G55: =G54+G49+G44 -> 10215614 | H55: =H54+H49+H44 -> 12128512 | I55: =I54+I49+I44 -> 13690885 | ... L55: =L54+L49+L44 -> 16407234
A57: Difference needed to balance | B57: =B55-B36 -> 0 | C57: =C55-C36 -> 0 | D57: =D55-D36 -> 0 | E57: =E55-E36 -> 0 | F57: =F55-F36 -> 0 | G57: =G55-G36 -> 0 | H57: =H55-H36 -> 0 | I57: =I55-I36 -> 0 | ... L57: =L55-L36 -> 0
A59: Min cash balance | C59: =C6*'Income Statement'!$J$43 -> 1970228.1 | D59: =D6*'Income Statement'!$J$43 -> 2335668.7 | E59: =E6*'Income Statement'!$J$43 -> 2768891.9 | F59: =F6*'Income Statement'!$J$43 -> 3282469.9 | G59: =G6*'Income Statement'!$J$43 -> 3891307 | H59: =H6*'Income Statement'!$J$43 -> 4280437.7 | I59: =I6*'Income Statement'!$J$43 -> 4622872.7 | J59: =J6*'Income Statement'!$J$43 -> 4946473.8 | ... L59: =L6*'Income Statement'!$J$43 -> 5453487.4
A60: Planned debt repayment | C60: =C61 -> 30953.309 | D60: =D61 -> -393379.23 | E60: =E61 -> -896417.57 | F60: =F61 -> -1492760.2 | G60: =G61 -> -2199713.2 | H60: =H61 -> -3187586.2 | I60: =I61 -> -3896735.1 | J60: =J61 -> -4074797.4 | ... L60: =L61 -> -5930797.1
A61: External Financing Needed (EFN) | C61: =C59+C22+C23+(C27-C28)-C38-((C45+C48))-$B$50-C52 -> 30953.309 | D61: =D59+D22+D23+(D27-D28)-D38-((D45+D48))-$B$50-D52 -> -393379.23 | E61: =E59+E22+E23+(E27-E28)-E38-((E45+E48))-$B$50-E52 -> -896417.57 | F61: =F59+F22+F23+(F27-F28)-F38-((F45+F48))-$B$50-F52 -> -1492760.2 | G61: =G59+G22+G23+(G27-G28)-G38-((G45+G48))-$B$50-G52 -> -2199713.2 | H61: =H59+H22+H23+(H27-H28)-H38-((H45+H48))-$B$50-H52 -> -3187586.2 | I61: =I59+I22+I23+(I27-I28)-I38-((I45+I48))-$B$50-I52 -> -3896735.1 | J61: =J59+J22+J23+(J27-J28)-J38-((J45+J48))-$B$50-J52 -> -4074797.4 | ... L61: =L59+L22+L23+(L27-L28)-L38-((L45+L48))-$B$50-L52 -> -5930797.1
C62: What a Shortfall Means | F62: What a Surplus Means
C63: EFN > 0 (positive number) | F63: EFN < 0 (negative number)
C64: Company needs additional external financing (debt, equity, or other) to support the projected growth. | F64: Company has excess financing: more internal funds than needed.
C65: It means the internally generated funds plus spontaneous liabilities are not enough to finance the new assets required for the growth. | F65: The firm can potentially pay down debt, repurchase stock, or increase dividends since it doesn’t need external funds to support growth.
A69: We have to make an assumption with goodwill as it has practically doubled from 2022 to 2025
A70: first change: current liabilities were not added to total liabilites and stockholders equity
A71: Operating leases cant stay consistent also
A74: NET DEBT | B74: =(B44+B49)-B21 -> -995807 | C74: =(C44+C49)-C21 -> -983795.7 | D74: =(D44+D49)-D21 -> -1206091.4 | E74: =(E44+E49)-E21 -> -1469618.8 | F74: =(F44+F49)-F21 -> -2378368.2 | G74: =(G44+G49)-G21 -> -3455673.8 | H74: =(H44+H49)-H21 -> -4562387.5 | I74: =(I44+I49)-I21 -> -5297989.7 | ... L74: =(L44+L49)-L21 -> -7873113.5
A76: RETURN ON DEBT | B76: =B16/B74 -> -0.90214971 | C76: =C16/C74 -> -0.91104361 | D76: =D16/D74 -> -0.88096493 | E76: =E16/E74 -> -0.85709487 | F76: =F16/F74 -> -0.62784038 | G76: =G16/G74 -> -0.51225988 | H76: =H16/H74 -> -0.34697969 | I76: =I16/I74 -> -0.22215573 | ... L76: =L16/L74 -> -0.31510507
B80: =(B12*(1-0.22))/(B44+B49) -> 0.0027063027 | C80: =(C12*(1-0.22))/(C44+C49) -> 0.005119871 | D80: =(D12*(1-0.22))/(D44+D49) -> 0.0052665519 | E80: =(E12*(1-0.22))/(E44+E49) -> 0.0053969798 | F80: =(F12*(1-0.22))/(F44+F49) -> 0.0055121311 | G80: =(G12*(1-0.22))/(G44+G49) -> 0.0056131564 | H80: =(H12*(1-0.22))/(H44+H49) -> 0.0053249527 | I80: =(I12*(1-0.22))/(I44+I49) -> 0.0049544792 | ... L80: =(L12*(1-0.22))/(L44+L49) -> 0.0057766666

Sheet Sheet1
A1: Income Statement (in thousands of dollars)
A2: Year | B2: 2025 | C2: 2026 | D2: 2027 | E2: 2028 | F2: 2029 | G2: 2030 | H2: 2031 | I2: 2032 | J2: 2033 | K2: 2034 | L2: 2035
A3: Net sales | B3: 4985612 | C3: =B3*(1+'Income Statement'!$J$33) -> 5910350.4 | D3: =C3*(1+'Income Statement'!$J$33) -> 7006610.5 | E3: =D3*(1+'Income Statement'!$J$33) -> 8306206.5 | F3: =E3*(1+'Income Statement'!$J$33) -> 9846853.5 | G3: =F3*(1+'Income Statement'!$J$33) -> 11673262 | H3: =G3*(1+'Income Statement'!$J$33) -> 13838435 | I3: =H3*(1+'Income Statement'!$J$33) -> 16405207 | J3: =I3*(1+'Income Statement'!$J$33) -> 19448068 | ... L3: =K3*(1+'Income Statement'!$J$33) -> 27331658
A4: Cost of Sales | B4: 2099949 | C4: ='Income Statement'!$J$36*Proforma!C3 -> 2752309.9 | D4: ='Income Statement'!$J$36*Proforma!D3 -> 3262812.3 | E4: ='Income Statement'!$J$36*Proforma!E3 -> 3868003.3 | F4: ='Income Statement'!$J$36*Proforma!F3 -> 4585446 | G4: ='Income Statement'!$J$36*Proforma!G3 -> 5435961.1 | H4: ='Income Statement'!$J$36*Proforma!H3 -> 6444230.8 | I4: ='Income Statement'!$J$36*Proforma!I3 -> 7639515.8 | J4: ='Income Statement'!$J$36*Proforma!J3 -> 9056504.1 | ... L4: ='Income Statement'!$J$36*Proforma!L3 -> 12727705
A5: Gross Profit | B5: =B3-B4 -> 2885663 | C5: =C3-C4 -> 3158040.4 | D5: =D3-D4 -> 3743798.2 | E5: =E3-E4 -> 4438203.2 | F5: =F3-F4 -> 5261407.4 | G5: =G3-G4 -> 6237300.7 | H5: =H3-H4 -> 7394204.1 | I5: =I3-I4 -> 8765691.5 | ... L5: =L3-L4 -> 14603953
A6: Selling, general, and administrative expenses | B6: 1706571 | C6: =C3*'Income Statement'!$J$37 -> 2006863.1 | D6: =D3*'Income Statement'!$J$37 -> 2379098.9 | E6: =E3*'Income Statement'!$J$37 -> 2820377.5 | F6: =F3*'Income Statement'!$J$37 -> 3343505.1 | G6: =G3*'Income Statement'!$J$37 -> 3963663.1 | H6: =H3*'Income Statement'!$J$37 -> 4698849 | I6: =I3*'Income Statement'!$J$37 -> 5570398.1 | J6: =J3*'Income Statement'!$J$37 -> 6603603.4 | ... L6: =L3*'Income Statement'!$J$37 -> 9280481
A7: EBIT, Earnings before interest & taxes | B7: =B5-B6 -> 1179092 | C7: =C5-C6 -> 1151177.4 | D7: =D5-D6 -> 1364699.4 | E7: =E5-E6 -> 1617825.7 | F7: =F5-F6 -> 1917902.3 | G7: =G5-G6 -> 2273637.6 | H7: =H5-H6 -> 2695355.1 | I7: =I5-I6 -> 3195293.4 | ... L7: =L5-L6 -> 5323472.1
A8: Interest income | B8: Assumption: Other income, net is excluded from the pro forma projections because it consists primarily of non-operating and non-recurring items (e.g., foreign currency gains/losses, asset sale gains/losses). These items are not reflective of the company’s ongoing operations and are immaterial relative to total EBIT.
A9: Interest expense | B9: 3517 | C9: =C3*'Income Statement'!$J$40 -> 7533.2585 | D9: =D3*'Income Statement'!$J$40 -> 8930.5379 | E9: =E3*'Income Statement'!$J$40 -> 10586.987 | F9: =F3*'Income Statement'!$J$40 -> 12550.676 | G9: =G3*'Income Statement'!$J$40 -> 14878.593 | H9: =H3*'Income Statement'!$J$40 -> 17638.296 | I9: =I3*'Income Statement'!$J$40 -> 20909.872 | J9: =J3*'Income Statement'!$J$40 -> 24788.264 | ... L9: =L3*'Income Statement'!$J$40 -> 34836.588
A10: Other income, net | B10: Assumption: Other income excluded due to immateriality and non-recurring nature.
A11: EBT, Income before income taxes | B11: =B7-B9 -> 1175575 | C11: =C7-C9 -> 1143644.1 | D11: =D7-D9 -> 1355768.8 | E11: =E7-E9 -> 1607238.7 | F11: =F7-F9 -> 1905351.7 | G11: =G7-G9 -> 2258759 | H11: =H7-H9 -> 2677716.8 | I11: =I7-I9 -> 3174383.5 | ... L11: =L7-L9 -> 5288635.6
A12: Income tax expense | B12: 277208 | C12: =C11*'Income Statement'!$J$38 -> 247363.32 | D12: =D11*'Income Statement'!$J$38 -> 293244.62 | E12: =E11*'Income Statement'!$J$38 -> 347636.05 | F12: =F11*'Income Statement'!$J$38 -> 412116.07 | G12: =G11*'Income Statement'!$J$38 -> 488555.95 | H12: =H11*'Income Statement'!$J$38 -> 579174 | I12: =I11*'Income Statement'!$J$38 -> 686600.01 | J12: =J11*'Income Statement'!$J$38 -> 813951.55 | ... L12: =L11*'Income Statement'!$J$38 -> 1143900
A13: Net Income | B13: =B11-B12 -> 898367 | C13: =C11-C12 -> 896280.78 | D13: =D11-D12 -> 1062524.2 | E13: =E11-E12 -> 1259602.7 | F13: =F11-F12 -> 1493235.6 | G13: =G11-G12 -> 1770203 | H13: =H11-H12 -> 2098542.8 | I13: =I11-I12 -> 2487783.5 | ... L13: =L11-L12 -> 4144735.6
A15: Balance Sheet (in thousands of dollars)
A16: Year | B16: 2025 | C16: 2026 | D16: 2027 | E16: 2028 | F16: 2029 | G16: 2030 | H16: 2031 | I16: 2032 | J16: 2033 | K16: 2034 | L16: 2035
A17: ASSETS
A18: Cash and cash equivalents | B18: =1889188 -> 1889188 | C18: =I13 -> 2487783.5 | D18: =('Income Statement'!$J$43*Proforma!D3) -> 2335668.7 | E18: =('Income Statement'!$J$43*Proforma!E3) -> 2768891.9 | F18: =('Income Statement'!$J$43*Proforma!F3)+693973 -> 3976442.9 | G18: =('Income Statement'!$J$43*Proforma!G3) -> 3891307 | H18: =('Income Statement'!$J$43*Proforma!H3)+1893949 -> 6507021.1 | I18: =('Income Statement'!$J$43*Proforma!I3) -> 5468711.3 | J18: =('Income Statement'!$J$43*Proforma!J3)+3580353 -> 10063409 | K18: =('Income Statement'!$J$43*Proforma!K3) -> 7685541.9 | L18: =('Income Statement'!$J$43*Proforma!L3)+5950369 -> 15061436
A19: Trade accounts receivable, net of allowances | B19: 332872 | C19: =C3*('Balance Sheet'!$J$51/365) -> 971564.44 | D19: =D3*('Balance Sheet'!$J$51/365) -> 1151771.6 | E19: =E3*('Balance Sheet'!$J$51/365) -> 1365403.8 | F19: =F3*('Balance Sheet'!$J$51/365) -> 1618660.8 | G19: =G3*('Balance Sheet'!$J$51/365) -> 1918892.3 | H19: =H3*('Balance Sheet'!$J$51/365) -> 2274811.2 | I19: =I3*('Balance Sheet'!$J$51/365) -> 2696746.4 | J19: =J3*('Balance Sheet'!$J$51/365) -> 3196942.7 | ... L19: =L3*('Balance Sheet'!$J$51/365) -> 4492875.2
A20: Inventories | B20: 495226 | C20: =C4 * ('Balance Sheet'!$J$52/365) -> 603246.02 | D20: =D4 * ('Balance Sheet'!$J$52/365) -> 715136.94 | E20: =E4 * ('Balance Sheet'!$J$52/365) -> 847781.55 | F20: =F4 * ('Balance Sheet'!$J$52/365) -> 1005029.3 | G20: =G4 * ('Balance Sheet'!$J$52/365) -> 1191443.5 | H20: =H4 * ('Balance Sheet'!$J$52/365) -> 1412434.1 | I20: =I4 * ('Balance Sheet'!$J$52/365) -> 1674414.4 | J20: =J4 * ('Balance Sheet'!$J$52/365) -> 1984987.2 | ... L20: =L4 * ('Balance Sheet'!$J$52/365) -> 2789633.9
A21: Prepaid expenses & Other Current Assets | B21: 106576 | C21: ='Balance Sheet'!$J$53*Proforma!C4 -> 142160.56 | D21: ='Balance Sheet'!$J$53*Proforma!D4 -> 168528.7 | E21: ='Balance Sheet'!$J$53*Proforma!E4 -> 199787.64 | F21: ='Balance Sheet'!$J$53*Proforma!F4 -> 236844.53 | G21: ='Balance Sheet'!$J$53*Proforma!G4 -> 280774.79 | H21: ='Balance Sheet'!$J$53*Proforma!H4 -> 332853.3 | I21: ='Balance Sheet'!$J$53*Proforma!I4 -> 394591.4 | J21: ='Balance Sheet'!$J$53*Proforma!J4 -> 467780.77 | ... L21: ='Balance Sheet'!$J$53*Proforma!L4 -> 657403.28
A22: Income tax receivable | B22: Non-operating; reflects timing of tax refunds, not a recurring operating driver. Including it complicates projections without improving accuracy.
A23: Total current assets | B23: =SUM(B18:B21) -> 2823862 | C23: =SUM(C18:C21) -> 4204754.5 | D23: =SUM(D18:D21) -> 4371106 | E23: =SUM(E18:E21) -> 5181864.9 | F23: =SUM(F18:F21) -> 6836977.5 | G23: =SUM(G18:G21) -> 7282417.7 | H23: =SUM(H18:H21) -> 10527120 | I23: =SUM(I18:I21) -> 10234464 | ... L23: =SUM(L18:L21) -> 23001348
A24: PPE gross | B24: 728563 | C24: =C3*'Balance Sheet'!$J$58 -> 998730.72 | D24: =D3*'Balance Sheet'!$J$58 -> 1183976.7 | E24: =E3*'Balance Sheet'!$J$58 -> 1403582.4 | F24: =F3*'Balance Sheet'!$J$58 -> 1663920.8 | G24: =G3*'Balance Sheet'!$J$58 -> 1972547.2 | H24: =H3*'Balance Sheet'!$J$58 -> 2338418.1 | I24: =I3*'Balance Sheet'!$J$58 -> 2772151.1 | J24: =J3*'Balance Sheet'!$J$58 -> 3286333.7 | ... L24: =L3*'Balance Sheet'!$J$58 -> 4618502.2
A25: Depreciation | B25: 402964 | C25: ='Balance Sheet'!$J$57*Proforma!C24 -> 547069.98 | D25: ='Balance Sheet'!$J$57*Proforma!D24 -> 648541.29 | E25: ='Balance Sheet'!$J$57*Proforma!E24 -> 768833.65 | F25: ='Balance Sheet'!$J$57*Proforma!F24 -> 911438 | G25: ='Balance Sheet'!$J$57*Proforma!G24 -> 1080492.8 | H25: ='Balance Sheet'!$J$57*Proforma!H24 -> 1280904.1 | I25: ='Balance Sheet'!$J$57*Proforma!I24 -> 1518488.1 | J25: ='Balance Sheet'!$J$57*Proforma!J24 -> 1800139.4 | ... L25: ='Balance Sheet'!$J$57*Proforma!L24 -> 2529855
A26: PPE net
A27: Operating lease assets | B27: 237352 | C27: ='Balance Sheet'!$J$54 -> 214882.5 | D27: ='Balance Sheet'!$J$54 -> 214882.5 | E27: ='Balance Sheet'!$J$54 -> 214882.5 | F27: ='Balance Sheet'!$J$54 -> 214882.5 | G27: ='Balance Sheet'!$J$54 -> 214882.5 | H27: ='Balance Sheet'!$J$54 -> 214882.5 | I27: ='Balance Sheet'!$J$54 -> 214882.5 | J27: ='Balance Sheet'!$J$54 -> 214882.5 | ... L27: ='Balance Sheet'!$J$54 -> 214882.5
A28: Goodwill | B28: 13990 | C28: ='Balance Sheet'!$J$55 -> 13990 | D28: ='Balance Sheet'!$J$55 -> 13990 | E28: ='Balance Sheet'!$J$55 -> 13990 | F28: ='Balance Sheet'!$J$55 -> 13990 | G28: ='Balance Sheet'!$J$55 -> 13990 | H28: ='Balance Sheet'!$J$55 -> 13990 | I28: ='Balance Sheet'!$J$55 -> 13990 | J28: ='Balance Sheet'!$J$55 -> 13990 | ... L28: ='Balance Sheet'!$J$55 -> 13990
A29: Other intangible assets, net of accumulated amortization | B29: 15699 | C29: ='Balance Sheet'!$J$59 -> 34981.333 | D29: ='Balance Sheet'!$J$59 -> 34981.333 | E29: ='Balance Sheet'!$J$59 -> 34981.333 | F29: ='Balance Sheet'!$J$59 -> 34981.333 | G29: ='Balance Sheet'!$J$59 -> 34981.333 | H29: ='Balance Sheet'!$J$59 -> 34981.333 | I29: ='Balance Sheet'!$J$59 -> 34981.333 | J29: ='Balance Sheet'!$J$59 -> 34981.333 | ... L29: ='Balance Sheet'!$J$59 -> 34981.333
A30: Deferred tax assets, net | B30: Non-operating; timing difference in taxes. Often excluded in operating asset base for ROIC/valuation.
A31: Other non-current assets | B31: 39546 | C31: =C3*'Balance Sheet'!$J$56 -> 73619.803 | D31: =D3*'Balance Sheet'!$J$56 -> 87274.908 | E31: =E3*'Balance Sheet'!$J$56 -> 103462.78 | F31: =F3*'Balance Sheet'!$J$56 -> 122653.2 | G31: =G3*'Balance Sheet'!$J$56 -> 145403.09 | H31: =H3*'Balance Sheet'!$J$56 -> 172372.67 | I31: =I3*'Balance Sheet'!$J$56 -> 204344.59 | J31: =J3*'Balance Sheet'!$J$56 -> 242246.71 | ... L31: =L3*'Balance Sheet'!$J$56 -> 340445.34
A32: Total Non-current Assets | B32: =B24-B25+B27+B28+B29+B31 -> 632186 | C32: =C24-C25+C27+C28+C29+C31 -> 789134.38 | D32: =D24-D25+D27+D28+D29+D31 -> 886564.16 | E32: =E24-E25+E27+E28+E29+E31 -> 1002065.3 | F32: =F24-F25+F27+F28+F29+F31 -> 1138989.9 | G32: =G24-G25+G27+G28+G29+G31 -> 1301311.3 | H32: =H24-H25+H27+H28+H29+H31 -> 1493740.4 | I32: =I24-I25+I27+I28+I29+I31 -> 1721861.5 | ... L32: =L24-L25+L27+L28+L29+L31 -> 2692946.4
A33: Total assets | B33: =B23+B32 -> 3456048 | C33: =C23+C32 -> 4993888.9 | D33: =D23+D32 -> 5257670.1 | E33: =E23+E32 -> 6183930.2 | F33: =F23+F32 -> 7975967.4 | G33: =G23+G32 -> 8583729 | H33: =H23+H32 -> 12020860 | I33: =I23+I32 -> 11956325 | ... L33: =L23+L32 -> 25694295
A34: LIABILITIES AND STOCKHOLDERS' EQUITY
A35: Trade accounts payable | B35: 417955 | C35: =C4*('Balance Sheet'!$J$63/365) -> 504182.66 | D35: =D4*('Balance Sheet'!$J$63/365) -> 597699.17 | E35: =E4*('Balance Sheet'!$J$63/365) -> 708561.26 | F35: =F4*('Balance Sheet'!$J$63/365) -> 839986.2 | G35: =G4*('Balance Sheet'!$J$63/365) -> 995788.03 | H35: =H4*('Balance Sheet'!$J$63/365) -> 1180488.2 | I35: =I4*('Balance Sheet'!$J$63/365) -> 1399446.8 | J35: =J4*('Balance Sheet'!$J$63/365) -> 1659018.2 | ... L35: =L4*('Balance Sheet'!$J$63/365) -> 2331528.1
A36: Accrued payroll | B36: 125417 | C36: =C4*'Balance Sheet'!$J$64 -> 143389.27 | D36: =D4*'Balance Sheet'!$J$64 -> 169985.31 | E36: =E4*'Balance Sheet'!$J$64 -> 201514.43 | F36: =F4*'Balance Sheet'!$J$64 -> 238891.61 | G36: =G4*'Balance Sheet'!$J$64 -> 283201.57 | H36: =H4*'Balance Sheet'!$J$64 -> 335730.19 | I36: =I4*'Balance Sheet'!$J$64 -> 398001.9 | J36: =J4*'Balance Sheet'!$J$64 -> 471823.86 | ... L36: =L4*'Balance Sheet'!$J$64 -> 663085.3
A37: Operating lease liabilities | B37: 54453 | C37: ='Balance Sheet'!$J$67*C3 -> 93291.11 | D37: ='Balance Sheet'!$J$67*D3 -> 110594.88 | E37: ='Balance Sheet'!$J$67*E3 -> 131108.17 | F37: ='Balance Sheet'!$J$67*F3 -> 155426.3 | G37: ='Balance Sheet'!$J$67*G3 -> 184254.99 | H37: ='Balance Sheet'!$J$67*H3 -> 218430.87 | I37: ='Balance Sheet'!$J$67*I3 -> 258945.73 | J37: ='Balance Sheet'!$J$67*J3 -> 306975.35 | ... L37: ='Balance Sheet'!$J$67*L3 -> 431412.78
A38: Other accrued expenses | B38: 142120 | C38: =C4*'Balance Sheet'!$J$65 -> 150729.21 | D38: =D4*'Balance Sheet'!$J$65 -> 178686.68 | E38: =E4*'Balance Sheet'!$J$65 -> 211829.74 | F38: =F4*'Balance Sheet'!$J$65 -> 251120.22 | G38: =G4*'Balance Sheet'!$J$65 -> 297698.35 | H38: =H4*'Balance Sheet'!$J$65 -> 352915.86 | I38: =I4*'Balance Sheet'!$J$65 -> 418375.2 | J38: =J4*'Balance Sheet'!$J$65 -> 495976.02 | ... L38: =L4*'Balance Sheet'!$J$65 -> 697027.93
A39: Income tax payable | B39: Non-operating liability; reflects timing of tax payments.
A40: Value added tax payable | B40: Government tax pass-through, not part of operations profitably.
A41: Total current liabilities | B41: =SUM(B35:B38) -> 739945 | C41: =SUM(C35:C38) -> 891592.25 | D41: =SUM(D35:D38) -> 1056966 | E41: =SUM(E35:E38) -> 1253013.6 | F41: =SUM(F35:F38) -> 1485424.3 | G41: =SUM(G35:G38) -> 1760942.9 | H41: =SUM(H35:H38) -> 2087565.1 | I41: =SUM(I35:I38) -> 2474769.7 | ... L41: =SUM(L35:L38) -> 4123054.1
A42: Long-term operating lease liabilities | B42: 222522 | C42: ='Balance Sheet'!$J$61 -> 204296 | D42: ='Balance Sheet'!$J$61 -> 204296 | E42: ='Balance Sheet'!$J$61 -> 204296 | F42: ='Balance Sheet'!$J$61 -> 204296 | G42: ='Balance Sheet'!$J$61 -> 204296 | H42: ='Balance Sheet'!$J$61 -> 204296 | I42: ='Balance Sheet'!$J$61 -> 204296 | J42: ='Balance Sheet'!$J$61 -> 204296 | ... L42: ='Balance Sheet'!$J$61 -> 204296
A43: Income tax liability | B43: Non-operating; timing difference.
A44: Deferred rent obligations | B44: Obsolete under ASC 842 unless separate.
A45: Other long-term liabilities | B45: =51189 -> 51189 | C45: =(C4*'Balance Sheet'!$J$69) -> 51785.507 | D45: =(D4*'Balance Sheet'!$J$69) -> 61390.756 | E45: =E4*'Balance Sheet'!$J$69 -> 72777.6 | F45: =(F4*'Balance Sheet'!$J$69) -> 86276.492 | G45: =(G4*'Balance Sheet'!$J$69)+62825 -> 165104.18 | H45: =(H4*'Balance Sheet'!$J$69) -> 121250.06 | I45: =(I4*'Balance Sheet'!$J$69)+62825 -> 206564.7 | J45: =(J4*'Balance Sheet'!$J$69) -> 170400.74 | K45: =(K4*'Balance Sheet'!$J$69)+62826 -> 264832.91 | L45: =(L4*'Balance Sheet'!$J$69) -> 239475.44
A46: Total Long Term liabilities | B46: =B42+B45 -> 273711 | C46: =C42+C45 -> 256081.51 | D46: =D42+D45 -> 265686.76 | E46: =E42+E45 -> 277073.6 | F46: =F42+F45 -> 290572.49 | G46: =G42+G45 -> 369400.18 | H46: =H42+H45 -> 325546.06 | I46: =I42+I45 -> 410860.7 | ... L46: =L42+L45 -> 443771.44
A47: Common stock ($0.01 par value; 125,000 shares authorized) | B47: 1502 | C47: =B47+C58 -> 1502 | D47: =B47+D58 -> 1502 | E47: =B47+E58 -> 1502 | F47: =E47 -> 1502 | G47: =F47 -> 1502 | H47: =G47 -> 1502 | I47: =H47 -> 1502 | J47: =I47 -> 1502 | K47: =J47 -> 1502 | L47: =K47 -> 1502
A48: Additional paid-in capital | B48: 253466 | C48: =B48 -> 253466 | D48: =C48 -> 253466 | E48: =D48 -> 253466 | F48: =E48 -> 253466 | G48: =F48 -> 253466 | H48: =G48 -> 253466 | I48: =H48 -> 253466 | J48: =I48 -> 253466 | ... L48: =K48 -> 253466
A49: Retained earnings | B49: 2307699 | C49: =B49+C13 -> 3203979.8 | D49: =C49+D13 -> 4266504 | E49: =D49+E13 -> 5526106.7 | F49: =E49+F13 -> 7019342.3 | G49: =F49+G13 -> 8789545.3 | H49: =G49+H13 -> 10888088 | I49: =H49+I13 -> 13375872 | J49: =I49+J13 -> 16325093 | ... L49: =K49+L13 -> 23966075
A50: Accumulated other comprehensive loss (Note 10) | B50: Relates to unrealized gains/losses; non-cash, non-operating.
A51: Total stockholders' equity | B51: =SUM(B47:B49) -> 2562667 | C51: =SUM(C47:C49) -> 3458947.8 | D51: =SUM(D47:D49) -> 4521472 | E51: =SUM(E47:E49) -> 5781074.7 | F51: =SUM(F47:F49) -> 7274310.3 | G51: =SUM(G47:G49) -> 9044513.3 | H51: =SUM(H47:H49) -> 11143056 | I51: =SUM(I47:I49) -> 13630840 | ... L51: =SUM(L47:L49) -> 24221043
A52: Total liabilities and stockholders' equity | B52: =B51+B46+B41 -> 3576323 | C52: =C51+C46+C41 -> 4606621.5 | D52: =D51+D46+D41 -> 5844124.8 | E52: =E51+E46+E41 -> 7311161.9 | F52: =F51+F46+F41 -> 9050307.1 | G52: =G51+G46+G41 -> 11174856 | H52: =H51+H46+H41 -> 13556167 | I52: =I51+I46+I41 -> 16516470 | ... L52: =L51+L46+L41 -> 28787869
A55: Plug into cash | B55: =B52-B33 -> 120275 | C55: =C52-C33 -> -387267.34 | D55: =D52-D33 -> 586454.66 | E55: =E52-E33 -> 1127231.7 | F55: =F52-F33 -> 1074339.7 | G55: =G52-G33 -> 2591127.4 | H55: =H52-H33 -> 1535307.1 | I55: =I52-I33 -> 4560144.9 | ... L55: =L52-L33 -> 3093573.7
C63: Your company needs additional external financing (debt, equity, or other) to support the projected growth. | F63: Your company has excess financing — more internal funds than needed.
C65: It means the internally generated funds plus spontaneous liabilities are not enough to finance the new assets required for the growth. | F65: The firm can potentially pay down debt, repurchase stock, or increase dividends since it doesn’t need external funds to support growth.
A66: first change: current liabilities were not added to total liabilites and stockholders equity
A67: We have to make an assumption with goodwill as it has practically doubled from 2022 to 2025
A68: Operating leases cant stay consistent also

Sheet Working Capital
A1: DECKERS OUTDOOR CORPORATION AND SUBSIDIARIES
A2: NET WORKING CAPITAL
A3: (dollar and share data amounts in thousands)
C4: Historical | I4: Projected
A5: Year | C5: 2020 | D5: 2021 | E5: 2022 | F5: 2023 | G5: 2024 | H5: 2025 | I5: 2026 | J5: 2027 | K5: 2028 | L5: 2029 | M5: 2030 | N5: 2031 | O5: 2032 | P5: 2033 | Q5: 2034 | R5: 2035
A6: Assets
B7: Trade accounts receivable, net of allowances | C7: ='Balance Sheet'!D8 -> 185596 | D7: ='Balance Sheet'!E8 -> 215718 | E7: ='Balance Sheet'!F8 -> 302688 | F7: ='Balance Sheet'!G8 -> 301511 | G7: ='Balance Sheet'!H8 -> 296565 | H7: ='Balance Sheet'!I8 -> 332872 | I7: ='Balance Sheet'!J8 -> 971564.44 | J7: ='Balance Sheet'!K8 -> 1151771.6 | ... R7: ='Balance Sheet'!S8 -> 4492875.2
B8: Inventories | C8: ='Balance Sheet'!D9 -> 311620 | D8: ='Balance Sheet'!E9 -> 278242 | E8: ='Balance Sheet'!F9 -> 506796 | F8: ='Balance Sheet'!G9 -> 532852 | G8: ='Balance Sheet'!H9 -> 474311 | H8: ='Balance Sheet'!I9 -> 495226 | I8: ='Balance Sheet'!J9 -> 603246.02 | J8: ='Balance Sheet'!K9 -> 715136.94 | ... R8: ='Balance Sheet'!S9 -> 2789633.9
B9: Cash and cash equivalents | C9: ='Balance Sheet'!D7 -> 649436 | D9: ='Balance Sheet'!E7 -> 1089361 | E9: ='Balance Sheet'!F7 -> 843527 | F9: ='Balance Sheet'!G7 -> 981795 | G9: ='Balance Sheet'!H7 -> 1502051 | H9: ='Balance Sheet'!I7 -> 1889188 | I9: ='Balance Sheet'!J7 -> 2131469.5 | J9: ='Balance Sheet'!K7 -> 2335668.7 | ... R9: ='Balance Sheet'!S7 -> 9111067.1
B10: Total Current Assets | C10: ='Balance Sheet'!D13 -> 1194111 | D10: ='Balance Sheet'!E13 -> 1650799 | E10: ='Balance Sheet'!F13 -> 1752128 | F10: ='Balance Sheet'!G13 -> 1910253 | G10: ='Balance Sheet'!H13 -> 2443483 | H10: ='Balance Sheet'!I13 -> 2860475 | I10: ='Balance Sheet'!J13 -> 3687199.1 | J10: ='Balance Sheet'!K13 -> 4371106 | ... R10: ='Balance Sheet'!S13 -> 17050979
A11: Liabilities
B12: Accrued payroll | C12: ='Balance Sheet'!D27 -> 42309 | D12: ='Balance Sheet'!E27 -> 79152 | E12: ='Balance Sheet'!F27 -> 67553 | F12: ='Balance Sheet'!G27 -> 63781 | G12: ='Balance Sheet'!H27 -> 123653 | H12: ='Balance Sheet'!I27 -> 125417 | I12: ='Balance Sheet'!J27 -> 143389.27 | J12: ='Balance Sheet'!K27 -> 169985.31 | ... R12: ='Balance Sheet'!S27 -> 663085.3
B13: Other accrued expenses | C13: ='Balance Sheet'!D29 -> 46281 | D13: ='Balance Sheet'!E29 -> 68995 | E13: ='Balance Sheet'!F29 -> 81400 | F13: ='Balance Sheet'!G29 -> 86753 | G13: ='Balance Sheet'!H29 -> 106785 | H13: ='Balance Sheet'!I29 -> 142120 | I13: ='Balance Sheet'!J29 -> 150729.21 | J13: ='Balance Sheet'!K29 -> 178686.68 | ... R13: ='Balance Sheet'!S29 -> 697027.93
B14: Total Current Liabilities | C14: ='Balance Sheet'!D32 -> 300946 | D14: ='Balance Sheet'!E32 -> 468368 | E14: ='Balance Sheet'!F32 -> 541684 | F14: ='Balance Sheet'!G32 -> 497380 | G14: ='Balance Sheet'!H32 -> 719993 | H14: ='Balance Sheet'!I32 -> 769941 | I14: ='Balance Sheet'!J32 -> 891592.25 | J14: ='Balance Sheet'!K32 -> 1056966 | ... R14: ='Balance Sheet'!S32 -> 4123054.1
A15: Net Working Capital (Total current assets – Total current liabilities)
B16: Working Capital | C16: =C10-C14 -> 893165 | D16: =D10-D14 -> 1182431 | E16: =E10-E14 -> 1210444 | F16: =F10-F14 -> 1412873 | G16: =G10-G14 -> 1723490 | H16: =H10-H14 -> 2090534 | I16: =I10-I14 -> 2795606.8 | J16: =J10-J14 -> 3314139.9 | ... R16: =R10-R14 -> 12927925
B17: Increase in Net Working Capital | C17: =D16-C16 -> 289266 | D17: =D16-C16 -> 289266 | E17: =E16-D16 -> 28013 | F17: =F16-E16 -> 202429 | G17: =G16-F16 -> 310617 | H17: =H16-G16 -> 367044 | I17: =I16-H16 -> 705072.82 | J17: =J16-I16 -> 518533.11 | K17: =K16-J16 -> 614711.36 | ... R17: =R16-Q16 -> 2022714

Sheet Capital Expenditure
A1: DECKERS OUTDOOR CORPORATION AND SUBSIDIARIES
A2: CAPITAL EXPENDITURE
A3: (dollar and share data amounts in thousands, assume fixed asset turnover is constant)
C4: Historical | I4: Projected
A5: Year | C5: 2020 | D5: 2021 | E5: 2022 | F5: 2023 | G5: 2024 | H5: 2025 | I5: 2026 | J5: 2027 | K5: 2028 | L5: 2029 | M5: 2030 | N5: 2031 | O5: 2032 | P5: 2033 | Q5: 2034 | R5: 2035
A6: Depreciation | C6: 235939 | D6: 266905 | E6: 282571 | F6: 317508 | G6: 349138 | H6: 402964 | I6: 547069.98 | J6: 648541.29 | K6: 768833.65 | L6: 911438 | M6: 1080492.8 | N6: 1280904.1 | O6: 1518488.1 | P6: 1800139.4 | Q6: 2134031.8 | R6: 2529855
A7: PPE net | C7: 209037 | D7: 206210 | E7: 222449 | F7: 266679 | G7: 302122 | H7: 325599 | I7: 451660.74 | J7: 535435.42 | K7: 634748.73 | L7: 752482.83 | M7: 892054.4 | N7: 1057513.9 | O7: 1253663.1 | P7: 1486194.3 | Q7: 1761855.7 | R7: 2088647.2
A8: change in PPE net | C8: =D7-C7 -> -2827 | D8: =D7-C7 -> -2827 | E8: =E7-D7 -> 16239 | F8: =F7-E7 -> 44230 | G8: =G7-F7 -> 35443 | H8: =H7-G7 -> 23477 | I8: =I7-H7 -> 126061.74 | J8: =J7-I7 -> 83774.673 | K8: =K7-J7 -> 99313.318 | ... R8: =R7-Q7 -> 326791.49
A9: CAPEX | C9: =C8+C6 -> 233112 | D9: =D8+D6 -> 264078 | E9: =E8+E6 -> 298810 | F9: =F8+F6 -> 361738 | G9: =G8+G6 -> 384581 | H9: =H8+H6 -> 426441 | I9: =I8+I6 -> 673131.72 | J9: =J8+J6 -> 732315.96 | ... Q9: =Q8+Q6 -> 2409693.2 | R9: =R6+R8 -> 2856646.5

Sheet Free Cash Flow
A1: DECKERS OUTDOOR CORPORATION AND SUBSIDIARIES
A2: FREE CASH FLOW
A3: (dollar and share data amounts in thousands, assume fixed asset turnover is constant)
C4: Historical | I4: Projected
B5: Year | C5: 2020 | D5: 2021 | E5: 2022 | F5: 2023 | G5: 2024 | H5: 2025 | I5: 2026 | J5: 2027 | K5: 2028 | L5: 2029 | M5: 2030 | N5: 2031 | O5: 2032 | P5: 2033 | Q5: 2034 | R5: 2035
B6: EBIT | C6: ='Income Statement'!D10 -> 338135 | D6: ='Income Statement'!E10 -> 504205 | E6: ='Income Statement'!F10 -> 564707 | F6: ='Income Statement'!G10 -> 652751 | G6: ='Income Statement'!H10 -> 927514 | H6: ='Income Statement'!I10 -> 1179092 | I6: =Proforma!C7 -> 1151177.4 | J6: =Proforma!D7 -> 1364699.4 | K6: =Proforma!E7 -> 1617825.7 | L6: =Proforma!F7 -> 1917902.3 | M6: =Proforma!G7 -> 2273637.6 | N6: =Proforma!H7 -> 2695355.1 | O6: =Proforma!I7 -> 3195293.4 | P6: =Proforma!J7 -> 3787960.9 | ... R6: =Proforma!L7 -> 5323472.1
B7: Taxes (35%) | C7: =35%*C6 -> 118347.25 | D7: =35%*D6 -> 176471.75 | E7: =35%*E6 -> 197647.45 | F7: =35%*F6 -> 228462.85 | G7: =35%*G6 -> 324629.9 | H7: =35%*H6 -> 412682.2 | I7: =35%*I6 -> 402912.08 | J7: =35%*J6 -> 477644.78 | ... R7: =35%*R6 -> 1863215.3
B8: Unlevered Net Income | C8: =C6-C7 -> 219787.75 | D8: =D6-D7 -> 327733.25 | E8: =E6-E7 -> 367059.55 | F8: =F6-F7 -> 424288.15 | G8: =G6-G7 -> 602884.1 | H8: =H6-H7 -> 766409.8 | I8: =I6-I7 -> 748265.29 | J8: =J6-J7 -> 887054.59 | ... R8: =R6-R7 -> 3460256.9
B9: Depreciation (+) | C9: =+'Balance Sheet'!D15 -> 235939 | D9: =+'Balance Sheet'!E15 -> 266905 | E9: =+'Balance Sheet'!F15 -> 282571 | F9: =+'Balance Sheet'!G15 -> 317508 | G9: =+'Balance Sheet'!H15 -> 349138 | H9: =+'Balance Sheet'!I15 -> 402964 | I9: =Proforma!C25 -> 547069.98 | J9: =Proforma!D25 -> 648541.29 | K9: =Proforma!E25 -> 768833.65 | L9: =Proforma!F25 -> 911438 | M9: =Proforma!G25 -> 1080492.8 | N9: =Proforma!H25 -> 1280904.1 | O9: =Proforma!I25 -> 1518488.1 | P9: =Proforma!J25 -> 1800139.4 | ... R9: =Proforma!L25 -> 2529855
B10: Increase in NWC (-) | C10: ='Working Capital'!C17 -> 289266 | D10: ='Working Capital'!D17 -> 289266 | E10: ='Working Capital'!E17 -> 28013 | F10: ='Working Capital'!F17 -> 202429 | G10: ='Working Capital'!G17 -> 310617 | H10: ='Working Capital'!H17 -> 367044 | I10: ='Working Capital'!I17 -> 705072.82 | J10: ='Working Capital'!J17 -> 518533.11 | ... R10: ='Working Capital'!R17 -> 2022714
B11: Capital Expenditure (-) | C11: ='Capital Expenditure'!C9 -> 233112 | D11: ='Capital Expenditure'!D9 -> 264078 | E11: ='Capital Expenditure'!E9 -> 298810 | F11: ='Capital Expenditure'!F9 -> 361738 | G11: ='Capital Expenditure'!G9 -> 384581 | H11: ='Capital Expenditure'!H9 -> 426441 | I11: ='Capital Expenditure'!I9 -> 673131.72 | J11: ='Capital Expenditure'!J9 -> 732315.96 | ... R11: ='Capital Expenditure'!R9 -> 2856646.5
B12: Free Cash Flow To Firm | C12: =C6*(1-0.35)+C9-C11-C10 -> -66651.25 | D12: =D6*(1-0.35)+D9-D11-D10 -> 41294.25 | E12: =E6*(1-0.35)+E9-E11-E10 -> 322807.55 | F12: =F6*(1-0.35)+F9-F11-F10 -> 177629.15 | G12: =G6*(1-0.35)+G9-G11-G10 -> 256824.1 | H12: =H6*(1-0.35)+H9-H11-H10 -> 375888.8 | I12: =I6*(1-0.35)+I9-I11-I10 -> -82869.276 | J12: =J6*(1-0.35)+J9-J11-J10 -> 284746.81 | ... R12: =R6*(1-0.35)+R9-R11-R10 -> 1110751.4

Sheet Capital Structure
B2: Planned Debt and Interest Payment
E3: Year | F3: 2020 | G3: 2021 | H3: 2022 | I3: 2023 | J3: 2024 | K3: 2025 | L3: 2026 | M3: 2027 | N3: 2028 | O3: 2029 | P3: 2030 | Q3: 2031 | R3: 2032 | S3: 2033 | T3: 2034 | U3: 2035
B4: Debt and Interest Table ($ 000)
B5: 1 | C5: Outstanding Debt | F5: ='Balance Sheet'!D25+'Balance Sheet'!D33+'Balance Sheet'!D34 -> 246625 | G5: ='Balance Sheet'!E25+'Balance Sheet'!E33+'Balance Sheet'!E34 -> 176274 | H5: ='Balance Sheet'!F25+'Balance Sheet'!F33+'Balance Sheet'!F34 -> 171972 | I5: ='Balance Sheet'!G25+'Balance Sheet'!G33+'Balance Sheet'!G34 -> 195723 | J5: ='Balance Sheet'!H25+'Balance Sheet'!H33+'Balance Sheet'!H34 -> 213298 | K5: ='Balanced Proforma'!B40+'Balanced Proforma'!B45 -> 276975 | L5: ='Balanced Proforma'!C40+'Balanced Proforma'!C45 -> 297587.11 | M5: ='Balanced Proforma'!D40+'Balanced Proforma'!D45 -> 314890.88 | N5: ='Balanced Proforma'!E40+'Balanced Proforma'!E45 -> 335404.17 | O5: ='Balanced Proforma'!F40+'Balanced Proforma'!F45 -> 359722.3 | P5: ='Balanced Proforma'!G40+'Balanced Proforma'!G45 -> 388550.99 | Q5: ='Balanced Proforma'!H40+'Balanced Proforma'!H45 -> 406976.49 | R5: ='Balanced Proforma'!I40+'Balanced Proforma'!I45 -> 423190.93 | ... U5: ='Balanced Proforma'!L40+'Balanced Proforma'!L45 -> 462520.87
B6: 2 | C6: Interest Term Loan | E6: 0.07465 | F6: =-F5*$E$6 -> -18410.556 | G6: =-G5*$E$6 -> -13158.854 | H6: =-H5*$E$6 -> -12837.71 | I6: =-I5*$E$6 -> -14610.722 | J6: =-J5*$E$6 -> -15922.696 | K6: =-K5*$E$6 -> -20676.184 | L6: =-L5*$E$6 -> -22214.878 | M6: =-M5*$E$6 -> -23506.604 | ... U6: =-U5*$E$6 -> -34527.183
B7: 3 | C7: Net Borrowing | G7: =G5-F5 -> -70351 | H7: =H5-G5 -> -4302 | I7: =I5-H5 -> 23751 | J7: =J5-I5 -> 17575 | K7: =K5-J5 -> 63677 | L7: =L5-K5 -> 20612.11 | M7: =M5-L5 -> 17303.767 | N7: =N5-M5 -> 20513.294 | ... U7: =U5-T5 -> 12296.423
C11: Interest Rate Assumption: Taken out the 10K the mid-point between 6.43% and 8.5%

Sheet Cost of Capital
A1: DECKERS OUTDOOR CORPORATION AND SUBSIDIARIES
A2: COST OF CAPITAL
A3: (dollar and share data amounts in thousands)
B4: DECKER'S CORP | C4: DECK | D4: 101.89 | E4: 2513013 | F4: 276975 | G4: =E4*D4 -> 2.5605089e+08 | H4: =1-I4 -> 0.8735 | I4: =12.65/100 -> 0.1265 | J4: 0.99 | K4: =H4+(J4*I4) -> 0.998735
B6: Firm | C6: Ticker | D6: Current Share Price | E6: Shares Outstanding (in thousand) | F6: Debt | G6: Equity | H6: E/D+E | I6: D/D+E | J6: βE | K6: βU
B7: Sketchers | C7: SKX | D7: 63 | E7: 149233 | F7: 1929135 | G7: =E7*D7 -> 9401679 | H7: =G7/(F7+G7) -> 0.82974436 | I7: =F7/(G7+H7) -> 0.20519046 | J7: 1.17 | K7: =H7+(J7*I7) -> 1.0698172
B8: Crocs | C8: CROX | D8: 74.9 | E8: 56500 | F8: 1701296 | G8: =E8*D8 -> 4231850 | H8: =G8/(F8+G8) -> 0.71325567 | I8: =F8/(G8+H8) -> 0.40202174 | J8: 1.14 | K8: =H8+(J8*I8) -> 1.1715605
B9: V.F. Corporation | C9: VFC | D9: 12.04 | E9: 389695.2 | F9: 5366068 | G9: =E9*D9 -> 4691930.2 | H9: =G9/(F9+G9) -> 0.46648748 | I9: =F9/(G9+H9) -> 1.1436802 | J9: 1.17 | K9: =H9+(J9*I9) -> 1.8045933
B10: Nike | C10: NIKE | D10: 74.2 | E10: 1476000 | F10: 11018000 | G10: =E10*D10 -> 109519200 | H10: =G10/(F10+G10) -> 0.90859253 | I10: =F10/(G10+H10) -> 0.10060336 | J10: 1.28 | K10: =H10+(J10*I10) -> 1.0373648
J11: Average βU | K11: =AVERAGE(K7:K10) -> 1.2708339
J12: Decker's βU | K12: =K4 -> 0.998735
J13: Rf | K13: 0.0427
J14: Rm - Rf | K14: 0.04
J16: Unlevered R | K16: =K13+K12*K14 -> 0.0826494
J17: Tax | K17: ='Income Statement'!J16/'Income Statement'!J15 -> 0.21629397
J18: D/(D+E) | K18: =I4 -> 0.1265
J19: Rd | K19: =1.25% -> 0.0125
J20: WACC | K20: =(K16*H4)+(K18*(1-K17)*K19) -> 0.073433486
B28: Firm | C28: Price (USD) | D28: Shares Outstanding (thousands) | E28: Debt (USD billions) | F28: Equity (USD billions) | G28: E/(D+E) | H28: D/(D+E)
B29: Skechers (SKX) | C29: 62.96 | D29: 149603 | E29: 2.25 | F29: ~18.8* | G29: ~89.3% | H29: ~10.7%
B30: Puma (PMMAF/PUM) | C30: — | D30: 147140 | E30: 2.58 | F30: 2.1 | G30: ~44.7% | H30: ~55.3%
B31: Crocs (CROX) | C31: 75.24 | D31: 54620 | E31: 1.77 | F31: 1.84 | G31: ~51% | H31: ~49%
B32: V.F. Corp (VFC) | C32: 11.83 | D32: — | E32: — | F32: — | G32: — | H32: —
B36: Firm | C36: Current Share Price Source | D36: Shares Outstanding Source | E36: Debt / Total Debt Source | F36: Equity (Book Value) Source | G36: Debt-to-Equity Source
B37: Skechers (SKX) | C37: Real-time price | D37: 149.60 M shares (StockAnalysis) | E37: Total debt $2.25 B (mrq) (Yahoo Finance) | F37: Shareholders' equity $4.512 B (quarterly) (YCharts) | G37: Debt/Equity ≈ 0.42 (StockAnalysis) (StockAnalysis)
B38: Puma (PMMAF / PUM) | C38: — (not retrieved via finance tool) | D38: 147.14 M shares (StockAnalysis) | E38: Total debt €3.03 B (StockAnalysis) (StockAnalysis) | F38: Equity €2.47 B (StockAnalysis) (StockAnalysis) | G38: Debt/Equity ≈ 1.23 (StockAnalysis)
B39: Crocs (CROX) | C39: Real-time price | D39: 54.62 M shares (StockAnalysis, YCharts) | E39: Debt/Equity data (mrq) ~124.8% (Yahoo Finance, Seeking Alpha) | F39: Equity (implied from total equity $1.42 B) (AlphaQuery) | G39: Debt/Equity ≈ 1.25 (StockAnalysis, GuruFocus)
B40: V.F. Corporation (VFC) | C40: Real-time price | D40: 390.62 M shares (StockAnalysis, Yahoo Finance) | E40: Debt/Equity 4.39 (StockAnalysis / GuruFocus) (StockAnalysis, GuruFocus) | F40: Equity ~ $1.29 B (derived via sources) (GuruFocus, Zacks) | G40: Debt/Equity ≈ 4.39 (StockAnalysis, GuruFocus)
G46: look at market value of equity: size of the firm
B47: what percent sales are in person stores vs online | E47: mix of wholesale vs retail | G47: avg debt to equity over 5 years
B48: Equity (E) = Market capitalization = Current share price × Number of shares outstanding | E48: share counts
E50: Debt to Equity Ratio
B51: % Sales Wholesale v DTC | C51: Wholesale | D51: DTC | E51: 2024 | F51: 2025
B52: Deckers | C52: 0.5729 | D52: 0.4271 | E52: 0.49 | F52: 0.1265
B53: Sketchers | C53: 0.5631 | D53: 0.4369 | E53: 0.09 | F53: 0.07
B54: Puma | C54: 0.7188 | D54: 0.2812 | E54: 0.61 | F54: 0.64
B55: Crocs | C55: 0.5032 | D55: 0.4968 | E55: 0.74 | F55: 1.15
B56: V.F. Corporation | C56: 0.56 | D56: 0.44 | E56: 3.6 | F56: 2.67
B57: Nike | C57: 0.58 | D57: 0.42 | E57: 0.6 | F57: 0.62

Sheet Value Investing
A1: DECKERS OUTDOOR CORPORATION AND SUBSIDIARIES
A2: FINAL VALUATION USING DCF
A3: (dollar and share data amounts in thousands)
B4: Historical | H4: Projected
A5: Year | B5: 2020 | C5: 2021 | D5: 2022 | E5: 2023 | F5: 2024 | G5: 2025 | H5: 2026 | I5: 2027 | J5: 2028 | K5: 2029 | L5: 2030 | M5: 2031 | N5: 2032 | O5: 2033 | P5: 2034 | Q5: 2035
A6: Unlevered Net Income | B6: ='Free Cash Flow'!C8 -> 219787.75 | C6: ='Free Cash Flow'!D8 -> 327733.25 | D6: ='Free Cash Flow'!E8 -> 367059.55 | E6: ='Free Cash Flow'!F8 -> 424288.15 | F6: ='Free Cash Flow'!G8 -> 602884.1 | G6: ='Free Cash Flow'!H8 -> 766409.8 | H6: ='Free Cash Flow'!I8 -> 748265.29 | I6: ='Free Cash Flow'!J8 -> 887054.59 | ... Q6: ='Free Cash Flow'!R8 -> 3460256.9
A7: Depreciation (+) | B7: ='Balance Sheet'!D15 -> 235939 | C7: ='Balance Sheet'!E15 -> 266905 | D7: ='Balance Sheet'!F15 -> 282571 | E7: ='Balance Sheet'!G15 -> 317508 | F7: ='Balance Sheet'!H15 -> 349138 | G7: ='Balance Sheet'!I15 -> 402964 | H7: ='Balance Sheet'!J15 -> 547069.98 | I7: ='Balance Sheet'!K15 -> 648541.29 | ... Q7: ='Balance Sheet'!S15 -> 2529855
A8: Increase in NWC (-) | B8: ='Free Cash Flow'!C10 -> 289266 | C8: ='Free Cash Flow'!D10 -> 289266 | D8: ='Free Cash Flow'!E10 -> 28013 | E8: ='Free Cash Flow'!F10 -> 202429 | F8: ='Free Cash Flow'!G10 -> 310617 | G8: ='Free Cash Flow'!H10 -> 367044 | H8: ='Free Cash Flow'!I10 -> 705072.82 | I8: ='Free Cash Flow'!J10 -> 518533.11 | ... Q8: ='Free Cash Flow'!R10 -> 2022714
A9: Capital Expenditure (-) | B9: ='Free Cash Flow'!C11 -> 233112 | C9: ='Free Cash Flow'!D11 -> 264078 | D9: ='Free Cash Flow'!E11 -> 298810 | E9: ='Free Cash Flow'!F11 -> 361738 | F9: ='Free Cash Flow'!G11 -> 384581 | G9: ='Free Cash Flow'!H11 -> 426441 | H9: ='Free Cash Flow'!I11 -> 673131.72 | I9: ='Free Cash Flow'!J11 -> 732315.96 | ... Q9: ='Free Cash Flow'!R11 -> 2856646.5
A10: Free Cash Flow To Firm | B10: ='Free Cash Flow'!C12 -> -66651.25 | C10: ='Free Cash Flow'!D12 -> 41294.25 | D10: ='Free Cash Flow'!E12 -> 322807.55 | E10: ='Free Cash Flow'!F12 -> 177629.15 | F10: ='Free Cash Flow'!G12 -> 256824.1 | G10: ='Free Cash Flow'!H12 -> 375888.8 | H10: ='Free Cash Flow'!I12 -> -82869.276 | I10: ='Free Cash Flow'!J12 -> 284746.81 | ... Q10: ='Free Cash Flow'!R12 -> 1110751.4
A13: Discount Factor | Q13: =Q10/(B37-B29) -> 47400177
A14: Using the Dividend Discount Model Method
A15: TV | B15: =Q13 -> 47400177 | D15: Share Price | E15: =B17/B23 -> 189.71814 | Q15: =Q13 -> 47400177
A16: EV | B16: =NPV(B37,H10:P10,Q10+Q15) -> 26677177
A17: E | B17: =B16-B24+'Balanced Proforma'!B21-B27 -> 28142789
A18: Using EV/EBITDA exit multiple | Q18: =('Balanced Proforma'!L10+'Free Cash Flow'!R9)*B25 -> 65851237
A19: TV | B19: =Q18 -> 65851237 | D19: Share Price | E19: =B21/B23 -> 250.95482
A20: EV | B20: =NPV(B37,H10:P10,Q10+Q18) -> 35761027
A21: E | B21: =B20-B24+'Balanced Proforma'!B21-B27 -> 37226639
H22: KKP NPV | I22: Sensitivity Analysis | R22: KKP NPV | S22: Sensitivity Analysis
A23: Shares Outstanding (In thousands) | B23: 148340 | I23: Growth Rate | S23: Exit Multiple
A24: Total Debt | B24: 266876 | C24: Taken from screenshot below | H24: =E15 -> 189.71814 | I24: 0.02 | J24: 0.025 | K24: 0.03 | L24: 0.035 | M24: 0.04 | N24: 0.045 | O24: 0.05 | R24: =E19 -> 250.95482 | S24: 8 | T24: 9 | U24: 10 | V24: 11 | W24: 12 | X24: 13 | Y24: 14
A25: EV/EBITDA | B25: 11.52 | C25: Taken from screenshot below | G25: Wacc | H25: 0.068 | I25: 113.99246 | J25: 123.38767 | K25: 135.2553 | L25: 150.71918 | M25: 171.70588 | N25: 201.81723 | O25: 248.6571 | Q25: Wacc | R25: 0.068 | S25: 192.86637 | T25: 212.82546 | U25: 232.78454 | V25: 252.74363 | W25: 272.70272 | X25: 292.6618 | Y25: 312.62089
H26: =6.9% -> 0.069 | I26: 111.45808 | J26: 120.3686 | K26: 131.56386 | L26: 146.05185 | M26: 165.53569 | N26: 193.1378 | O26: 235.26734 | R26: =6.9% -> 0.069 | S26: 191.23086 | T26: 211.00402 | U26: 230.77718 | V26: 250.55034 | W26: 270.3235 | X26: 290.09667 | Y26: 309.86983
A27: Lease Obligation | B27: =276975 -> 276975 | H27: 0.07 | I27: 109.02775 | J27: 117.48654 | K27: 128.06003 | L27: 141.65451 | M27: 159.78049 | N27: 185.15687 | O27: 223.22142 | R27: 0.07 | S27: 189.61176 | T27: 209.2009 | U27: 228.79004 | V27: 248.37919 | W27: 267.96833 | X27: 287.55747 | Y27: 307.14661
H28: 0.071 | I28: 106.69531 | J28: 114.73253 | K28: 124.73005 | L28: 137.50465 | M28: 154.4001 | N28: 177.79379 | O28: 212.32735 | R28: 0.071 | S28: 188.0089 | T28: 207.41591 | U28: 226.82291 | V28: 246.22991 | W28: 265.63692 | X28: 285.04392 | Y28: 304.45092
A29: g | B29: 0.05 | H29: 0.072 | I29: 104.4551 | J29: 112.09837 | K29: 121.56148 | L29: 133.58218 | M29: 149.35934 | N29: 170.97991 | O29: 202.428 | R29: 0.072 | S29: 186.42211 | T29: 205.64884 | U29: 224.87556 | V29: 244.10229 | W29: 263.32901 | X29: 282.55574 | Y29: 301.78247
A30: Rf | B30: 0.0427 | H30: 0.073 | I30: 102.30188 | J30: 109.57657 | K30: 118.54304 | L30: 129.86911 | M30: 144.62733 | N30: 164.65633 | O30: 193.3936 | R30: 0.073 | S30: 184.8512 | T30: 203.89949 | U30: 222.94778 | V30: 241.99607 | W30: 261.04436 | X30: 280.09265 | Y30: 299.14093
A31: Rm - Rf | B31: 0.055 | H31: 0.074 | I31: 100.2308 | J31: 107.1602 | K31: 115.66447 | L31: 126.34932 | M31: 140.17678 | N31: 158.77232 | O31: 185.11601 | R31: 0.074 | S31: 183.296 | T31: 202.16767 | U31: 221.03935 | V31: 239.91102 | W31: 258.78269 | X31: 277.65436 | Y31: 296.52603
A32: Beta | B32: 0.99 | H32: 0.075 | I32: 98.237351 | J32: 104.84294 | K32: 112.91643 | L32: 123.00829 | M32: 135.98355 | N32: 153.28389 | O32: 177.50437 | R32: 0.075 | S32: 181.75634 | T32: 200.45319 | U32: 219.15005 | V32: 237.8469 | W32: 256.54376 | X32: 275.24061 | Y32: 293.93746
A33: Unlevered R | B33: ='Cost of Capital'!K16 -> 0.0826494 | H33: 0.076 | I33: 96.317363 | J33: 102.61892 | K33: 110.29037 | L33: 119.83292 | M33: 132.02617 | N33: 148.15273 | O33: 170.48181 | R33: 0.076 | S33: 180.23204 | T33: 198.75586 | U33: 217.27968 | V33: 235.80349 | W33: 254.32731 | X33: 272.85113 | Y33: 291.37494
A34: Tax | B34: ='Cost of Capital'!K17 -> 0.21629397
A35: D/(D+E) | B35: ='Cost of Capital'!K18 -> 0.1265
A36: Rd | B36: 0.0125
A37: WACC | B37: ='Cost of Capital'!K20 -> 0.073433486

Sheet Appendix
A1: Assumptions
A3: Income Statement Line Item | B3: Include in Pro Forma? | C3: Reasoning
A4: Net sales | B4: Yes | C4: Primary revenue driver; all operating projections start here.
A5: Cost of Sales | B5: Yes | C5: Tied to sales via gross margin or COGS % of sales; key for projecting gross profit.
A6: Gross Profit | B6: — | C6: Calculated from sales − COGS; no need to directly project.
A7: Selling, general, and administrative expenses | B7: Yes | C7: Major operating expense; usually modeled as % of sales.
A8: Income from operations | B8: — | C8: Derived from gross profit − SG&A; no direct projection.
A9: Interest income | B9: No (for FCFF) | C9: Non-operating; comes from excess cash & investments. Ignored in core operating forecast unless you are doing a full cash + debt schedule.
A10: Interest expense | B10: No (for FCFF) | C10: Financing cost; excluded from unlevered free cash flow because FCFF is before debt service.
A11: Other income, net | B11: No | C11: Usually non-recurring, non-operating gains/losses (asset sales, legal settlements). Unless a consistent recurring item, exclude.
A12: Total other (income) expense, net | B12: No | C12: Aggregates non-operating items (above two lines); excluded from FCFF.
A13: Income before income taxes | B13: — | C13: Derived figure; not directly projected.
A14: Income tax expense | B14: Yes (effective tax rate) | C14: Apply effective tax rate to EBIT to get after-tax operating income (NOPAT) in FCFF model.
... A22: Weighted-average common shares outstanding (Basic & Diluted) | B22: No (unless doing per-share valuation) | C22: Not part of operating projections; only needed for EPS or per-share equity value.
A23: Balance Sheet Asset Line Item
A24: Cash and cash equivalents | B24: Yes (as a balancing figure in the BS, not driver in FCFF) | C24: Needed to complete the balance sheet. Not part of operating assets in valuation, but important for reconciling equity value.
A25: Trade accounts receivable | B25: Yes | C25: Directly tied to sales via Days Sales Outstanding (DSO). Key for projecting working capital changes.
A26: Inventories | B26: Yes | C26: Tied to cost of goods sold (COGS) via Days Inventory Held (DIH). Drives working capital needs.
A27: Prepaid expenses | B27: Yes | C27: Usually projected as % of COGS. Operating current asset.
A28: Other current assets | B28: Yes | C28: Often modeled as % of sales. Includes items necessary for operations.
A29: Income tax receivable | B29: No (can exclude for FCFF modeling) | C29: Non-operating; reflects timing of tax refunds, not a recurring operating driver. Including it complicates projections without improving accuracy.
A30: Total current assets | B30: — | C30: Sum of current asset components you keep.
A31: PPE gross | B31: Yes | C31: Needed for CapEx projections and depreciation schedule.
A32: Depreciation | B32: Yes (as part of projection assumptions, not a BS item) | C32: Used for cash flow reconciliation and PPE roll-forward.
A33: PPE net | B33: — | C33: Derived from PPE gross minus accumulated depreciation.
A34: Operating lease assets | B34: Yes | C34: Required under ASC 842; tied to lease liabilities; treated as operating asset.
A35: Goodwill | B35: Yes (fixed unless acquisition) | C35: Intangible but part of total invested capital. Usually held constant unless modeling acquisitions.
... A40: Total assets | B40: — | C40: Sum of current + non-current assets.
A41: Balance Sheet Liability and Equity Item
A42: Short-term borrowings | B42: Yes (if any outstanding) | C42: Part of financing; needed for net debt calc.
A43: Trade accounts payable | B43: Yes | C43: Operating liability tied to COGS via Days Payable Outstanding (DPO).
A44: Accrued payroll | B44: Yes | C44: Operating liability; can project as % of COGS or sales.
A45: Operating lease liabilities | B45: Yes | C45: Matched to operating lease assets.
A46: Other accrued expenses | B46: Yes | C46: Operating liability; project as % of COGS.
A47: Income tax payable | B47: No (for FCFF) | C47: Non-operating liability; reflects timing of tax payments.
A48: Value added tax payable | B48: No | C48: Government tax pass-through, not part of operations profitably.
A49: Total current liabilities | B49: — | C49: Sum of included current liabilities.
A50: Long-term operating lease liabilities | B50: Yes | C50: Required to match operating lease assets; flows from lease amortization schedule.
A51: Mortgage Payable | B51: Yes (if material) | C51: Financing liability; affects net debt, not FCFF.
A52: Income tax liability | B52: No | C52: Non-operating; timing difference.
A53: Deferred rent obligations | B53: No (often rolled into lease liabilities under new rules) | C53: Obsolete under ASC 842 unless separate.
... A61: Total liabilities and stockholders' equity | B61: — | C61: Sum of liabilities + equity.
A64: Sources:
A65: https://home.treasury.gov/resource-center/data-chart-center/interest-rates/TextView?type=daily_treasury_yield_curve&field_tdr_date_value_month=202508
A66: https://pages.stern.nyu.edu/~adamodar/
A67: https://finance.yahoo.com/quote/DECK/
A70: Firm | B70: Price (USD) | C70: Shares Outstanding (thousands) | D70: Debt (USD billions) | E70: Equity (USD billions) | F70: E/(D+E) | G70: D/(D+E)
A71: Skechers (SKX) | B71: 62.96 | C71: 149603 | D71: 2.25 | E71: ~18.8* | F71: ~89.3% | G71: ~10.7%
A72: Puma (PMMAF/PUM) | B72: — | C72: 147140 | D72: 2.58 | E72: 2.1 | F72: ~44.7% | G72: ~55.3%
A73: Crocs (CROX) | B73: 75.24 | C73: 54620 | D73: 1.77 | E73: 1.84 | F73: ~51% | G73: ~49%
A74: V.F. Corp (VFC) | B74: 11.83 | C74: — | D74: — | E74: — | F74: — | G74: —
A78: Firm | B78: Current Share Price Source | C78: Shares Outstanding Source | D78: Debt / Total Debt Source | E78: Equity (Book Value) Source | F78: Debt-to-Equity Source
A79: Skechers (SKX) | B79: Real-time price | C79: 149.60 M shares (StockAnalysis) | D79: Total debt $2.25 B (mrq) (Yahoo Finance) | E79: Shareholders' equity $4.512 B (quarterly) (YCharts) | F79: Debt/Equity ≈ 0.42 (StockAnalysis) (StockAnalysis)
A80: Puma (PMMAF / PUM) | B80: — (not retrieved via finance tool) | C80: 147.14 M shares (StockAnalysis) | D80: Total debt €3.03 B (StockAnalysis) (StockAnalysis) | E80: Equity €2.47 B (StockAnalysis) (StockAnalysis) | F80: Debt/Equity ≈ 1.23 (StockAnalysis)
A81: Crocs (CROX) | B81: Real-time price | C81: 54.62 M shares (StockAnalysis, YCharts) | D81: Debt/Equity data (mrq) ~124.8% (Yahoo Finance, Seeking Alpha) | E81: Equity (implied from total equity $1.42 B) (AlphaQuery) | F81: Debt/Equity ≈ 1.25 (StockAnalysis, GuruFocus)
A82: V.F. Corporation (VFC) | B82: Real-time price | C82: 390.62 M shares (StockAnalysis, Yahoo Finance) | D82: Debt/Equity 4.39 (StockAnalysis / GuruFocus) (StockAnalysis, GuruFocus) | E82: Equity ~ $1.29 B (derived via sources) (GuruFocus, Zacks) | F82: Debt/Equity ≈ 4.39 (StockAnalysis, GuruFocus)
A88: Comps validation | F88: look at market value of equity: size of the firm
A89: what percent sales are in person stores vs online | D89: mix of wholesale vs retail | F89: avg debt to equity over 5 years
A90: Equity (E) = Market capitalization = Current share price × Number of shares outstanding | D90: share counts
D92: Debt to Equity Ratio
A93: % Sales Wholesale v DTC | B93: Wholesale | C93: DTC | D93: 2024 | E93: 2025
A94: Deckers | B94: 0.5729 | C94: 0.4271 | D94: 0.49 | E94: 0.1265
A95: Sketchers | B95: 0.5631 | C95: 0.4369 | D95: 0.09 | E95: 0.07
A96: Puma | B96: 0.7188 | C96: 0.2812 | D96: 0.61 | E96: 0.64
A97: Crocs | B97: 0.5032 | C97: 0.4968 | D97: 0.74 | E97: 1.15
A98: V.F. Corporation | B98: 0.56 | C98: 0.44 | D98: 3.6 | E98: 2.67
A99: Nike | B99: 0.58 | C99: 0.42 | D99: 0.6 | E99: 0.62
