Workbook
Name IQ_CH: 110000
Name IQ_CQ: 5000
Name IQ_CY: 10000
Name IQ_DAILY: 500000
Name IQ_FH: 100000
Name IQ_FQ: 500
Name IQ_FY: 1000
Name IQ_LTM: 2000
Name IQ_MONTH: 15000
Name IQ_NTM: 6000
Name IQ_WEEK: 50000
Name IQ_YTD: 3000

Sheet Cover Sheet
B2: Starbucks Corporation (NasdaqGS:SBUX), 10 Years Valuation
B3: Prepared by:
B4: Shaira Katuwal
B6: Kelley Deliverables Affirmation:
B7: As a Kelley student, I will act professionally with civility and respect toward others and with honor and integrity in all my work.
B8: I have neither given nor received unauthorized aid on this deliverable.
B10: Overview:
B11: Segment | C11: Description | D11: FY2023 % of Total Revenue (approx.)
B12: North America | C12: Primarily U.S. and Canada company-operated and licensed stores | D12: 0.73
B13: International | C13: Company-operated and licensed stores outside North America | D13: 0.23
B14: Channel Development | C14: Packaged coffee, tea, and ready-to-drink products sold through grocery stores and partners | D14: 0.04
B16: Starting Comments:
B17: Starbucks uses a 52/53-week fiscal year calendar (not a fixed “December 31” calendar year).
B18: Most fiscal years have 52 weeks. Every 5-6 years, one year has 53 weeks to realign the calendar.
B19: The extra week usually lands in the last quarter (Q4).
B20: Did not adjust these to exactly 365-day years because: The difference between 52 and 53 weeks is only about 2% of a year, which is immaterial in most valuation or forecasting contexts.
B21: Resources used: Capital IQ, AI tools, Professor Damodaran's website
B23: Summary of valuation
B24: Based on the pro forma financials, Starbucks’ Enterprise Value (EV) is estimated at $105.3B, leading to an Equity Value of $84.5B and an implied share price of $78.89 (based on 1,054.9 million shares outstanding). The valuation uses a Discounted Cash Flow (DCF) approach with forecasted Free Cash Flow to the Firm (FCFF) from 2025-2034 and a terminal value (TV) calculated using a perpetuity growth model.
B25: Key assumptions and adjustments
B26: Revenue & NOPAT growth: Forecasted based on historical growth trends and Starbucks’ guidance.
B27: CapEx stabilization: After 2030, CapEx assumed to stabilize at approx. 4-5% of sales, in line with historical Starbucks performance, to prevent negative FCFF.
B28: Net Working Capital (NWC): Historical trend of negative NWC continues, reflecting Starbucks’ operational efficiency.
... B44: Share repurchases, dividends, or changes in capital structure beyond historical trends are not explicitly modeled.

Sheet Historical Balance Sheet
A2: All values are in USD (in millions)
A3: Balance Sheet as of: | B3: Sep-27-2015 | C3: Oct-02-2016 | D3: Oct-01-2017 | E3: Sep-30-2018 | F3: Sep-29-2019 | G3: Sep-27-2020 | H3: Oct-03-2021 | I3: Oct-02-2022 | J3: Oct-01-2023 | K3: Sep-29-2024
A4: ASSETS
A5: Current Assets
A6: Cash and Cash Equivalents | B6: 1530.1 | C6: 2128.8 | D6: 2462.3 | E6: 8756.3 | F6: 2686.6 | G6: 4350.9 | H6: 6455.7 | I6: 2818.4 | J6: 3551.5 | K6: 3286.2
A7: Short-term Investments | B7: 81.3 | C7: 134.4 | D7: 228.6 | E7: 181.5 | F7: 70.5 | G7: 281.2 | H7: 162.2 | I7: 364.5 | J7: 401.5 | K7: 257
A8: Trading Asset Securities | B8: 0 | C8: 0 | D8: 0 | E8: 0 | F8: 0 | G8: 0 | H8: 0 | I8: 0 | J8: 0.4 | K8: 0
A9: Total Cash & ST Investments | B9: =SUM(B6:B8) -> 1611.4 | C9: =SUM(C6:C8) -> 2263.2 | D9: =SUM(D6:D8) -> 2690.9 | E9: =SUM(E6:E8) -> 8937.8 | F9: =SUM(F6:F8) -> 2757.1 | G9: =SUM(G6:G8) -> 4632.1 | H9: =SUM(H6:H8) -> 6617.9 | I9: =SUM(I6:I8) -> 3182.9 | ... K9: =SUM(K6:K8) -> 3543.2
A10: Accounts Receivable, Net | B10: 719 | C10: 768.8 | D10: 870.4 | E10: 693.1 | F10: 879.2 | G10: 883.4 | H10: 940 | I10: 1175.5 | J10: 1184.1 | K10: 1213.8
A11: Other Receivable | B11: 0 | C11: 0 | D11: 68 | E11: 955.4 | F11: 141.1 | G11: 512 | H11: 193.1 | I11: 69.4 | J11: 0 | K11: 0
A12: Total Receivables | B12: =SUM(B10:B11) -> 719 | C12: =SUM(C10:C11) -> 768.8 | D12: =SUM(D10:D11) -> 938.4 | E12: =SUM(E10:E11) -> 1648.5 | F12: =SUM(F10:F11) -> 1020.3 | G12: =SUM(G10:G11) -> 1395.4 | H12: =SUM(H10:H11) -> 1133.1 | I12: =SUM(I10:I11) -> 1244.9 | ... K12: =SUM(K10:K11) -> 1213.8
A13: Inventories | B13: 1306.4 | C13: 1378.5 | D13: 1364 | E13: 1400.5 | F13: 1529.4 | G13: 1551.4 | H13: 1603.9 | I13: 2176.6 | J13: 1806.4 | K13: 1777.3
A14: Prepaid Expenses | B14: 283.4 | C14: 319.7 | D14: 276.7 | E14: 482.9 | F14: 334.5 | G14: 211.9 | H14: 253.9 | I14: 339.2 | J14: 298.3 | K14: 292
A15: Restricted Cash | B15: 0 | C15: 0 | D15: 0 | E15: 0 | F15: 0 | G15: 0 | H15: 0 | I15: 0 | J15: 20.6 | K15: 12.4
A16: Other Current Assets | B16: 50.8 | C16: 27.7 | D16: 13.4 | E16: 24.5 | F16: 12.6 | G16: 15.6 | H16: 147.6 | I16: 75.1 | J16: 40.6 | K16: 8.7
A17: Total Current Assets | B17: =B9+B12+SUM(B13:B16) -> 3971 | C17: =C9+C12+SUM(C13:C16) -> 4757.9 | D17: =D9+D12+SUM(D13:D16) -> 5283.4 | E17: =E9+E12+SUM(E13:E16) -> 12494.2 | F17: =F9+F12+SUM(F13:F16) -> 5653.9 | G17: =G9+G12+SUM(G13:G16) -> 7806.4 | H17: =H9+H12+SUM(H13:H16) -> 9756.4 | I17: =I9+I12+SUM(I13:I16) -> 7018.7 | ... K17: =K9+K12+SUM(K13:K16) -> 6847.4
A19: Non Current Assets
A20: Gross Property, Plant & Equipment | B20: 9641.8 | C20: 10573.3 | D20: 11584 | E20: 13197.1 | F20: 14273.5 | G20: 22289.4 | H20: 23064.8 | I20: 23625.4 | J20: 25722.8 | K20: 28727.2
A21: Accumulated Depreciation | B21: 5553.5 | C21: 6039.5 | D21: 6664.5 | E21: 7268 | F21: 7841.8 | G21: 7913.9 | H21: 8459.3 | I21: 9049.3 | J21: 9923.1 | K21: 10775.5
A22: Net Property, Plant & Equipment | B22: =B20-B21 -> 4088.3 | C22: =C20-C21 -> 4533.8 | D22: =D20-D21 -> 4919.5 | E22: =E20-E21 -> 5929.1 | F22: =F20-F21 -> 6431.7 | G22: =G20-G21 -> 14375.5 | H22: =H20-H21 -> 14605.5 | I22: =I20-I21 -> 14576.1 | ... K22: =K20-K21 -> 17951.7
A24: Long-term Investments | B24: 664.5 | C24: 1496.2 | D24: 1023.9 | E24: 602.4 | F24: 634.3 | G24: 730.6 | H24: 572.9 | I24: 590.3 | J24: 687.3 | K24: 739.9
A25: Goodwill | B25: 1575.4 | C25: 1719.6 | D25: 1539.2 | E25: 3541.6 | F25: 3490.8 | G25: 3597.2 | H25: 3677.3 | I25: 3283.5 | J25: 3218.3 | K25: 3315.7
A26: Other Intangibles | B26: 520.4 | C26: 516.3 | D26: 441.4 | E26: 1042.2 | F26: 781.8 | G26: 552.1 | H26: 349.9 | I26: 155.9 | J26: 120.5 | K26: 100.9
A27: Deferred Tax Assets, LT | B27: 1180.8 | C27: 885.4 | D27: 795.4 | E27: 134.7 | F27: 1765.8 | G27: 1789.9 | H27: 1874.8 | I27: 1799.7 | J27: 1769.8 | K27: 1766.7
A28: Other Long-Term Assets | B28: 415.9 | C28: 403.3 | D28: 362.8 | E28: 412.2 | F28: 461.3 | G28: 522.8 | H28: 555.8 | I28: 554.2 | J28: 546.5 | K28: 617
A29: Total Assets | B29: =B17+SUM(B24:B28)+B22 -> 12416.3 | C29: =C17+SUM(C24:C28)+C22 -> 14312.5 | D29: =D17+SUM(D24:D28)+D22 -> 14365.6 | E29: =E17+SUM(E24:E28)+E22 -> 24156.4 | F29: =F17+SUM(F24:F28)+F22 -> 19219.6 | G29: =G17+SUM(G24:G28)+G22 -> 29374.5 | H29: =H17+SUM(H24:H28)+H22 -> 31392.6 | I29: =I17+SUM(I24:I28)+I22 -> 27978.4 | ... K29: =K17+SUM(K24:K28)+K22 -> 31339.3
A31: LIABILITIES
A32: Accounts Payable | B32: 684.2 | C32: 730.6 | D32: 782.5 | E32: 1179.3 | F32: 1189.7 | G32: 997.9 | H32: 1211.6 | I32: 1441.4 | J32: 1544.3 | K32: 1595.5
A33: Accrued Exp. | B33: 884.3 | C33: 894.3 | D33: 891 | E33: 1218.5 | F33: 1228.7 | G33: 1179.5 | H33: 1326.7 | I33: 1273.2 | J33: 1361.2 | K33: 1323.8
A34: Short-term Borrowings | B34: 0 | C34: 0 | D34: 0 | E34: 0 | F34: 0 | G34: 438.8 | H34: 0 | I34: 175 | J34: 33.5 | K34: 0
A35: Curr. Port. of LT Debt | B35: 0 | C35: 399.9 | D35: 0 | E35: 349.9 | F35: 0 | G35: 1249.9 | H35: 998.9 | I35: 1761 | J35: 1818.6 | K35: 1248.9
A36: Curr. Port. of Leases | B36: 0 | C36: 0 | D36: 0 | E36: 0 | F36: 0 | G36: 1248.8 | H36: 1251.3 | I36: 1245.7 | J36: 1275.3 | K36: 1463.1
A37: Curr. Income Taxes Payable | B37: 259 | C37: 368.4 | D37: 226.6 | E37: 102.8 | F37: 1291.7 | G37: 98.2 | H37: 348 | I37: 139.2 | J37: 189.3 | K37: 123.5
A38: Unearned Revenue, Current | B38: 983.8 | C38: 1171.2 | D38: 1288.5 | E38: 1642.9 | F38: 1269 | G38: 1456.5 | H38: 1596.1 | I38: 1641.9 | J38: 1700.2 | K38: 1781.2
A39: Other Current Liabilities | B39: 836.8 | C39: 982.4 | D39: 1032.1 | E39: 1190.8 | F39: 1189.6 | G39: 677.2 | H39: 1418.8 | I39: 1474.4 | J39: 1422.9 | K39: 1534
A40: Total Current Liabilities | B40: =SUM(B32:B39) -> 3648.1 | C40: =SUM(C32:C39) -> 4546.8 | D40: =SUM(D32:D39) -> 4220.7 | E40: =SUM(E32:E39) -> 5684.2 | F40: =SUM(F32:F39) -> 6168.7 | G40: =SUM(G32:G39) -> 7346.8 | H40: =SUM(H32:H39) -> 8151.4 | I40: =SUM(I32:I39) -> 9151.8 | ... K40: =SUM(K32:K39) -> 9070
A42: Long-Term Debt | B42: 2347.5 | C42: 3185.3 | D42: 3932.6 | E42: 9122.7 | F42: 11169.6 | G42: 14728.9 | H42: 13618.2 | I42: 13153.9 | J42: 13589 | K42: 14338.7
A43: Long-Term Leases | B43: 0 | C43: 0 | D43: 0 | E43: 0 | F43: 0 | G43: 7661.7 | H43: 7738 | I43: 7515.2 | J43: 7924.8 | K43: 8771.6
A44: Unearned Revenue, Non-Current | B44: 0 | C44: 0 | D44: 4.4 | E44: 6775.7 | F44: 6744.4 | G44: 6598.5 | H44: 6463 | I44: 6279.7 | J44: 6101.8 | K44: 5963.6
A45: Def. Tax Liability, Non-Curr. | B45: 43.4 | C45: 14.7 | D45: 6.3 | E45: 270.2 | F45: 186.4 | G45: 158.1 | H45: 148.5 | I45: 118.6 | J45: 14.6 | K45: 21.1
A46: Other Non-Current Liabilities | B46: 557.5 | C46: 675 | D46: 744.6 | E46: 1127.8 | F46: 1181.5 | G46: 679.9 | H46: 588 | I46: 457.9 | J46: 457.8 | K46: 615.9
A47: Total Liabilities | B47: 6596.5 | C47: 8421.8 | D47: 8908.6 | E47: 22980.6 | F47: 25450.6 | G47: 37173.9 | H47: 36707.1 | I47: 36677.1 | J47: 37433.3 | K47: 38780.9
A49: Common Stock | B49: 1.5 | C49: 1.5 | D49: 1.4 | E49: 1.3 | F49: 1.2 | G49: 1.2 | H49: 1.2 | I49: 1.1 | J49: 1.1 | K49: 1.1
A50: Additional Paid In Capital | B50: 41.1 | C50: 41.1 | D50: 41.1 | E50: 41.1 | F50: 41.1 | G50: 373.9 | H50: 846.1 | I50: 205.3 | J50: 38.1 | K50: 322.6
A51: Retained Earnings | B51: 5974.8 | C51: 5949.8 | D51: 5563.2 | E51: 1457.4 | F51: -5771.2 | G51: -7815.6 | H51: -6315.7 | I51: -8449.8 | J51: -7255.8 | K51: -7343.8
A52: Treasury Stock | B52: 0 | C52: 0 | D52: 0 | E52: 0 | F52: 0 | G52: 0 | H52: 0 | I52: 0 | J52: 0 | K52: 0
A53: Comprehensive Inc. and Other | B53: =--199.4 -> 199.4 | C53: =--108.4 -> 108.4 | D53: =--155.6 -> 155.6 | E53: =--330.3 -> 330.3 | F53: =--503.3 -> 503.3 | G53: =--364.6 -> 364.6 | H53: -147.2 | I53: =--463.2 -> 463.2 | J53: =--778.2 -> 778.2 | K53: =--428.8 -> 428.8
A54: Total Common Equity | B54: =B49+B50+B51+B52-B53 -> 5818 | C54: =C49+C50+C51+C52-C53 -> 5884 | D54: =D49+D50+D51+D52-D53 -> 5450.1 | E54: =E49+E50+E51+E52-E53 -> 1169.5 | F54: =F49+F50+F51+F52-F53 -> -6232.2 | G54: =G49+G50+G51+G52-G53 -> -7805.1 | H54: =H49+H50+H51+H52-H53 -> -5321.2 | I54: =I49+I50+I51+I52-I53 -> -8706.6 | ... K54: =K49+K50+K51+K52-K53 -> -7448.9
A56: Minority Interest | B56: 1.8 | C56: 6.7 | D56: 6.9 | E56: 6.3 | F56: 1.2 | G56: 5.7 | H56: 6.7 | I56: 7.9 | J56: 7 | K56: 7.3
A58: Total Equity | B58: =B54+B56 -> 5819.8 | C58: =C54+C56 -> 5890.7 | D58: =D54+D56 -> 5457 | E58: =E54+E56 -> 1175.8 | F58: =F54+F56 -> -6231 | G58: =G54+G56 -> -7799.4 | H58: =H54+H56 -> -5314.5 | I58: =I54+I56 -> -8698.7 | ... K58: =K54+K56 -> -7441.6
A60: Total Liabilities And Equity | B60: =B58+B47 -> 12416.3 | C60: =C58+C47 -> 14312.5 | D60: =D58+D47 -> 14365.6 | E60: =E58+E47 -> 24156.4 | F60: =F58+F47 -> 19219.6 | G60: =G58+G47 -> 29374.5 | H60: =H58+H47 -> 31392.6 | I60: =I58+I47 -> 27978.4 | ... K60: =K58+K47 -> 31339.3
A62: Supplemental Items
A63: Total Shares Out. on Filing Date | B63: 1484.8 | C63: 1455.4 | D63: 1422.8 | E63: 1240.6 | F63: 1181 | G63: 1173.7 | H63: 1173.2 | I63: 1147.8 | J63: 1136.7 | K63: 1133.8
A64: Total Shares Out. on Balance Sheet Date | B64: 1485.1 | C64: 1460.5 | D64: 1431.6 | E64: 1309.1 | F64: 1184.6 | G64: 1173.3 | H64: 1180 | I64: 1147.9 | J64: 1142.6 | K64: 1133.5
A65: Book Value/Share | B65: 3.92 | C65: 4.03 | D65: 3.81 | E65: 0.89 | F65: -5.26 | G65: -6.65 | H65: -4.51 | I65: -7.58 | J65: -7 | K65: -6.57
A66: Tangible Book Value | B66: 3722.2 | C66: 3648.1 | D66: 3469.5 | E66: -3414.3 | F66: -10504.8 | G66: -11954.4 | H66: -9348.4 | I66: -12146 | J66: -11333.6 | K66: -10865.5
A67: Tangible Book Value/Share | B67: 2.51 | C67: 2.5 | D67: 2.42 | E67: -2.61 | F67: -8.87 | G67: -10.19 | H67: -7.92 | I67: -10.58 | J67: -9.92 | K67: -9.59
A68: Total Debt | B68: 2347.5 | C68: 3585.2 | D68: 3932.6 | E68: 9472.6 | F68: 11169.6 | G68: 25328.1 | H68: 23606.4 | I68: 23850.8 | J68: 24641.2 | K68: 25822.3
A69: Net Debt | B69: 736.1 | C69: 1322 | D69: 1241.7 | E69: 534.8 | F69: 8412.5 | G69: 20696 | H69: 16988.5 | I69: 20667.9 | J69: 20687.8 | K69: 22279.1
A70: Debt Equivalent Oper. Leases | B70: 9007.2 | C70: 9668.8 | D70: 10509.6 | E70: 17905.6 | F70: 19202.4 | G70: 19528.8 | H70: 20492 | I70: 21392.8 | J70: 22968 | K70: 24404.8
A71: Total Minority Interest | B71: 1.8 | C71: 6.7 | D71: 6.9 | E71: 6.3 | F71: 1.2 | G71: 5.7 | H71: 6.7 | I71: 7.9 | J71: 7 | K71: 7.3
A72: Equity Method Investments | B72: 306.4 | C72: 305.7 | D72: 432.8 | E72: 296 | F72: 336.1 | G72: 426.4 | H72: 216 | I72: 283.1 | J72: 415.7 | K72: 424.1
A73: Inventory Method | B73: Avg Cost | C73: Avg Cost | D73: Avg Cost | E73: Avg Cost | F73: Avg Cost | G73: Avg Cost | H73: Avg Cost | I73: Avg Cost | J73: NA | K73: Spec. ID
A74: Raw Materials Inventory | B74: 179 | C74: 207.9 | D74: 220.8 | E74: 257.6 | F74: 308.4 | G74: 369.3 | H74: 370.8 | I74: 416.8 | J74: 413.8 | K74: 475.7
A75: Finished Goods Inventory | B75: 1127.4 | C75: 1170.6 | D75: 1143.2 | E75: 1142.9 | F75: 1221 | G75: 1182.1 | H75: 1233.1 | I75: 1759.8 | J75: 1392.6 | K75: 1301.6
A76: Land | B76: 46.6 | C76: 46.6 | D76: 46.9 | E76: 46.8 | F76: 46.8 | G76: 46 | H76: 46.2 | I76: 46.1 | J76: 46.1 | K76: 56.9
A77: Buildings | B77: 411.5 | C77: 458.4 | D77: 481.7 | E77: 557.3 | F77: 691.5 | G77: 586.8 | H77: 587.6 | I77: 555.4 | J77: 666.5 | K77: 684.8
A78: Machinery | B78: 3531.6 | C78: 3904 | D78: 4244.6 | E78: 4718.3 | F78: 5228.1 | G78: 4882.6 | H78: 5183.3 | I78: 5382.8 | J78: 4959.2 | K78: 5444.8
A79: Construction in Progress | B79: 242.5 | C79: 271.4 | D79: 409.8 | E79: 501.9 | F79: 358.5 | G79: 377.3 | H79: 374.1 | I79: 558.7 | J79: 607.5 | K79: 750.9
A80: Leasehold Improvements | B80: 5409.6 | C80: 5892.9 | D80: 6401 | E80: 7372.8 | F80: 7948.6 | G80: 8262.6 | H80: 8637.6 | I80: 9066.8 | J80: 10133.7 | K80: 11453.9
A81: Full Time Employees | B81: 238000 | C81: 254000 | D81: 277000 | E81: 291000 | F81: 346000 | G81: 349000 | H81: 383000 | I81: 402000 | J81: 381000 | K81: 361000
A82: Accum. Allowance for Doubtful Accts | B82: 10.8 | C82: 9.4 | D82: 9.8 | E82: 8 | F82: 6.7 | G82: 27.1 | H82: 25.6 | I82: 27.2 | J82: 23.8 | K82: 21.2
A83: Filing Date | B83: 43056 | C83: 43420 | D83: 43784 | E83: 44147 | F83: 44519 | G83: 44883 | H83: 45247 | I83: 45616 | J83: 45616 | K83: 45616
A84: Restatement Type | B84: RS | C84: RS | D84: NC | E84: NC | F84: NC | G84: NC | H84: NC | I84: NC | J84: NC | K84: O
A85: Calculation Type | B85: RUP | C85: RUP | D85: RUP | E85: RUP | F85: RUP | G85: RUP | H85: RUP | I85: RUP | J85: REP | K85: REP

Sheet Historical Income Statement
A2: All values are in USD (in millions)
A3: Income Statement For the Fiscal Period Ending | B3: Sep-27-2015 | C3: Oct-02-2016 | D3: Oct-01-2017 | E3: Sep-30-2018 | F3: Sep-29-2019 | G3: Sep-27-2020 | H3: Oct-03-2021 | I3: Oct-02-2022 | J3: Oct-01-2023 | K3: Sep-29-2024
A4: Revenue | B4: 19162.7 | C4: 18998.3 | D4: 20005.7 | E4: 22342.5 | F4: 24419.4 | G4: 21491.7 | H4: 27290.6 | I4: 30231.6 | J4: 33975 | K4: 34271
A5: Other Revenue | B5: 0 | C5: 2317.6 | D5: 2381.1 | E5: 2377 | F5: 2089.2 | G5: 2026.3 | H5: 1770 | I5: 2018.7 | J5: 2000.6 | K5: 1905.2
A6: Total Revenue | B6: =SUM(B4:B5) -> 19162.7 | C6: =SUM(C4:C5) -> 21315.9 | D6: =SUM(D4:D5) -> 22386.8 | E6: =SUM(E4:E5) -> 24719.5 | F6: =SUM(F4:F5) -> 26508.6 | G6: =SUM(G4:G5) -> 23518 | H6: =SUM(H4:H5) -> 29060.6 | I6: =SUM(I4:I5) -> 32250.3 | ... K6: =SUM(K4:K5) -> 36176.2
A7: Cost of Goods Sold | B7: 13198.6 | C7: 14573.3 | D7: 15552.2 | E7: 17402.9 | F7: 19020.5 | G7: 18376.9 | H7: 20625.2 | I7: 23864.9 | J7: 26106.2 | K7: 26443.8
A8: Gross Profit | B8: =B6-B7 -> 5964.1 | C8: =C6-C7 -> 6742.6 | D8: =D6-D7 -> 6834.6 | E8: =E6-E7 -> 7316.6 | F8: =F6-F7 -> 7488.1 | G8: =G6-G7 -> 5141.1 | H8: =H6-H7 -> 8435.4 | I8: =I6-I7 -> 8385.4 | ... K8: =K6-K7 -> 9732.4
A9: Selling General & Admin Exp. | B9: 1196.7 | C9: 1408.9 | D9: 1408.4 | E9: 1704.6 | F9: 1824.1 | G9: 1679.6 | H9: 1932.6 | I9: 2032 | J9: 2441.3 | K9: 2523.3
A10: R & D Exp. | B10: 0 | C10: 0 | D10: 0 | E10: 0 | F10: 0 | G10: 0 | H10: 0 | I10: 0 | J10: 0 | K10: 0
A11: Depreciation & Amort. | B11: 893.9 | C11: 980.8 | D11: 1011.4 | E11: 1247 | F11: 1377.3 | G11: 1431.3 | H11: 1441.7 | I11: 1447.9 | J11: 1362.6 | K11: 1512.6
A12: Other Operating Expense/(Income) | B12: 522.4 | C12: 499.2 | D12: 518 | E12: 554.9 | F12: 371 | G12: 430.3 | H12: 359.5 | I12: 461.5 | J12: 539.4 | K12: 565.6
A13: Other Operating Expense, Total | B13: =SUM(B9:B12) -> 2613 | C13: =SUM(C9:C12) -> 2888.9 | D13: =SUM(D9:D12) -> 2937.8 | E13: =SUM(E9:E12) -> 3506.5 | F13: =SUM(F9:F12) -> 3572.4 | G13: =SUM(G9:G12) -> 3541.2 | H13: =SUM(H9:H12) -> 3733.8 | I13: =SUM(I9:I12) -> 3941.4 | ... K13: =SUM(K9:K12) -> 4601.5
A14: Earnings Before Interest and Taxes, Operating Income EBIT | B14: =B8-B13 -> 3351.1 | C14: =C8-C13 -> 3853.7 | D14: =D8-D13 -> 3896.8 | E14: =E8-E13 -> 3810.1 | F14: =F8-F13 -> 3915.7 | G14: =G8-G13 -> 1599.9 | H14: =H8-H13 -> 4701.6 | I14: =I8-I13 -> 4444 | ... K14: =K8-K13 -> 5130.9
A15: Interest Expense | B15: 70.5 | C15: 81.3 | D15: 92.5 | E15: 170.3 | F15: 331 | G15: 437 | H15: 473.4 | I15: 482.9 | J15: 550.1 | K15: 562
A16: Interest and Invest. Income | B16: 0 | C16: 153 | D16: 16.7 | E16: 33 | F16: 131.3 | G16: 45 | H16: 69.1 | I16: 0 | J16: 93.8 | K16: 125.7
A17: Net Interest Expense | B17: =B15-B16 -> 70.5 | C17: =C15-C16 -> -71.7 | D17: =D15-D16 -> 75.8 | E17: =E15-E16 -> 137.3 | F17: =F15-F16 -> 199.7 | G17: =G15-G16 -> 392 | H17: =H15-H16 -> 404.3 | I17: =I15-I16 -> 482.9 | ... K17: =K15-K16 -> 436.3
A18: Income/(Loss) from Affiliates | B18: 249.9 | C18: 318.2 | D18: 391.4 | E18: 301.2 | F18: 298 | G18: 322.5 | H18: 385.3 | I18: 234.1 | J18: 298.4 | K18: 301.2
A19: Currency Exchange Gains (Loss) | B19: 73.3 | C19: -106.8 | D19: 62.7 | E19: 6.5 | F19: -27.9 | G19: 0.3 | H19: 20.2 | I19: 99.9 | J19: -3.1 | K19: 0.2
A20: Other Non-Operating Inc. (Expense) | B20: -24.2 | C20: 54.8 | D20: 105.9 | E20: 157.2 | F20: -7.8 | G20: -10.5 | H20: 2.6 | I20: -2.5 | J20: -7.5 | K20: -2
A21: Earnings Before Taxes (EBT Excl. Unusual Items) | B21: =B14-B17+B18+B19+B20 -> 3579.6 | C21: =C14-C17+C18+C19+C20 -> 4191.6 | D21: =D14-D17+D18+D19+D20 -> 4381 | E21: =E14-E17+E18+E19+E20 -> 4137.7 | F21: =F14-F17+F18+F19+F20 -> 3978.3 | G21: =G14-G17+G18+G19+G20 -> 1520.2 | H21: =H14-H17+H18+H19+H20 -> 4705.4 | I21: =I14-I17+I18+I19+I20 -> 4292.6 | ... K21: =K14-K17+K18+K19+K20 -> 4994
A22: Restructuring Charges | B22: 0 | C22: 0 | D22: -153.5 | E22: -224.4 | F22: -135.8 | G22: -278.7 | H22: -170.4 | I22: -46 | J22: -21.8 | K22: 0
A23: Merger & Related Restruct. Charges | B23: 0 | C23: 0 | D23: 0 | E23: -3.6 | F23: 0 | G23: 0 | H23: 0 | I23: 0 | J23: 0 | K23: 0
A24: Impairment of Goodwill | B24: 0 | C24: 0 | D24: 0 | E24: 0 | F24: 0 | G24: 0 | H24: 0 | I24: 0 | J24: 0 | K24: 0
A25: Gain (Loss) On Sale Of Invest. | B25: 391.6 | C25: 1.6 | D25: -4.1 | E25: 1372.8 | F25: 0.9 | G25: 4.9 | H25: 1.8 | I25: -0.4 | J25: -0.7 | K25: -1.2
A26: Gain (Loss) On Sale Of Assets | B26: -7.1 | C26: 5.4 | D26: 94.1 | E26: 497.5 | F26: 622.8 | G26: 0 | H26: 864.5 | I26: 0 | J26: 91.3 | K26: 0
A27: Asset Writedown | B27: 0 | C27: 0 | D27: 0 | E27: 0 | F27: 0 | G27: -109.6 | H27: -44.4 | I27: -14.3 | J27: -23.2 | K27: -23.3
A28: Other Unusual Items | B28: -61.1 | C28: 0 | D28: 0 | E28: 0 | F28: 0 | G28: 27.6 | H28: 0 | I28: 0 | J28: -1.3 | K28: 0.1
A29: Earnings Before Taxes (EBT Including Unusual Items) | B29: =B21+SUM(B22:B28) -> 3903 | C29: =C21+SUM(C22:C28) -> 4198.6 | D29: =D21+SUM(D22:D28) -> 4317.5 | E29: =E21+SUM(E22:E28) -> 5780 | F29: =F21+SUM(F22:F28) -> 4466.2 | G29: =G21+SUM(G22:G28) -> 1164.4 | H29: =H21+SUM(H22:H28) -> 5356.9 | I29: =I21+SUM(I22:I28) -> 4231.9 | ... K29: =K21+SUM(K22:K28) -> 4969.6
A30: Income Tax Expense | B30: 1143.7 | C30: 1379.7 | D30: 1432.6 | E30: 1262 | F30: 871.6 | G30: 239.7 | H30: 1156.6 | I30: 948.5 | J30: 1277.2 | K30: 1207.3
A31: Earnings from Continued Operations | B31: =B29-B30 -> 2759.3 | C31: =C29-C30 -> 2818.9 | D31: =D29-D30 -> 2884.9 | E31: =E29-E30 -> 4518 | F31: =F29-F30 -> 3594.6 | G31: =G29-G30 -> 924.7 | H31: =H29-H30 -> 4200.3 | I31: =I29-I30 -> 3283.4 | ... K31: =K29-K30 -> 3762.3
A32: Earnings of Discontinued Operations | B32: 0 | C32: 0 | D32: 0 | E32: 0 | F32: 0 | G32: 0 | H32: 0 | I32: 0 | J32: 0 | K32: 0
A33: Extraordinary Item & Account. Change | B33: 0 | C33: 0 | D33: 0 | E33: 0 | F33: 0 | G33: 0 | H33: 0 | I33: 0 | J33: 0 | K33: 0
A34: Net Income to Company | B34: =B31+B32+B33 -> 2759.3 | C34: =C31+C32+C33 -> 2818.9 | D34: =D31+D32+D33 -> 2884.9 | E34: =E31+E32+E33 -> 4518 | F34: =F31+F32+F33 -> 3594.6 | G34: =G31+G32+G33 -> 924.7 | H34: =H31+H32+H33 -> 4200.3 | I34: =I31+I32+I33 -> 3283.4 | ... K34: =K31+K32+K33 -> 3762.3
A35: Minority Interest in Earnings | B35: 1.9 | C35: 1.2 | D35: 0.2 | E35: -0.3 | F35: -4.6 | G35: -3.6 | H35: 1 | I35: 1.8 | J35: 0.2 | K35: 1.4
A36: Net Income | B36: =B34-B35 -> 2757.4 | C36: =C34-C35 -> 2817.7 | D36: =D34-D35 -> 2884.7 | E36: =E34-E35 -> 4518.3 | F36: =F34-F35 -> 3599.2 | G36: =G34-G35 -> 928.3 | H36: =H34-H35 -> 4199.3 | I36: =I34-I35 -> 3281.6 | ... K36: =K34-K35 -> 3760.9
A37: Pref. Dividends and Other Adjustment | B37: 0 | C37: 0 | D37: 0 | E37: 0 | F37: 0 | G37: 0 | H37: 0 | I37: 0 | J37: 0 | K37: 0
A38: NI to Common Incl Extra Items | B38: =B36+B37 -> 2757.4 | C38: =C36+C37 -> 2817.7 | D38: =D36+D37 -> 2884.7 | E38: =E36+E37 -> 4518.3 | F38: =F36+F37 -> 3599.2 | G38: =G36+G37 -> 928.3 | H38: =H36+H37 -> 4199.3 | I38: =I36+I37 -> 3281.6 | ... K38: =K36+K37 -> 3760.9
A39: NI to Common Excl. Extra Items | B39: =B36 -> 2757.4 | C39: =C36 -> 2817.7 | D39: =D36 -> 2884.7 | E39: =E36 -> 4518.3 | F39: =F36 -> 3599.2 | G39: =G36 -> 928.3 | H39: =H36 -> 4199.3 | I39: =I36 -> 3281.6 | ... K39: =K36 -> 3760.9
A41: Per Share Items
A42: Basic EPS | B42: 1.84 | C42: 1.91 | D42: 1.99 | E42: 3.27 | F42: 2.95 | G42: 0.79 | H42: 3.57 | I42: 2.85 | J42: 3.6 | K42: 3.32
A43: Basic EPS Excluding Extra Items | B43: 1.843305 | C43: 1.914718 | D43: 1.990134 | E43: 3.267737 | F43: 2.947264 | G43: 0.791524 | H43: 3.565981 | I43: 2.8454 | J43: 3.596529 | K43: 3.317075
A44: Weighted Avg. Basic Shares Out. | B44: 1495.9 | C44: 1471.6 | D44: 1449.5 | E44: 1382.7 | F44: 1221.2 | G44: 1172.8 | H44: 1177.6 | I44: 1153.3 | J44: 1146.8 | K44: 1133.8
A46: Diluted EPS | B46: 1.82 | C46: 1.9 | D46: 1.97 | E46: 3.24 | F46: 2.92 | G46: 0.79 | H46: 3.54 | I46: 2.83 | J46: 3.58 | K46: 3.31
A47: Diluted EPS Excl. Extra Items | B47: 1.82 | C47: 1.9 | D47: 1.97 | E47: 3.24 | F47: 2.92 | G47: 0.79 | H47: 3.54 | I47: 2.83 | J47: 3.58 | K47: 3.31
A48: Weighted Avg. Diluted Shares Out. | B48: 1513.4 | C48: 1486.7 | D48: 1461.5 | E48: 1394.6 | F48: 1233.2 | G48: 1181.8 | H48: 1185.5 | I48: 1158.5 | J48: 1151.3 | K48: 1137.3
A50: Normalized Basic EPS | B50: 1.49 | C50: 1.78 | D50: 1.89 | E50: 1.87 | F50: 2.04 | G50: 0.81 | H50: 2.5 | I50: 2.32 | J50: 2.92 | K50: 2.75
A51: Normalized Diluted EPS | B51: 1.477038 | C51: 1.761317 | D51: 1.873366 | E51: 1.854555 | F51: 2.019978 | G51: 0.80701 | H51: 2.47986 | I51: 2.314264 | J51: 2.908277 | K51: 2.743207
A53: Dividends per Share | B53: 0.68 | C53: 0.85 | D53: 1.05 | E53: 1.32 | F53: 1.49 | G53: 1.68 | H53: 1.84 | I53: 2 | J53: 2.16 | K53: 2.32
A54: Payout Ratio % | B54: 0.336766 | C54: 0.418071 | D54: 0.50279 | E54: 0.385853 | F54: 0.489358 | G54: 2.072067 | H54: 0.504607 | I54: 0.689694 | J54: 0.589598 | K54: 0.687335
A56: Shares per Depository Receipt | B56: 1 | C56: 1 | D56: 1 | E56: 1 | F56: 1 | G56: 1 | H56: 1 | I56: 1 | J56: 1 | K56: 1
A58: Supplemental Items
A59: EBITDA | B59: 4284.9 | C59: 4883.8 | D59: 4963.9 | E59: 5116 | F59: 5365 | G59: 3103.1 | H59: 6225.7 | I59: 5973.4 | J59: 6976.4 | K59: 6723.3
A60: EBITA | B60: 3401.1 | C60: 3911 | D60: 3954.3 | E60: 3996.6 | F60: 4148.5 | G60: 1823.6 | H60: 4925 | I60: 4636.7 | J60: 5547.6 | K60: 5151.3
A61: EBIT | B61: 3351.1 | C61: 3853.7 | D61: 3896.8 | E61: 3810.1 | F61: 3915.7 | G61: 1599.9 | H61: 4701.6 | I61: 4444 | J61: 5526.1 | K61: 5130.9
A62: EBITDAR | B62: 5410.8 | C62: 6092.4 | D62: 6277.6 | E62: 7354.2 | F62: 7765.3 | G62: 5544.2 | H62: 8787.2 | I62: 8647.5 | J62: 9847.4 | K62: 9773.9
A63: As Reported Total Revenue* | B63: 19162.7 | C63: 21315.9 | D63: 22386.8 | E63: 24719.5 | F63: 26508.6 | G63: 23518 | H63: 29060.6 | I63: 32250.3 | J63: 35975.6 | K63: 36176.2
A64: Effective Tax Rate % | B64: 0.293031 | C64: 0.328609 | D64: 0.331812 | E64: 0.218339 | F64: 0.195154 | G64: 0.205857 | H64: 0.215908 | I64: 0.224131 | J64: 0.236435 | K64: 0.242937
A65: Current Domestic Taxes | B65: 951.1 | C65: 870.6 | D65: 1101.8 | E65: 208.2 | F65: 1862.1 | G65: 86.8 | H65: 871.8 | I65: 641.6 | J65: 914.1 | K65: 892.1
A66: Current Foreign Taxes | B66: 172.2 | C66: 218.5 | D66: 216.6 | E66: 327 | F66: 458.3 | G66: 181.4 | H66: 409.8 | I66: 283.8 | J66: 422.4 | K66: 328.8
A67: Total Current Taxes | B67: 1123.3 | C67: 1089.1 | D67: 1318.4 | E67: 535.2 | F67: 2320.4 | G67: 268.2 | H67: 1281.6 | I67: 925.4 | J67: 1336.5 | K67: 1220.9
A68: Deferred Domestic Taxes | B68: 60.5 | C68: 377.1 | D68: 135.4 | E68: 735.2 | F68: -1396.9 | G68: -13.2 | H68: 4 | I68: 103.1 | J68: 116.2 | K68: 10
A69: Deferred Foreign Taxes | B69: -40.1 | C69: -86.5 | D69: -21.2 | E69: -8.4 | F69: -51.9 | G69: -15.3 | H69: -129 | I69: -80 | J69: -175.5 | K69: -23.6
A70: Total Deferred Taxes | B70: 20.4 | C70: 290.6 | D70: 114.2 | E70: 726.8 | F70: -1448.8 | G70: -28.5 | H70: -125 | I70: 23.1 | J70: -59.3 | K70: -13.6
A72: Normalized Net Income | B72: 2235.35 | C72: 2618.55 | D72: 2737.925 | E72: 2586.3625 | F72: 2491.0375 | G72: 953.725 | H72: 2939.875 | I72: 2681.075 | J72: 3348.3 | K72: 3119.85
A73: Interest on Long Term Debt | B73: 74.2 | C73: 81.3 | D73: 92.5 | E73: NA | F73: NA | G73: NA | H73: 469.8 | I73: NA | J73: NA | K73: NA
A74: Filing Date | B74: 43056 | C74: 43420 | D74: 43784 | E74: 44147 | F74: 44519 | G74: 44883 | H74: 45247 | I74: 45616 | J74: 45616 | K74: 45616
A75: Restatement Type | B75: RC | C75: RC | D75: RC | E75: RC | F75: NC | G75: NC | H75: NC | I75: NC | J75: NC | K75: O
A76: Calculation Type | B76: REP | C76: REP | D76: REP | E76: REP | F76: REP | G76: REP | H76: REP | I76: REP | J76: REP | K76: REP
A78: Supplemental Operating Expense Items
A79: Advertising Exp. | B79: 227.9 | C79: 248.6 | D79: 282.6 | E79: 260.3 | F79: 245.7 | G79: 258.8 | H79: 305.1 | I79: 416.7 | J79: 507.8 | K79: 597.3
A80: General and Administrative Exp. | B80: 1196.7 | C80: 1408.9 | D80: 1408.4 | E80: 1704.6 | F80: 1824.1 | G80: 1679.6 | H80: 1932.6 | I80: 2032 | J80: 2441.3 | K80: 2523.3
A81: Net Rental Exp. | B81: 1125.9 | C81: 1208.6 | D81: 1313.7 | E81: 2238.2 | F81: 2400.3 | G81: 2441.1 | H81: 2561.5 | I81: 2674.1 | J81: 2871 | K81: 3050.6
A82: Imputed Oper. Lease Interest Exp. | B82: 288.91495 | C82: 264.9928 | D82: 258.62024 | E82: 454.94549 | F82: 615.82097 | G82: 467.63664 | H82: 396.47922 | I82: 435.34348 | J82: 521.09798 | K82: 543.56811
A83: Imputed Oper. Lease Depreciation | B83: 836.98505 | C83: 943.6072 | D83: 1055.0798 | E83: 1783.2545 | F83: 1784.479 | G83: 1973.4634 | H83: 2165.0208 | I83: 2238.7565 | J83: 2349.902 | K83: 2507.0319
A85: Stock-Based Comp., G&A Exp. | B85: 0 | C85: 218.1 | D85: 0 | E85: 0 | F85: 0 | G85: 0 | H85: 0 | I85: 0 | J85: 0 | K85: 0
A86: Stock-Based Comp., Unallocated | B86: 209.8 | C86: 0 | D86: 176 | E86: 250.3 | F86: 308 | G86: 248.6 | H86: 319.1 | I86: 271.5 | J86: 302.7 | K86: 308.3
A87: Stock-Based Comp., Total | B87: =B86+B85 -> 209.8 | C87: =C86+C85 -> 218.1 | D87: =D86+D85 -> 176 | E87: =E86+E85 -> 250.3 | F87: =F86+F85 -> 308 | G87: =G86+G85 -> 248.6 | H87: =H86+H85 -> 319.1 | I87: =I86+I85 -> 271.5 | ... K87: =K86+K85 -> 308.3
A89: * Occasionally, certain items classified as Revenue by the company will be re-classified as other income if it is deemed to be non-recurring and unrelated to the core business of the firm. This field shows Total Revenue exactly as reported by the firm on its consolidated statement of income.
A90: Note: For multiple class companies, per share items are primary class equivalent, and for foreign companies listed as primary ADRs, per share items are ADR-equivalent.

Sheet Historical CashFlow Statement
A2: All values are in USD (in millions)
A3: Cash Flow Statement For the Fiscal Period Ending | B3: 12 months Sep-27-2015 | C3: 12 months Oct-02-2016 | D3: 12 months Oct-01-2017 | E3: 12 months Sep-30-2018 | F3: 12 months Sep-29-2019 | G3: 12 months Sep-27-2020 | H3: 12 months Oct-03-2021 | I3: 12 months Oct-02-2022 | J3: 12 months Oct-01-2023 | K3: 12 months Sep-29-2024
A4: Operating Activities
A5: Net Earnings, Including Noncontrolling Interests | B5: 2759.3 | C5: 2818.9 | D5: 2884.9 | E5: 4518 | F5: 3594.6 | G5: 924.7 | H5: 4200.3 | I5: 3283.4 | J5: 4124.7 | K5: 3762.3
A6: Depreciation and Amortization | B6: 933.8 | C6: 1030.1 | D6: 1067.1 | E6: 1305.9 | F6: 1449.3 | G6: 1503.2 | H6: 1524.1 | I6: 1529.4 | J6: 1450.3 | K6: 1592.4
A7: Gain on Sale of Assets | B7: - | C7: - | D7: - | E7: - | F7: - | G7: - | H7: - | I7: - | J7: -91.3 | K7: -
A8: Loss on Retirement and Impairment of Assets | B8: - | C8: - | D8: - | E8: 75.6 | F8: 142.6 | G8: 454.4 | H8: 226.2 | I8: 91.4 | J8: 101.4 | K8: 121.5
A9: Net Gain Resulting from Divestiture of Certain Retail Operations | B9: - | C9: -6.1 | D9: -93.5 | E9: -499.2 | F9: -622.8 | G9: - | H9: -864.5 | I9: - | J9: - | K9: -
A10: Gain Resulting from Sale/acquisition of Equity in Joint Ventures | B10: - | C10: - | D10: - | E10: -1376.4 | F10: - | G10: - | H10: - | I10: - | J10: - | K10: -
A11: Goodwill Impairments | B11: - | C11: - | D11: 87.2 | E11: 37.6 | F11: 10.5 | G11: - | H11: - | I11: - | J11: - | K11: -
A12: Gain Resulting from Acquisition/sale of Equity in Joint Ventures and Certain Retail Operations | B12: -394.3 | C12: - | D12: - | E12: - | F12: - | G12: - | H12: - | I12: - | J12: - | K12: -
A13: Equity in (Income)/losses of Investees | B13: -190.2 | C13: -250.2 | D13: -310.2 | E13: -242.8 | F13: -250.6 | G13: -280.7 | H13: -347.3 | I13: -268.7 | J13: -301.8 | K13: -306.4
A14: Distributions Received from Equity Method Investees | B14: 148.2 | C14: 223.3 | D14: 186.6 | E14: 226.8 | F14: 216.8 | G14: 227.7 | H14: 336 | I14: 231.2 | J14: 222.8 | K14: 333.3
A15: Stock based Compensation | B15: 209.8 | C15: 218.1 | D15: 176 | E15: 250.3 | F15: 308 | G15: 248.6 | H15: 319.1 | I15: 271.5 | J15: 302.7 | K15: 308.3
A16: Excess Tax Benefit from Exercise of Stock Options | B16: -132.4 | C16: - | D16: - | E16: - | F16: - | G16: - | H16: - | I16: - | J16: - | K16: -
A17: Deferred Income Taxes, Net | B17: 21.2 | C17: 265.7 | D17: 95.1 | E17: 714.9 | F17: -1495.4 | G17: -25.8 | H17: -146.2 | I17: -37.8 | J17: -59.4 | K17: -13.8
A18: Others | B18: 53.8 | C18: 45.1 | D18: 68.9 | E18: 13.4 | F18: 45.3 | G18: 24.5 | H18: -6 | I18: -67.8 | J18: 26.8 | K18: 31.9
A19: Loss on Extinguishment of Debt | B19: 61.1 | C19: - | D19: - | E19: - | F19: - | G19: - | H19: - | I19: - | J19: - | K19: -
A20: Non-cash Lease Costs | B20: - | C20: - | D20: - | E20: - | F20: - | G20: 1197.6 | H20: 1248.6 | I20: 1497.7 | J20: 1365.9 | K20: 1314.9
A21: Accounts Receivable | B21: -82.8 | C21: -55.6 | D21: -96.8 | E21: 131 | F21: -197.7 | G21: -2.7 | H21: -43 | I21: -326.1 | J21: -4.1 | K21: 18.4
A22: Inventories | B22: -207.9 | C22: -67.5 | D22: 14 | E22: -41.2 | F22: -173 | G22: -10.9 | H22: -49.8 | I22: -641 | J22: 366.4 | K22: 42.8
A23: Change in Accounts Payable | B23: 137.7 | C23: 46.9 | D23: 46.4 | E23: 391.6 | F23: 31.9 | G23: -210.8 | H23: 189.9 | I23: 345.5 | J23: 100.1 | K23: 28
A24: Income Taxes Payables | B24: - | C24: - | D24: -91.9 | E24: 146 | F24: 1237.1 | G24: -1214.6 | H24: 286.1 | I24: -149.6 | J24: 52.5 | K24: -61.9
A25: Deferred Revenue | B25: - | C25: 180.4 | D25: 130.8 | E25: 7109.4 | F25: -30.5 | G25: 31 | H25: -6.1 | I25: -75.8 | J25: -110.8 | K25: -72.2
A26: Stored Value Card Liability | B26: 170.3 | C26: - | D26: - | E26: - | F26: - | G26: - | H26: - | I26: - | J26: - | K26: -
A27: Prepaid Expenses and Other Current Assets | B27: - | C27: - | D27: -20 | E27: -839.5 | F27: 922 | G27: - | H27: - | I27: - | J27: - | K27: -
A28: Other Operating Assets and Liabilities | B28: 261.5 | C28: 248.8 | D28: 107.2 | E28: 16.4 | F28: -141.1 | G28: -37 | H28: 609.8 | I28: 339.6 | J28: -93.7 | K28: 291
A29: Operating Lease Liability | B29: - | C29: - | D29: - | E29: - | F29: - | G29: -1231.4 | H29: -1488.1 | I29: -1625.6 | J29: -1443.8 | K29: -1294.9
A30: Cash Flow from Operating Activities | B30: 3749.1 | C30: 4697.9 | D30: 4251.8 | E30: 11937.8 | F30: 5047 | G30: 1597.8 | H30: 5989.1 | I30: 4397.3 | J30: 6008.7 | K30: 6095.6
A32: Investing Activities
A33: Others | B33: 6.8 | C33: 24.9 | D33: 54.3 | E33: 5.6 | F33: -56.2 | G33: -44.4 | H33: -81.2 | I33: -126.3 | J33: -56.1 | K33: -72.7
A34: Additions to Property Plant and Equipment | B34: -1303.7 | C34: -1440.3 | D34: -1519.4 | E34: -1976.4 | F34: -1806.6 | G34: -1483.6 | H34: -1470 | I34: -1841.3 | J34: -2333.6 | K34: -2777.5
A35: Proceeds from the Sale of Property, Plant & Equipment | B35: - | C35: - | D35: - | E35: - | F35: - | G35: - | H35: - | I35: - | J35: 110 | K35: -
A36: Acquisitions, Net of Cash Acquired | B36: -284.3 | C36: - | D36: - | E36: -1311.3 | F36: - | G36: - | H36: - | I36: - | J36: - | K36: -
A37: Net Proceeds from the Divestiture of Certain Operations | B37: - | C37: 69.6 | D37: 85.4 | E37: 608.2 | F37: 684.3 | G37: - | H37: 1175 | I37: 59.3 | J37: - | K37: -
A38: Proceeds from Sale of Equity in Joint Ventures and Certain Retail Operations | B38: 8.9 | C38: - | D38: - | E38: - | F38: - | G38: - | H38: - | I38: - | J38: - | K38: -
A39: Purchase of Investments | B39: -567.4 | C39: -1585.7 | D39: -674.4 | E39: -191.9 | F39: -190.4 | G39: -443.9 | H39: -432 | I39: -377.9 | J39: -610.5 | K39: -627.5
A40: Sale of Investment | B40: 600.6 | C40: 680.7 | D40: 1054.5 | E40: 459 | F40: 298.3 | G40: 186.7 | H40: 143.2 | I40: 72.6 | J40: 2.5 | K40: 10.3
A41: Maturities and Calls of Investments | B41: 18.8 | C41: 27.9 | D41: 149.6 | E41: 45.3 | F41: 59.8 | G41: 73.7 | H41: 345.5 | I41: 67.3 | J41: 616.9 | K41: 768.2
A42: Cash Flow from Investing Activities | B42: -1520.3 | C42: -2222.9 | D42: -850 | E42: -2361.5 | F42: -1010.8 | G42: -1711.5 | H42: -319.5 | I42: -2146.3 | J42: -2270.8 | K42: -2699.2
A44: Financing Activities
A45: Others | B45: -18.1 | C45: -8.4 | D45: -4.4 | E45: -41.2 | F45: -17.5 | G45: -37.7 | H45: - | I45: -9.2 | J45: -11.1 | K45: -10.6
A46: Net Proceeds from Issuances of Long-term Debt | B46: -610.1 | C46: 1254.5 | D46: -400 | E46: 5584.1 | F46: -350 | G46: 4727.6 | H46: -1250 | I46: -1000 | J46: -1000 | K46: -1825.1
A47: Net Proceeds from Issuances of Long-term Debt | B47: 848.5 | C47: - | D47: 750.2 | E47: - | F47: 1996 | G47: - | H47: - | I47: 1498.1 | J47: 1497.8 | K47: 1995.3
A48: Net Proceeds from Issuance of Short-term Debt | B48: - | C48: - | D48: - | E48: - | F48: - | G48: 1406.6 | H48: 215.1 | I48: 36.6 | J48: 114.6 | K48: 123.8
A49: Repayments of Short-term Debt | B49: - | C49: - | D49: - | E49: - | F49: - | G49: -967.7 | H49: -349.8 | I49: -36.6 | J49: -78.8 | K49: -157.5
A50: Short-term Debt, Notes Payable, Etc | B50: - | C50: - | D50: - | E50: - | F50: - | G50: - | H50: - | I50: 175 | J50: -175 | K50: -
A51: Net (payments)/proceeds from issuance of Commercial paper | B51: - | C51: - | D51: - | E51: - | F51: - | G51: - | H51: -296.5 | I51: - | J51: - | K51: -
A52: Proceeds from Issuance of Common Stock | B52: 191.8 | C52: 160.7 | D52: 150.8 | E52: 153.9 | F52: 409.8 | G52: 298.8 | H52: 246.2 | I52: 101.6 | J52: 167.4 | K52: 108
A53: Repurchase of Common Stock | B53: -1436.1 | C53: -1995.6 | D53: -2042.5 | E53: -7133.5 | F53: -10222.3 | G53: -1698.9 | H53: - | I53: -4013 | J53: -984.4 | K53: -1266.7
A54: Minimum Tax Withholdings on Share Based Awards | B54: -75.5 | C54: -106 | D54: -82.8 | E54: -62.7 | F54: -111.6 | G54: -91.9 | H54: -97 | I54: -127.2 | J54: -89.3 | K54: -100.4
A55: Cash Dividends Paid | B55: -928.6 | C55: -1178 | D55: -1450.4 | E55: -1743.4 | F55: -1761.3 | G55: -1923.5 | H55: -2119 | I55: -2263.3 | J55: -2431.8 | K55: -2585
A56: Tax Benefit from Exercise of Nonqualified Stock Options | B56: 132.4 | C56: - | D56: - | E56: - | F56: - | G56: - | H56: - | I56: - | J56: - | K56: -
A57: Cash Used or Restricted for Purchase of Noncontrolling Interest | B57: -360.8 | C57: - | D57: - | E57: - | F57: - | G57: - | H57: - | I57: - | J57: - | K57: -
A58: Cash Flow from Financing Activities | B58: -2256.5 | C58: -1872.8 | D58: -3079.1 | E58: -3242.8 | F58: -10056.9 | G58: 1713.3 | H58: -3651 | I58: -5638 | J58: -2990.6 | K58: -3718.2
A60: Other Adjustments
A61: Foreign Exchange Rate Effect on Cash and Cash Equivalents | B61: -150.6 | C61: -3.5 | D61: 10.8 | E61: -39.5 | F61: -49 | G61: 64.7 | H61: 86.2 | I61: -250.3 | J61: -14.2 | K61: 56.5
A62: Cash Flow Net Changes in Cash | B62: -178.3 | C62: 598.7 | D62: 333.5 | E62: 6294 | F62: -6069.7 | G62: 1664.3 | H62: 2104.8 | I62: -3637.3 | J62: 733.1 | K62: -265.3

Sheet Real Revenue
A1: (All values are in $million USD)
A3: Net Sales as of: | B3: 2015 | C3: =B3+1 -> 2016 | D3: =C3+1 -> 2017 | E3: =D3+1 -> 2018 | F3: =E3+1 -> 2019 | G3: =F3+1 -> 2020 | H3: =G3+1 -> 2021 | I3: =H3+1 -> 2022 | J3: =I3+1 -> 2023 | K3: =J3+1 -> 2024
A4: Net Revenue (millions) | B4: ='Historical Income Statement'!B6 -> 19162.7 | C4: ='Historical Income Statement'!C6 -> 21315.9 | D4: ='Historical Income Statement'!D6 -> 22386.8 | E4: ='Historical Income Statement'!E6 -> 24719.5 | F4: ='Historical Income Statement'!F6 -> 26508.6 | G4: ='Historical Income Statement'!G6 -> 23518 | H4: ='Historical Income Statement'!H6 -> 29060.6 | I4: ='Historical Income Statement'!I6 -> 32250.3 | ... K4: ='Historical Income Statement'!K6 -> 36176.2
A7: Real Sales (in 2024 USD) | B7: =B3 -> 2015 | C7: =C3 -> 2016 | D7: =D3 -> 2017 | E7: =E3 -> 2018 | F7: =F3 -> 2019 | G7: =G3 -> 2020 | H7: =H3 -> 2021 | I7: =I3 -> 2022 | ... K7: =K3 -> 2024
A8: Net Real Revenue (millions) | B8: =B4*C17 -> 25569.576 | C8: =C4*C18 -> 27864.594 | D8: =D4*C19 -> 28660.033 | E8: =E4*C20 -> 31053.237 | F8: =F4*C21 -> 32556.783 | G8: =G4*C22 -> 28495.736 | H8: =H4*C23 -> 32896.718 | I8: =I4*C24 -> 34293.999 | J8: =J4*C25 -> 37014.596 | K8: =K4*C26 -> 36176.2
A10: Real Annual Revenue Growth Rates, 2015-2024 | B10: =B7 -> 2015 | C10: =C7 -> 2016 | D10: =D7 -> 2017 | E10: =E7 -> 2018 | F10: =F7 -> 2019 | G10: =G7 -> 2020 | H10: =H7 -> 2021 | I10: =I7 -> 2022 | ... K10: =K7 -> 2024 | L10: Average Growth Rate Over the Period
A11: Real Growth Rate | C11: =(C8/B8)-1 -> 0.089755809 | D11: =(D8/C8)-1 -> 0.028546597 | E11: =(E8/D8)-1 -> 0.083503165 | F11: =(F8/E8)-1 -> 0.04841834 | G11: =(G8/F8)-1 -> -0.12473734 | H11: =(H8/G8)-1 -> 0.15444351 | I11: =(I8/H8)-1 -> 0.042474787 | J11: =(J8/I8)-1 -> 0.079331583 | K11: =(K8/J8)-1 -> -0.022650414 | L11: {=GEOMEAN(1+C11:K11)-1} -> 0.039308263
A12: Real GDP (Start of Year) | B12: 18666.621 | C12: 19001.69 | D12: 19398.343 | E12: 20044.077 | F12: 20431.641 | G12: 20709.212 | H12: 21082.134 | I12: 21932.71 | J12: 22439.607 | K12: 23082.119
A13: Real GDP Growth Rate | C13: =(C12-B12)/B12 -> 0.017950169 | D13: =(D12-C12)/C12 -> 0.020874617 | E13: =(E12-D12)/D12 -> 0.033288101 | F13: =(F12-E12)/E12 -> 0.019335587 | G13: =(G12-F12)/F12 -> 0.01358535 | H13: =(H12-G12)/G12 -> 0.018007542 | I13: =(I12-H12)/H12 -> 0.040345821 | J13: =(J12-I12)/I12 -> 0.023111462 | K13: =(K12-J12)/J12 -> 0.028632944 | L13: {=GEOMEAN(1+C13:K13)-1} -> 0.02387173
A14: Correlation, Real Sales vs Real GDP | B14: =CORREL(C11:K11,C13:K13) -> 0.15573221
A16: Year | B16: CPI (September) | C16: Adjustment Factor | D16: Rate of Growth
A17: 2015 | B17: 236.525 | C17: =$B$26/B17 -> 1.334341
A18: =A17+1 -> 2016 | B18: 241.432 | C18: =$B$26/B18 -> 1.3072211 | D18: =(B18-B17)/B17 -> 0.020746221
A19: =A18+1 -> 2017 | B19: 246.524 | C19: =$B$26/B19 -> 1.2802202 | D19: =(B19-B18)/B18 -> 0.021090825
A20: =A19+1 -> 2018 | B20: 251.233 | C20: =$B$26/B20 -> 1.2562243 | D20: =(B20-B19)/B19 -> 0.019101588
A21: =A20+1 -> 2019 | B21: 256.974 | C21: =$B$26/B21 -> 1.2281593 | D21: =(B21-B20)/B20 -> 0.022851297
A22: =A21+1 -> 2020 | B22: 260.474 | C22: =$B$26/B22 -> 1.2116564 | D22: =(B22-B21)/B21 -> 0.013620055
A23: =A22+1 -> 2021 | B23: 278.802 | C23: =$B$26/B23 -> 1.1320041 | D23: =(B23-B22)/B22 -> 0.070364029
A24: =A23+1 -> 2022 | B24: 296.797 | C24: =$B$26/B24 -> 1.0633699 | D24: =(B24-B23)/B23 -> 0.064544013
A25: =A24+1 -> 2023 | B25: 306.746 | C25: =$B$26/B25 -> 1.0288806 | D25: =(B25-B24)/B24 -> 0.033521228
A26: =A25+1 -> 2024 | B26: 315.605 | C26: =$B$26/B26 -> 1 | D26: =(B26-B25)/B25 -> 0.028880572
A29: Additional Comments:
A30: The -2.27%: Under normal circumstances, we would disregard this figure when calcultaing the average growth rate. However, since the growth rate in 2020 was negative due to the effect of the pandemic, whose effects are going to be felt in the upcoming years, we shall include this figure in our calculations.
A31: Correlation measures the linear relationship between Starbucks real sales growth and US real GDP growth.
A32: A low correlation means that Starbucks’ sales don’t strongly move with the economy, they are relatively independent of GDP trends. Hence, good argument for NOT using expected growth in GDP approach to forecast sales.
A33: Correlation measures the linear relationship between Starbucks real sales growth and US real GDP growth.
A34: A low correlation means that Starbucks’ sales don’t strongly move with the economy, they are relatively independent of GDP trends. Hence, good argument for NOT using expected growth in GDP approach to forecast sales.
A35: The “Real GDP (Start of Year)” numbers are the same no matter which company you are valuing, because they come from official macroeconomic data (BEA/FRED) and represent the entire US economy.

Sheet Real Operating Costs
A1: (All values are in $million)
B2: 2015 | C2: =B2+1 -> 2016 | D2: =C2+1 -> 2017 | E2: =D2+1 -> 2018 | F2: =E2+1 -> 2019 | G2: =F2+1 -> 2020 | H2: =G2+1 -> 2021 | I2: =H2+1 -> 2022 | J2: =I2+1 -> 2023 | K2: =J2+1 -> 2024
A3: Revenues | B3: ='Historical Income Statement'!B6 -> 19162.7 | C3: ='Historical Income Statement'!C6 -> 21315.9 | D3: ='Historical Income Statement'!D6 -> 22386.8 | E3: ='Historical Income Statement'!E6 -> 24719.5 | F3: ='Historical Income Statement'!F6 -> 26508.6 | G3: ='Historical Income Statement'!G6 -> 23518 | H3: ='Historical Income Statement'!H6 -> 29060.6 | I3: ='Historical Income Statement'!I6 -> 32250.3 | ... K3: ='Historical Income Statement'!K6 -> 36176.2
A5: Expenses:
A6: Cost of goods sold | B6: ='Historical Income Statement'!B7 -> 13198.6 | C6: ='Historical Income Statement'!C7 -> 14573.3 | D6: ='Historical Income Statement'!D7 -> 15552.2 | E6: ='Historical Income Statement'!E7 -> 17402.9 | F6: ='Historical Income Statement'!F7 -> 19020.5 | G6: ='Historical Income Statement'!G7 -> 18376.9 | H6: ='Historical Income Statement'!H7 -> 20625.2 | I6: ='Historical Income Statement'!I7 -> 23864.9 | ... K6: ='Historical Income Statement'!K7 -> 26443.8
A7: Selling General & Admin Exp. | B7: ='Historical Income Statement'!B9 -> 1196.7 | C7: ='Historical Income Statement'!C9 -> 1408.9 | D7: ='Historical Income Statement'!D9 -> 1408.4 | E7: ='Historical Income Statement'!E9 -> 1704.6 | F7: ='Historical Income Statement'!F9 -> 1824.1 | G7: ='Historical Income Statement'!G9 -> 1679.6 | H7: ='Historical Income Statement'!H9 -> 1932.6 | I7: ='Historical Income Statement'!I9 -> 2032 | ... K7: ='Historical Income Statement'!K9 -> 2523.3
A8: Depreciation and Amortization | B8: ='Historical Income Statement'!B11 -> 893.9 | C8: ='Historical Income Statement'!C11 -> 980.8 | D8: ='Historical Income Statement'!D11 -> 1011.4 | E8: ='Historical Income Statement'!E11 -> 1247 | F8: ='Historical Income Statement'!F11 -> 1377.3 | G8: ='Historical Income Statement'!G11 -> 1431.3 | H8: ='Historical Income Statement'!H11 -> 1441.7 | I8: ='Historical Income Statement'!I11 -> 1447.9 | ... K8: ='Historical Income Statement'!K11 -> 1512.6
A9: Other Operating Expense/(Income) | B9: ='Historical Income Statement'!B12 -> 522.4 | C9: ='Historical Income Statement'!C12 -> 499.2 | D9: ='Historical Income Statement'!D12 -> 518 | E9: ='Historical Income Statement'!E12 -> 554.9 | F9: ='Historical Income Statement'!F12 -> 371 | G9: ='Historical Income Statement'!G12 -> 430.3 | H9: ='Historical Income Statement'!H12 -> 359.5 | I9: ='Historical Income Statement'!I12 -> 461.5 | ... K9: ='Historical Income Statement'!K12 -> 565.6
A10: Adjusted Net Operating Costs | B10: =B6+B7-B8+B9 -> 14023.8 | C10: =C6+C7-C8+C9 -> 15500.6 | D10: =D6+D7-D8+D9 -> 16467.2 | E10: =E6+E7-E8+E9 -> 18415.4 | F10: =F6+F7-F8+F9 -> 19838.3 | G10: =G6+G7-G8+G9 -> 19055.5 | H10: =H6+H7-H8+H9 -> 21475.6 | I10: =I6+I7-I8+I9 -> 24910.5 | ... K10: =K6+K7-K8+K9 -> 28020.1
A14: Real Sales (in 2024 USD) | B14: =B2 -> 2015 | C14: =C2 -> 2016 | D14: =D2 -> 2017 | E14: =E2 -> 2018 | F14: =F2 -> 2019 | G14: =G2 -> 2020 | H14: =H2 -> 2021 | I14: =I2 -> 2022 | ... K14: =K2 -> 2024
A15: Net Real Costs (millions) | B15: =B10*C24 -> 18712.531 | C15: =C10*C25 -> 20262.711 | D15: =D10*C26 -> 21081.642 | E15: =E10*C27 -> 23133.873 | F15: =F10*C28 -> 24364.592 | G15: =G10*C29 -> 23088.719 | H15: =H10*C30 -> 24310.467 | I15: =I10*C31 -> 26489.076 | J15: =J10*C32 -> 28524.994 | K15: =K10*C33 -> 28020.1
A16: Net Real Revenue (millions) | B16: ='Real Revenue'!B8 -> 25569.576 | C16: ='Real Revenue'!C8 -> 27864.594 | D16: ='Real Revenue'!D8 -> 28660.033 | E16: ='Real Revenue'!E8 -> 31053.237 | F16: ='Real Revenue'!F8 -> 32556.783 | G16: ='Real Revenue'!G8 -> 28495.736 | H16: ='Real Revenue'!H8 -> 32896.718 | I16: ='Real Revenue'!I8 -> 34293.999 | ... K16: ='Real Revenue'!K8 -> 36176.2
A17: Correlation, Real Costs vs Real Sales | B17: =CORREL(B15:K15,B16:K16) -> 0.97612696
A19: Real Annual Revenue Growth Rates, 2015-2024 | B19: =B14 -> 2015 | C19: =C14 -> 2016 | D19: =D14 -> 2017 | E19: =E14 -> 2018 | F19: =F14 -> 2019 | G19: =G14 -> 2020 | H19: =H14 -> 2021 | I19: =I14 -> 2022 | ... K19: =K14 -> 2024
A20: Real Growth Rate | C20: =(C15/B15)-1 -> 0.082841817 | D20: =(D15/C15)-1 -> 0.040415652 | E20: =(E15/D15)-1 -> 0.097346841 | F20: =(F15/E15)-1 -> 0.053199869 | G20: =(G15/F15)-1 -> -0.052365855 | H20: =(H15/G15)-1 -> 0.052915338 | I20: =(I15/H15)-1 -> 0.089616112 | J20: =(J15/I15)-1 -> 0.076858756 | K20: =(K15/J15)-1 -> -0.017700044
A23: Year | B23: CPI (September) | C23: Adjustment Factor | D23: Rate of Growth
A24: 2015 | B24: 236.525 | C24: =$B$33/B24 -> 1.334341
A25: =A24+1 -> 2016 | B25: 241.432 | C25: =$B$33/B25 -> 1.3072211 | D25: =(B25-B24)/B24 -> 0.020746221
A26: =A25+1 -> 2017 | B26: 246.524 | C26: =$B$33/B26 -> 1.2802202 | D26: =(B26-B25)/B25 -> 0.021090825
A27: =A26+1 -> 2018 | B27: 251.233 | C27: =$B$33/B27 -> 1.2562243 | D27: =(B27-B26)/B26 -> 0.019101588
A28: =A27+1 -> 2019 | B28: 256.974 | C28: =$B$33/B28 -> 1.2281593 | D28: =(B28-B27)/B27 -> 0.022851297
A29: =A28+1 -> 2020 | B29: 260.474 | C29: =$B$33/B29 -> 1.2116564 | D29: =(B29-B28)/B28 -> 0.013620055
A30: =A29+1 -> 2021 | B30: 278.802 | C30: =$B$33/B30 -> 1.1320041 | D30: =(B30-B29)/B29 -> 0.070364029
A31: =A30+1 -> 2022 | B31: 296.797 | C31: =$B$33/B31 -> 1.0633699 | D31: =(B31-B30)/B30 -> 0.064544013
A32: =A31+1 -> 2023 | B32: 306.746 | C32: =$B$33/B32 -> 1.0288806 | D32: =(B32-B31)/B31 -> 0.033521228
A33: =A32+1 -> 2024 | B33: 315.605 | C33: =$B$33/B33 -> 1 | D33: =(B33-B32)/B32 -> 0.028880572
A35: Additional Comments:
A36: Calculation of Net Real Operating Costs = COGS + SG&A − Depreciation caused problems:
A37: Depreciation is non-cash, so subtracting just that made costs artificially small in later years.
A38: This led to the weird negative correlation with revenue. To fix this, added other expenses to the calculation
A39: Correlation = 0.98 is very high and positive, almost perfect.
A40: This means that Net Real Operating Costs increase almost proportionally with Real Revenue.
A41: In other words, as Starbucks earns more revenue, its costs rise in a very predictable way.
A42: This is exactly what we expect for a stable operating business, revenues and operating expenses are strongly linked.

Sheet Forecasting Sales
A2: Real Sales (in 2024 USD) | B2: 2015 | C2: 2016 | D2: 2017 | E2: 2018 | F2: 2019 | G2: 2020 | H2: 2021 | I2: 2022 | J2: 2023 | K2: 2024
A3: Net Real Revenue (millions) | B3: ='Real Operating Costs'!B16 -> 25569.576 | C3: ='Real Operating Costs'!C16 -> 27864.594 | D3: ='Real Operating Costs'!D16 -> 28660.033 | E3: ='Real Operating Costs'!E16 -> 31053.237 | F3: ='Real Operating Costs'!F16 -> 32556.783 | G3: ='Real Operating Costs'!G16 -> 28495.736 | H3: ='Real Operating Costs'!H16 -> 32896.718 | I3: ='Real Operating Costs'!I16 -> 34293.999 | ... K3: ='Real Operating Costs'!K16 -> 36176.2
A4: Net Real Operating Costs (millions) | B4: ='Real Operating Costs'!B15 -> 18712.531 | C4: ='Real Operating Costs'!C15 -> 20262.711 | D4: ='Real Operating Costs'!D15 -> 21081.642 | E4: ='Real Operating Costs'!E15 -> 23133.873 | F4: ='Real Operating Costs'!F15 -> 24364.592 | G4: ='Real Operating Costs'!G15 -> 23088.719 | H4: ='Real Operating Costs'!H15 -> 24310.467 | I4: ='Real Operating Costs'!I15 -> 26489.076 | ... K4: ='Real Operating Costs'!K15 -> 28020.1
A21: Period | B21: Net Real Revenue (millions) | C21: Forecasts
A22: 2015 | B22: 25569.576
A23: 2016 | B23: 27864.594
A24: 2017 | B24: 28660.033
A25: 2018 | B25: 31053.237
A26: 2019 | B26: 32556.783
A27: 2021 | B27: 32896.718 | C27: Excluding year 2020: COVID
A28: 2022 | B28: 34293.999
A29: 2023 | B29: 37014.596 | C29: FORECAST.LINEAR Approach
A30: 2024 | B30: 36176.2 | C30: Projected Sales | D30: Projected Growth Rates
A31: 2025 | C31: =_xlfn.FORECAST.LINEAR(A31,$B$22:$B$30,$A$22:$A$30) -> 38288.669 | D31: =(C31-B29)/B29 -> 0.034420842 | E31: Slight post-COVID normalization
A32: 2026 | C32: =_xlfn.FORECAST.LINEAR(A32,$B$22:$B$30,$A$22:$A$30) -> 39458.915 | D32: =(C32-C31)/C31 -> 0.030563763
A33: 2027 | C33: =_xlfn.FORECAST.LINEAR(A33,$B$22:$B$30,$A$22:$A$30) -> 40629.161 | D33: =(C33-C32)/C32 -> 0.029657324 | E33: Growth rate decreasing hereon, Reflects mature company stabilization
A34: 2028 | C34: =_xlfn.FORECAST.LINEAR(A34,$B$22:$B$30,$A$22:$A$30) -> 41799.407 | D34: =(C34-C33)/C33 -> 0.028803101
A35: 2029 | C35: =_xlfn.FORECAST.LINEAR(A35,$B$22:$B$30,$A$22:$A$30) -> 42969.653 | D35: =(C35-C34)/C34 -> 0.027996709
A36: 2030 | C36: =_xlfn.FORECAST.LINEAR(A36,$B$22:$B$30,$A$22:$A$30) -> 44139.899 | D36: =(C36-C35)/C35 -> 0.02723424
A37: 2031 | C37: =_xlfn.FORECAST.LINEAR(A37,$B$22:$B$30,$A$22:$A$30) -> 45310.144 | D37: =(C37-C36)/C36 -> 0.0265122
A38: 2032 | C38: =_xlfn.FORECAST.LINEAR(A38,$B$22:$B$30,$A$22:$A$30) -> 46480.39 | D38: =(C38-C37)/C37 -> 0.025827457
A39: 2033 | C39: =_xlfn.FORECAST.LINEAR(A39,$B$22:$B$30,$A$22:$A$30) -> 47650.636 | D39: =(C39-C38)/C38 -> 0.025177194
A40: 2034 | C40: =_xlfn.FORECAST.LINEAR(A40,$B$22:$B$30,$A$22:$A$30) -> 48820.882 | D40: =(C40-C39)/C39 -> 0.024558871
C42: Additional Commment: I used FORECAST.LINEAR() because the trend is mostly linear beside COVID year where the dip is an outlier. Excluding year 2020 as an outlier, 2020 was a pandemic shock year, not representative of Starbucks’ long-term fundamentals.

Sheet Forecasting Costs
A2: Period | B2: 2015 | C2: =B2+1 -> 2016 | D2: =C2+1 -> 2017 | E2: =D2+1 -> 2018 | F2: =E2+1 -> 2019 | G2: =F2+1 -> 2020 | H2: =G2+1 -> 2021 | I2: =H2+1 -> 2022 | J2: =I2+1 -> 2023 | K2: =J2+1 -> 2024
A3: Net Real Revenue (millions) | B3: ='Real Operating Costs'!B16 -> 25569.576 | C3: ='Real Operating Costs'!C16 -> 27864.594 | D3: ='Real Operating Costs'!D16 -> 28660.033 | E3: ='Real Operating Costs'!E16 -> 31053.237 | F3: ='Real Operating Costs'!F16 -> 32556.783 | G3: ='Real Operating Costs'!G16 -> 28495.736 | H3: ='Real Operating Costs'!H16 -> 32896.718 | I3: ='Real Operating Costs'!I16 -> 34293.999 | ... K3: ='Real Operating Costs'!K16 -> 36176.2
A4: Net Real Operating Costs (millions) | B4: ='Real Operating Costs'!B15 -> 18712.531 | C4: ='Real Operating Costs'!C15 -> 20262.711 | D4: ='Real Operating Costs'!D15 -> 21081.642 | E4: ='Real Operating Costs'!E15 -> 23133.873 | F4: ='Real Operating Costs'!F15 -> 24364.592 | G4: ='Real Operating Costs'!G15 -> 23088.719 | H4: ='Real Operating Costs'!H15 -> 24310.467 | I4: ='Real Operating Costs'!I15 -> 26489.076 | ... K4: ='Real Operating Costs'!K15 -> 28020.1
J5: Correlation | K5: =CORREL(B3:K3,B4:K4) -> 0.97612696 | L5: positive correlation, this confirms again that Net Real Operating Costs increase almost proportionally with Real Revenue.
A21: Period | B21: Net Real Revenue (millions) | C21: Net Real Operating Costs
A22: 2015 | B22: 25569.576 | C22: 10795.219 | E22: Costs = f(Revenues) intercept | H22: =INTERCEPT(C22:C30,B22:B30) -> 38871.15 | I22: excluded 2020 here as well for consistency
A23: 2016 | B23: 27864.594 | C23: 11682.766 | E23: Costs = f(Revenues) slope | H23: =SLOPE(C22:C30,B22:B30) -> -1.0954159
A24: 2017 | B24: 28660.033 | C24: 9554.0272
A25: 2018 | B25: 31053.237 | C25: 579.37065
A26: 2019 | B26: 32556.783 | C26: 548.74156
A27: 2021 | B27: 32896.718 | C27: 555.7008
A28: 2022 | B28: 34293.999 | C28: 621.11437
A29: 2023 | B29: 37014.596 | C29: 1109.8535
A30: 2024 | B30: 36176.2 | C30: 1010.7
A31: 2025 | B31: ='Forecasting Sales'!C31 -> 38288.669 | C31: =$H$22+$H$23*B31 -> -3070.8668
A32: 2026 | B32: ='Forecasting Sales'!C32 -> 39458.915 | C32: =$H$22+$H$23*B32 -> -4352.7727
A33: 2027 | B33: ='Forecasting Sales'!C33 -> 40629.161 | C33: =$H$22+$H$23*B33 -> -5634.6785
A34: 2028 | B34: ='Forecasting Sales'!C34 -> 41799.407 | C34: =$H$22+$H$23*B34 -> -6916.5844
A35: 2029 | B35: ='Forecasting Sales'!C35 -> 42969.653 | C35: =$H$22+$H$23*B35 -> -8198.4903
A36: 2030 | B36: ='Forecasting Sales'!C36 -> 44139.899 | C36: =$H$22+$H$23*B36 -> -9480.3961
A37: 2031 | B37: ='Forecasting Sales'!C37 -> 45310.144 | C37: =$H$22+$H$23*B37 -> -10762.302
A38: 2032 | B38: ='Forecasting Sales'!C38 -> 46480.39 | C38: =$H$22+$H$23*B38 -> -12044.208
A39: 2033 | B39: ='Forecasting Sales'!C39 -> 47650.636 | C39: =$H$22+$H$23*B39 -> -13326.114
A40: 2034 | B40: ='Forecasting Sales'!C40 -> 48820.882 | C40: =$H$22+$H$23*B40 -> -14608.02

Sheet Interest & Taxes
A1: All values are in $million, USD
B2: 2015 | C2: =B2+1 -> 2016 | D2: =C2+1 -> 2017 | E2: =D2+1 -> 2018 | F2: =E2+1 -> 2019 | G2: =F2+1 -> 2020 | H2: =G2+1 -> 2021 | I2: =H2+1 -> 2022 | J2: =I2+1 -> 2023 | K2: =J2+1 -> 2024
A3: Total Revenue (Net Real Revenue) | B3: ='Real Operating Costs'!B16 -> 25569.576 | C3: ='Real Operating Costs'!C16 -> 27864.594 | D3: ='Real Operating Costs'!D16 -> 28660.033 | E3: ='Real Operating Costs'!E16 -> 31053.237 | F3: ='Real Operating Costs'!F16 -> 32556.783 | G3: ='Real Operating Costs'!G16 -> 28495.736 | H3: ='Real Operating Costs'!H16 -> 32896.718 | I3: ='Real Operating Costs'!I16 -> 34293.999 | ... K3: ='Real Operating Costs'!K16 -> 36176.2
A4: EBITDA | B4: ='Historical Income Statement'!B59 -> 4284.9 | C4: ='Historical Income Statement'!C59 -> 4883.8 | D4: ='Historical Income Statement'!D59 -> 4963.9 | E4: ='Historical Income Statement'!E59 -> 5116 | F4: ='Historical Income Statement'!F59 -> 5365 | G4: ='Historical Income Statement'!G59 -> 3103.1 | H4: ='Historical Income Statement'!H59 -> 6225.7 | I4: ='Historical Income Statement'!I59 -> 5973.4 | ... K4: ='Historical Income Statement'!K59 -> 6723.3
A6: Long-Term Debt | B6: ='Historical Balance Sheet'!B42 -> 2347.5 | C6: ='Historical Balance Sheet'!C42 -> 3185.3 | D6: ='Historical Balance Sheet'!D42 -> 3932.6 | E6: ='Historical Balance Sheet'!E42 -> 9122.7 | F6: ='Historical Balance Sheet'!F42 -> 11169.6 | G6: ='Historical Balance Sheet'!G42 -> 14728.9 | H6: ='Historical Balance Sheet'!H42 -> 13618.2 | I6: ='Historical Balance Sheet'!I42 -> 13153.9 | ... K6: ='Historical Balance Sheet'!K42 -> 14338.7
A7: Interest Expense | B7: ='Historical Income Statement'!B17 -> 70.5 | C7: ='Historical Income Statement'!C17 -> -71.7 | D7: ='Historical Income Statement'!D17 -> 75.8 | E7: ='Historical Income Statement'!E17 -> 137.3 | F7: ='Historical Income Statement'!F17 -> 199.7 | G7: ='Historical Income Statement'!G17 -> 392 | H7: ='Historical Income Statement'!H17 -> 404.3 | I7: ='Historical Income Statement'!I17 -> 482.9 | ... K7: ='Historical Income Statement'!K17 -> 436.3
A8: Imputed Rate (Effectove Interest Rate) | B8: =B7/B6 -> 0.030031949 | C8: =C7/C6 -> -0.022509654 | D8: =D7/D6 -> 0.01927478 | E8: =E7/E6 -> 0.015050369 | F8: =F7/F6 -> 0.017878886 | G8: =G7/G6 -> 0.026614343 | H8: =H7/H6 -> 0.029688211 | I8: =I7/I6 -> 0.036711546 | ... K8: =K7/K6 -> 0.030428142
A10: Interest on debt | B10: =AVERAGE(B8:K8) -> 0.02167472
A11: Income tax rate | B11: =B17 -> 0.26043366 | C11: This one is biased by having historics from before flat corporate rate was implemented. May understate future tax burden if Starbucks’ operations or tax policy changes. Going to use 31%
B13: =B2 -> 2015 | C13: =C2 -> 2016 | D13: =D2 -> 2017 | E13: =E2 -> 2018 | F13: =F2 -> 2019 | G13: =G2 -> 2020 | H13: =H2 -> 2021 | I13: =I2 -> 2022 | ... K13: =K2 -> 2024
A14: Earnings before tax | B14: ='Historical Income Statement'!B21 -> 3579.6 | C14: ='Historical Income Statement'!C21 -> 4191.6 | D14: ='Historical Income Statement'!D21 -> 4381 | E14: ='Historical Income Statement'!E21 -> 4137.7 | F14: ='Historical Income Statement'!F21 -> 3978.3 | G14: ='Historical Income Statement'!G21 -> 1520.2 | H14: ='Historical Income Statement'!H21 -> 4705.4 | I14: ='Historical Income Statement'!I21 -> 4292.6 | ... K14: ='Historical Income Statement'!K21 -> 4994
A15: Income tax | B15: ='Historical Income Statement'!B30 -> 1143.7 | C15: ='Historical Income Statement'!C30 -> 1379.7 | D15: ='Historical Income Statement'!D30 -> 1432.6 | E15: ='Historical Income Statement'!E30 -> 1262 | F15: ='Historical Income Statement'!F30 -> 871.6 | G15: ='Historical Income Statement'!G30 -> 239.7 | H15: ='Historical Income Statement'!H30 -> 1156.6 | I15: ='Historical Income Statement'!I30 -> 948.5 | ... K15: ='Historical Income Statement'!K30 -> 1207.3
A16: Tax rate | B16: =B15/B14 -> 0.31950497 | C16: =C15/C14 -> 0.32915832 | D16: =D15/D14 -> 0.32700297 | E16: =E15/E14 -> 0.30500036 | F16: =F15/F14 -> 0.21908856 | G16: =G15/G14 -> 0.15767662 | H16: =H15/H14 -> 0.24580269 | I16: =I15/I14 -> 0.22096165 | ... K16: =K15/K14 -> 0.2417501
A17: Average tax rate | B17: =AVERAGE(B16:K16) -> 0.26043366
A19: Normalized effective Tax rate | B19: 0.31
A21: Additional Comments:
A22: Calculated based on Net Real Revenue (millions) because it accounts for inflation and is correct predictor for valuation
A23: Doesn’t look like my tax rate had any outliers, including year 2021 and 2022 where there were changes due to Trump's tax policy
A24: The 31% is normalized / smoothed effective tax rate calculated by CapIQ

Sheet Fixed Asset Forecasting
A1: (All values are in $million USD)
B2: 2015 | C2: =B2+1 -> 2016 | D2: =C2+1 -> 2017 | E2: =D2+1 -> 2018 | F2: =E2+1 -> 2019 | G2: =F2+1 -> 2020 | H2: =G2+1 -> 2021 | I2: =H2+1 -> 2022 | J2: =I2+1 -> 2023 | K2: =J2+1 -> 2024
A3: Gross Property, Plant & Equipment | B3: ='Historical Balance Sheet'!B20 -> 9641.8 | C3: ='Historical Balance Sheet'!C20 -> 10573.3 | D3: ='Historical Balance Sheet'!D20 -> 11584 | E3: ='Historical Balance Sheet'!E20 -> 13197.1 | F3: ='Historical Balance Sheet'!F20 -> 14273.5 | G3: ='Historical Balance Sheet'!G20 -> 22289.4 | H3: ='Historical Balance Sheet'!H20 -> 23064.8 | I3: ='Historical Balance Sheet'!I20 -> 23625.4 | ... K3: ='Historical Balance Sheet'!K20 -> 28727.2
A4: Pct Change | C4: =(C3-B3)/B3 -> 0.096610591 | D4: =(D3-C3)/C3 -> 0.095589835 | E4: =(E3-D3)/D3 -> 0.13925242 | F4: =(F3-E3)/E3 -> 0.081563374 | G4: =(G3-F3)/F3 -> 0.56159316 | H4: =(H3-G3)/G3 -> 0.034787836 | I4: =(I3-H3)/H3 -> 0.024305435 | J4: =(J3-I3)/I3 -> 0.088777333 | K4: =(K3-J3)/J3 -> 0.1167991
A6: Long-term Investments | B6: ='Historical Balance Sheet'!B24 -> 664.5 | C6: ='Historical Balance Sheet'!C24 -> 1496.2 | D6: ='Historical Balance Sheet'!D24 -> 1023.9 | E6: ='Historical Balance Sheet'!E24 -> 602.4 | F6: ='Historical Balance Sheet'!F24 -> 634.3 | G6: ='Historical Balance Sheet'!G24 -> 730.6 | H6: ='Historical Balance Sheet'!H24 -> 572.9 | I6: ='Historical Balance Sheet'!I24 -> 590.3 | ... K6: ='Historical Balance Sheet'!K24 -> 739.9
A7: Goodwill | B7: ='Historical Balance Sheet'!B25 -> 1575.4 | C7: ='Historical Balance Sheet'!C25 -> 1719.6 | D7: ='Historical Balance Sheet'!D25 -> 1539.2 | E7: ='Historical Balance Sheet'!E25 -> 3541.6 | F7: ='Historical Balance Sheet'!F25 -> 3490.8 | G7: ='Historical Balance Sheet'!G25 -> 3597.2 | H7: ='Historical Balance Sheet'!H25 -> 3677.3 | I7: ='Historical Balance Sheet'!I25 -> 3283.5 | ... K7: ='Historical Balance Sheet'!K25 -> 3315.7
A8: Other Intangibles | B8: ='Historical Balance Sheet'!B26 -> 520.4 | C8: ='Historical Balance Sheet'!C26 -> 516.3 | D8: ='Historical Balance Sheet'!D26 -> 441.4 | E8: ='Historical Balance Sheet'!E26 -> 1042.2 | F8: ='Historical Balance Sheet'!F26 -> 781.8 | G8: ='Historical Balance Sheet'!G26 -> 552.1 | H8: ='Historical Balance Sheet'!H26 -> 349.9 | I8: ='Historical Balance Sheet'!I26 -> 155.9 | ... K8: ='Historical Balance Sheet'!K26 -> 100.9
A9: Deferred Charges, LT | B9: ='Historical Balance Sheet'!B27 -> 1180.8 | C9: ='Historical Balance Sheet'!C27 -> 885.4 | D9: ='Historical Balance Sheet'!D27 -> 795.4 | E9: ='Historical Balance Sheet'!E27 -> 134.7 | F9: ='Historical Balance Sheet'!F27 -> 1765.8 | G9: ='Historical Balance Sheet'!G27 -> 1789.9 | H9: ='Historical Balance Sheet'!H27 -> 1874.8 | I9: ='Historical Balance Sheet'!I27 -> 1799.7 | ... K9: ='Historical Balance Sheet'!K27 -> 1766.7
A10: Other Long-Term Assets | B10: ='Historical Balance Sheet'!B28 -> 415.9 | C10: ='Historical Balance Sheet'!C28 -> 403.3 | D10: ='Historical Balance Sheet'!D28 -> 362.8 | E10: ='Historical Balance Sheet'!E28 -> 412.2 | F10: ='Historical Balance Sheet'!F28 -> 461.3 | G10: ='Historical Balance Sheet'!G28 -> 522.8 | H10: ='Historical Balance Sheet'!H28 -> 555.8 | I10: ='Historical Balance Sheet'!I28 -> 554.2 | ... K10: ='Historical Balance Sheet'!K28 -> 617
B11: =SUM(B6:B10) -> 4357 | C11: =SUM(C6:C10) -> 5020.8 | D11: =SUM(D6:D10) -> 4162.7 | E11: =SUM(E6:E10) -> 5733.1 | F11: =SUM(F6:F10) -> 7134 | G11: =SUM(G6:G10) -> 7192.6 | H11: =SUM(H6:H10) -> 7030.7 | I11: =SUM(I6:I10) -> 6383.6 | ... K11: =SUM(K6:K10) -> 6540.2
A12: Pct Change | C12: =(C11-B11)/B11 -> 0.15235254 | D12: =(D11-C11)/C11 -> -0.17090902 | E12: =(E11-D11)/D11 -> 0.37725515 | F12: =(F11-E11)/E11 -> 0.24435297 | G12: =(G11-F11)/F11 -> 0.0082141856 | H12: =(H11-G11)/G11 -> -0.022509246 | I12: =(I11-H11)/H11 -> -0.0920392 | J12: =(J11-I11)/I11 -> -0.0064540385 | K12: =(K11-J11)/J11 -> 0.031186932

Sheet Dividend Forecasting
B2: 2015 | C2: =B2+1 -> 2016 | D2: =C2+1 -> 2017 | E2: =D2+1 -> 2018 | F2: =E2+1 -> 2019 | G2: =F2+1 -> 2020 | H2: =G2+1 -> 2021 | I2: =H2+1 -> 2022 | J2: =I2+1 -> 2023 | K2: =J2+1 -> 2024
A3: Dividends per Share | B3: ='Historical Income Statement'!B53 -> 0.68 | C3: ='Historical Income Statement'!C53 -> 0.85 | D3: ='Historical Income Statement'!D53 -> 1.05 | E3: ='Historical Income Statement'!E53 -> 1.32 | F3: ='Historical Income Statement'!F53 -> 1.49 | G3: ='Historical Income Statement'!G53 -> 1.68 | H3: ='Historical Income Statement'!H53 -> 1.84 | I3: ='Historical Income Statement'!I53 -> 2 | ... K3: ='Historical Income Statement'!K53 -> 2.32
A4: Payout Ratio % | B4: ='Historical Income Statement'!B54 -> 0.336766 | C4: ='Historical Income Statement'!C54 -> 0.418071 | D4: ='Historical Income Statement'!D54 -> 0.50279 | E4: ='Historical Income Statement'!E54 -> 0.385853 | F4: ='Historical Income Statement'!F54 -> 0.489358 | G4: ='Historical Income Statement'!G54 -> 2.072067 | H4: ='Historical Income Statement'!H54 -> 0.504607 | I4: ='Historical Income Statement'!I54 -> 0.689694 | ... K4: ='Historical Income Statement'!K54 -> 0.687335
A6: Dividend Growth Rate | C6: =(C3-B3)/C3 -> 0.2 | D6: =(D3-C3)/D3 -> 0.19047619 | E6: =(E3-D3)/E3 -> 0.20454545 | F6: =(F3-E3)/F3 -> 0.11409396 | G6: =(G3-F3)/G3 -> 0.11309524 | H6: =(H3-G3)/H3 -> 0.086956522 | I6: =(I3-H3)/I3 -> 0.08 | J6: =(J3-I3)/J3 -> 0.074074074 | K6: =(K3-J3)/K3 -> 0.068965517
A7: Dividend Growth Amount | C7: =C3-B3 -> 0.17 | D7: =D3-C3 -> 0.2 | E7: =E3-D3 -> 0.27 | F7: =F3-E3 -> 0.17 | G7: =G3-F3 -> 0.19 | H7: =H3-G3 -> 0.16 | I7: =I3-H3 -> 0.16 | J7: =J3-I3 -> 0.16 | K7: =K3-J3 -> 0.16

Sheet Net Working Capital
A1: (All values are in $million USD)
A3: Analysis of Net Working Capital | B3: 2015 | C3: =B3+1 -> 2016 | D3: =C3+1 -> 2017 | E3: =D3+1 -> 2018 | F3: =E3+1 -> 2019 | G3: =F3+1 -> 2020 | H3: =G3+1 -> 2021 | I3: =H3+1 -> 2022 | J3: =I3+1 -> 2023 | K3: =J3+1 -> 2024
A4: Revenues | B4: ='Historical Income Statement'!B6 -> 19162.7 | C4: ='Historical Income Statement'!C6 -> 21315.9 | D4: ='Historical Income Statement'!D6 -> 22386.8 | E4: ='Historical Income Statement'!E6 -> 24719.5 | F4: ='Historical Income Statement'!F6 -> 26508.6 | G4: ='Historical Income Statement'!G6 -> 23518 | H4: ='Historical Income Statement'!H6 -> 29060.6 | I4: ='Historical Income Statement'!I6 -> 32250.3 | ... K4: ='Historical Income Statement'!K6 -> 36176.2
A5: Cost of Goods Sold | B5: ='Historical Income Statement'!B7 -> 13198.6 | C5: ='Historical Income Statement'!C7 -> 14573.3 | D5: ='Historical Income Statement'!D7 -> 15552.2 | E5: ='Historical Income Statement'!E7 -> 17402.9 | F5: ='Historical Income Statement'!F7 -> 19020.5 | G5: ='Historical Income Statement'!G7 -> 18376.9 | H5: ='Historical Income Statement'!H7 -> 20625.2 | I5: ='Historical Income Statement'!I7 -> 23864.9 | ... K5: ='Historical Income Statement'!K7 -> 26443.8
A6: Selling General & Admin Exp. | B6: ='Historical Income Statement'!B9 -> 1196.7 | C6: ='Historical Income Statement'!C9 -> 1408.9 | D6: ='Historical Income Statement'!D9 -> 1408.4 | E6: ='Historical Income Statement'!E9 -> 1704.6 | F6: ='Historical Income Statement'!F9 -> 1824.1 | G6: ='Historical Income Statement'!G9 -> 1679.6 | H6: ='Historical Income Statement'!H9 -> 1932.6 | I6: ='Historical Income Statement'!I9 -> 2032 | ... K6: ='Historical Income Statement'!K9 -> 2523.3
A7: Depreciation & Amort. | B7: ='Historical Income Statement'!B11 -> 893.9 | C7: ='Historical Income Statement'!C11 -> 980.8 | D7: ='Historical Income Statement'!D11 -> 1011.4 | E7: ='Historical Income Statement'!E11 -> 1247 | F7: ='Historical Income Statement'!F11 -> 1377.3 | G7: ='Historical Income Statement'!G11 -> 1431.3 | H7: ='Historical Income Statement'!H11 -> 1441.7 | I7: ='Historical Income Statement'!I11 -> 1447.9 | ... K7: ='Historical Income Statement'!K11 -> 1512.6
A8: Other Operating Expense/(Income) | B8: ='Historical Income Statement'!B12 -> 522.4 | C8: ='Historical Income Statement'!C12 -> 499.2 | D8: ='Historical Income Statement'!D12 -> 518 | E8: ='Historical Income Statement'!E12 -> 554.9 | F8: ='Historical Income Statement'!F12 -> 371 | G8: ='Historical Income Statement'!G12 -> 430.3 | H8: ='Historical Income Statement'!H12 -> 359.5 | I8: ='Historical Income Statement'!I12 -> 461.5 | ... K8: ='Historical Income Statement'!K12 -> 565.6
A9: Operating Costs | B9: ='Historical Income Statement'!B13+'Historical Income Statement'!B7 -> 15811.6 | C9: ='Historical Income Statement'!C13+'Historical Income Statement'!C7 -> 17462.2 | D9: ='Historical Income Statement'!D13+'Historical Income Statement'!D7 -> 18490 | E9: ='Historical Income Statement'!E13+'Historical Income Statement'!E7 -> 20909.4 | F9: ='Historical Income Statement'!F13+'Historical Income Statement'!F7 -> 22592.9 | G9: ='Historical Income Statement'!G13+'Historical Income Statement'!G7 -> 21918.1 | H9: ='Historical Income Statement'!H13+'Historical Income Statement'!H7 -> 24359 | I9: ='Historical Income Statement'!I13+'Historical Income Statement'!I7 -> 27806.3 | ... K9: ='Historical Income Statement'!K13+'Historical Income Statement'!K7 -> 31045.3
A11: Current Assets
A12: Cash and Cash Equivalents | B12: ='Historical Balance Sheet'!B6 -> 1530.1 | C12: ='Historical Balance Sheet'!C6 -> 2128.8 | D12: ='Historical Balance Sheet'!D6 -> 2462.3 | E12: ='Historical Balance Sheet'!E6 -> 8756.3 | F12: ='Historical Balance Sheet'!F6 -> 2686.6 | G12: ='Historical Balance Sheet'!G6 -> 4350.9 | H12: ='Historical Balance Sheet'!H6 -> 6455.7 | I12: ='Historical Balance Sheet'!I6 -> 2818.4 | ... K12: ='Historical Balance Sheet'!K6 -> 3286.2
A13: Short-term Investments | B13: ='Historical Balance Sheet'!B7 -> 81.3 | C13: ='Historical Balance Sheet'!C7 -> 134.4 | D13: ='Historical Balance Sheet'!D7 -> 228.6 | E13: ='Historical Balance Sheet'!E7 -> 181.5 | F13: ='Historical Balance Sheet'!F7 -> 70.5 | G13: ='Historical Balance Sheet'!G7 -> 281.2 | H13: ='Historical Balance Sheet'!H7 -> 162.2 | I13: ='Historical Balance Sheet'!I7 -> 364.5 | ... K13: ='Historical Balance Sheet'!K7 -> 257
A14: Trading Asset Securities | B14: ='Historical Balance Sheet'!B8 -> 0 | C14: ='Historical Balance Sheet'!C8 -> 0 | D14: ='Historical Balance Sheet'!D8 -> 0 | E14: ='Historical Balance Sheet'!E8 -> 0 | F14: ='Historical Balance Sheet'!F8 -> 0 | G14: ='Historical Balance Sheet'!G8 -> 0 | H14: ='Historical Balance Sheet'!H8 -> 0 | I14: ='Historical Balance Sheet'!I8 -> 0 | ... K14: ='Historical Balance Sheet'!K8 -> 0
A15: Receivables | B15: ='Historical Balance Sheet'!B12 -> 719 | C15: ='Historical Balance Sheet'!C12 -> 768.8 | D15: ='Historical Balance Sheet'!D12 -> 938.4 | E15: ='Historical Balance Sheet'!E12 -> 1648.5 | F15: ='Historical Balance Sheet'!F12 -> 1020.3 | G15: ='Historical Balance Sheet'!G12 -> 1395.4 | H15: ='Historical Balance Sheet'!H12 -> 1133.1 | I15: ='Historical Balance Sheet'!I12 -> 1244.9 | ... K15: ='Historical Balance Sheet'!K12 -> 1213.8
A16: Inventories | B16: ='Historical Balance Sheet'!B13 -> 1306.4 | C16: ='Historical Balance Sheet'!C13 -> 1378.5 | D16: ='Historical Balance Sheet'!D13 -> 1364 | E16: ='Historical Balance Sheet'!E13 -> 1400.5 | F16: ='Historical Balance Sheet'!F13 -> 1529.4 | G16: ='Historical Balance Sheet'!G13 -> 1551.4 | H16: ='Historical Balance Sheet'!H13 -> 1603.9 | I16: ='Historical Balance Sheet'!I13 -> 2176.6 | ... K16: ='Historical Balance Sheet'!K13 -> 1777.3
A17: Prepaid Expenses | B17: ='Historical Balance Sheet'!B14 -> 283.4 | C17: ='Historical Balance Sheet'!C14 -> 319.7 | D17: ='Historical Balance Sheet'!D14 -> 276.7 | E17: ='Historical Balance Sheet'!E14 -> 482.9 | F17: ='Historical Balance Sheet'!F14 -> 334.5 | G17: ='Historical Balance Sheet'!G14 -> 211.9 | H17: ='Historical Balance Sheet'!H14 -> 253.9 | I17: ='Historical Balance Sheet'!I14 -> 339.2 | ... K17: ='Historical Balance Sheet'!K14 -> 292
A18: Restricted Cash | B18: ='Historical Balance Sheet'!B15 -> 0 | C18: ='Historical Balance Sheet'!C15 -> 0 | D18: ='Historical Balance Sheet'!D15 -> 0 | E18: ='Historical Balance Sheet'!E15 -> 0 | F18: ='Historical Balance Sheet'!F15 -> 0 | G18: ='Historical Balance Sheet'!G15 -> 0 | H18: ='Historical Balance Sheet'!H15 -> 0 | I18: ='Historical Balance Sheet'!I15 -> 0 | ... K18: ='Historical Balance Sheet'!K15 -> 12.4
A19: Other Current Assets | B19: ='Historical Balance Sheet'!B16 -> 50.8 | C19: ='Historical Balance Sheet'!C16 -> 27.7 | D19: ='Historical Balance Sheet'!D16 -> 13.4 | E19: ='Historical Balance Sheet'!E16 -> 24.5 | F19: ='Historical Balance Sheet'!F16 -> 12.6 | G19: ='Historical Balance Sheet'!G16 -> 15.6 | H19: ='Historical Balance Sheet'!H16 -> 147.6 | I19: ='Historical Balance Sheet'!I16 -> 75.1 | ... K19: ='Historical Balance Sheet'!K16 -> 8.7
A21: Current Liabilites
A22: Accounts Payable | B22: ='Historical Balance Sheet'!B32 -> 684.2 | C22: ='Historical Balance Sheet'!C32 -> 730.6 | D22: ='Historical Balance Sheet'!D32 -> 782.5 | E22: ='Historical Balance Sheet'!E32 -> 1179.3 | F22: ='Historical Balance Sheet'!F32 -> 1189.7 | G22: ='Historical Balance Sheet'!G32 -> 997.9 | H22: ='Historical Balance Sheet'!H32 -> 1211.6 | I22: ='Historical Balance Sheet'!I32 -> 1441.4 | ... K22: ='Historical Balance Sheet'!K32 -> 1595.5
A23: Accrued Expense | B23: ='Historical Balance Sheet'!B33 -> 884.3 | C23: ='Historical Balance Sheet'!C33 -> 894.3 | D23: ='Historical Balance Sheet'!D33 -> 891 | E23: ='Historical Balance Sheet'!E33 -> 1218.5 | F23: ='Historical Balance Sheet'!F33 -> 1228.7 | G23: ='Historical Balance Sheet'!G33 -> 1179.5 | H23: ='Historical Balance Sheet'!H33 -> 1326.7 | I23: ='Historical Balance Sheet'!I33 -> 1273.2 | ... K23: ='Historical Balance Sheet'!K33 -> 1323.8
A24: Short-term Borrowings | B24: ='Historical Balance Sheet'!B34 -> 0 | C24: ='Historical Balance Sheet'!C34 -> 0 | D24: ='Historical Balance Sheet'!D34 -> 0 | E24: ='Historical Balance Sheet'!E34 -> 0 | F24: ='Historical Balance Sheet'!F34 -> 0 | G24: ='Historical Balance Sheet'!G34 -> 438.8 | H24: ='Historical Balance Sheet'!H34 -> 0 | I24: ='Historical Balance Sheet'!I34 -> 175 | ... K24: ='Historical Balance Sheet'!K34 -> 0
A25: Curr. Port. of LT Debt | B25: ='Historical Balance Sheet'!B35 -> 0 | C25: ='Historical Balance Sheet'!C35 -> 399.9 | D25: ='Historical Balance Sheet'!D35 -> 0 | E25: ='Historical Balance Sheet'!E35 -> 349.9 | F25: ='Historical Balance Sheet'!F35 -> 0 | G25: ='Historical Balance Sheet'!G35 -> 1249.9 | H25: ='Historical Balance Sheet'!H35 -> 998.9 | I25: ='Historical Balance Sheet'!I35 -> 1761 | ... K25: ='Historical Balance Sheet'!K35 -> 1248.9
A26: Curr. Port. of Leases | B26: ='Historical Balance Sheet'!B36 -> 0 | C26: ='Historical Balance Sheet'!C36 -> 0 | D26: ='Historical Balance Sheet'!D36 -> 0 | E26: ='Historical Balance Sheet'!E36 -> 0 | F26: ='Historical Balance Sheet'!F36 -> 0 | G26: ='Historical Balance Sheet'!G36 -> 1248.8 | H26: ='Historical Balance Sheet'!H36 -> 1251.3 | I26: ='Historical Balance Sheet'!I36 -> 1245.7 | ... K26: ='Historical Balance Sheet'!K36 -> 1463.1
A27: Curr. Income Taxes Payable | B27: ='Historical Balance Sheet'!B37 -> 259 | C27: ='Historical Balance Sheet'!C37 -> 368.4 | D27: ='Historical Balance Sheet'!D37 -> 226.6 | E27: ='Historical Balance Sheet'!E37 -> 102.8 | F27: ='Historical Balance Sheet'!F37 -> 1291.7 | G27: ='Historical Balance Sheet'!G37 -> 98.2 | H27: ='Historical Balance Sheet'!H37 -> 348 | I27: ='Historical Balance Sheet'!I37 -> 139.2 | ... K27: ='Historical Balance Sheet'!K37 -> 123.5
A28: Unearned Revenue, Current | B28: ='Historical Balance Sheet'!B38 -> 983.8 | C28: ='Historical Balance Sheet'!C38 -> 1171.2 | D28: ='Historical Balance Sheet'!D38 -> 1288.5 | E28: ='Historical Balance Sheet'!E38 -> 1642.9 | F28: ='Historical Balance Sheet'!F38 -> 1269 | G28: ='Historical Balance Sheet'!G38 -> 1456.5 | H28: ='Historical Balance Sheet'!H38 -> 1596.1 | I28: ='Historical Balance Sheet'!I38 -> 1641.9 | ... K28: ='Historical Balance Sheet'!K38 -> 1781.2
A29: Other Current Liabilities | B29: ='Historical Balance Sheet'!B39 -> 836.8 | C29: ='Historical Balance Sheet'!C39 -> 982.4 | D29: ='Historical Balance Sheet'!D39 -> 1032.1 | E29: ='Historical Balance Sheet'!E39 -> 1190.8 | F29: ='Historical Balance Sheet'!F39 -> 1189.6 | G29: ='Historical Balance Sheet'!G39 -> 677.2 | H29: ='Historical Balance Sheet'!H39 -> 1418.8 | I29: ='Historical Balance Sheet'!I39 -> 1474.4 | ... K29: ='Historical Balance Sheet'!K39 -> 1534
A31: Net Working Capital | B31: =SUM(B12:B19)-SUM(B22:B29) -> 322.9 | C31: =SUM(C12:C19)-SUM(C22:C29) -> 211.1 | D31: =SUM(D12:D19)-SUM(D22:D29) -> 1062.7 | E31: =SUM(E12:E19)-SUM(E22:E29) -> 6810 | F31: =SUM(F12:F19)-SUM(F22:F29) -> -514.8 | G31: =SUM(G12:G19)-SUM(G22:G29) -> 459.6 | H31: =SUM(H12:H19)-SUM(H22:H29) -> 1605 | I31: =SUM(I12:I19)-SUM(I22:I29) -> -2133.1 | ... K31: =SUM(K12:K19)-SUM(K22:K29) -> -2222.6
A33: Pertinent Ratios as % of Revenue | L33: Average
A34: Cash and cash equivalents/Sales | B34: =B12/B4 -> 0.079847829 | C34: =C12/C4 -> 0.099869112 | D34: =D12/D4 -> 0.10998892 | E34: =E12/E4 -> 0.35422642 | F34: =F12/F4 -> 0.10134824 | G34: =G12/G4 -> 0.18500298 | H34: =H12/H4 -> 0.22214614 | I34: =I12/I4 -> 0.087391435 | ... K34: =K12/K4 -> 0.090838728 | L34: =AVERAGE(B34:K34) -> 0.14293795
A35: COGS/Sales | B35: =B5/B4 -> 0.68876515 | C35: =C5/C4 -> 0.68368213 | D35: =D5/D4 -> 0.69470402 | E35: =E5/E4 -> 0.70401505 | F35: =F5/F4 -> 0.71752186 | G35: =G5/G4 -> 0.78139723 | H35: =H5/H4 -> 0.7097307 | I35: =I5/I4 -> 0.73999002 | ... K35: =K5/K4 -> 0.7309723 | L35: =AVERAGE(B35:K35) -> 0.71764425
A36: Selling General & Admin Exp./Sales | B36: =B6/B4 -> 0.062449446 | C36: =C6/C4 -> 0.0660962 | D36: =D6/D4 -> 0.062912073 | E36: =E6/E4 -> 0.068957705 | F36: =F6/F4 -> 0.068811631 | G36: =G6/G4 -> 0.071417638 | H36: =H6/H4 -> 0.066502412 | I36: =I6/I4 -> 0.063007166 | ... K36: =K6/K4 -> 0.069750278 | L36: =AVERAGE(B36:K36) -> 0.066776443
A37: Depreciation & Amort./Sales | B37: =B7/B4 -> 0.046647915 | C37: =C7/C4 -> 0.046012601 | D37: =D7/D4 -> 0.045178409 | E37: =E7/E4 -> 0.050446004 | F37: =F7/F4 -> 0.051956723 | G37: =G7/G4 -> 0.060859767 | H37: =H7/H4 -> 0.049610125 | I37: =I7/I4 -> 0.044895706 | ... K37: =K7/K4 -> 0.04181202 | L37: =AVERAGE(B37:K37) -> 0.047529494
A38: Other Operating Expense/Sales | B38: =B8/B4 -> 0.027261294 | C38: =C8/C4 -> 0.023419138 | D38: =D8/D4 -> 0.023138635 | E38: =E8/E4 -> 0.022447865 | F38: =F8/F4 -> 0.013995458 | G38: =G8/G4 -> 0.018296624 | H38: =H8/H4 -> 0.012370701 | I38: =I8/I4 -> 0.014309944 | ... K38: =K8/K4 -> 0.015634588 | L38: =AVERAGE(B38:K38) -> 0.018586774
A39: Operating Costs/Sales | B39: =B9/B4 -> 0.82512381 | C39: =C9/C4 -> 0.81921007 | D39: =D9/D4 -> 0.82593314 | E39: =E9/E4 -> 0.84586662 | F39: =F9/F4 -> 0.85228567 | G39: =G9/G4 -> 0.93197126 | H39: =H9/H4 -> 0.83821394 | I39: =I9/I4 -> 0.86220283 | ... K39: =K9/K4 -> 0.85816918 | L39: =AVERAGE(B39:K39) -> 0.85053696
A40: Prepaid Exp./Sales | B40: =B17/B4 -> 0.014789148 | C40: =C17/C4 -> 0.014998194 | D40: =D17/D4 -> 0.012359962 | E40: =E17/E4 -> 0.019535185 | F40: =F17/F4 -> 0.012618546 | G40: =G17/G4 -> 0.0090101199 | H40: =H17/H4 -> 0.0087369153 | I40: =I17/I4 -> 0.010517732 | ... K40: =K17/K4 -> 0.0080716051 | L40: =AVERAGE(B40:K40) -> 0.011892914
A41: Total of Short-term Investment/Sales | B41: =(B13+B14)/B4 -> 0.0042426172 | C41: =(C13+C14)/C4 -> 0.0063051525 | D41: =(D13+D14)/D4 -> 0.010211375 | E41: =(E13+E14)/E4 -> 0.0073423815 | F41: =(F13+F14)/F4 -> 0.0026595143 | G41: =(G13+G14)/G4 -> 0.011956799 | H41: =(H13+H14)/H4 -> 0.0055814402 | I41: =(I13+I14)/I4 -> 0.01130222 | ... K41: =(K13+K14)/K4 -> 0.0071041182 | L41: =AVERAGE(B41:K41) -> 0.0077877078
A42: Accrued Exp./Sales | B42: =B23/B$4 -> 0.046146942 | C42: =C23/C$4 -> 0.041954597 | D42: =D23/D$4 -> 0.039800239 | E42: =E23/E$4 -> 0.049293068 | F42: =F23/F$4 -> 0.046350996 | G42: =G23/G$4 -> 0.050153074 | H42: =H23/H$4 -> 0.045652877 | I42: =I23/I$4 -> 0.039478703 | ... K42: =K23/K$4 -> 0.036593119 | L42: =AVERAGE(B42:K42) -> 0.043326037
A43: Curr. Port. of LT Debt/Sales | B43: =B25/B$4 -> 0 | C43: =C25/C$4 -> 0.018760643 | D43: =D25/D$4 -> 0 | E43: =E25/E$4 -> 0.014154817 | F43: =F25/F$4 -> 0 | G43: =G25/G$4 -> 0.053146526 | H43: =H25/H$4 -> 0.034373 | I43: =I25/I$4 -> 0.054604143 | ... K43: =K25/K$4 -> 0.034522697 | L43: =AVERAGE(B43:K43) -> 0.026011276
A44: Curr. Port. of Leases/Sales | B44: =B26/B$4 -> 0 | C44: =C26/C$4 -> 0 | D44: =D26/D$4 -> 0 | E44: =E26/E$4 -> 0 | F44: =F26/F$4 -> 0 | G44: =G26/G$4 -> 0.053099753 | H44: =H26/H$4 -> 0.043058299 | I44: =I26/I$4 -> 0.038625997 | ... K44: =K26/K$4 -> 0.040443717 | L44: =AVERAGE(B44:K44) -> 0.021067679
A45: Curr. Income Taxes Payable/Sales | B45: =B27/B4 -> 0.013515841 | C45: =C27/C4 -> 0.017282873 | D45: =D27/D4 -> 0.010122036 | E45: =E27/E4 -> 0.0041586602 | F45: =F27/F4 -> 0.048727583 | G45: =G27/G4 -> 0.0041755251 | H45: =H27/H4 -> 0.011974976 | I45: =I27/I4 -> 0.0043162389 | ... K45: =K27/K4 -> 0.0034138467 | L45: =AVERAGE(B45:K45) -> 0.012294948
A46: Curr. Unearned Revenue/Sales | B46: =B28/B4 -> 0.051339321 | C46: =C28/C4 -> 0.0549449 | D46: =D28/D4 -> 0.057556238 | E46: =E28/E4 -> 0.0664617 | F46: =F28/F4 -> 0.047871257 | G46: =G28/G4 -> 0.061931287 | H46: =H28/H4 -> 0.054923161 | I46: =I28/I4 -> 0.050911154 | ... K46: =K28/K4 -> 0.049236791 | L46: =AVERAGE(B46:K46) -> 0.054243562
A47: Other Current Liabilities/Sales | B47: =B29/B$4 -> 0.043668168 | C47: =C29/C$4 -> 0.046087662 | D47: =D29/D$4 -> 0.046103061 | E47: =E29/E$4 -> 0.048172495 | F47: =F29/F$4 -> 0.044876003 | G47: =G29/G$4 -> 0.028794966 | H47: =H29/H$4 -> 0.048822117 | I47: =I29/I$4 -> 0.045717404 | ... K47: =K29/K$4 -> 0.042403569 | L47: =AVERAGE(B47:K47) -> 0.043419725
A49: Turnovers/Days Metrics
A50: Receivables turnover | B50: =B4/B15 -> 26.651878 | C50: =C4/C15 -> 27.726197 | D50: =D4/D15 -> 23.856351 | E50: =E4/E15 -> 14.995147 | F50: =F4/F15 -> 25.981182 | G50: =G4/G15 -> 16.853949 | H50: =H4/H15 -> 25.646986 | I50: =I4/I15 -> 25.905936 | ... K50: =K4/K15 -> 29.804086 | L50: =AVERAGE(B50:K50) -> 24.780394
A51: Days' sales in receivables | B51: =365/B50 -> 13.695095 | C51: =365/C50 -> 13.164445 | D51: =365/D50 -> 15.299909 | E51: =365/E50 -> 24.341208 | F51: =365/F50 -> 14.04863 | G51: =365/G50 -> 21.656646 | H51: =365/H50 -> 14.231692 | I51: =365/I50 -> 14.089435 | ... K51: =365/K50 -> 12.246643 | L51: =AVERAGE(B51:K51) -> 15.47873
A52: Inventory turnover | B52: =B4/B16 -> 14.668325 | C52: =C4/C16 -> 15.463112 | D52: =D4/D16 -> 16.41261 | E52: =E4/E16 -> 17.650482 | F52: =F4/F16 -> 17.332679 | G52: =G4/G16 -> 15.159211 | H52: =H4/H16 -> 18.118711 | I52: =I4/I16 -> 14.816824 | ... K52: =K4/K16 -> 20.354583 | L52: =AVERAGE(B52:K52) -> 16.989217
A53: Days' sales in inventory | B53: =365/B52 -> 24.88355 | C53: =365/C52 -> 23.604563 | D53: =365/D52 -> 22.238998 | E53: =365/E52 -> 20.679322 | F53: =365/F52 -> 21.058487 | G53: =365/G52 -> 24.07777 | H53: =365/H52 -> 20.144921 | I53: =365/I52 -> 24.634158 | ... K53: =365/K52 -> 17.93208 | L53: =AVERAGE(B53:K53) -> 21.758116
A54: Payables turnover | B54: =B4/B22 -> 28.007454 | C54: =C4/C22 -> 29.175883 | D54: =D4/D22 -> 28.609329 | E54: =E4/E22 -> 20.961163 | F54: =F4/F22 -> 22.281752 | G54: =G4/G22 -> 23.567492 | H54: =H4/H22 -> 23.985309 | I54: =I4/I22 -> 22.374289 | ... K54: =K4/K22 -> 22.673895 | L54: =AVERAGE(B54:K54) -> 24.49323
A55: Days' sales in payables | B55: =365/B54 -> 13.032245 | C55: =365/C54 -> 12.510333 | D55: =365/D54 -> 12.758076 | E55: =365/E54 -> 17.413156 | F55: =365/F54 -> 16.381118 | G55: =365/G54 -> 15.487435 | H55: =365/H54 -> 15.217649 | I55: =365/I54 -> 16.313368 | ... K55: =365/K54 -> 16.097807 | L55: =AVERAGE(B55:K55) -> 15.087929
A56: NWC turnover | B56: =B4/B31 -> 59.345618 | C56: =C4/C31 -> 100.97537 | D56: =D4/D31 -> 21.065964 | E56: =E4/E31 -> 3.6298825 | F56: =F4/F31 -> -51.493007 | G56: =G4/G31 -> 51.170583 | H56: =H4/H31 -> 18.106293 | I56: =I4/I31 -> -15.118982 | ... K56: =K4/K31 -> -16.276523 | L56: =AVERAGE(B56:K56) -> 15.378651
A57: Day's sales in NWC | B57: =365/B56 -> 6.150412 | C57: =365/C56 -> 3.614743 | D57: =365/D56 -> 17.326527 | E57: =365/E56 -> 100.55422 | F57: =365/F56 -> -7.0883411 | G57: =365/G56 -> 7.1330045 | H57: =365/H56 -> 20.158737 | I57: =365/I56 -> -24.141837 | ... K57: =365/K56 -> -22.424937 | L57: =AVERAGE(B57:K57) -> 8.0565888

Sheet Pro Forma Statement Step 1
A1: All values are in $million USD (unless otherwise stated)
A2: A) Sales Analysis
C3: 2024 | D3: 2025 | E3: 2026 | F3: 2027 | G3: 2028 | H3: 2029 | I3: 2030 | J3: 2031 | K3: 2032 | L3: 2033 | M3: 2034
A4: Projected Real Revenue Growth Rate | D4: =(D6-C6)/C6 -> 0.058393902 | E4: =(E6-D6)/D6 -> 0.030563763 | F4: =(F6-E6)/E6 -> 0.029657324 | G4: =(G6-F6)/F6 -> 0.028803101 | H4: =(H6-G6)/G6 -> 0.027996709 | I4: =(I6-H6)/H6 -> 0.02723424 | J4: =(J6-I6)/I6 -> 0.0265122 | K4: =(K6-J6)/J6 -> 0.025827457 | ... M4: =(M6-L6)/L6 -> 0.024558871
A6: Real revenues | B6: From 'Real Revenues' and 'Forcasting Sales' Tab | C6: ='Forecasting Sales'!K3 -> 36176.2 | D6: {=TRANSPOSE('Forecasting Sales'!C31:C40)} -> 38288.669 | E6: 39458.915 | F6: 40629.161 | G6: 41799.407 | H6: 42969.653 | I6: 44139.899 | J6: 45310.144 | K6: 46480.39 | L6: 47650.636 | M6: 48820.882
A7: Annual inflation rate | B7: Given in instructions (and Prof. Adair's best guess) | D7: =3% -> 0.03 | E7: =D7 -> 0.03 | F7: =E7 -> 0.03 | G7: =F7 -> 0.03 | H7: =G7 -> 0.03 | I7: =H7 -> 0.03 | J7: =I7 -> 0.03 | K7: =J7 -> 0.03 | L7: =K7 -> 0.03 | M7: =L7 -> 0.03
A8: Cummulative adjustment factor | B8: From 'Real Revenues' tab, growing with inflation | C8: ='Real Revenue'!C26 -> 1 | D8: =C8*(1+D7) -> 1.03 | E8: =D8*(1+E7) -> 1.0609 | F8: =E8*(1+F7) -> 1.092727 | G8: =F8*(1+G7) -> 1.1255088 | H8: =G8*(1+H7) -> 1.1592741 | I8: =H8*(1+I7) -> 1.1940523 | J8: =I8*(1+J7) -> 1.2298739 | K8: =J8*(1+K7) -> 1.2667701 | ... M8: =L8*(1+M7) -> 1.3439164
A10: Nominal revenues | C10: =C6 -> 36176.2 | D10: =D6*D8 -> 39437.33 | E10: =E6*E8 -> 41861.963 | F10: =F6*F8 -> 44396.581 | G10: =G6*G8 -> 47045.601 | H10: =H6*H8 -> 49813.604 | I10: =I6*I8 -> 52705.347 | J10: =J6*J8 -> 55725.762 | K10: =K6*K8 -> 58879.968 | ... M10: =M6*M8 -> 65611.183
A11: Projected growth in nominal revenue | D11: =(D10/C10)-1 -> 0.090145719 | E11: =(E10/D10)-1 -> 0.061480676 | F11: =(F10/E10)-1 -> 0.060547043 | G11: =(G10/F10)-1 -> 0.059667194 | H11: =(H10/G10)-1 -> 0.05883661 | I11: =(I10/H10)-1 -> 0.058051267 | J11: =(J10/I10)-1 -> 0.057307566 | K11: =(K10/J10)-1 -> 0.056602281 | ... M11: =(M10/L10)-1 -> 0.055295637
A13: B) PARAMETER ESTIMATES FOR PRO FORMA
C14: =C3 -> 2024 | D14: =D3 -> 2025 | E14: =E3 -> 2026 | F14: =F3 -> 2027 | G14: =G3 -> 2028 | H14: =H3 -> 2029 | I14: =I3 -> 2030 | J14: =J3 -> 2031 | ... M14: =M3 -> 2034
A15: Nominal revenue Growth Rate | D15: =D11 -> 0.090145719 | E15: =E11 -> 0.061480676 | F15: =F11 -> 0.060547043 | G15: =G11 -> 0.059667194 | H15: =H11 -> 0.05883661 | I15: =I11 -> 0.058051267 | J15: =J11 -> 0.057307566 | K15: =K11 -> 0.056602281 | ... M15: =M11 -> 0.055295637
A17: COGS/Sales | B17: Avg from 'Net Working Capital' tab | D17: ='Net Working Capital'!$L$35 -> 0.71764425 | E17: ='Net Working Capital'!$L$35 -> 0.71764425 | F17: ='Net Working Capital'!$L$35 -> 0.71764425 | G17: ='Net Working Capital'!$L$35 -> 0.71764425 | H17: ='Net Working Capital'!$L$35 -> 0.71764425 | I17: ='Net Working Capital'!$L$35 -> 0.71764425 | J17: ='Net Working Capital'!$L$35 -> 0.71764425 | K17: ='Net Working Capital'!$L$35 -> 0.71764425 | ... M17: ='Net Working Capital'!$L$35 -> 0.71764425
A18: Selling General & Admin Exp./Sales | B18: Avg from 'Net Working Capital' tab | D18: ='Net Working Capital'!$L$36 -> 0.066776443 | E18: ='Net Working Capital'!$L$36 -> 0.066776443 | F18: ='Net Working Capital'!$L$36 -> 0.066776443 | G18: ='Net Working Capital'!$L$36 -> 0.066776443 | H18: ='Net Working Capital'!$L$36 -> 0.066776443 | I18: ='Net Working Capital'!$L$36 -> 0.066776443 | J18: ='Net Working Capital'!$L$36 -> 0.066776443 | K18: ='Net Working Capital'!$L$36 -> 0.066776443 | ... M18: ='Net Working Capital'!$L$36 -> 0.066776443
A19: Depreciation & Amort./Sales | B19: Avg from 'Net Working Capital' tab | D19: ='Net Working Capital'!$L$37 -> 0.047529494 | E19: ='Net Working Capital'!$L$37 -> 0.047529494 | F19: ='Net Working Capital'!$L$37 -> 0.047529494 | G19: ='Net Working Capital'!$L$37 -> 0.047529494 | H19: ='Net Working Capital'!$L$37 -> 0.047529494 | I19: ='Net Working Capital'!$L$37 -> 0.047529494 | J19: ='Net Working Capital'!$L$37 -> 0.047529494 | K19: ='Net Working Capital'!$L$37 -> 0.047529494 | ... M19: ='Net Working Capital'!$L$37 -> 0.047529494
A20: Other Operating Expenses/Sales | B20: Avg from 'Net Working Capital' tab, including this because it’s a constant recurring expense | D20: ='Net Working Capital'!$L$38 -> 0.018586774 | E20: ='Net Working Capital'!$L$38 -> 0.018586774 | F20: ='Net Working Capital'!$L$38 -> 0.018586774 | G20: ='Net Working Capital'!$L$38 -> 0.018586774 | H20: ='Net Working Capital'!$L$38 -> 0.018586774 | I20: ='Net Working Capital'!$L$38 -> 0.018586774 | J20: ='Net Working Capital'!$L$38 -> 0.018586774 | K20: ='Net Working Capital'!$L$38 -> 0.018586774 | ... M20: ='Net Working Capital'!$L$38 -> 0.018586774
A21: Coefficient of (COGS+SG&A - Depreciation+other expense) to revenue | B21: From 'Forecasting Costs' tab | D21: ='Forecasting Costs'!$H$23 -> -1.0954159 | E21: ='Forecasting Costs'!$H$23 -> -1.0954159 | F21: ='Forecasting Costs'!$H$23 -> -1.0954159 | G21: ='Forecasting Costs'!$H$23 -> -1.0954159 | H21: ='Forecasting Costs'!$H$23 -> -1.0954159 | I21: ='Forecasting Costs'!$H$23 -> -1.0954159 | J21: ='Forecasting Costs'!$H$23 -> -1.0954159 | K21: ='Forecasting Costs'!$H$23 -> -1.0954159 | ... M21: ='Forecasting Costs'!$H$23 -> -1.0954159
A22: Current Existing Long-Term Debt Levels | B22: From 2024 Annual Report, indirectly through WACC tab | D22: {=TRANSPOSE(WACC!N5:N14)} -> 14380 | E22: 13060 | F22: 11740 | G22: 10420 | H22: 9100 | I22: 8200 | J22: 7300 | K22: 6400 | L22: 5500 | M22: 4600
A23: Interest on Current Existing LT Debt | B23: From 'WACC' tab, Weighted average coupon from blown-out debt schedule 2025 | D23: {=TRANSPOSE(WACC!O5:O14)} -> 0.037590577 | E23: 0.037738706 | F23: 0.037920145 | G23: 0.038147553 | H23: 0.038440934 | I23: 0.038544207 | J23: 0.038672945 | K23: 0.038837891 | L23: 0.039056818 | M23: 0.039361413
A24: Additional LT Debt Amount | B24: Assumed incremental debt to maintain target D/E. $400M is an assumption to reflect planned incremental debt issuance for 2025. It’s a placeholder for modeling, not an actual reported number. To keep financing needs steady, we increase incremental debt slightly — hence 500. 2027: More repayments happen, financing needs are higher, so we assume 800 of new debt. Later years: Capex or buybacks grow, so incremental debt needed becomes 3400, 6400, 7300, etc. | D24: 400 | E24: 500 | F24: 800 | G24: 3400 | H24: 6400 | I24: 7300 | J24: 8200 | K24: 111300 | L24: 14500 | M24: 15800
A25: Additional LT Debt Rate | B25: Current rate from A-rated Corp bond issues | D25: 0.047 | E25: =D25 -> 0.047 | F25: =E25 -> 0.047 | G25: =F25 -> 0.047 | H25: =G25 -> 0.047 | I25: =H25 -> 0.047 | J25: =I25 -> 0.047 | K25: =J25 -> 0.047 | L25: =K25 -> 0.047 | M25: =L25 -> 0.047
A26: ST Debt Rate | B26: Current rate from A.1 commercial paper and CP rate | D26: 0.0425 | E26: =D26 -> 0.0425 | F26: =E26 -> 0.0425 | G26: =F26 -> 0.0425 | H26: =G26 -> 0.0425 | I26: =H26 -> 0.0425 | J26: =I26 -> 0.0425 | K26: =J26 -> 0.0425 | L26: =K26 -> 0.0425 | M26: =L26 -> 0.0425
A27: Assumed Commercial Paper Avg Balance | B27: From 2024 Annual Report, growing at same rate as sales | D27: =1+D11 -> 1.0901457 | E27: =D27*(1+E15) -> 1.1571686 | F27: =E27*(1+F15) -> 1.2272318 | G27: =F27*(1+G15) -> 1.3004572 | H27: =G27*(1+H15) -> 1.3769717 | I27: =H27*(1+I15) -> 1.4569067 | J27: =I27*(1+J15) -> 1.5403985 | K27: =J27*(1+K15) -> 1.6275885 | L27: =K27*(1+L15) -> 1.7186236 | M27: =L27*(1+M15) -> 1.813656
A28: Effective income tax rate | B28: From 'Interest & Taxes' tab | D28: 0.31 | E28: =D28 -> 0.31 | F28: =E28 -> 0.31 | G28: =F28 -> 0.31 | H28: =G28 -> 0.31 | I28: =H28 -> 0.31 | J28: =I28 -> 0.31 | K28: =J28 -> 0.31 | L28: =K28 -> 0.31 | M28: =L28 -> 0.31
A30: Cash and cash equivalents as a percent of revenues | B30: Avg from 'Net Working Capital' tab | D30: ='Net Working Capital'!$L$34 -> 0.14293795 | E30: ='Net Working Capital'!$L$34 -> 0.14293795 | F30: ='Net Working Capital'!$L$34 -> 0.14293795 | G30: ='Net Working Capital'!$L$34 -> 0.14293795 | H30: ='Net Working Capital'!$L$34 -> 0.14293795 | I30: ='Net Working Capital'!$L$34 -> 0.14293795 | J30: ='Net Working Capital'!$L$34 -> 0.14293795 | K30: ='Net Working Capital'!$L$34 -> 0.14293795 | ... M30: ='Net Working Capital'!$L$34 -> 0.14293795
A31: Average receivables turnover | B31: Avg from 'Net Working Capital' tab | D31: ='Net Working Capital'!$L$50 -> 24.780394 | E31: ='Net Working Capital'!$L$50 -> 24.780394 | F31: ='Net Working Capital'!$L$50 -> 24.780394 | G31: ='Net Working Capital'!$L$50 -> 24.780394 | H31: ='Net Working Capital'!$L$50 -> 24.780394 | I31: ='Net Working Capital'!$L$50 -> 24.780394 | J31: ='Net Working Capital'!$L$50 -> 24.780394 | K31: ='Net Working Capital'!$L$50 -> 24.780394 | ... M31: ='Net Working Capital'!$L$50 -> 24.780394
A32: Average inventory turnover | B32: Avg from 'Net Working Capital' tab | D32: ='Net Working Capital'!$L$52 -> 16.989217 | E32: ='Net Working Capital'!$L$52 -> 16.989217 | F32: ='Net Working Capital'!$L$52 -> 16.989217 | G32: ='Net Working Capital'!$L$52 -> 16.989217 | H32: ='Net Working Capital'!$L$52 -> 16.989217 | I32: ='Net Working Capital'!$L$52 -> 16.989217 | J32: ='Net Working Capital'!$L$52 -> 16.989217 | K32: ='Net Working Capital'!$L$52 -> 16.989217 | ... M32: ='Net Working Capital'!$L$52 -> 16.989217
A33: COGS/Sales | B33: Avg from 'Net Working Capital' tab | D33: ='Net Working Capital'!$L$35 -> 0.71764425 | E33: ='Net Working Capital'!$L$35 -> 0.71764425 | F33: ='Net Working Capital'!$L$35 -> 0.71764425 | G33: ='Net Working Capital'!$L$35 -> 0.71764425 | H33: ='Net Working Capital'!$L$35 -> 0.71764425 | I33: ='Net Working Capital'!$L$35 -> 0.71764425 | J33: ='Net Working Capital'!$L$35 -> 0.71764425 | K33: ='Net Working Capital'!$L$35 -> 0.71764425 | ... M33: ='Net Working Capital'!$L$35 -> 0.71764425
A34: Selling General & Admin Exp./Sales | B34: Avg from 'Net Working Capital' tab | D34: ='Net Working Capital'!$L$36 -> 0.066776443 | E34: ='Net Working Capital'!$L$36 -> 0.066776443 | F34: ='Net Working Capital'!$L$36 -> 0.066776443 | G34: ='Net Working Capital'!$L$36 -> 0.066776443 | H34: ='Net Working Capital'!$L$36 -> 0.066776443 | I34: ='Net Working Capital'!$L$36 -> 0.066776443 | J34: ='Net Working Capital'!$L$36 -> 0.066776443 | K34: ='Net Working Capital'!$L$36 -> 0.066776443 | ... M34: ='Net Working Capital'!$L$36 -> 0.066776443
A35: Depreciation & Amort./Sales | B35: Avg from 'Net Working Capital' tab | D35: ='Net Working Capital'!$L$37 -> 0.047529494 | E35: ='Net Working Capital'!$L$37 -> 0.047529494 | F35: ='Net Working Capital'!$L$37 -> 0.047529494 | G35: ='Net Working Capital'!$L$37 -> 0.047529494 | H35: ='Net Working Capital'!$L$37 -> 0.047529494 | I35: ='Net Working Capital'!$L$37 -> 0.047529494 | J35: ='Net Working Capital'!$L$37 -> 0.047529494 | K35: ='Net Working Capital'!$L$37 -> 0.047529494 | ... M35: ='Net Working Capital'!$L$37 -> 0.047529494
A36: Other Operating Expense/Sales | B36: Avg from 'Net Working Capital' tab | D36: ='Net Working Capital'!$L$38 -> 0.018586774 | E36: ='Net Working Capital'!$L$38 -> 0.018586774 | F36: ='Net Working Capital'!$L$38 -> 0.018586774 | G36: ='Net Working Capital'!$L$38 -> 0.018586774 | H36: ='Net Working Capital'!$L$38 -> 0.018586774 | I36: ='Net Working Capital'!$L$38 -> 0.018586774 | J36: ='Net Working Capital'!$L$38 -> 0.018586774 | K36: ='Net Working Capital'!$L$38 -> 0.018586774 | ... M36: ='Net Working Capital'!$L$38 -> 0.018586774
A37: Operating Costs/Sales | B37: Avg from 'Net Working Capital' tab | D37: ='Net Working Capital'!$L$39 -> 0.85053696 | E37: ='Net Working Capital'!$L$39 -> 0.85053696 | F37: ='Net Working Capital'!$L$39 -> 0.85053696 | G37: ='Net Working Capital'!$L$39 -> 0.85053696 | H37: ='Net Working Capital'!$L$39 -> 0.85053696 | I37: ='Net Working Capital'!$L$39 -> 0.85053696 | J37: ='Net Working Capital'!$L$39 -> 0.85053696 | K37: ='Net Working Capital'!$L$39 -> 0.85053696 | ... M37: ='Net Working Capital'!$L$39 -> 0.85053696
A38: Prepaid Exp./Sales | B38: Avg from 'Net Working Capital' tab | D38: ='Net Working Capital'!$L$40 -> 0.011892914 | E38: ='Net Working Capital'!$L$40 -> 0.011892914 | F38: ='Net Working Capital'!$L$40 -> 0.011892914 | G38: ='Net Working Capital'!$L$40 -> 0.011892914 | H38: ='Net Working Capital'!$L$40 -> 0.011892914 | I38: ='Net Working Capital'!$L$40 -> 0.011892914 | J38: ='Net Working Capital'!$L$40 -> 0.011892914 | K38: ='Net Working Capital'!$L$40 -> 0.011892914 | ... M38: ='Net Working Capital'!$L$40 -> 0.011892914
A39: Other CA/Sales | B39: Avg from 'Net Working Capital' tab, Total of Short-term investment | D39: ='Net Working Capital'!$L$41 -> 0.0077877078 | E39: ='Net Working Capital'!$L$41 -> 0.0077877078 | F39: ='Net Working Capital'!$L$41 -> 0.0077877078 | G39: ='Net Working Capital'!$L$41 -> 0.0077877078 | H39: ='Net Working Capital'!$L$41 -> 0.0077877078 | I39: ='Net Working Capital'!$L$41 -> 0.0077877078 | J39: ='Net Working Capital'!$L$41 -> 0.0077877078 | K39: ='Net Working Capital'!$L$41 -> 0.0077877078 | ... M39: ='Net Working Capital'!$L$41 -> 0.0077877078
A40: Fixed asset & depreciation growth | B40: From 'FA Forecasting' tab | D40: ='Fixed Asset Forecasting'!$K$4 -> 0.1167991 | E40: ='Fixed Asset Forecasting'!$K$4 -> 0.1167991 | F40: ='Fixed Asset Forecasting'!$K$4 -> 0.1167991 | G40: ='Fixed Asset Forecasting'!$K$4 -> 0.1167991 | H40: ='Fixed Asset Forecasting'!$K$4 -> 0.1167991 | I40: ='Fixed Asset Forecasting'!$K$4 -> 0.1167991 | J40: ='Fixed Asset Forecasting'!$K$4 -> 0.1167991 | K40: ='Fixed Asset Forecasting'!$K$4 -> 0.1167991 | ... M40: ='Fixed Asset Forecasting'!$K$4 -> 0.1167991
A41: Other LT Assets Growth Rate | B41: From 'FA Forecasting' tab | D41: ='Fixed Asset Forecasting'!$K$12 -> 0.031186932 | E41: ='Fixed Asset Forecasting'!$K$12 -> 0.031186932 | F41: ='Fixed Asset Forecasting'!$K$12 -> 0.031186932 | G41: ='Fixed Asset Forecasting'!$K$12 -> 0.031186932 | H41: ='Fixed Asset Forecasting'!$K$12 -> 0.031186932 | I41: ='Fixed Asset Forecasting'!$K$12 -> 0.031186932 | J41: ='Fixed Asset Forecasting'!$K$12 -> 0.031186932 | K41: ='Fixed Asset Forecasting'!$K$12 -> 0.031186932 | ... M41: ='Fixed Asset Forecasting'!$K$12 -> 0.031186932
A42: Payables turnover | B42: Avg from 'Net Working Capital' tab | D42: ='Net Working Capital'!$L$54 -> 24.49323 | E42: ='Net Working Capital'!$L$54 -> 24.49323 | F42: ='Net Working Capital'!$L$54 -> 24.49323 | G42: ='Net Working Capital'!$L$54 -> 24.49323 | H42: ='Net Working Capital'!$L$54 -> 24.49323 | I42: ='Net Working Capital'!$L$54 -> 24.49323 | J42: ='Net Working Capital'!$L$54 -> 24.49323 | K42: ='Net Working Capital'!$L$54 -> 24.49323 | ... M42: ='Net Working Capital'!$L$54 -> 24.49323
A43: Accrued Exp./Sales | B43: Avg from 'Net Working Capital' tab | D43: ='Net Working Capital'!$L$42 -> 0.043326037 | E43: ='Net Working Capital'!$L$42 -> 0.043326037 | F43: ='Net Working Capital'!$L$42 -> 0.043326037 | G43: ='Net Working Capital'!$L$42 -> 0.043326037 | H43: ='Net Working Capital'!$L$42 -> 0.043326037 | I43: ='Net Working Capital'!$L$42 -> 0.043326037 | J43: ='Net Working Capital'!$L$42 -> 0.043326037 | K43: ='Net Working Capital'!$L$42 -> 0.043326037 | ... M43: ='Net Working Capital'!$L$42 -> 0.043326037
A44: Curr. Port. of LT Debt/Sales | B44: Avg from 'Net Working Capital' tab | D44: ='Net Working Capital'!$L$43 -> 0.026011276 | E44: ='Net Working Capital'!$L$43 -> 0.026011276 | F44: ='Net Working Capital'!$L$43 -> 0.026011276 | G44: ='Net Working Capital'!$L$43 -> 0.026011276 | H44: ='Net Working Capital'!$L$43 -> 0.026011276 | I44: ='Net Working Capital'!$L$43 -> 0.026011276 | J44: ='Net Working Capital'!$L$43 -> 0.026011276 | K44: ='Net Working Capital'!$L$43 -> 0.026011276 | ... M44: ='Net Working Capital'!$L$43 -> 0.026011276
A45: Curr. Port. of Leases/Sales | B45: Avg from 'Net Working Capital' tab | D45: ='Net Working Capital'!$L$44 -> 0.021067679 | E45: ='Net Working Capital'!$L$44 -> 0.021067679 | F45: ='Net Working Capital'!$L$44 -> 0.021067679 | G45: ='Net Working Capital'!$L$44 -> 0.021067679 | H45: ='Net Working Capital'!$L$44 -> 0.021067679 | I45: ='Net Working Capital'!$L$44 -> 0.021067679 | J45: ='Net Working Capital'!$L$44 -> 0.021067679 | K45: ='Net Working Capital'!$L$44 -> 0.021067679 | ... M45: ='Net Working Capital'!$L$44 -> 0.021067679
A46: Curr. Income Taxes Payable/Sales | B46: Avg from 'Net Working Capital' tab | D46: ='Net Working Capital'!$L$45 -> 0.012294948 | E46: ='Net Working Capital'!$L$45 -> 0.012294948 | F46: ='Net Working Capital'!$L$45 -> 0.012294948 | G46: ='Net Working Capital'!$L$45 -> 0.012294948 | H46: ='Net Working Capital'!$L$45 -> 0.012294948 | I46: ='Net Working Capital'!$L$45 -> 0.012294948 | J46: ='Net Working Capital'!$L$45 -> 0.012294948 | K46: ='Net Working Capital'!$L$45 -> 0.012294948 | ... M46: ='Net Working Capital'!$L$45 -> 0.012294948
A47: Unearned Revenue, Current/Sales | B47: Avg from 'Net Working Capital' tab | D47: ='Net Working Capital'!$L$46 -> 0.054243562 | E47: ='Net Working Capital'!$L$46 -> 0.054243562 | F47: ='Net Working Capital'!$L$46 -> 0.054243562 | G47: ='Net Working Capital'!$L$46 -> 0.054243562 | H47: ='Net Working Capital'!$L$46 -> 0.054243562 | I47: ='Net Working Capital'!$L$46 -> 0.054243562 | J47: ='Net Working Capital'!$L$46 -> 0.054243562 | K47: ='Net Working Capital'!$L$46 -> 0.054243562 | ... M47: ='Net Working Capital'!$L$46 -> 0.054243562
A48: Other Current Liabilities/Sales | B48: Avg from 'Net Working Capital' tab | D48: ='Net Working Capital'!$L$47 -> 0.043419725 | E48: ='Net Working Capital'!$L$47 -> 0.043419725 | F48: ='Net Working Capital'!$L$47 -> 0.043419725 | G48: ='Net Working Capital'!$L$47 -> 0.043419725 | H48: ='Net Working Capital'!$L$47 -> 0.043419725 | I48: ='Net Working Capital'!$L$47 -> 0.043419725 | J48: ='Net Working Capital'!$L$47 -> 0.043419725 | K48: ='Net Working Capital'!$L$47 -> 0.043419725 | ... M48: ='Net Working Capital'!$L$47 -> 0.043419725
A49: Annual Growth Rate of LT Liabilities | B49: Assuming it is equal to inflation rate | D49: =D7 -> 0.03 | E49: =E7 -> 0.03 | F49: =F7 -> 0.03 | G49: =G7 -> 0.03 | H49: =H7 -> 0.03 | I49: =I7 -> 0.03 | J49: =J7 -> 0.03 | K49: =K7 -> 0.03 | ... M49: =M7 -> 0.03
A50: Number of Shares Outstanding | B50: From 'WACC' tab, as provided by CapIQ | D50: =WACC!B3 -> 1136900000 | E50: =D50-D51 -> 1124900000 | F50: =E50-E51 -> 1114900000 | G50: =F50-F51 -> 1104900000 | H50: =G50-G51 -> 1094900000 | I50: =H50-H51 -> 1084900000 | J50: =I50-I51 -> 1074900000 | K50: =J50-J51 -> 1064900000 | L50: =K50-K51 -> 1054900000 | M50: =L50-L51 -> 1044900000
A51: Number of Shares Repurchased | B51: Assumption to continue reducing shares; based on FY 2024 buyback (~12.8 m shares in 2024). Assumption for modeling: Starbucks keeps repurchasing to maintain target D/E ratio. | D51: 12000000 | E51: 10000000 | F51: =E51 -> 10000000 | G51: =F51 -> 10000000 | H51: =G51 -> 10000000 | I51: =H51 -> 10000000 | J51: =I51 -> 10000000 | K51: =J51 -> 10000000 | L51: =K51 -> 10000000 | M51: =L51 -> 10000000
A52: Price at Repurchase | D52: 100 | E52: 100 | F52: =E52 -> 100 | G52: =F52 -> 100 | H52: =G52 -> 100 | I52: =H52 -> 100 | J52: =I52 -> 100 | K52: =J52 -> 100 | L52: =K52 -> 100 | M52: =L52 -> 100
A53: Dividends per Share | B53: Assumption for Slow, steady growth reflecting payout policy. Assuming something like 5–7% annual growth per year. Taking 6% as average growth rate | C53: ='Dividend Forecasting'!K3 -> 2.32 | D53: =C53*(1+6%) -> 2.4592 | E53: =D53*(1+6%) -> 2.606752 | F53: =E53*(1+6%) -> 2.7631571 | G53: =F53*(1+6%) -> 2.9289465 | H53: =G53*(1+6%) -> 3.1046833 | I53: =H53*(1+6%) -> 3.2909643 | J53: =I53*(1+6%) -> 3.4884222 | K53: =J53*(1+6%) -> 3.6977275 | ... M53: =L53*(1+6%) -> 4.1547667
A56: C) PRO FORMAS
A58: INCOME STATEMENTS | D58: =D3 -> 2025 | E58: =E3 -> 2026 | F58: =F3 -> 2027 | G58: =G3 -> 2028 | H58: =H3 -> 2029 | I58: =I3 -> 2030 | J58: =J3 -> 2031 | K58: =K3 -> 2032 | ... M58: =M3 -> 2034
A59: Revenue | B59: From Real Revenue Forecast adjusted for expected inflation (see above). Already takes into account other revenue as seen in the historical income statement | D59: =D10 -> 39437.33 | E59: =E10 -> 41861.963 | F59: =F10 -> 44396.581 | G59: =G10 -> 47045.601 | H59: =H10 -> 49813.604 | I59: =I10 -> 52705.347 | J59: =J10 -> 55725.762 | K59: =K10 -> 58879.968 | ... M59: =M10 -> 65611.183
A60: Total Revenue | D60: =D59 -> 39437.33 | E60: =E59 -> 41861.963 | F60: =F59 -> 44396.581 | G60: =G59 -> 47045.601 | H60: =H59 -> 49813.604 | I60: =I59 -> 52705.347 | J60: =J59 -> 55725.762 | K60: =K59 -> 58879.968 | ... M60: =M59 -> 65611.183
A61: Cost of Goods Sold | D61: =D17*D60 -> 28301.973 | E61: =E17*E60 -> 30041.997 | F61: =F17*F60 -> 31860.951 | G61: =G17*G60 -> 33762.005 | H61: =H17*H60 -> 35748.447 | I61: =I17*I60 -> 37823.69 | J61: =J17*J60 -> 39991.273 | K61: =K17*K60 -> 42254.87 | ... M61: =M17*M60 -> 47085.488
A62: Gross Profit | D62: =D60-D61 -> 11135.357 | E62: =E60-E61 -> 11819.966 | F62: =F60-F61 -> 12535.63 | G62: =G60-G61 -> 13283.596 | H62: =H60-H61 -> 14065.158 | I62: =I60-I61 -> 14881.658 | J62: =J60-J61 -> 15734.489 | K62: =K60-K61 -> 16625.097 | ... M62: =M60-M61 -> 18525.695
A63: Selling General & Admin Exp. | D63: =D18*D59 -> 2633.4846 | E63: =E18*E59 -> 2795.393 | F63: =F18*F59 -> 2964.6458 | G63: =G18*G59 -> 3141.5379 | H63: =H18*H59 -> 3326.3753 | I63: =I18*I59 -> 3519.4756 | J63: =J18*J59 -> 3721.1682 | K63: =K18*K59 -> 3931.7948 | ... M63: =M18*M59 -> 4381.2814
A64: Depreciation & Amort. | D64: =D19*D59 -> 1874.4363 | E64: =E19*E59 -> 1989.6779 | F64: =F19*F59 -> 2110.1471 | G64: =G19*G59 -> 2236.0536 | H64: =H19*H59 -> 2367.6154 | I64: =I19*I59 -> 2505.0585 | J64: =J19*J59 -> 2648.6173 | K64: =K19*K59 -> 2798.5351 | ... M64: =M19*M59 -> 3118.4663
A65: Other Operating Expense/(Income) | D65: =D59*D36 -> 733.01275 | E65: =E59*E36 -> 778.07887 | F65: =F59*F36 -> 825.18924 | G65: =G59*G36 -> 874.42597 | H65: =H59*H36 -> 925.87423 | I65: =I59*I36 -> 979.6224 | J65: =J59*J36 -> 1035.7622 | K65: =K59*K36 -> 1094.3887 | ... M65: =M59*M36 -> 1219.5003
A66: Other Operating Exp., Total | D66: =SUM(D63:D65) -> 5240.9337 | E66: =SUM(E63:E65) -> 5563.1498 | F66: =SUM(F63:F65) -> 5899.9821 | G66: =SUM(G63:G65) -> 6252.0175 | H66: =SUM(H63:H65) -> 6619.865 | I66: =SUM(I63:I65) -> 7004.1565 | J66: =SUM(J63:J65) -> 7405.5477 | K66: =SUM(K63:K65) -> 7824.7186 | ... M66: =SUM(M63:M65) -> 8719.248
A67: Earnings Before Interest and Taxes, Operating Income EBIT | D67: =D62-D66 -> 5894.423 | E67: =E62-E66 -> 6256.8161 | F67: =F62-F66 -> 6635.6478 | G67: =G62-G66 -> 7031.5783 | H67: =H62-H66 -> 7445.2926 | I67: =I62-I66 -> 7877.5012 | J67: =J62-J66 -> 8328.9416 | K67: =K62-K66 -> 8800.3787 | ... M67: =M62-M66 -> 9806.4466
A68: Net Interest Exp. | B68: Calculated from Debt levels and rates listed in Parameters section | D68: =(D22*D23)+(D24*D25)+(D26*D100) -> 632.12772 | E68: =(E22*E23)+(E24*E25)+(E26*E100) -> 593.61698 | F68: =(F22*F23)+(F24*F25)+(F26*F100) -> 564.70921 | G68: =(G22*G23)+(G24*G25)+(G26*G100) -> 644.11255 | H68: =(H22*H23)+(H24*H25)+(H26*H100) -> 742.53545 | I68: =(I22*I23)+(I24*I25)+(I26*I100) -> 756.4217 | J68: =(J22*J23)+(J24*J25)+(J26*J100) -> 770.54538 | K68: =(K22*K23)+(K24*K25)+(K26*K100) -> 5588.316 | ... M68: =(M22*M23)+(M24*M25)+(M26*M100) -> 1044.7373
A69: Earnings Before Taxes (EBT Excl. Unusual Items) | D69: =D67-D68 -> 5262.2953 | E69: =E67-E68 -> 5663.1991 | F69: =F67-F68 -> 6070.9386 | G69: =G67-G68 -> 6387.4658 | H69: =H67-H68 -> 6702.7571 | I69: =I67-I68 -> 7121.0795 | J69: =J67-J68 -> 7558.3963 | K69: =K67-K68 -> 3212.0628 | ... M69: =M67-M68 -> 8761.7093
A70: Income Tax Expense | D70: =D28*D69 -> 1631.3115 | E70: =E28*E69 -> 1755.5917 | F70: =F28*F69 -> 1881.991 | G70: =G28*G69 -> 1980.1144 | H70: =H28*H69 -> 2077.8547 | I70: =I28*I69 -> 2207.5347 | J70: =J28*J69 -> 2343.1028 | K70: =K28*K69 -> 995.73946 | ... M70: =M28*M69 -> 2716.1299
A71: Earnings from Continued Operations | D71: =D69-D70 -> 3630.9838 | E71: =E69-E70 -> 3907.6074 | F71: =F69-F70 -> 4188.9477 | G71: =G69-G70 -> 4407.3514 | H71: =H69-H70 -> 4624.9024 | I71: =I69-I70 -> 4913.5449 | J71: =J69-J70 -> 5215.2934 | K71: =K69-K70 -> 2216.3233 | ... M71: =M69-M70 -> 6045.5794
A72: Net Income | D72: =D71 -> 3630.9838 | E72: =E71 -> 3907.6074 | F72: =F71 -> 4188.9477 | G72: =G71 -> 4407.3514 | H72: =H71 -> 4624.9024 | I72: =I71 -> 4913.5449 | J72: =J71 -> 5215.2934 | K72: =K71 -> 2216.3233 | ... M72: =M71 -> 6045.5794
A74: Dividends | B74: Shares outstanding * DPS | D74: =D50*D53/1000000 -> 2795.8645 | E74: =E50*E53/1000000 -> 2932.3353 | F74: =F50*F53/1000000 -> 3080.6439 | G74: =G50*G53/1000000 -> 3236.193 | H74: =H50*H53/1000000 -> 3399.3178 | I74: =I50*I53/1000000 -> 3570.3672 | J74: =J50*J53/1000000 -> 3749.705 | K74: =K50*K53/1000000 -> 3937.71 | ... M74: =M50*M53/1000000 -> 4341.3157
A75: Addition to retained earnings | B75: RE= NI-Div | D75: =D72-D74 -> 835.11928 | E75: =E72-E74 -> 975.27208 | F75: =F72-F74 -> 1108.3038 | G75: =G72-G74 -> 1171.1583 | H75: =H72-H74 -> 1225.5846 | I75: =I72-I74 -> 1343.1777 | J75: =J72-J74 -> 1465.5884 | K75: =K72-K74 -> -1721.3867 | ... M75: =M72-M74 -> 1704.2637
A78: BALANCE SHEETS | D78: 2025 | E78: 2026 | F78: 2027 | G78: 2028 | H78: 2029 | I78: 2030 | J78: 2031 | K78: 2032 | L78: 2033 | M78: 2034
A79: ASSETS
A80: Cash And Equivalents | D80: =D59*D30 -> 5637.091 | E80: =E59*E30 -> 5983.6632 | F80: =F59*F30 -> 6345.9563 | G80: =G59*G30 -> 6724.6017 | H80: =H59*H30 -> 7120.2544 | I80: =I59*I30 -> 7533.5942 | J80: =J59*J30 -> 7965.3262 | K80: =K59*K30 -> 8416.1818 | ... M80: =M59*M30 -> 9378.3279
A81: Total Short Term Investments | D81: =D39*D59 -> 307.1264 | E81: =E39*E59 -> 326.00874 | F81: =F39*F59 -> 345.74761 | G81: =G39*G59 -> 366.37739 | H81: =H39*H59 -> 387.9338 | I81: =I39*I59 -> 410.45385 | J81: =J39*J59 -> 433.97596 | K81: =K39*K59 -> 458.53999 | ... M81: =M39*M59 -> 510.96072
A82: Total Cash & ST Investments | D82: =SUM(D80:D81) -> 5944.2174 | E82: =SUM(E80:E81) -> 6309.6719 | F82: =SUM(F80:F81) -> 6691.7039 | G82: =SUM(G80:G81) -> 7090.9791 | H82: =SUM(H80:H81) -> 7508.1882 | I82: =SUM(I80:I81) -> 7944.0481 | J82: =SUM(J80:J81) -> 8399.3021 | K82: =SUM(K80:K81) -> 8874.7218 | ... M82: =SUM(M80:M81) -> 9889.2886
A83: Total Receivables | D83: =D59/D31 -> 1591.473 | E83: =E59/E31 -> 1689.3179 | F83: =F59/F31 -> 1791.6011 | G83: =G59/G31 -> 1898.5009 | H83: =H59/H31 -> 2010.2022 | I83: =I59/I31 -> 2126.897 | J83: =J59/J31 -> 2248.7843 | K83: =K59/K31 -> 2376.0707 | ... M83: =M59/M31 -> 2647.7054
A84: Inventory | D84: =D59/D32 -> 2321.3153 | E84: =E59/E32 -> 2464.0313 | F84: =F59/F32 -> 2613.2211 | G84: =G59/G32 -> 2769.1447 | H84: =H59/H32 -> 2932.0718 | I84: =I59/I32 -> 3102.2823 | J84: =J59/J32 -> 3280.0665 | K84: =K59/K32 -> 3465.7258 | ... M84: =M59/M32 -> 3861.9309
A85: Prepaid Exp. | D85: =D38*D59 -> 469.02476 | E85: =E38*E59 -> 497.86072 | F85: =F38*F59 -> 528.00471 | G85: =G38*G59 -> 559.50927 | H85: =H38*H59 -> 592.4289 | I85: =I38*I59 -> 626.82015 | J85: =J38*J59 -> 662.74169 | K85: =K38*K59 -> 700.25438 | ... M85: =M38*M59 -> 780.30814
A86: Total Current Assets | D86: =SUM(D82:D85) -> 10326.031 | E86: =SUM(E82:E85) -> 10960.882 | F86: =SUM(F82:F85) -> 11624.531 | G86: =SUM(G82:G85) -> 12318.134 | H86: =SUM(H82:H85) -> 13042.891 | I86: =SUM(I82:I85) -> 13800.048 | J86: =SUM(J82:J85) -> 14590.895 | K86: =SUM(K82:K85) -> 15416.773 | ... M86: =SUM(M82:M85) -> 17179.233
A87: Gross Property, Plant & Equipment | B87: Started this sequence by growing FAs at same rate as final year, which was ALSO in line with statements in 2024 Annual Report | D87: ='Historical Balance Sheet'!K20*(1+'Pro Forma Statement Step 1'!D40) -> 32082.511 | E87: =D87*(1+E40) -> 35829.72 | F87: =E87*(1+F40) -> 40014.599 | G87: =F87*(1+G40) -> 44688.268 | H87: =G87*(1+H40) -> 49907.818 | I87: =H87*(1+I40) -> 55737.006 | J87: =I87*(1+J40) -> 62247.039 | K87: =J87*(1+K40) -> 69517.437 | L87: =K87*(1+L40) -> 77637.012 | M87: =L87*(1+M40) -> 86704.945
A88: Accumulated Depreciation | D88: ='Historical Balance Sheet'!K21*(1+'Pro Forma Statement Step 1'!D40) -> 12034.069 | E88: =D88*(1+E40) -> 13439.637 | F88: =E88*(1+F40) -> 15009.375 | G88: =F88*(1+G40) -> 16762.456 | H88: =G88*(1+H40) -> 18720.296 | I88: =H88*(1+I40) -> 20906.81 | J88: =I88*(1+J40) -> 23348.707 | K88: =J88*(1+K40) -> 26075.815 | L88: =K88*(1+L40) -> 29121.447 | M88: =L88*(1+M40) -> 32522.805
A89: Net Property, Plant & Equipment | D89: =D87+D88 -> 44116.58 | E89: =E87+E88 -> 49269.357 | F89: =F87+F88 -> 55023.974 | G89: =G87+G88 -> 61450.725 | H89: =H87+H88 -> 68628.114 | I89: =I87+I88 -> 76643.816 | J89: =J87+J88 -> 85595.746 | K89: =K87+K88 -> 95593.252 | ... M89: =M87+M88 -> 119227.75
A90: Other Long-Term Assets | B90: Bundled a lot of other stuff into Other LTA, as we are unlikely to change them. Including LT Investments, Goodwill, Other Intangibles, Deferred Charges | D90: =('Historical Balance Sheet'!K29-'Historical Balance Sheet'!K22)*(1+'Pro Forma Statement Step 1'!D41) -> 13805.118 | E90: =D90*(1+E41) -> 14235.657 | F90: =E90*(1+F41) -> 14679.624 | G90: =F90*(1+G41) -> 15137.436 | H90: =G90*(1+H41) -> 15609.527 | I90: =H90*(1+I41) -> 16096.34 | J90: =I90*(1+J41) -> 16598.335 | K90: =J90*(1+K41) -> 17115.986 | L90: =K90*(1+L41) -> 17649.782 | M90: =L90*(1+M41) -> 18200.224
A91: Total Assets | D91: =D86+D89+D90 -> 68247.729 | E91: =E86+E89+E90 -> 74465.896 | F91: =F86+F89+F90 -> 81328.129 | G91: =G86+G89+G90 -> 88906.295 | H91: =H86+H89+H90 -> 97280.532 | I91: =I86+I89+I90 -> 106540.2 | J91: =J86+J89+J90 -> 116784.98 | K91: =K86+K89+K90 -> 128126.01 | ... M91: =M86+M89+M90 -> 154607.21
A93: LIABILITIES
A94: Accounts Payable | D94: =D59/D42 -> 1610.1319 | E94: =E59/E42 -> 1709.1238 | F94: =F59/F42 -> 1812.6062 | G94: =G59/G42 -> 1920.7594 | H94: =H59/H42 -> 2033.7703 | I94: =I59/I42 -> 2151.8333 | J94: =J59/J42 -> 2275.1496 | K94: =K59/K42 -> 2403.9283 | ... M94: =M59/M42 -> 2678.7477
A95: Accrued Exp. | D95: =D$59*D43 -> 1708.6632 | E95: =E$59*E43 -> 1813.713 | F95: =F$59*F43 -> 1923.5279 | G95: =G$59*G43 -> 2038.2994 | H95: =H$59*H43 -> 2158.2261 | I95: =I$59*I43 -> 2283.5138 | J95: =J$59*J43 -> 2414.3765 | K95: =K$59*K43 -> 2551.0357 | ... M95: =M$59*M43 -> 2842.6725
A96: Curr. Port. of LT Debt | D96: =WACC!G9-WACC!N5 -> 1320 | E96: =WACC!N5-WACC!N6 -> 1320 | F96: =WACC!N6-WACC!N7 -> 1320 | G96: =WACC!N7-WACC!N8 -> 1320 | H96: =WACC!N8-WACC!N9 -> 1320 | I96: =WACC!N9-WACC!N10 -> 900 | J96: =WACC!N10-WACC!N11 -> 900 | K96: =WACC!N11-WACC!N12 -> 900 | L96: =WACC!N12-WACC!N13 -> 900 | M96: =WACC!N13-WACC!N14 -> 900
A97: Curr. Port. of Leases | D97: =D$59*D45 -> 830.85301 | E97: =E$59*E45 -> 881.93442 | F97: =F$59*F45 -> 935.33294 | G97: =G$59*G45 -> 991.14163 | H97: =H$59*H45 -> 1049.457 | I97: =I$59*I45 -> 1110.3794 | J97: =J$59*J45 -> 1174.0125 | K97: =K$59*K45 -> 1240.4643 | ... M97: =M$59*M45 -> 1382.2754
A98: Curr. Income Taxes Payable | D98: =D$59*D46 -> 484.87992 | E98: =E$59*E46 -> 514.69066 | F98: =F$59*F46 -> 545.85366 | G98: =G$59*G46 -> 578.42322 | H98: =H$59*H46 -> 612.45568 | I98: =I$59*I46 -> 648.0095 | J98: =J$59*J46 -> 685.14535 | K98: =K$59*K46 -> 723.92614 | ... M98: =M$59*M46 -> 806.68608
A99: Unearned Revenue, Current | D99: =D$59*D47 -> 2139.2212 | E99: =E$59*E47 -> 2270.742 | F99: =F$59*F47 -> 2408.2287 | G99: =G$59*G47 -> 2551.921 | H99: =H$59*H47 -> 2702.0673 | I99: =I$59*I47 -> 2858.9258 | J99: =J$59*J47 -> 3022.7638 | K99: =K$59*K47 -> 3193.8592 | ... M99: =M$59*M47 -> 3558.9843
A100: Other Current Liabilities | D100: =D$59*D48 -> 1712.358 | E100: =E$59*E48 -> 1817.6349 | F100: =F$59*F48 -> 1927.6874 | G100: =G$59*G48 -> 2042.7071 | H100: =H$59*H48 -> 2162.893 | I100: =I$59*I48 -> 2288.4517 | J100: =J$59*J48 -> 2419.5973 | K100: =K$59*K48 -> 2556.552 | ... M100: =M$59*M48 -> 2848.8195
A101: Total Current Liabilities | D101: =SUM(D94:D100) -> 9806.1072 | E101: =SUM(E94:E100) -> 10327.839 | F101: =SUM(F94:F100) -> 10873.237 | G101: =SUM(G94:G100) -> 11443.252 | H101: =SUM(H94:H100) -> 12038.869 | I101: =SUM(I94:I100) -> 12241.113 | J101: =SUM(J94:J100) -> 12891.045 | K101: =SUM(K94:K100) -> 13569.766 | ... M101: =SUM(M94:M100) -> 15018.185
A102: Long-Term Debt | D102: =D22+D24 -> 14780 | E102: =E22+E24 -> 13560 | F102: =F22+F24 -> 12540 | G102: =G22+G24 -> 13820 | H102: =H22+H24 -> 15500 | I102: =I22+I24 -> 15500 | J102: =J22+J24 -> 15500 | K102: =K22+K24 -> 117700 | ... M102: =M22+M24 -> 20400
A103: Long-Term Leases | D103: ='Historical Balance Sheet'!K43*(1+'Pro Forma Statement Step 1'!D49) -> 9034.748 | E103: =D103*(1+E$49) -> 9305.7904 | F103: =E103*(1+F$49) -> 9584.9642 | G103: =F103*(1+G$49) -> 9872.5131 | H103: =G103*(1+H$49) -> 10168.688 | I103: =H103*(1+I$49) -> 10473.749 | J103: =I103*(1+J$49) -> 10787.962 | K103: =J103*(1+K$49) -> 11111.6 | L103: =K103*(1+L$49) -> 11444.948 | M103: =L103*(1+M$49) -> 11788.297
A104: Unearned Revenue, Non-Current | D104: ='Historical Balance Sheet'!K44*(1+'Pro Forma Statement Step 1'!D49) -> 6142.508 | E104: =D104*(1+E$49) -> 6326.7832 | F104: =E104*(1+F$49) -> 6516.5867 | G104: =F104*(1+G$49) -> 6712.0843 | H104: =G104*(1+H$49) -> 6913.4469 | I104: =H104*(1+I$49) -> 7120.8503 | J104: =I104*(1+J$49) -> 7334.4758 | K104: =J104*(1+K$49) -> 7554.5101 | L104: =K104*(1+L$49) -> 7781.1454 | M104: =L104*(1+M$49) -> 8014.5797
A105: Def. Tax Liability, Non-Curr. | D105: ='Historical Balance Sheet'!K45*(1+'Pro Forma Statement Step 1'!D49) -> 21.733 | E105: =D105*(1+E$49) -> 22.38499 | F105: =E105*(1+F$49) -> 23.05654 | G105: =F105*(1+G$49) -> 23.748236 | H105: =G105*(1+H$49) -> 24.460683 | I105: =H105*(1+I$49) -> 25.194503 | J105: =I105*(1+J$49) -> 25.950339 | K105: =J105*(1+K$49) -> 26.728849 | L105: =K105*(1+L$49) -> 27.530714 | M105: =L105*(1+M$49) -> 28.356636
A106: Other Non-Current Liabilities | D106: ='Historical Balance Sheet'!K46*(1+'Pro Forma Statement Step 1'!D49) -> 634.377 | E106: =D106*(1+E$49) -> 653.40831 | F106: =E106*(1+F$49) -> 673.01056 | G106: =F106*(1+G$49) -> 693.20088 | H106: =G106*(1+H$49) -> 713.9969 | I106: =H106*(1+I$49) -> 735.41681 | J106: =I106*(1+J$49) -> 757.47931 | K106: =J106*(1+K$49) -> 780.20369 | L106: =K106*(1+L$49) -> 803.6098 | M106: =L106*(1+M$49) -> 827.7181
A107: Total Liabilities | D107: =SUM(D101:D106) -> 40419.473 | E107: =SUM(E101:E106) -> 40196.206 | F107: =SUM(F101:F106) -> 40210.855 | G107: =SUM(G101:G106) -> 42564.798 | H107: =SUM(H101:H106) -> 45359.462 | I107: =SUM(I101:I106) -> 46096.324 | J107: =SUM(J101:J106) -> 47296.912 | K107: =SUM(K101:K106) -> 150742.81 | ... M107: =SUM(M101:M106) -> 56077.137
A109: Common Stock | B109: Common Stock accounts start with values from last balance sheet. Par value of common stock: Assuming $0.10 per share (typical for Starbucks). Starting balances (FY2024 10-K estimates): | D109: =0.1*D50/1000000 -> 113.69 | E109: =0.1*E50/1000000 -> 112.49 | F109: =0.1*F50/1000000 -> 111.49 | G109: =0.1*G50/1000000 -> 110.49 | H109: =0.1*H50/1000000 -> 109.49 | I109: =0.1*I50/1000000 -> 108.49 | J109: =0.1*J50/1000000 -> 107.49 | K109: =0.1*K50/1000000 -> 106.49 | ... M109: =0.1*M50/1000000 -> 104.49
A110: Additional Paid In Capital | B110: Starting from historical APIC as APICt-1, APICt​=APICt−1​−(Shares repurchased×(Repurchase price – Par)) | C110: ='Historical Balance Sheet'!K50 -> 322.6 | D110: =C110-((D51/1000000)*(D52-0.1)) -> -876.2 | E110: =D110-((E51/1000000)*(E52-0.1)) -> -1875.2 | F110: =E110-((F51/1000000)*(F52-0.1)) -> -2874.2 | G110: =F110-((G51/1000000)*(G52-0.1)) -> -3873.2 | H110: =G110-((H51/1000000)*(H52-0.1)) -> -4872.2 | I110: =H110-((I51/1000000)*(I52-0.1)) -> -5871.2 | J110: =I110-((J51/1000000)*(J52-0.1)) -> -6870.2 | K110: =J110-((K51/1000000)*(K52-0.1)) -> -7869.2 | ... M110: =L110-((M51/1000000)*(M52-0.1)) -> -9867.2
A111: Retained Earnings | B111: RE at t​ = RE at t−1​+Net Income at t​−Dividends Paid at t. https://www.retirewithryne.com/newsletter/confused-about-starbucks | C111: ='Historical Balance Sheet'!K51 -> -7343.8 | D111: =C111+D72-D74 -> -6508.6807 | E111: =D111+E72-E74 -> -5533.4086 | F111: =E111+F72-F74 -> -4425.1049 | G111: =F111+G72-G74 -> -3253.9465 | H111: =G111+H72-H74 -> -2028.3619 | I111: =H111+I72-I74 -> -685.18424 | J111: =I111+J72-J74 -> 780.40415 | K111: =J111+K72-K74 -> -940.98258 | ... M111: =L111+M72-M74 -> 2342.7827
A112: Treasury Stock | D112: 0 | E112: 0 | F112: 0 | G112: 0 | H112: 0 | I112: 0 | J112: 0 | K112: 0 | L112: 0 | M112: 0
A113: Comprehensive Inc. and Other | B113: Growing these at the same rate as nominal Sales | D113: ='Historical Balance Sheet'!K53*(1+'Pro Forma Statement Step 1'!D11) -> 467.45448 | E113: =D113*(1+E11) -> 496.1939 | F113: =E113*(1+F11) -> 526.23698 | G113: =F113*(1+G11) -> 557.63606 | H113: =G113*(1+H11) -> 590.44547 | I113: =H113*(1+I11) -> 624.72158 | J113: =I113*(1+J11) -> 660.52286 | K113: =J113*(1+K11) -> 697.90996 | L113: =K113*(1+L11) -> 736.94581 | M113: =L113*(1+M11) -> 777.6957
...

Sheet WACC
A1: Values in absolute amounts
B2: Class A Shares | E2: Debt Issue | F2: Coupon Rate | G2: Outstanding | I2: "Blown-Out" Debt Schedule Also Called Debt Amortization Schedule
A3: Number of Shares outstanding | B3: 1136900000 | C3: Derived from CapIQ | E3: Due 2025-2029 | F3: =AVERAGE(F31:F38) -> 0.036125 | G3: =SUM(B31:B38) -> 6600 | I3: Coupon | J3: =F3 -> 0.036125 | K3: =F4 -> 0.0375 | L3: =F7 -> 0.0425 | M3: =F8 -> 0.03425
A4: Current Market Price per share | B4: 87.26 | E4: Due 2030-2034 | F4: =AVERAGE(F39:F44) -> 0.0375 | G4: =SUM(B39:B44) -> 4500 | I4: Year | J4: Due 2025-2029 | K4: Due 2030-2034 | L4: Due 2045-2049 | M4: Due 2050+ | N4: Total Amount of Financing | O4: Weighted Average Coupon
A5: Beta | B5: 0.98 | C5: Derived from CapIQ | E5: Due 2035-2039 | F5: =AVERAGE(0) -> 0 | G5: =0 -> 0 | I5: 2025 | J5: =G3*0.8 -> 5280 | K5: =$G$4 -> 4500 | L5: =$G$7 -> 2850 | M5: =$G$8 -> 1750 | N5: =SUM(J5:M5) -> 14380 | O5: =SUMPRODUCT(J5:M5,$J$3:$M$3)/N5 -> 0.037590577
A6: Riskfree Rate | B6: 0.0471 | C6: 10 yrs US Treasury Yeild, as of 11/21/2025, https://home.treasury.gov/resource-center/data-chart-center/interest-rates/TextView?type=daily_treasury_yield_curve&field_tdr_date_value=2025 | E6: Due 2040-2044 | F6: =AVERAGE(0) -> 0 | G6: =0 -> 0 | I6: 2026 | J6: =G3*0.6 -> 3960 | K6: =$G$4 -> 4500 | L6: =$G$7 -> 2850 | M6: =$G$8 -> 1750 | N6: =SUM(J6:M6) -> 13060 | O6: =SUMPRODUCT(J6:M6,$J$3:$M$3)/N6 -> 0.037738706
A7: Market Risk Premium | B7: 0.0433 | C7: Professor Damodaran Equity Risk Premium as of January 2025, https://pages.stern.nyu.edu/~adamodar/New_Home_Page/datafile/ctryprem.html | E7: Due 2045-2049 | F7: =AVERAGE(F45:F48) -> 0.0425 | G7: =SUM(B45:B48) -> 2850 | I7: 2027 | J7: =G3*0.4 -> 2640 | K7: =$G$4 -> 4500 | L7: =$G$7 -> 2850 | M7: =$G$8 -> 1750 | N7: =SUM(J7:M7) -> 11740 | O7: =SUMPRODUCT(J7:M7,$J$3:$M$3)/N7 -> 0.037920145
A8: Cost of equity | B8: =B6+(B5*B7) -> 0.089534 | E8: Due 2050+ | F8: =AVERAGE(F49:F50) -> 0.03425 | G8: =SUM(B49:B50) -> 1750 | I8: 2028 | J8: =G3*0.2 -> 1320 | K8: =$G$4 -> 4500 | L8: =$G$7 -> 2850 | M8: =$G$8 -> 1750 | N8: =SUM(J8:M8) -> 10420 | O8: =SUMPRODUCT(J8:M8,$J$3:$M$3)/N8 -> 0.038147553
F9: =SUMPRODUCT(F3:F8,G3:G8) / SUM(G3:G8)/100 -> 0.00037467357 | G9: =SUM(G3:G8) -> 15700 | I9: 2029 | J9: 0 | K9: =$G$4 -> 4500 | L9: =$G$7 -> 2850 | M9: =$G$8 -> 1750 | N9: =SUM(J9:M9) -> 9100 | O9: =SUMPRODUCT(J9:M9,$J$3:$M$3)/N9 -> 0.038440934
A10: Pretax cost of debt | B10: =F9 -> 0.00037467357 | I10: 2030 | J10: 0 | K10: =G4*0.8 -> 3600 | L10: =$G$7 -> 2850 | M10: =$G$8 -> 1750 | N10: =SUM(J10:M10) -> 8200 | O10: =SUMPRODUCT(J10:M10,$J$3:$M$3)/N10 -> 0.038544207
A11: tax rate | B11: ='Interest & Taxes'!B19 -> 0.31 | E11: Maturity Bucket | F11: Period | G11: Annual Amortization (in million$ USD) | I11: 2031 | J11: 0 | K11: =G4*0.6 -> 2700 | L11: =$G$7 -> 2850 | M11: =$G$8 -> 1750 | N11: =SUM(J11:M11) -> 7300 | O11: =SUMPRODUCT(J11:M11,$J$3:$M$3)/N11 -> 0.038672945
A12: after tax cost of debt | B12: =B10*(1-B11) -> 0.00025852476 | E12: 2025–2029 | F12: 5 | G12: =G3/F12 -> 1320 | I12: 2032 | J12: 0 | K12: =G4*0.4 -> 1800 | L12: =$G$7 -> 2850 | M12: =$G$8 -> 1750 | N12: =SUM(J12:M12) -> 6400 | O12: =SUMPRODUCT(J12:M12,$J$3:$M$3)/N12 -> 0.038837891
E13: 2030–2034 | F13: 5 | G13: =G4/F13 -> 900 | I13: 2033 | J13: 0 | K13: =G4*0.2 -> 900 | L13: =$G$7 -> 2850 | M13: =$G$8 -> 1750 | N13: =SUM(J13:M13) -> 5500 | O13: =SUMPRODUCT(J13:M13,$J$3:$M$3)/N13 -> 0.039056818
A14: Market Value of Equity | B14: =(B4*B3) -> 99205894000 | E14: 2045–2049 | F14: 5 | G14: =G7/F14 -> 570 | I14: 2034 | J14: 0 | K14: 0 | L14: =$G$7 -> 2850 | M14: =$G$8 -> 1750 | N14: =SUM(J14:M14) -> 4600 | O14: =SUMPRODUCT(J14:M14,$J$3:$M$3)/N14 -> 0.039361413
A15: Market Value of Debt | B15: 26611500000 | C15: Derived from CapIQ | E15: 2050+ | F15: assumed long-term constant until 2049 | G15: =G8 -> 1750 | I15: 2045 | J15: 0 | K15: 0 | L15: =$G$7 -> 2850 | M15: =$G$8 -> 1750 | N15: =SUM(J15:M15) -> 4600 | O15: =SUMPRODUCT(J15:M15,$J$3:$M$3)/N15 -> 0.039361413
A16: Total | B16: =SUM(B14:B15) -> 125817394000 | I16: 2046 | J16: 0 | K16: 0 | L16: =$G$7 -> 2850 | M16: =$G$8 -> 1750 | N16: =SUM(J16:M16) -> 4600 | O16: =SUMPRODUCT(J16:M16,$J$3:$M$3)/N16 -> 0.039361413
A17: Weight of Equity | B17: =B14/B16 -> 0.78849109 | I17: 2047 | J17: 0 | K17: 0 | L17: =$G$7 -> 2850 | M17: =$G$8 -> 1750 | N17: =SUM(J17:M17) -> 4600 | O17: =SUMPRODUCT(J17:M17,$J$3:$M$3)/N17 -> 0.039361413
A18: Weight of Debt | B18: =B15/B16 -> 0.21150891 | I18: 2048 | J18: 0 | K18: 0 | L18: =$G$7 -> 2850 | M18: =$G$8 -> 1750 | N18: =SUM(J18:M18) -> 4600 | O18: =SUMPRODUCT(J18:M18,$J$3:$M$3)/N18 -> 0.039361413
I19: 2049 | J19: 0 | K19: 0 | L19: =$G$7 -> 2850 | M19: =$G$8 -> 1750 | N19: =SUM(J19:M19) -> 4600 | O19: =SUMPRODUCT(J19:M19,$J$3:$M$3)/N19 -> 0.039361413
A21: WACC= | B21: =(B17*B8)+(B18*B12) -> 0.070651441
A26: Long-Term Debt From Note 9, FY2024 10K
A27: Issuance | B27: Face Value (Sep 29, 2024) | C27: Estimated Fair Value (Sep 29, 2024) | D27: Face Value (Oct 1, 2023) | E27: Estimated Fair Value (Oct 1, 2023) | F27: Stated Interest Rate | G27: Effective Interest Rate
A28: October 2023 notes(2) | B28: 0 | C28: 0 | D28: 750 | E28: 749.9 | F28: 0.0385 | G28: 0.02859
A29: February 2024 notes(3) | B29: 0 | C29: 0 | D29: 500 | E29: 504.2 | F29: 0.05848 | G29: 0.06079
A30: March 2024 notes(4) | B30: 0 | C30: 0 | D30: 569.3 | E30: 569.3 | F30: 0.00372 | G30: 0.00462
A31: August 2025 notes | B31: 1250 | C31: 1243.4 | D31: 1250 | E31: 1210.5 | F31: 0.038 | G31: 0.03721
A32: February 2026 notes | B32: 1000 | C32: 1008.3 | D32: 1000 | E32: 985.5 | F32: 0.0475 | G32: 0.04788
A33: June 2026 notes | B33: 500 | C33: 486.8 | D33: 500 | E33: 463.5 | F33: 0.0245 | G33: 0.02511
A34: February 2027 notes | B34: 1000 | C34: 1017.8 | D34: 0 | E34: 0 | F34: 0.0485 | G34: 0.04958
A35: March 2027 notes | B35: 500 | C35: 477.1 | D35: 500 | E35: 446.1 | F35: 0.02 | G35: 0.02058
A36: March 2028 notes | B36: 600 | C36: 590.3 | D36: 600 | E36: 554.7 | F36: 0.035 | G36: 0.03529
A37: November 2028 notes | B37: 750 | C37: 748.4 | D37: 750 | E37: 704.5 | F37: 0.04 | G37: 0.03958
A38: August 2029 notes(2) | B38: 1000 | C38: 977.3 | D38: 1000 | E38: 904.1 | F38: 0.0355 | G38: 0.0384
A39: March 2030 notes | B39: 750 | C39: 679 | D39: 750 | E39: 615.1 | F39: 0.0225 | G39: 0.03084
... A50: November 2050 notes | B50: 1250 | C50: 954.4 | D50: 1250 | E50: 843.4 | F50: 0.035 | G50: 0.03528
A51: Total | B51: =SUM(B28:B50) -> 15700 | C51: =SUM(C28:C50) -> 14646.7 | D51: =SUM(D28:D50) -> 15519.3 | E51: =SUM(E28:E50) -> 13426.2
A52: Aggregate debt issuance costs and unamortized premium/(discount), net | B52: -113.8 | D52: -113.1
A53: Hedge accounting fair value adjustment(2) | B53: -17.8 | D53: -40
A54: Total | B54: =B51+B52+B53 -> 15568.4 | D54: =D51+D52+D53 -> 15366.2

Sheet Pro Forma Statement Step 2
A1: All values are in $million USD (unless otherwise stated)
A2: A) Sales Analysis
C3: 2024 | D3: 2025 | E3: 2026 | F3: 2027 | G3: 2028 | H3: 2029 | I3: 2030 | J3: 2031 | K3: 2032 | L3: 2033 | M3: 2034
A4: Projected Real Revenue Growth Rate | D4: =(D6-C6)/C6 -> 0.058393902 | E4: =(E6-D6)/D6 -> 0.030563763 | F4: =(F6-E6)/E6 -> 0.029657324 | G4: =(G6-F6)/F6 -> 0.028803101 | H4: =(H6-G6)/G6 -> 0.027996709 | I4: =(I6-H6)/H6 -> 0.02723424 | J4: =(J6-I6)/I6 -> 0.0265122 | K4: =(K6-J6)/J6 -> 0.025827457 | ... M4: =(M6-L6)/L6 -> 0.024558871
A6: Real revenues | B6: From 'Real Revenues' and 'Forcasting Sales' Tab | C6: ='Forecasting Sales'!K3 -> 36176.2 | D6: {=TRANSPOSE('Forecasting Sales'!C31:C40)} -> 38288.669 | E6: 39458.915 | F6: 40629.161 | G6: 41799.407 | H6: 42969.653 | I6: 44139.899 | J6: 45310.144 | K6: 46480.39 | L6: 47650.636 | M6: 48820.882
A7: Annual inflation rate | B7: Given in instructions (and Prof. Adair's best guess) | D7: =3% -> 0.03 | E7: =D7 -> 0.03 | F7: =E7 -> 0.03 | G7: =F7 -> 0.03 | H7: =G7 -> 0.03 | I7: =H7 -> 0.03 | J7: =I7 -> 0.03 | K7: =J7 -> 0.03 | L7: =K7 -> 0.03 | M7: =L7 -> 0.03
A8: Cummulative adjustment factor | B8: From 'Real Revenues' tab, growing with inflation | C8: ='Real Revenue'!C26 -> 1 | D8: =C8*(1+D7) -> 1.03 | E8: =D8*(1+E7) -> 1.0609 | F8: =E8*(1+F7) -> 1.092727 | G8: =F8*(1+G7) -> 1.1255088 | H8: =G8*(1+H7) -> 1.1592741 | I8: =H8*(1+I7) -> 1.1940523 | J8: =I8*(1+J7) -> 1.2298739 | K8: =J8*(1+K7) -> 1.2667701 | ... M8: =L8*(1+M7) -> 1.3439164
A10: Nominal revenues | C10: =C6 -> 36176.2 | D10: =D6*D8 -> 39437.33 | E10: =E6*E8 -> 41861.963 | F10: =F6*F8 -> 44396.581 | G10: =G6*G8 -> 47045.601 | H10: =H6*H8 -> 49813.604 | I10: =I6*I8 -> 52705.347 | J10: =J6*J8 -> 55725.762 | K10: =K6*K8 -> 58879.968 | ... M10: =M6*M8 -> 65611.183
A11: Projected growth in nominal revenue | D11: =(D10/C10)-1 -> 0.090145719 | E11: =(E10/D10)-1 -> 0.061480676 | F11: =(F10/E10)-1 -> 0.060547043 | G11: =(G10/F10)-1 -> 0.059667194 | H11: =(H10/G10)-1 -> 0.05883661 | I11: =(I10/H10)-1 -> 0.058051267 | J11: =(J10/I10)-1 -> 0.057307566 | K11: =(K10/J10)-1 -> 0.056602281 | ... M11: =(M10/L10)-1 -> 0.055295637
A13: B) PARAMETER ESTIMATES FOR PRO FORMA
C14: =C3 -> 2024 | D14: =D3 -> 2025 | E14: =E3 -> 2026 | F14: =F3 -> 2027 | G14: =G3 -> 2028 | H14: =H3 -> 2029 | I14: =I3 -> 2030 | J14: =J3 -> 2031 | ... M14: =M3 -> 2034
A15: Nominal revenue Growth Rate | D15: =D11 -> 0.090145719 | E15: =E11 -> 0.061480676 | F15: =F11 -> 0.060547043 | G15: =G11 -> 0.059667194 | H15: =H11 -> 0.05883661 | I15: =I11 -> 0.058051267 | J15: =J11 -> 0.057307566 | K15: =K11 -> 0.056602281 | ... M15: =M11 -> 0.055295637
A17: COGS/Sales | B17: Avg from 'Net Working Capital' tab | D17: ='Net Working Capital'!$L$35 -> 0.71764425 | E17: ='Net Working Capital'!$L$35 -> 0.71764425 | F17: ='Net Working Capital'!$L$35 -> 0.71764425 | G17: ='Net Working Capital'!$L$35 -> 0.71764425 | H17: ='Net Working Capital'!$L$35 -> 0.71764425 | I17: ='Net Working Capital'!$L$35 -> 0.71764425 | J17: ='Net Working Capital'!$L$35 -> 0.71764425 | K17: ='Net Working Capital'!$L$35 -> 0.71764425 | ... M17: ='Net Working Capital'!$L$35 -> 0.71764425
A18: Selling General & Admin Exp./Sales | B18: Avg from 'Net Working Capital' tab | D18: ='Net Working Capital'!$L$36 -> 0.066776443 | E18: ='Net Working Capital'!$L$36 -> 0.066776443 | F18: ='Net Working Capital'!$L$36 -> 0.066776443 | G18: ='Net Working Capital'!$L$36 -> 0.066776443 | H18: ='Net Working Capital'!$L$36 -> 0.066776443 | I18: ='Net Working Capital'!$L$36 -> 0.066776443 | J18: ='Net Working Capital'!$L$36 -> 0.066776443 | K18: ='Net Working Capital'!$L$36 -> 0.066776443 | ... M18: ='Net Working Capital'!$L$36 -> 0.066776443
A19: Depreciation & Amort./Sales | B19: Avg from 'Net Working Capital' tab | D19: ='Net Working Capital'!$L$37 -> 0.047529494 | E19: ='Net Working Capital'!$L$37 -> 0.047529494 | F19: ='Net Working Capital'!$L$37 -> 0.047529494 | G19: ='Net Working Capital'!$L$37 -> 0.047529494 | H19: ='Net Working Capital'!$L$37 -> 0.047529494 | I19: ='Net Working Capital'!$L$37 -> 0.047529494 | J19: ='Net Working Capital'!$L$37 -> 0.047529494 | K19: ='Net Working Capital'!$L$37 -> 0.047529494 | ... M19: ='Net Working Capital'!$L$37 -> 0.047529494
A20: Other Operating Expenses/Sales | B20: Avg from 'Net Working Capital' tab, including this because it’s a constant recurring expense | D20: ='Net Working Capital'!$L$38 -> 0.018586774 | E20: ='Net Working Capital'!$L$38 -> 0.018586774 | F20: ='Net Working Capital'!$L$38 -> 0.018586774 | G20: ='Net Working Capital'!$L$38 -> 0.018586774 | H20: ='Net Working Capital'!$L$38 -> 0.018586774 | I20: ='Net Working Capital'!$L$38 -> 0.018586774 | J20: ='Net Working Capital'!$L$38 -> 0.018586774 | K20: ='Net Working Capital'!$L$38 -> 0.018586774 | ... M20: ='Net Working Capital'!$L$38 -> 0.018586774
A21: Coefficient of (COGS+SG&A - Depreciation+other expense) to revenue | B21: From 'Forecasting Costs' tab | D21: ='Forecasting Costs'!$H$23 -> -1.0954159 | E21: ='Forecasting Costs'!$H$23 -> -1.0954159 | F21: ='Forecasting Costs'!$H$23 -> -1.0954159 | G21: ='Forecasting Costs'!$H$23 -> -1.0954159 | H21: ='Forecasting Costs'!$H$23 -> -1.0954159 | I21: ='Forecasting Costs'!$H$23 -> -1.0954159 | J21: ='Forecasting Costs'!$H$23 -> -1.0954159 | K21: ='Forecasting Costs'!$H$23 -> -1.0954159 | ... M21: ='Forecasting Costs'!$H$23 -> -1.0954159
A22: Current Existing Long-Term Debt Levels | B22: From 2024 Annual Report, indirectly through WACC tab. Descending | D22: {=TRANSPOSE(WACC!N5:N14)} -> 14380 | E22: 13060 | F22: 11740 | G22: 10420 | H22: 9100 | I22: 8200 | J22: 7300 | K22: 6400 | L22: 5500 | M22: 4600
A23: Interest on Current Existing LT Debt | B23: From 'WACC' tab, Weighted average coupon from blown-out debt schedule 2025 | D23: {=TRANSPOSE(WACC!O5:O14)} -> 0.037590577 | E23: 0.037738706 | F23: 0.037920145 | G23: 0.038147553 | H23: 0.038440934 | I23: 0.038544207 | J23: 0.038672945 | K23: 0.038837891 | L23: 0.039056818 | M23: 0.039361413
A24: Additional LT Debt Amount | B24: Assumed incremental debt to maintain target D/E. $400M is an assumption to reflect planned incremental debt issuance for 2025. reasonable, smooth, and reflect Starbucks' real leverage strategy. It’s a placeholder for modeling, not an actual reported number. To keep financing needs steady, we increase incremental debt slightly, hence 500. 2027: More repayments happen, financing needs are higher, so we assume 800 of new debt. Later years: transition to long-run stable policy | D24: 400 | E24: 500 | F24: 800 | G24: 1000 | H24: 1000 | I24: 1000 | J24: 1000 | K24: 1000 | L24: 1000 | M24: 1000
A25: Additional LT Debt Rate | B25: Current rate from A-rated Corp bond issues | D25: 0.047 | E25: =D25 -> 0.047 | F25: =E25 -> 0.047 | G25: =F25 -> 0.047 | H25: =G25 -> 0.047 | I25: =H25 -> 0.047 | J25: =I25 -> 0.047 | K25: =J25 -> 0.047 | L25: =K25 -> 0.047 | M25: =L25 -> 0.047
A26: ST Debt Rate | B26: Current rate from A.1 commercial paper and CP rate | D26: 0.0425 | E26: =D26 -> 0.0425 | F26: =E26 -> 0.0425 | G26: =F26 -> 0.0425 | H26: =G26 -> 0.0425 | I26: =H26 -> 0.0425 | J26: =I26 -> 0.0425 | K26: =J26 -> 0.0425 | L26: =K26 -> 0.0425 | M26: =L26 -> 0.0425
A27: Assumed Commercial Paper Avg Balance | B27: From 2024 Annual Report, growing at same rate as sales | D27: =1+D11 -> 1.0901457 | E27: =D27*(1+E15) -> 1.1571686 | F27: =E27*(1+F15) -> 1.2272318 | G27: =F27*(1+G15) -> 1.3004572 | H27: =G27*(1+H15) -> 1.3769717 | I27: =H27*(1+I15) -> 1.4569067 | J27: =I27*(1+J15) -> 1.5403985 | K27: =J27*(1+K15) -> 1.6275885 | L27: =K27*(1+L15) -> 1.7186236 | M27: =L27*(1+M15) -> 1.813656
A28: Effective income tax rate | B28: From 'Interest & Taxes' tab | D28: 0.31 | E28: =D28 -> 0.31 | F28: =E28 -> 0.31 | G28: =F28 -> 0.31 | H28: =G28 -> 0.31 | I28: =H28 -> 0.31 | J28: =I28 -> 0.31 | K28: =J28 -> 0.31 | L28: =K28 -> 0.31 | M28: =L28 -> 0.31
A30: Cash and cash equivalents as a percent of revenues | B30: Avg from 'Net Working Capital' tab | D30: ='Net Working Capital'!$L$34 -> 0.14293795 | E30: ='Net Working Capital'!$L$34 -> 0.14293795 | F30: ='Net Working Capital'!$L$34 -> 0.14293795 | G30: ='Net Working Capital'!$L$34 -> 0.14293795 | H30: ='Net Working Capital'!$L$34 -> 0.14293795 | I30: ='Net Working Capital'!$L$34 -> 0.14293795 | J30: ='Net Working Capital'!$L$34 -> 0.14293795 | K30: ='Net Working Capital'!$L$34 -> 0.14293795 | ... M30: ='Net Working Capital'!$L$34 -> 0.14293795
A31: Average receivables turnover | B31: Avg from 'Net Working Capital' tab | D31: ='Net Working Capital'!$L$50 -> 24.780394 | E31: ='Net Working Capital'!$L$50 -> 24.780394 | F31: ='Net Working Capital'!$L$50 -> 24.780394 | G31: ='Net Working Capital'!$L$50 -> 24.780394 | H31: ='Net Working Capital'!$L$50 -> 24.780394 | I31: ='Net Working Capital'!$L$50 -> 24.780394 | J31: ='Net Working Capital'!$L$50 -> 24.780394 | K31: ='Net Working Capital'!$L$50 -> 24.780394 | ... M31: ='Net Working Capital'!$L$50 -> 24.780394
A32: Average inventory turnover | B32: Avg from 'Net Working Capital' tab | D32: ='Net Working Capital'!$L$52 -> 16.989217 | E32: ='Net Working Capital'!$L$52 -> 16.989217 | F32: ='Net Working Capital'!$L$52 -> 16.989217 | G32: ='Net Working Capital'!$L$52 -> 16.989217 | H32: ='Net Working Capital'!$L$52 -> 16.989217 | I32: ='Net Working Capital'!$L$52 -> 16.989217 | J32: ='Net Working Capital'!$L$52 -> 16.989217 | K32: ='Net Working Capital'!$L$52 -> 16.989217 | ... M32: ='Net Working Capital'!$L$52 -> 16.989217
A33: COGS/Sales | B33: Avg from 'Net Working Capital' tab | D33: ='Net Working Capital'!$L$35 -> 0.71764425 | E33: ='Net Working Capital'!$L$35 -> 0.71764425 | F33: ='Net Working Capital'!$L$35 -> 0.71764425 | G33: ='Net Working Capital'!$L$35 -> 0.71764425 | H33: ='Net Working Capital'!$L$35 -> 0.71764425 | I33: ='Net Working Capital'!$L$35 -> 0.71764425 | J33: ='Net Working Capital'!$L$35 -> 0.71764425 | K33: ='Net Working Capital'!$L$35 -> 0.71764425 | ... M33: ='Net Working Capital'!$L$35 -> 0.71764425
A34: Selling General & Admin Exp./Sales | B34: Avg from 'Net Working Capital' tab | D34: ='Net Working Capital'!$L$36 -> 0.066776443 | E34: ='Net Working Capital'!$L$36 -> 0.066776443 | F34: ='Net Working Capital'!$L$36 -> 0.066776443 | G34: ='Net Working Capital'!$L$36 -> 0.066776443 | H34: ='Net Working Capital'!$L$36 -> 0.066776443 | I34: ='Net Working Capital'!$L$36 -> 0.066776443 | J34: ='Net Working Capital'!$L$36 -> 0.066776443 | K34: ='Net Working Capital'!$L$36 -> 0.066776443 | ... M34: ='Net Working Capital'!$L$36 -> 0.066776443
A35: Depreciation & Amort./Sales | B35: Avg from 'Net Working Capital' tab | D35: ='Net Working Capital'!$L$37 -> 0.047529494 | E35: ='Net Working Capital'!$L$37 -> 0.047529494 | F35: ='Net Working Capital'!$L$37 -> 0.047529494 | G35: ='Net Working Capital'!$L$37 -> 0.047529494 | H35: ='Net Working Capital'!$L$37 -> 0.047529494 | I35: ='Net Working Capital'!$L$37 -> 0.047529494 | J35: ='Net Working Capital'!$L$37 -> 0.047529494 | K35: ='Net Working Capital'!$L$37 -> 0.047529494 | ... M35: ='Net Working Capital'!$L$37 -> 0.047529494
A36: Other Operating Expense/Sales | B36: Avg from 'Net Working Capital' tab | D36: ='Net Working Capital'!$L$38 -> 0.018586774 | E36: ='Net Working Capital'!$L$38 -> 0.018586774 | F36: ='Net Working Capital'!$L$38 -> 0.018586774 | G36: ='Net Working Capital'!$L$38 -> 0.018586774 | H36: ='Net Working Capital'!$L$38 -> 0.018586774 | I36: ='Net Working Capital'!$L$38 -> 0.018586774 | J36: ='Net Working Capital'!$L$38 -> 0.018586774 | K36: ='Net Working Capital'!$L$38 -> 0.018586774 | ... M36: ='Net Working Capital'!$L$38 -> 0.018586774
A37: Operating Costs/Sales | B37: Avg from 'Net Working Capital' tab | D37: ='Net Working Capital'!$L$39 -> 0.85053696 | E37: ='Net Working Capital'!$L$39 -> 0.85053696 | F37: ='Net Working Capital'!$L$39 -> 0.85053696 | G37: ='Net Working Capital'!$L$39 -> 0.85053696 | H37: ='Net Working Capital'!$L$39 -> 0.85053696 | I37: ='Net Working Capital'!$L$39 -> 0.85053696 | J37: ='Net Working Capital'!$L$39 -> 0.85053696 | K37: ='Net Working Capital'!$L$39 -> 0.85053696 | ... M37: ='Net Working Capital'!$L$39 -> 0.85053696
A38: Prepaid Exp./Sales | B38: Avg from 'Net Working Capital' tab | D38: ='Net Working Capital'!$L$40 -> 0.011892914 | E38: ='Net Working Capital'!$L$40 -> 0.011892914 | F38: ='Net Working Capital'!$L$40 -> 0.011892914 | G38: ='Net Working Capital'!$L$40 -> 0.011892914 | H38: ='Net Working Capital'!$L$40 -> 0.011892914 | I38: ='Net Working Capital'!$L$40 -> 0.011892914 | J38: ='Net Working Capital'!$L$40 -> 0.011892914 | K38: ='Net Working Capital'!$L$40 -> 0.011892914 | ... M38: ='Net Working Capital'!$L$40 -> 0.011892914
A39: Other CA/Sales | B39: Avg from 'Net Working Capital' tab, Total of Short-term investment | D39: ='Net Working Capital'!$L$41 -> 0.0077877078 | E39: ='Net Working Capital'!$L$41 -> 0.0077877078 | F39: ='Net Working Capital'!$L$41 -> 0.0077877078 | G39: ='Net Working Capital'!$L$41 -> 0.0077877078 | H39: ='Net Working Capital'!$L$41 -> 0.0077877078 | I39: ='Net Working Capital'!$L$41 -> 0.0077877078 | J39: ='Net Working Capital'!$L$41 -> 0.0077877078 | K39: ='Net Working Capital'!$L$41 -> 0.0077877078 | ... M39: ='Net Working Capital'!$L$41 -> 0.0077877078
A40: Fixed asset & depreciation growth | B40: From 'FA Forecasting' tab | D40: ='Fixed Asset Forecasting'!$K$4 -> 0.1167991 | E40: ='Fixed Asset Forecasting'!$K$4 -> 0.1167991 | F40: ='Fixed Asset Forecasting'!$K$4 -> 0.1167991 | G40: ='Fixed Asset Forecasting'!$K$4 -> 0.1167991 | H40: ='Fixed Asset Forecasting'!$K$4 -> 0.1167991 | I40: ='Fixed Asset Forecasting'!$K$4 -> 0.1167991 | J40: ='Fixed Asset Forecasting'!$K$4 -> 0.1167991 | K40: ='Fixed Asset Forecasting'!$K$4 -> 0.1167991 | ... M40: ='Fixed Asset Forecasting'!$K$4 -> 0.1167991
A41: Other LT Assets Growth Rate | B41: From 'FA Forecasting' tab | D41: ='Fixed Asset Forecasting'!$K$12 -> 0.031186932 | E41: ='Fixed Asset Forecasting'!$K$12 -> 0.031186932 | F41: ='Fixed Asset Forecasting'!$K$12 -> 0.031186932 | G41: ='Fixed Asset Forecasting'!$K$12 -> 0.031186932 | H41: ='Fixed Asset Forecasting'!$K$12 -> 0.031186932 | I41: ='Fixed Asset Forecasting'!$K$12 -> 0.031186932 | J41: ='Fixed Asset Forecasting'!$K$12 -> 0.031186932 | K41: ='Fixed Asset Forecasting'!$K$12 -> 0.031186932 | ... M41: ='Fixed Asset Forecasting'!$K$12 -> 0.031186932
A42: Payables turnover | B42: Avg from 'Net Working Capital' tab | D42: ='Net Working Capital'!$L$54 -> 24.49323 | E42: ='Net Working Capital'!$L$54 -> 24.49323 | F42: ='Net Working Capital'!$L$54 -> 24.49323 | G42: ='Net Working Capital'!$L$54 -> 24.49323 | H42: ='Net Working Capital'!$L$54 -> 24.49323 | I42: ='Net Working Capital'!$L$54 -> 24.49323 | J42: ='Net Working Capital'!$L$54 -> 24.49323 | K42: ='Net Working Capital'!$L$54 -> 24.49323 | ... M42: ='Net Working Capital'!$L$54 -> 24.49323
A43: Accrued Exp./Sales | B43: Avg from 'Net Working Capital' tab | D43: ='Net Working Capital'!$L$42 -> 0.043326037 | E43: ='Net Working Capital'!$L$42 -> 0.043326037 | F43: ='Net Working Capital'!$L$42 -> 0.043326037 | G43: ='Net Working Capital'!$L$42 -> 0.043326037 | H43: ='Net Working Capital'!$L$42 -> 0.043326037 | I43: ='Net Working Capital'!$L$42 -> 0.043326037 | J43: ='Net Working Capital'!$L$42 -> 0.043326037 | K43: ='Net Working Capital'!$L$42 -> 0.043326037 | ... M43: ='Net Working Capital'!$L$42 -> 0.043326037
A44: Curr. Port. of LT Debt/Sales | B44: Avg from 'Net Working Capital' tab | D44: ='Net Working Capital'!$L$43 -> 0.026011276 | E44: ='Net Working Capital'!$L$43 -> 0.026011276 | F44: ='Net Working Capital'!$L$43 -> 0.026011276 | G44: ='Net Working Capital'!$L$43 -> 0.026011276 | H44: ='Net Working Capital'!$L$43 -> 0.026011276 | I44: ='Net Working Capital'!$L$43 -> 0.026011276 | J44: ='Net Working Capital'!$L$43 -> 0.026011276 | K44: ='Net Working Capital'!$L$43 -> 0.026011276 | ... M44: ='Net Working Capital'!$L$43 -> 0.026011276
A45: Curr. Port. of Leases/Sales | B45: Avg from 'Net Working Capital' tab | D45: ='Net Working Capital'!$L$44 -> 0.021067679 | E45: ='Net Working Capital'!$L$44 -> 0.021067679 | F45: ='Net Working Capital'!$L$44 -> 0.021067679 | G45: ='Net Working Capital'!$L$44 -> 0.021067679 | H45: ='Net Working Capital'!$L$44 -> 0.021067679 | I45: ='Net Working Capital'!$L$44 -> 0.021067679 | J45: ='Net Working Capital'!$L$44 -> 0.021067679 | K45: ='Net Working Capital'!$L$44 -> 0.021067679 | ... M45: ='Net Working Capital'!$L$44 -> 0.021067679
A46: Curr. Income Taxes Payable/Sales | B46: Avg from 'Net Working Capital' tab | D46: ='Net Working Capital'!$L$45 -> 0.012294948 | E46: ='Net Working Capital'!$L$45 -> 0.012294948 | F46: ='Net Working Capital'!$L$45 -> 0.012294948 | G46: ='Net Working Capital'!$L$45 -> 0.012294948 | H46: ='Net Working Capital'!$L$45 -> 0.012294948 | I46: ='Net Working Capital'!$L$45 -> 0.012294948 | J46: ='Net Working Capital'!$L$45 -> 0.012294948 | K46: ='Net Working Capital'!$L$45 -> 0.012294948 | ... M46: ='Net Working Capital'!$L$45 -> 0.012294948
A47: Unearned Revenue, Current/Sales | B47: Avg from 'Net Working Capital' tab | D47: ='Net Working Capital'!$L$46 -> 0.054243562 | E47: ='Net Working Capital'!$L$46 -> 0.054243562 | F47: ='Net Working Capital'!$L$46 -> 0.054243562 | G47: ='Net Working Capital'!$L$46 -> 0.054243562 | H47: ='Net Working Capital'!$L$46 -> 0.054243562 | I47: ='Net Working Capital'!$L$46 -> 0.054243562 | J47: ='Net Working Capital'!$L$46 -> 0.054243562 | K47: ='Net Working Capital'!$L$46 -> 0.054243562 | ... M47: ='Net Working Capital'!$L$46 -> 0.054243562
A48: Other Current Liabilities/Sales | B48: Avg from 'Net Working Capital' tab | D48: ='Net Working Capital'!$L$47 -> 0.043419725 | E48: ='Net Working Capital'!$L$47 -> 0.043419725 | F48: ='Net Working Capital'!$L$47 -> 0.043419725 | G48: ='Net Working Capital'!$L$47 -> 0.043419725 | H48: ='Net Working Capital'!$L$47 -> 0.043419725 | I48: ='Net Working Capital'!$L$47 -> 0.043419725 | J48: ='Net Working Capital'!$L$47 -> 0.043419725 | K48: ='Net Working Capital'!$L$47 -> 0.043419725 | ... M48: ='Net Working Capital'!$L$47 -> 0.043419725
A49: Annual Growth Rate of LT Liabilities | B49: Assuming it is equal to inflation rate | D49: =D7 -> 0.03 | E49: =E7 -> 0.03 | F49: =F7 -> 0.03 | G49: =G7 -> 0.03 | H49: =H7 -> 0.03 | I49: =I7 -> 0.03 | J49: =J7 -> 0.03 | K49: =K7 -> 0.03 | ... M49: =M7 -> 0.03
A50: Number of Shares Outstanding | B50: From 'WACC' tab, as provided by CapIQ | D50: =WACC!B3 -> 1136900000 | E50: =D50-D51 -> 1124900000 | F50: =E50-E51 -> 1114900000 | G50: =F50-F51 -> 1104900000 | H50: =G50-G51 -> 1094900000 | I50: =H50-H51 -> 1084900000 | J50: =I50-I51 -> 1074900000 | K50: =J50-J51 -> 1064900000 | L50: =K50-K51 -> 1054900000 | M50: =L50-L51 -> 1044900000
A51: Number of Shares Repurchased | B51: Assumption to continue reducing shares; based on FY 2024 buyback (~12.8 m shares in 2024). Assumption for modeling: Starbucks keeps repurchasing to maintain target D/E ratio. | D51: 12000000 | E51: 10000000 | F51: =E51 -> 10000000 | G51: =F51 -> 10000000 | H51: =G51 -> 10000000 | I51: =H51 -> 10000000 | J51: =I51 -> 10000000 | K51: =J51 -> 10000000 | L51: =K51 -> 10000000 | M51: =L51 -> 10000000
A52: Price at Repurchase | D52: 100 | E52: 100 | F52: =E52 -> 100 | G52: =F52 -> 100 | H52: =G52 -> 100 | I52: =H52 -> 100 | J52: =I52 -> 100 | K52: =J52 -> 100 | L52: =K52 -> 100 | M52: =L52 -> 100
A53: Dividends per Share | B53: Assumption for Slow, steady growth reflecting payout policy. Assuming something like 5–7% annual growth per year. Taking 6% as average growth rate | C53: ='Dividend Forecasting'!K3 -> 2.32 | D53: =C53*(1+6%) -> 2.4592 | E53: =D53*(1+6%) -> 2.606752 | F53: =E53*(1+6%) -> 2.7631571 | G53: =F53*(1+6%) -> 2.9289465 | H53: =G53*(1+6%) -> 3.1046833 | I53: =H53*(1+6%) -> 3.2909643 | J53: =I53*(1+6%) -> 3.4884222 | K53: =J53*(1+6%) -> 3.6977275 | ... M53: =L53*(1+6%) -> 4.1547667
A56: C) PRO FORMAS
A58: INCOME STATEMENTS | D58: =D3 -> 2025 | E58: =E3 -> 2026 | F58: =F3 -> 2027 | G58: =G3 -> 2028 | H58: =H3 -> 2029 | I58: =I3 -> 2030 | J58: =J3 -> 2031 | K58: =K3 -> 2032 | ... M58: =M3 -> 2034
A59: Revenue | B59: From Real Revenue Forecast adjusted for expected inflation (see above). Already takes into account other revenue as seen in the historical income statement | D59: =D10 -> 39437.33 | E59: =E10 -> 41861.963 | F59: =F10 -> 44396.581 | G59: =G10 -> 47045.601 | H59: =H10 -> 49813.604 | I59: =I10 -> 52705.347 | J59: =J10 -> 55725.762 | K59: =K10 -> 58879.968 | ... M59: =M10 -> 65611.183
A60: Total Revenue | D60: =D59 -> 39437.33 | E60: =E59 -> 41861.963 | F60: =F59 -> 44396.581 | G60: =G59 -> 47045.601 | H60: =H59 -> 49813.604 | I60: =I59 -> 52705.347 | J60: =J59 -> 55725.762 | K60: =K59 -> 58879.968 | ... M60: =M59 -> 65611.183
A61: Cost of Goods Sold | D61: =D17*D60 -> 28301.973 | E61: =E17*E60 -> 30041.997 | F61: =F17*F60 -> 31860.951 | G61: =G17*G60 -> 33762.005 | H61: =H17*H60 -> 35748.447 | I61: =I17*I60 -> 37823.69 | J61: =J17*J60 -> 39991.273 | K61: =K17*K60 -> 42254.87 | ... M61: =M17*M60 -> 47085.488
A62: Gross Profit | D62: =D60-D61 -> 11135.357 | E62: =E60-E61 -> 11819.966 | F62: =F60-F61 -> 12535.63 | G62: =G60-G61 -> 13283.596 | H62: =H60-H61 -> 14065.158 | I62: =I60-I61 -> 14881.658 | J62: =J60-J61 -> 15734.489 | K62: =K60-K61 -> 16625.097 | ... M62: =M60-M61 -> 18525.695
A63: Selling General & Admin Exp. | D63: =D18*D59 -> 2633.4846 | E63: =E18*E59 -> 2795.393 | F63: =F18*F59 -> 2964.6458 | G63: =G18*G59 -> 3141.5379 | H63: =H18*H59 -> 3326.3753 | I63: =I18*I59 -> 3519.4756 | J63: =J18*J59 -> 3721.1682 | K63: =K18*K59 -> 3931.7948 | ... M63: =M18*M59 -> 4381.2814
A64: Depreciation & Amort. | D64: =D19*D59 -> 1874.4363 | E64: =E19*E59 -> 1989.6779 | F64: =F19*F59 -> 2110.1471 | G64: =G19*G59 -> 2236.0536 | H64: =H19*H59 -> 2367.6154 | I64: =I19*I59 -> 2505.0585 | J64: =J19*J59 -> 2648.6173 | K64: =K19*K59 -> 2798.5351 | ... M64: =M19*M59 -> 3118.4663
A65: Other Operating Expense/(Income) | D65: =D59*D36 -> 733.01275 | E65: =E59*E36 -> 778.07887 | F65: =F59*F36 -> 825.18924 | G65: =G59*G36 -> 874.42597 | H65: =H59*H36 -> 925.87423 | I65: =I59*I36 -> 979.6224 | J65: =J59*J36 -> 1035.7622 | K65: =K59*K36 -> 1094.3887 | ... M65: =M59*M36 -> 1219.5003
A66: Other Operating Exp., Total | D66: =SUM(D63:D65) -> 5240.9337 | E66: =SUM(E63:E65) -> 5563.1498 | F66: =SUM(F63:F65) -> 5899.9821 | G66: =SUM(G63:G65) -> 6252.0175 | H66: =SUM(H63:H65) -> 6619.865 | I66: =SUM(I63:I65) -> 7004.1565 | J66: =SUM(J63:J65) -> 7405.5477 | K66: =SUM(K63:K65) -> 7824.7186 | ... M66: =SUM(M63:M65) -> 8719.248
A67: Earnings Before Interest and Taxes, Operating Income EBIT | D67: =D62-D66 -> 5894.423 | E67: =E62-E66 -> 6256.8161 | F67: =F62-F66 -> 6635.6478 | G67: =G62-G66 -> 7031.5783 | H67: =H62-H66 -> 7445.2926 | I67: =I62-I66 -> 7877.5012 | J67: =J62-J66 -> 8328.9416 | K67: =K62-K66 -> 8800.3787 | ... M67: =M62-M66 -> 9806.4466
A68: Net Interest Exp. | B68: Calculated from Debt levels and rates listed in Parameters section | D68: =(D22*D23)+(D24*D25)+(D26*D100) -> 632.12772 | E68: =(E22*E23)+(E24*E25)+(E26*E100) -> 593.61698 | F68: =(F22*F23)+(F24*F25)+(F26*F100) -> 564.70921 | G68: =(G22*G23)+(G24*G25)+(G26*G100) -> 531.31255 | H68: =(H22*H23)+(H24*H25)+(H26*H100) -> 488.73545 | I68: =(I22*I23)+(I24*I25)+(I26*I100) -> 460.3217 | J68: =(J22*J23)+(J24*J25)+(J26*J100) -> 432.14538 | K68: =(K22*K23)+(K24*K25)+(K26*K100) -> 404.21596 | ... M68: =(M22*M23)+(M24*M25)+(M26*M100) -> 349.13733
A69: Earnings Before Taxes (EBT Excl. Unusual Items) | D69: =D67-D68 -> 5262.2953 | E69: =E67-E68 -> 5663.1991 | F69: =F67-F68 -> 6070.9386 | G69: =G67-G68 -> 6500.2658 | H69: =H67-H68 -> 6956.5571 | I69: =I67-I68 -> 7417.1795 | J69: =J67-J68 -> 7896.7963 | K69: =K67-K68 -> 8396.1628 | ... M69: =M67-M68 -> 9457.3093
A70: Income Tax Expense | D70: =D28*D69 -> 1631.3115 | E70: =E28*E69 -> 1755.5917 | F70: =F28*F69 -> 1881.991 | G70: =G28*G69 -> 2015.0824 | H70: =H28*H69 -> 2156.5327 | I70: =I28*I69 -> 2299.3257 | J70: =J28*J69 -> 2448.0068 | K70: =K28*K69 -> 2602.8105 | ... M70: =M28*M69 -> 2931.7659
A71: Earnings from Continued Operations | D71: =D69-D70 -> 3630.9838 | E71: =E69-E70 -> 3907.6074 | F71: =F69-F70 -> 4188.9477 | G71: =G69-G70 -> 4485.1834 | H71: =H69-H70 -> 4800.0244 | I71: =I69-I70 -> 5117.8539 | J71: =J69-J70 -> 5448.7894 | K71: =K69-K70 -> 5793.3523 | ... M71: =M69-M70 -> 6525.5434
A72: Net Income | D72: =D71 -> 3630.9838 | E72: =E71 -> 3907.6074 | F72: =F71 -> 4188.9477 | G72: =G71 -> 4485.1834 | H72: =H71 -> 4800.0244 | I72: =I71 -> 5117.8539 | J72: =J71 -> 5448.7894 | K72: =K71 -> 5793.3523 | ... M72: =M71 -> 6525.5434
A74: Dividends | B74: Shares outstanding * DPS | D74: =D50*D53/1000000 -> 2795.8645 | E74: =E50*E53/1000000 -> 2932.3353 | F74: =F50*F53/1000000 -> 3080.6439 | G74: =G50*G53/1000000 -> 3236.193 | H74: =H50*H53/1000000 -> 3399.3178 | I74: =I50*I53/1000000 -> 3570.3672 | J74: =J50*J53/1000000 -> 3749.705 | K74: =K50*K53/1000000 -> 3937.71 | ... M74: =M50*M53/1000000 -> 4341.3157
A75: Addition to retained earnings | B75: RE= NI-Div | D75: =D72-D74 -> 835.11928 | E75: =E72-E74 -> 975.27208 | F75: =F72-F74 -> 1108.3038 | G75: =G72-G74 -> 1248.9903 | H75: =H72-H74 -> 1400.7066 | I75: =I72-I74 -> 1547.4867 | J75: =J72-J74 -> 1699.0844 | K75: =K72-K74 -> 1855.6423 | ... M75: =M72-M74 -> 2184.2277
A78: BALANCE SHEETS | D78: 2025 | E78: 2026 | F78: 2027 | G78: 2028 | H78: 2029 | I78: 2030 | J78: 2031 | K78: 2032 | L78: 2033 | M78: 2034
A79: ASSETS
A80: Cash And Equivalents | D80: =D59*D30 -> 5637.091 | E80: =E59*E30 -> 5983.6632 | F80: =F59*F30 -> 6345.9563 | G80: =G59*G30 -> 6724.6017 | H80: =H59*H30 -> 7120.2544 | I80: =I59*I30 -> 7533.5942 | J80: =J59*J30 -> 7965.3262 | K80: =K59*K30 -> 8416.1818 | ... M80: =M59*M30 -> 9378.3279
A81: Total Short Term Investments | D81: =D39*D59 -> 307.1264 | E81: =E39*E59 -> 326.00874 | F81: =F39*F59 -> 345.74761 | G81: =G39*G59 -> 366.37739 | H81: =H39*H59 -> 387.9338 | I81: =I39*I59 -> 410.45385 | J81: =J39*J59 -> 433.97596 | K81: =K39*K59 -> 458.53999 | ... M81: =M39*M59 -> 510.96072
A82: Total Cash & ST Investments | D82: =SUM(D80:D81) -> 5944.2174 | E82: =SUM(E80:E81) -> 6309.6719 | F82: =SUM(F80:F81) -> 6691.7039 | G82: =SUM(G80:G81) -> 7090.9791 | H82: =SUM(H80:H81) -> 7508.1882 | I82: =SUM(I80:I81) -> 7944.0481 | J82: =SUM(J80:J81) -> 8399.3021 | K82: =SUM(K80:K81) -> 8874.7218 | ... M82: =SUM(M80:M81) -> 9889.2886
A83: Total Receivables | D83: =D59/D31 -> 1591.473 | E83: =E59/E31 -> 1689.3179 | F83: =F59/F31 -> 1791.6011 | G83: =G59/G31 -> 1898.5009 | H83: =H59/H31 -> 2010.2022 | I83: =I59/I31 -> 2126.897 | J83: =J59/J31 -> 2248.7843 | K83: =K59/K31 -> 2376.0707 | ... M83: =M59/M31 -> 2647.7054
A84: Inventory | D84: =D59/D32 -> 2321.3153 | E84: =E59/E32 -> 2464.0313 | F84: =F59/F32 -> 2613.2211 | G84: =G59/G32 -> 2769.1447 | H84: =H59/H32 -> 2932.0718 | I84: =I59/I32 -> 3102.2823 | J84: =J59/J32 -> 3280.0665 | K84: =K59/K32 -> 3465.7258 | ... M84: =M59/M32 -> 3861.9309
A85: Prepaid Exp. | D85: =D38*D59 -> 469.02476 | E85: =E38*E59 -> 497.86072 | F85: =F38*F59 -> 528.00471 | G85: =G38*G59 -> 559.50927 | H85: =H38*H59 -> 592.4289 | I85: =I38*I59 -> 626.82015 | J85: =J38*J59 -> 662.74169 | K85: =K38*K59 -> 700.25438 | ... M85: =M38*M59 -> 780.30814
A86: Total Current Assets | D86: =SUM(D82:D85) -> 10326.031 | E86: =SUM(E82:E85) -> 10960.882 | F86: =SUM(F82:F85) -> 11624.531 | G86: =SUM(G82:G85) -> 12318.134 | H86: =SUM(H82:H85) -> 13042.891 | I86: =SUM(I82:I85) -> 13800.048 | J86: =SUM(J82:J85) -> 14590.895 | K86: =SUM(K82:K85) -> 15416.773 | ... M86: =SUM(M82:M85) -> 17179.233
A87: Gross Property, Plant & Equipment | B87: Started this sequence by growing FAs at same rate as final year, which was ALSO in line with statements in 2024 Annual Report | D87: ='Historical Balance Sheet'!K20*(1+'Pro Forma Statement Step 2'!D40) -> 32082.511 | E87: =D87*(1+E40) -> 35829.72 | F87: =E87*(1+F40) -> 40014.599 | G87: =F87*(1+G40) -> 44688.268 | H87: =G87*(1+H40) -> 49907.818 | I87: =H87*(1+I40) -> 55737.006 | J87: =I87*(1+J40) -> 62247.039 | K87: =J87*(1+K40) -> 69517.437 | L87: =K87*(1+L40) -> 77637.012 | M87: =L87*(1+M40) -> 86704.945
A88: Accumulated Depreciation | D88: ='Historical Balance Sheet'!K21*(1+'Pro Forma Statement Step 2'!D40) -> 12034.069 | E88: =D88*(1+E40) -> 13439.637 | F88: =E88*(1+F40) -> 15009.375 | G88: =F88*(1+G40) -> 16762.456 | H88: =G88*(1+H40) -> 18720.296 | I88: =H88*(1+I40) -> 20906.81 | J88: =I88*(1+J40) -> 23348.707 | K88: =J88*(1+K40) -> 26075.815 | L88: =K88*(1+L40) -> 29121.447 | M88: =L88*(1+M40) -> 32522.805
A89: Net Property, Plant & Equipment | D89: =D87+D88 -> 44116.58 | E89: =E87+E88 -> 49269.357 | F89: =F87+F88 -> 55023.974 | G89: =G87+G88 -> 61450.725 | H89: =H87+H88 -> 68628.114 | I89: =I87+I88 -> 76643.816 | J89: =J87+J88 -> 85595.746 | K89: =K87+K88 -> 95593.252 | ... M89: =M87+M88 -> 119227.75
A90: Other Long-Term Assets | B90: Bundled a lot of other stuff into Other LTA, as we are unlikely to change them. Including LT Investments, Goodwill, Other Intangibles, Deferred Charges | D90: =('Historical Balance Sheet'!K29-'Historical Balance Sheet'!K22)*(1+'Pro Forma Statement Step 2'!D41) -> 13805.118 | E90: =D90*(1+E41) -> 14235.657 | F90: =E90*(1+F41) -> 14679.624 | G90: =F90*(1+G41) -> 15137.436 | H90: =G90*(1+H41) -> 15609.527 | I90: =H90*(1+I41) -> 16096.34 | J90: =I90*(1+J41) -> 16598.335 | K90: =J90*(1+K41) -> 17115.986 | L90: =K90*(1+L41) -> 17649.782 | M90: =L90*(1+M41) -> 18200.224
A91: Total Assets | D91: =D86+D89+D90 -> 68247.729 | E91: =E86+E89+E90 -> 74465.896 | F91: =F86+F89+F90 -> 81328.129 | G91: =G86+G89+G90 -> 88906.295 | H91: =H86+H89+H90 -> 97280.532 | I91: =I86+I89+I90 -> 106540.2 | J91: =J86+J89+J90 -> 116784.98 | K91: =K86+K89+K90 -> 128126.01 | ... M91: =M86+M89+M90 -> 154607.21
A93: LIABILITIES
A94: Accounts Payable | D94: =D59/D42 -> 1610.1319 | E94: =E59/E42 -> 1709.1238 | F94: =F59/F42 -> 1812.6062 | G94: =G59/G42 -> 1920.7594 | H94: =H59/H42 -> 2033.7703 | I94: =I59/I42 -> 2151.8333 | J94: =J59/J42 -> 2275.1496 | K94: =K59/K42 -> 2403.9283 | ... M94: =M59/M42 -> 2678.7477
A95: Accrued Exp. | D95: =D$59*D43 -> 1708.6632 | E95: =E$59*E43 -> 1813.713 | F95: =F$59*F43 -> 1923.5279 | G95: =G$59*G43 -> 2038.2994 | H95: =H$59*H43 -> 2158.2261 | I95: =I$59*I43 -> 2283.5138 | J95: =J$59*J43 -> 2414.3765 | K95: =K$59*K43 -> 2551.0357 | ... M95: =M$59*M43 -> 2842.6725
A96: Curr. Port. of LT Debt | D96: =WACC!G9-WACC!N5 -> 1320 | E96: =WACC!N5-WACC!N6 -> 1320 | F96: =WACC!N6-WACC!N7 -> 1320 | G96: =WACC!N7-WACC!N8 -> 1320 | H96: =WACC!N8-WACC!N9 -> 1320 | I96: =WACC!N9-WACC!N10 -> 900 | J96: =WACC!N10-WACC!N11 -> 900 | K96: =WACC!N11-WACC!N12 -> 900 | L96: =WACC!N12-WACC!N13 -> 900 | M96: =WACC!N13-WACC!N14 -> 900
A97: Curr. Port. of Leases | D97: =D$59*D45 -> 830.85301 | E97: =E$59*E45 -> 881.93442 | F97: =F$59*F45 -> 935.33294 | G97: =G$59*G45 -> 991.14163 | H97: =H$59*H45 -> 1049.457 | I97: =I$59*I45 -> 1110.3794 | J97: =J$59*J45 -> 1174.0125 | K97: =K$59*K45 -> 1240.4643 | ... M97: =M$59*M45 -> 1382.2754
A98: Curr. Income Taxes Payable | D98: =D$59*D46 -> 484.87992 | E98: =E$59*E46 -> 514.69066 | F98: =F$59*F46 -> 545.85366 | G98: =G$59*G46 -> 578.42322 | H98: =H$59*H46 -> 612.45568 | I98: =I$59*I46 -> 648.0095 | J98: =J$59*J46 -> 685.14535 | K98: =K$59*K46 -> 723.92614 | ... M98: =M$59*M46 -> 806.68608
A99: Unearned Revenue, Current | D99: =D$59*D47 -> 2139.2212 | E99: =E$59*E47 -> 2270.742 | F99: =F$59*F47 -> 2408.2287 | G99: =G$59*G47 -> 2551.921 | H99: =H$59*H47 -> 2702.0673 | I99: =I$59*I47 -> 2858.9258 | J99: =J$59*J47 -> 3022.7638 | K99: =K$59*K47 -> 3193.8592 | ... M99: =M$59*M47 -> 3558.9843
A100: Other Current Liabilities | D100: =D$59*D48 -> 1712.358 | E100: =E$59*E48 -> 1817.6349 | F100: =F$59*F48 -> 1927.6874 | G100: =G$59*G48 -> 2042.7071 | H100: =H$59*H48 -> 2162.893 | I100: =I$59*I48 -> 2288.4517 | J100: =J$59*J48 -> 2419.5973 | K100: =K$59*K48 -> 2556.552 | ... M100: =M$59*M48 -> 2848.8195
A101: Total Current Liabilities | D101: =SUM(D94:D100) -> 9806.1072 | E101: =SUM(E94:E100) -> 10327.839 | F101: =SUM(F94:F100) -> 10873.237 | G101: =SUM(G94:G100) -> 11443.252 | H101: =SUM(H94:H100) -> 12038.869 | I101: =SUM(I94:I100) -> 12241.113 | J101: =SUM(J94:J100) -> 12891.045 | K101: =SUM(K94:K100) -> 13569.766 | ... M101: =SUM(M94:M100) -> 15018.185
A102: Long-Term Debt | B102: GAP FIX: adding more debt because that is consistent with starbuck's historical performance. Balancing the ratio calculated from WACC | D102: =D22+D24 +(WACC!$B$18*'Pro Forma Statement Step 2'!D119) -> 22104.975 | E102: =E22+E24 +(WACC!$B$18*'Pro Forma Statement Step 2'!E119) -> 22246.59 | F102: =F22+F24 +(WACC!$B$18*'Pro Forma Statement Step 2'!F119) -> 22645.653 | G102: =G22+G24 +(WACC!$B$18*'Pro Forma Statement Step 2'!G119) -> 23078.939 | H102: =H22+H24 +(WACC!$B$18*'Pro Forma Statement Step 2'!H119) -> 23481.903 | I102: =I22+I24 +(WACC!$B$18*'Pro Forma Statement Step 2'!I119) -> 24451.863 | J102: =J22+J24 +(WACC!$B$18*'Pro Forma Statement Step 2'!J119) -> 25499.712 | K102: =K22+K24 +(WACC!$B$18*'Pro Forma Statement Step 2'!K119) -> 26736.398 | ... M102: =M22+M24 +(WACC!$B$18*'Pro Forma Statement Step 2'!M119) -> 29878.42
A103: Long-Term Leases | D103: ='Historical Balance Sheet'!K43*(1+'Pro Forma Statement Step 2'!D49) -> 9034.748 | E103: =D103*(1+E$49) -> 9305.7904 | F103: =E103*(1+F$49) -> 9584.9642 | G103: =F103*(1+G$49) -> 9872.5131 | H103: =G103*(1+H$49) -> 10168.688 | I103: =H103*(1+I$49) -> 10473.749 | J103: =I103*(1+J$49) -> 10787.962 | K103: =J103*(1+K$49) -> 11111.6 | L103: =K103*(1+L$49) -> 11444.948 | M103: =L103*(1+M$49) -> 11788.297
A104: Unearned Revenue, Non-Current | D104: ='Historical Balance Sheet'!K44*(1+'Pro Forma Statement Step 2'!D49) -> 6142.508 | E104: =D104*(1+E$49) -> 6326.7832 | F104: =E104*(1+F$49) -> 6516.5867 | G104: =F104*(1+G$49) -> 6712.0843 | H104: =G104*(1+H$49) -> 6913.4469 | I104: =H104*(1+I$49) -> 7120.8503 | J104: =I104*(1+J$49) -> 7334.4758 | K104: =J104*(1+K$49) -> 7554.5101 | L104: =K104*(1+L$49) -> 7781.1454 | M104: =L104*(1+M$49) -> 8014.5797
A105: Def. Tax Liability, Non-Curr. | D105: ='Historical Balance Sheet'!K45*(1+'Pro Forma Statement Step 2'!D49) -> 21.733 | E105: =D105*(1+E$49) -> 22.38499 | F105: =E105*(1+F$49) -> 23.05654 | G105: =F105*(1+G$49) -> 23.748236 | H105: =G105*(1+H$49) -> 24.460683 | I105: =H105*(1+I$49) -> 25.194503 | J105: =I105*(1+J$49) -> 25.950339 | K105: =J105*(1+K$49) -> 26.728849 | L105: =K105*(1+L$49) -> 27.530714 | M105: =L105*(1+M$49) -> 28.356636
A106: Other Non-Current Liabilities | D106: ='Historical Balance Sheet'!K46*(1+'Pro Forma Statement Step 2'!D49) -> 634.377 | E106: =D106*(1+E$49) -> 653.40831 | F106: =E106*(1+F$49) -> 673.01056 | G106: =F106*(1+G$49) -> 693.20088 | H106: =G106*(1+H$49) -> 713.9969 | I106: =H106*(1+I$49) -> 735.41681 | J106: =I106*(1+J$49) -> 757.47931 | K106: =J106*(1+K$49) -> 780.20369 | L106: =K106*(1+L$49) -> 803.6098 | M106: =L106*(1+M$49) -> 827.7181
A107: Total Liabilities | D107: =SUM(D101:D106) -> 47744.448 | E107: =SUM(E101:E106) -> 48882.795 | F107: =SUM(F101:F106) -> 50316.508 | G107: =SUM(G101:G106) -> 51823.737 | H107: =SUM(H101:H106) -> 53341.365 | I107: =SUM(I101:I106) -> 55048.187 | J107: =SUM(J101:J106) -> 57296.624 | K107: =SUM(K101:K106) -> 59779.206 | ... M107: =SUM(M101:M106) -> 65555.556
A109: Common Stock | B109: Common Stock accounts start with values from last balance sheet. Par value of common stock: Assuming $0.10 per share (typical for Starbucks). Starting balances (FY2024 10-K estimates): | D109: =0.1*D50/1000000 -> 113.69 | E109: =0.1*E50/1000000 -> 112.49 | F109: =0.1*F50/1000000 -> 111.49 | G109: =0.1*G50/1000000 -> 110.49 | H109: =0.1*H50/1000000 -> 109.49 | I109: =0.1*I50/1000000 -> 108.49 | J109: =0.1*J50/1000000 -> 107.49 | K109: =0.1*K50/1000000 -> 106.49 | ... M109: =0.1*M50/1000000 -> 104.49
A110: Additional Paid In Capital | B110: Starting from historical APIC as APICt-1, APICt​=APICt−1​−(Shares repurchased×(Repurchase price – Par)) | C110: ='Historical Balance Sheet'!K50 -> 322.6 | D110: =C110-((D51/1000000)*(D52-0.1)) -> -876.2 | E110: =D110-((E51/1000000)*(E52-0.1)) -> -1875.2 | F110: =E110-((F51/1000000)*(F52-0.1)) -> -2874.2 | G110: =F110-((G51/1000000)*(G52-0.1)) -> -3873.2 | H110: =G110-((H51/1000000)*(H52-0.1)) -> -4872.2 | I110: =H110-((I51/1000000)*(I52-0.1)) -> -5871.2 | J110: =I110-((J51/1000000)*(J52-0.1)) -> -6870.2 | K110: =J110-((K51/1000000)*(K52-0.1)) -> -7869.2 | ... M110: =L110-((M51/1000000)*(M52-0.1)) -> -9867.2
A111: Retained Earnings | B111: RE at t​ = RE at t−1​+Net Income at t​−Dividends Paid at t. https://www.retirewithryne.com/newsletter/confused-about-starbucks | C111: ='Historical Balance Sheet'!K51 -> -7343.8 | D111: =C111+D72-D74 -> -6508.6807 | E111: =D111+E72-E74 -> -5533.4086 | F111: =E111+F72-F74 -> -4425.1049 | G111: =F111+G72-G74 -> -3176.1145 | H111: =G111+H72-H74 -> -1775.4079 | I111: =H111+I72-I74 -> -227.92124 | J111: =I111+J72-J74 -> 1471.1632 | K111: =J111+K72-K74 -> 3326.8054 | ... M111: =L111+M72-M74 -> 7528.3397
A112: Treasury Stock | D112: 0 | E112: 0 | F112: 0 | G112: 0 | H112: 0 | I112: 0 | J112: 0 | K112: 0 | L112: 0 | M112: 0
A113: Comprehensive Inc. and Other | B113: Growing these at the same rate as nominal Sales | D113: ='Historical Balance Sheet'!K53*(1+'Pro Forma Statement Step 2'!D11) -> 467.45448 | E113: =D113*(1+E11) -> 496.1939 | F113: =E113*(1+F11) -> 526.23698 | G113: =F113*(1+G11) -> 557.63606 | H113: =G113*(1+H11) -> 590.44547 | I113: =H113*(1+I11) -> 624.72158 | J113: =I113*(1+J11) -> 660.52286 | K113: =J113*(1+K11) -> 697.90996 | L113: =K113*(1+L11) -> 736.94581 | M113: =L113*(1+M11) -> 777.6957
...

Sheet Completed Valuation
A1: All values are in $million USD (unless otherwise stated)
A3: Final valuation based on the proforma
B4: 1 | C4: 2 | D4: 3 | E4: 4 | F4: 5 | G4: 6 | H4: 7 | I4: 8 | J4: 9 | K4: 10
B5: 2025 | C5: 2026 | D5: 2027 | E5: 2028 | F5: 2029 | G5: 2030 | H5: 2031 | I5: 2032 | J5: 2033 | K5: 2034
A6: NOPAT | B6: ='Pro Forma Statement Step 2'!D124 -> 4067.1519 | C6: ='Pro Forma Statement Step 2'!E124 -> 4317.2031 | D6: ='Pro Forma Statement Step 2'!F124 -> 4578.597 | E6: ='Pro Forma Statement Step 2'!G124 -> 4851.789 | F6: ='Pro Forma Statement Step 2'!H124 -> 5137.2519 | G6: ='Pro Forma Statement Step 2'!I124 -> 5435.4758 | H6: ='Pro Forma Statement Step 2'!J124 -> 5746.9697 | I6: ='Pro Forma Statement Step 2'!K124 -> 6072.2613 | ... K6: ='Pro Forma Statement Step 2'!M124 -> 6766.4481
A7: Operating Cash after non-cash | B7: ='Pro Forma Statement Step 2'!D125 -> 5941.5882 | C7: ='Pro Forma Statement Step 2'!E125 -> 6306.8811 | D7: ='Pro Forma Statement Step 2'!F125 -> 6688.7441 | E7: ='Pro Forma Statement Step 2'!G125 -> 7087.8427 | F7: ='Pro Forma Statement Step 2'!H125 -> 7504.8673 | G7: ='Pro Forma Statement Step 2'!I125 -> 7940.5343 | H7: ='Pro Forma Statement Step 2'!J125 -> 8395.587 | I7: ='Pro Forma Statement Step 2'!K125 -> 8870.7964 | ... K7: ='Pro Forma Statement Step 2'!M125 -> 9884.9145
A8: Capex | B8: ='Pro Forma Statement Step 2'!D126 -> 0 | C8: ='Pro Forma Statement Step 2'!E126 -> 5152.777 | D8: ='Pro Forma Statement Step 2'!F126 -> 5754.6168 | E8: ='Pro Forma Statement Step 2'!G126 -> 6426.7509 | F8: ='Pro Forma Statement Step 2'!H126 -> 7177.3896 | G8: ='Pro Forma Statement Step 2'!I126 -> 2635.2674 | H8: ='Pro Forma Statement Step 2'!J126 -> 2786.2881 | I8: ='Pro Forma Statement Step 2'!K126 -> 2943.9984 | ... K8: ='Pro Forma Statement Step 2'!M126 -> 3280.5591
A9: NWC | B9: ='Pro Forma Statement Step 2'!D127 -> -2788.5612 | C9: ='Pro Forma Statement Step 2'!E127 -> -2960.0038 | D9: ='Pro Forma Statement Step 2'!F127 -> -3139.2233 | E9: ='Pro Forma Statement Step 2'!G127 -> -3326.5319 | F9: ='Pro Forma Statement Step 2'!H127 -> -3522.2538 | G9: ='Pro Forma Statement Step 2'!I127 -> -3726.7251 | H9: ='Pro Forma Statement Step 2'!J127 -> -3940.2946 | I9: ='Pro Forma Statement Step 2'!K127 -> -4163.3243 | ... K9: ='Pro Forma Statement Step 2'!M127 -> -4639.2796
A10: Change in NWC | B10: ='Pro Forma Statement Step 2'!D128 -> 0 | C10: ='Pro Forma Statement Step 2'!E128 -> -171.44263 | D10: ='Pro Forma Statement Step 2'!F128 -> -179.21948 | E10: ='Pro Forma Statement Step 2'!G128 -> -187.30864 | F10: ='Pro Forma Statement Step 2'!H128 -> -195.72186 | G10: ='Pro Forma Statement Step 2'!I128 -> -204.4713 | H10: ='Pro Forma Statement Step 2'!J128 -> -213.56954 | I10: ='Pro Forma Statement Step 2'!K128 -> -223.02966 | ... K10: ='Pro Forma Statement Step 2'!M128 -> -243.0901
A11: FCFF | B11: ='Pro Forma Statement Step 2'!D129 -> 5941.5882 | C11: ='Pro Forma Statement Step 2'!E129 -> 1325.5467 | D11: ='Pro Forma Statement Step 2'!F129 -> 1113.3468 | E11: ='Pro Forma Statement Step 2'!G129 -> 848.40045 | F11: ='Pro Forma Statement Step 2'!H129 -> 523.19956 | G11: ='Pro Forma Statement Step 2'!I129 -> 5509.7383 | H11: ='Pro Forma Statement Step 2'!J129 -> 5822.8685 | I11: ='Pro Forma Statement Step 2'!K129 -> 6149.8277 | ... K11: ='Pro Forma Statement Step 2'!M129 -> 6847.4454
A13: TV using Perpetuity Growth | K13: =(K11*(1+'Pro Forma Statement Step 2'!C143))/(WACC!B21-'Pro Forma Statement Step 2'!C143) -> 153743.92
A14: PV | B14: =(B11)/(1+WACC!$B$21)^B4 -> 5549.5075 | C14: =(C11)/(1+WACC!$B$21)^C4 -> 1156.3753 | D14: =(D11)/(1+WACC!$B$21)^D4 -> 907.16469 | E14: =(E11)/(1+WACC!$B$21)^E4 -> 645.66681 | F14: =(F11)/(1+WACC!$B$21)^F4 -> 371.90056 | G14: =(G11)/(1+WACC!$B$21)^G4 -> 3657.9885 | H14: =(H11)/(1+WACC!$B$21)^H4 -> 3610.7734 | I14: =(I11)/(1+WACC!$B$21)^I4 -> 3561.8703 | J14: =(J11)/(1+WACC!$B$21)^J4 -> 3511.4753 | K14: =(K11+K13)/(1+WACC!$B$21)^K4 -> 81141.145
A16: Enterprise Value | B16: =SUM(B14:K14) -> 104113.87
B19: 2034
A20: Long-term debt | B20: ='Pro Forma Statement Step 2'!M102 -> 29878.42
A21: Current portion of LT Debt | B21: ='Pro Forma Statement Step 2'!M96 -> 900
A22: Cash and ST Investments | B22: ='Pro Forma Statement Step 2'!M82 -> 9889.2886
A23: Net Debt | B23: =B20+B21-B22 -> 20889.131
A25: Equity Value | B25: =B16-B23 -> 83224.736 | C25: EV- Net Debt
A26: Shares Outstanding | B26: =('Pro Forma Statement Step 2'!M50+'Pro Forma Statement Step 2'!M51)/1000000 -> 1054.9
A27: Implied Price per share | B27: =B25/B26 -> 78.893484 | C27: USD/share
A30: Observations:
A31: FCFF trajectory:
A32: FCFF starts smaller after 2025 but recovers and grows steadily, which aligns with a mature, cash-generative company like Starbucks.
A33: This is realistic because CapEx is now stabilized relative to revenue, avoiding negative free cash flows in later years.
A34: Terminal Value (TV):
A35: Positive and reasonable using a perpetuity growth approach, reflecting a stable long-term growth rate.
A36: Present Value (PV) and Enterprise Value (EV):
A37: The PV of FCFF plus PV of terminal value gives a healthy EV of approx. $105B, which is in line with Starbucks’ market capitalization trends (assuming you adjust for net debt later).
A38: CapEx and WACC Justification: CapEx was stabilized at 4–5% of revenue after 2030, consistent with Starbucks’ historical post-expansion spending patterns, to avoid negative FCFF and reflect a mature company profile. The WACC of 7.02% reflects the firm’s target capital structure with 79% equity and 21% debt, aligning with Starbucks’ historical leverage and current market conditions.
A39: Future Price / Target Price: Based on the projected FCFF, balanced pro forma, and PV calculations, the implied share price in 2034 is $78.89, reflecting a modest decline from today’s market price due to ongoing CapEx requirements and moderate growth assumptions.
A41: Final Recommendation:
A42: Based on our valuation analysis, Starbucks Corporation's implied stock price was determined to be $78.89, compared to the current market price of approximately $85.00. This suggests the stock is currently trading at a slight premium relative to its intrinsic value, indicating that Starbucks is overvalued at its present price. Accordingly, my analysis supports a Sell recommendation for this position. It is worth noting, however, the current market price closer to $85 may be partially explained by the offsetting effects of share repurchases against slow growth in Free Cash Flow to the Firm (FCFF), a factor that investors should consider when interpreting this valuation.
